Workbook
Name cmp_conditional: Lookups!$B$30
Name cmp_suitable: Lookups!$B$29
Name mcp_min_compliance: Lookups!$B$31
Name p_autonomy: Scoping!$C$20
Name p_background: Scoping!$C$21
Name p_confidential: Scoping!$C$12
Name p_decisions: Scoping!$C$16
Name p_downstream: Scoping!$C$15
Name p_eu: Scoping!$C$13
Name p_finetune: Scoping!$C$18
Name p_local: Scoping!$C$22
Name p_locus: Scoping!$C$25
Name p_mcp: Scoping!$C$27
Name p_memory: Scoping!$C$23
Name p_multiagent: Scoping!$C$24
Name p_open: Scoping!$C$28
Name p_personal: Scoping!$C$11
Name p_provider: Scoping!$C$9
Name p_rag: Scoping!$C$17
Name p_role: Scoping!$C$26
Name p_stage: Scoping!$C$10
Name p_tools: Scoping!$C$19
Name p_users: Scoping!$C$14
Name t_readiness: Lookups!$B$25
Name t_residual: Lookups!$B$26

Sheet README & Logic
A1: LLM & Agent Security Assessment Workbook - Logic (v0.6.8-r4, repaired)
A3: Purpose | B3: Assess an LLM- or agent-powered integration before pilot, production, or material change.
A4: Quick start (approx. 2-3 h first pass) | B4: 1) Scoping sheet: system header plus 19 profile questions (10-15 min, system owner + assessor). Applicability of every control is derived automatically; grey rows are out of scope; answers outside the dropdown lists count as open questions. 2) Assessment Matrix: answer the white rows Yes / Partial / No and attach evidence for every Yes or Partial (60-90 min). Detail columns (scoring, remediation bookkeeping, related/guidance, exemption fields) ship collapsed; expand the column groups with the + buttons above the grid when you need them. 3) MCP checklists if S19 = Yes. 4) Dashboard decision and sign-off.
A5: Roles | B5: System owner fills the Scoping header and answers. Assessor answers controls. Security/legal review 1.3, 2.5, 2.7, 5.4, and domain 7. The accountable risk owner signs the Dashboard and is the only role that may grant exemptions. A control owned by another department and awaiting its review stays applicable; ownership is never a reason to mark a control out of scope.
A6: Scoping logic | B6: Each control carries an applicability rule referencing the Scoping answers (shown in the Applicability column). Unanswered Scoping questions never deactivate a control (fail-safe: in doubt, a control stays applicable), and out-of-list answers count as open questions. To overrule the automatic result for a single row, use the Override column and justify it in Notes.
A7: Hard gates | B7: Any applicable Blocker control answered No results in a BLOCK. A Blocker answered Partial is a BLOCK in Production and an ESCALATE in Pilot/PoC. Any Major answered No is an ESCALATE. Remediation closes a gate by re-testing and re-answering the control (Status alone never clears a gate).
A8: Exemption procedure | B8: To exempt a gate formally: set Status = Accepted Risk and fill the exemption columns X-Z (reference: risk-owner decision, committee minute, or ticket; approver; date). The Gate Flag then shows the stage-sensitive gate with an (exempted) suffix, the Dashboard counts it, and the decision can move to CONDITIONAL APPROVAL, never to silent approval. Exemptions with missing reference/approver/date are flagged per row and block completion. Remediation closes a gate by re-testing and re-answering the control. Three distinct review decisions use these columns: an applicability review of an auto-applicable Blocker (override needs X-Z), an approved criticality variation below the shipped baseline (needs rationale in Notes and approver in Y), and acceptance of an unmet applicable Blocker or Major requirement (Accepted Risk + X-Z converts the gate into a counted exemption and caps the decision at CONDITIONAL APPROVAL). For Moderate and Minor controls, Status = Accepted Risk documents the acceptance in the residual view; it is not a formal gate exemption and does not by itself force a conditional decision. It still needs reference, approver and date in X-Z, as does every other Status = Accepted Risk entry (integrity check).
A9: Scoring | B9: Yes = 1.0, Partial = 0.5, No = 0.0. Weight follows Criticality automatically (Lookups table; change Criticality and Weight updates). Likelihood and Impact are assessor inputs with 1-5 scales defined on Lookups; the shipped values are generic defaults, adjust them per system. Residual per answered control = Weight x Likelihood x Impact x (1 - score); the Dashboard aggregates this as a weighted residual-exposure / control-gap index - a relative prioritization measure, not a calibrated loss estimate. Unanswered controls contribute their full exposure separately. The policy thresholds on Lookups (readiness minima, residual thresholds, MCP minimum compliance rate, Comparator cutoffs) are validated: blank, non-numeric, out-of-range or inconsistently ordered settings are integrity flags that hold the decision, and data validation guides legitimate edits.
A10: Decision | B10: INCOMPLETE until Scoping is complete and valid, every applicable control has a response, integrity checks pass, and (if S19 = Yes) every MCP side has an explicit Required selection and each required side is assessed with complete context. Contradictions between S19 and the Required switches block completion; a required checklist is never silently ignored. BLOCKED if any blocker is open or a required MCP side verdicts NO-GO, i.e. an open mandatory checkpoint or a compliance rate below the Lookups minimum (blocking verdicts outrank evidence-only conditions). CONDITIONAL APPROVAL if readiness < minimum, escalations or exemptions exist, evidence is missing, a control sits at/above the residual threshold, or an MCP side verdicts CONDITIONAL GO. Otherwise APPROVABLE. The final decision is signed off by the accountable risk owner on the Dashboard. Invalid or error-valued shared configuration holds both deployment and sourcing. Operational answers, evidence, status and remediation/exemption inputs are checked for calculation errors without making unused operational metadata a sourcing dependency. Required MCP sides have separate context, answer/evidence and exclusion-review validity states; errors cannot count as clean evidence. A confirmed mandatory failure remains visible alongside incomplete inputs.
A11: Assessment object | B11: Score the entire LLM system, not just the base model: model, provider, deployment, prompts, RAG/vector DB, tools/plugins/agents, APIs, data flows, logging, and operations.
A12: Agentic scope | B12: Domain 9 (Agentic AI) activates by autonomy and by capability: an autonomy level other than None activates the core agentic controls, while 9.4 (tools, S11), 9.5 (local device access, S14), 9.7 (persistent memory, S15) and 9.11 (multi-agent / MCP, S16 or S19) activate on their own triggers even when S12 = None. It covers autonomy classification, human-in-the-loop gates, agent identity and least privilege, tool allowlisting, sandboxing and egress control, indirect prompt injection, persistent memory, background operation limits, action logging, kill switch, multi-agent / MCP supply chain, autonomy anomaly monitoring, and agent credential lifecycle.
A13: Evidence principle | B13: Every Yes or Partial should be supported by evidence: architecture diagram, contract/DPA, model card, SBOM/AIBOM, audit report, test report, ticket, policy, or log sample. The Guidance column states the expected evidence per control. Missing evidence is counted on the Dashboard and prevents an unconditional approval.
A14: Glossary | B14: Blocker: non-negotiable gate. Major: requires escalation when unmet. Moderate/Minor: gradable. Partial: defined per control in the Guidance column. Autonomy (S12): Assisted = human approves every action; Supervised = human approves material actions; Autonomous = acts without per-action approval. Role (S18): Assist = output informs a human; Steer = output controls or prioritizes a process; Intervene = output executes changes in systems or the physical world. Verdicts: INCOMPLETE / BLOCKED / CONDITIONAL APPROVAL / APPROVABLE.
... A16: Print | B16: Print setup is landscape, fit-to-width, with repeating header rows (approx. 20 pages for the full workbook in a v0.6.3 headless render; re-verify the current page layout before circulating hard copies). Native Microsoft Excel print and interaction acceptance is still pending.
A17: Useful reference mappings
A18: OWASP LLM Top 10 | B18: Map application threat scenarios such as prompt injection, insecure output handling, model denial of service, supply chain, sensitive information disclosure, excessive agency, and vector/embedding weaknesses. Per-control mapping sits in the Guidance column.
A19: OWASP Agentic Security | B19: Threats and mitigations specific to agentic systems (tool misuse, memory poisoning, identity spoofing, cascading agent failures).
A20: NIST AI RMF / GenAI Profile | B20: Governance, mapping, measurement, and management of GenAI risks.
A21: MITRE ATLAS | B21: Adversarial AI tactics and techniques for threat models and test plans.
A22: EU AI Act / GPAI | B22: Role classification, high-risk duties, GPAI obligations, transparency, logging, human oversight, and compliance roadmap.
A23: Reference | B23: Plain-text URL
A24: OWASP Top 10 for LLM Applications | B24: https://owasp.org/www-project-top-10-for-large-language-model-applications/
A25: OWASP GenAI Security Project | B25: https://genai.owasp.org/
A26: NIST AI Risk Management Framework | B26: https://www.nist.gov/itl/ai-risk-management-framework
A27: NIST AI RMF Generative AI Profile | B27: https://www.nist.gov/publications/artificial-intelligence-risk-management-framework-generative-artificial-intelligence
A28: MITRE ATLAS | B28: https://atlas.mitre.org/
A29: European Commission AI Act overview | B29: https://digital-strategy.ec.europa.eu/en/policies/regulatory-framework-ai
... A34: Migration between versions | B34: Sheet 'Migration': paste the old version's sheets as values into the 'Old ...' sheets, check the status lines, then copy each blue block to the named target cell with Paste Special > Values + Skip blanks (unprotect the target sheet first, no password). Rows are matched by control ID and the Assessment Matrix columns by header text, so controls or columns that moved or are new keep the current values. Template-owned cells (criticality baseline, MCP severity, lookups) are not migrated.

Sheet Scoping
A1: Scoping - answer this sheet first, it steers the whole assessment
B3: System / use case name
B4: Assessor / accountable owner
B5: Date
B6: Assessment version (of the system / this assessment)
A8: ID | B8: Question | C8: Answer | D8: What the answer switches | E8: Validity
A9: S1 | B9: Provider / deployment model | D9: Provider, contract, and supply-chain controls (2.2, 2.3, 2.5, 2.7, 3.9, 5.2, 5.6, 5.8, 7.2, 7.3). | E9: =IF(IFERROR(C9="",TRUE()),"blank",IF(IFERROR(OR(C9="External SaaS / API",C9="COTS (on-prem or managed)",C9="Self-hosted / open weights",C9="Internal development"),FALSE()),"valid","invalid")) -> blank
A10: S2 | B10: Stage of use | D10: Production-only operations controls (2.4, 2.6, 5.1, 5.3, 6.1, 6.4, 6.5, 6.6, 8.2, 8.5). | E10: =IF(IFERROR(C10="",TRUE()),"blank",IF(IFERROR(OR(C10="Pilot / PoC",C10="Production"),FALSE()),"valid","invalid")) -> blank
A11: S3 | B11: Personal data is processed | D11: Privacy controls (4.5, 6.1, 7.1, 7.2). | E11: =IF(IFERROR(C11="",TRUE()),"blank",IF(IFERROR(OR(C11="Yes",C11="No"),FALSE()),"valid","invalid")) -> blank
A12: S4 | B12: Confidential or regulated data is processed | D12: Disclosure and monitoring controls (4.5, 6.1, 6.5, 7.2). S4 = Yes also raises control 2.7 to Blocker criticality. | E12: =IF(IFERROR(C12="",TRUE()),"blank",IF(IFERROR(OR(C12="Yes",C12="No"),FALSE()),"valid","invalid")) -> blank
A13: S5 | B13: EU market or EU users are in scope | D13: AI Act controls (1.3, 7.4). | E13: =IF(IFERROR(C13="",TRUE()),"blank",IF(IFERROR(OR(C13="Yes",C13="No"),FALSE()),"valid","invalid")) -> blank
A14: S6 | B14: User group | D14: Abuse, volume, and external-exposure controls (4.4, 6.3). | E14: =IF(IFERROR(C14="",TRUE()),"blank",IF(IFERROR(OR(C14="Internal (limited group)",C14="Internal (broad)",C14="External / public"),FALSE()),"valid","invalid")) -> blank
A15: S7 | B15: Outputs feed downstream systems or are executed (code, SQL, workflows, mails) | D15: Output handling controls (3.6, 4.9). | E15: =IF(IFERROR(C15="",TRUE()),"blank",IF(IFERROR(OR(C15="Yes",C15="No"),FALSE()),"valid","invalid")) -> blank
A16: S8 | B16: Output supports consequential decisions about people | D16: Human oversight control (1.4); indicator for AI Act high-risk review in 1.3. | E16: =IF(IFERROR(C16="",TRUE()),"blank",IF(IFERROR(OR(C16="Yes",C16="No"),FALSE()),"valid","invalid")) -> blank
A17: S9 | B17: RAG, vector database, or knowledge base is used | D17: Retrieval controls (3.5, 4.3). | E17: =IF(IFERROR(C17="",TRUE()),"blank",IF(IFERROR(OR(C17="Yes",C17="No"),FALSE()),"valid","invalid")) -> blank
A18: S10 | B18: Fine-tuning or model adaptation is performed | D18: Training-data controls (4.3, 5.5). | E18: =IF(IFERROR(C18="",TRUE()),"blank",IF(IFERROR(OR(C18="Yes",C18="No"),FALSE()),"valid","invalid")) -> blank
A19: S11 | B19: Tools, plugins, or function calling are used | D19: Tool controls (3.2, 3.6, 3.9, 4.6, 9.4). | E19: =IF(IFERROR(C19="",TRUE()),"blank",IF(IFERROR(OR(C19="Yes",C19="No"),FALSE()),"valid","invalid")) -> blank
A20: S12 | B20: Autonomy level of the system | D20: Activates autonomy-dependent agent controls and 1.5. Tools, local access, memory and MCP can keep specific controls relevant even when autonomy is None. | E20: =IF(IFERROR(C20="",TRUE()),"blank",IF(IFERROR(OR(C20="None (chat or single completions)",C20="Assisted (human approves every action)",C20="Supervised (human approves material actions)",C20="Autonomous (acts without per-action approval)"),FALSE()),"valid","invalid")) -> blank
A21: S13 | B21: Continuous or scheduled background operation (agent runs without a user session) | D21: Background limits and kill-switch emphasis (9.8). | E21: =IF(IFERROR(C21="",TRUE()),"blank",IF(IFERROR(OR(C21="Yes",C21="No"),FALSE()),"valid","invalid")) -> blank
A22: S14 | B22: Local device access (files, shell, browser control) | D22: Isolation and egress control (9.5). | E22: =IF(IFERROR(C22="",TRUE()),"blank",IF(IFERROR(OR(C22="Yes",C22="No"),FALSE()),"valid","invalid")) -> blank
A23: S15 | B23: Persistent memory across sessions | D23: Memory governance (9.7). | E23: =IF(IFERROR(C23="",TRUE()),"blank",IF(IFERROR(OR(C23="Yes",C23="No"),FALSE()),"valid","invalid")) -> blank
A24: S16 | B24: Multi-agent setup or external agents are used (regardless of protocol) | D24: Agent supply-chain control (9.11); domain 9 emphasis. MCP itself is declared separately in S19. | E24: =IF(IFERROR(C24="",TRUE()),"blank",IF(IFERROR(OR(C24="Yes",C24="No"),FALSE()),"valid","invalid")) -> blank
A25: S17 | B25: Primary deployment locus | D25: Positions the system in the AI Defense Matrix; Production / OT proximity activates control 3.7. | E25: =IF(IFERROR(C25="",TRUE()),"blank",IF(IFERROR(OR(C25="End user client / endpoint",C25="Cloud or SaaS tenant",C25="Own data center / servers",C25="Network or gateway (inline)",C25="Production / OT proximity"),FALSE()),"valid","invalid")) -> blank
A26: S18 | B26: Operational role of the output | D26: Sets verdict strictness (readiness minimum and residual threshold, see Lookups); Steer/Intervene keeps human-oversight control 1.4 applicable. | E26: =IF(IFERROR(C26="",TRUE()),"blank",IF(IFERROR(OR(C26="Assist (informs a human)",C26="Steer (controls or prioritizes a process)",C26="Intervene (executes changes in systems or the physical world)"),FALSE()),"valid","invalid")) -> blank
A27: S19 | B27: MCP (Model Context Protocol) servers or clients are used | D27: Authoritative MCP scope: the MCP checklists become hard gates; each side must be explicitly Required Yes/No; feeds 9.11. | E27: =IF(IFERROR(C27="",TRUE()),"blank",IF(IFERROR(OR(C27="Yes",C27="No"),FALSE()),"valid","invalid")) -> blank
B28: Open or invalid scoping questions | C28: =COUNTIF($E$9:$E$27,"blank")+COUNTIF($E$9:$E$27,"invalid") -> 19
B29: Consistency hint | C29: =IFERROR(IF(AND($C$20="None (chat or single completions)",OR($C$21="Yes",$C$22="Yes",$C$24="Yes")),"Check S12: background operation, local access, or multi-agent answered Yes although autonomy is None.",""),"")
B30: Consistency hint | C30: =IFERROR(IF(AND($C$19="No",$C$20<>"None (chat or single completions)",$C$20<>""),"Check S11/S12: autonomy above None usually implies tool use, but S11 = No.",""),"")
B31: Consistency hint | C31: =IFERROR(IF(AND($C$24="Yes",$C$19="No"),"Check S16/S11: multi-agent or MCP setups use tools or function calling, but S11 = No.",""),"")
B32: Consistency hint | C32: =IFERROR(IF(AND($C$25="Production / OT proximity",$C$26="Assist (informs a human)"),"Check S17/S18: OT-adjacent deployment whose output only informs a human.",""),"")
B33: Consistency hint (hard) | C33: =IFERROR(IF(AND($C$27="Yes",'MCP Server Checklist'!$I$2="No",'MCP Client Checklist'!$I$2="No"),"S19 = Yes but neither MCP side is marked Required: the decision stays INCOMPLETE. Mark at least one side Required and assess it, or set S19 = No.",""),"")
B34: Consistency hint (hard) | C34: =IFERROR(IF(AND($C$27="No",OR('MCP Server Checklist'!$I$2="Yes",'MCP Client Checklist'!$I$2="Yes")),"S19 = No but an MCP side is marked Required: the decision stays INCOMPLETE. A required checklist is never silently ignored: set the side to Required = No or answer S19 = Yes.",""),"")
B35: Consistency hint | C35: =IFERROR(IF(AND($C$24="Yes",$C$27="No"),"Check S16/S19: multi-agent setups often use MCP; confirm no agent connects to MCP servers or clients.",""),"")
B36: Consistency hint | C36: =IF(COUNTIF($E$9:$E$27,"invalid")>0,"One or more scoping answers are outside the allowed lists; they count as open questions.","")
A38: Hint classes | B38: Soft hints flag unlikely combinations to review. Hard contradictions (S19 vs the Required switches) are binding: they keep the decision at INCOMPLETE until resolved, so a required checklist can never be silently excluded.

Sheet Assessment Matrix
A1: ID | B1: Domain | C1: Applicability | D1: Control / Assessment Question | E1: Criticality | F1: Weight | G1: Likelihood (1-5) | H1: Impact (1-5) | I1: Applicable? | J1: Override (applicability) | K1: Response | L1: Implementation Score | M1: Residual Risk | N1: Gate Flag | O1: Evidence / Link | P1: Owner | Q1: Remediation / Decision | R1: Target Date | S1: Status | T1: Notes | U1: Row Check | V1: Related controls (scope) | W1: Guidance: what good looks like, evidence, Partial definition, framework mapping | X1: Exemption reference | Y1: Exemption approver | Z1: Exemption date | AA1: Integrity flag: N/A on applicable (ID) | AB1: Integrity flag: override without reason (ID) | AC1: Integrity flag: invalid value / exemption gap / floor (ID + reason) | AD1: Baseline criticality (v0.6.5 ship state) | AE1: Unused helper column (reserved; empty since v0.6.8-r1) | AF1: Shared configuration validity flag (typed) | AG1: Editable-input error flag (typed) | AH1: Config flag IDs (typed) | AI1: Automatic applicability before override | AJ1: Invalid response flag | AK1: Likelihood / impact validity flag | AL1: Status validity flag | AM1: Exemption metadata validity flag | AN1: Applicable N/A flag | AO1: Override rationale flag | AP1: Missing / unusable evidence flag | AQ1: Operational row integrity flag (typed) | AR1: Valid applicable answer (1/0) | AS1: Readiness numerator | AT1: Readiness denominator | AU1: Input error locations | AV1: Configuration issue details | AW1: Operational issue details
A2: 1.1 | B2: Use Case & Data | C2: Auto: always | D2: Business purpose, accountable owner, users, and intended decisions are documented. | E2: Major | F2: =IFERROR(IF($E2="Blocker",Lookups!$B$8,IF($E2="Major",Lookups!$B$9,IF($E2="Moderate",Lookups!$B$10,IF($E2="Minor",Lookups!$B$11,0)))),0) -> 4 | G2: 3 | H2: 3 | I2: =IFERROR(IF(OR($J2="Yes",$J2="No"),$J2,"Yes"),"Yes") -> Yes | L2: =IFERROR(IF(OR($I2="No",$K2="N/A"),"",IF($K2="Yes",1,IF($K2="Partial",0.5,IF($K2="No",0,"")))),"") | M2: =IFERROR(IF(OR($I2="No",$K2="N/A"),"",$F2*IF(OR($G2="",NOT(ISNUMBER($G2))),3,$G2)*IF(OR($H2="",NOT(ISNUMBER($H2))),3,$H2)*IF($K2="",1,1-$L2)),"") -> 36 | N2: =IFERROR(IF(OR($I2="No",$K2="N/A",$K2=""),"",IF(AND(IFERROR(AND($S2="Accepted Risk",$AM2=0),FALSE()),OR(AND($E2="Blocker",OR($K2="No",$K2="Partial")),AND($E2="Major",$K2="No"))),IF(AND($E2="Blocker",$K2="No"),"BLOCK",IF(AND($E2="Blocker",$K2="Partial"),IF(p_stage="Pilot / PoC","ESCALATE","BLOCK"),IF(AND($E2="Major",$K2="No"),"ESCALATE","")))&" (exempted)",IF(AND($E2="Blocker",$K2="No"),"BLOCK",IF(AND($E2="Blocker",$K2="Partial"),IF(p_stage="Pilot / PoC","ESCALATE","BLOCK"),IF(AND($E2="Major",$K2="No"),"ESCALATE",""))))),"") | U2: =_xlfn.TEXTJOIN("; ",TRUE(),$AV2,$AW2,IF($AP2>0,"Evidence missing or unusable","")) | W2: Good: one-page charter naming business purpose, accountable owner, user groups, and intended decisions. Evidence: charter, Confluence page, product ticket. Partial: documented but owner or intended decisions unclear. Advisory map (partial): NIST AI RMF Govern. | AA2: =IF($AN2>0,$A2,"") | AB2: =IF($AO2>0,$A2,"") | AC2: =IF($AQ2>0,$A2&" ("&$U2&")","") | AD2: Major | AF2: =IF(OR(IFERROR(NOT(OR($J2="",$J2="Yes",$J2="No")),TRUE()),IFERROR(IF($E2="",$I2="Yes",NOT(OR($E2="Blocker",$E2="Major",$E2="Moderate",$E2="Minor"))),TRUE()),IFERROR(IF($J2<>"",$T2="",FALSE()),TRUE()),IFERROR(IF(AND($A2="2.7",$I2="Yes",p_confidential="Yes"),$E2<>"Blocker",FALSE()),TRUE()),IFERROR(IF(AND($A2="5.8",$I2="Yes"),OR($E2="Moderate",$E2="Minor"),FALSE()),TRUE()),IF(IFERROR(AND($J2="No",$AI2="Yes",OR($AD2="Blocker",AND($A2="2.7",p_confidential="Yes"))),FALSE()),NOT(AND(IFERROR($X2<>"",FALSE()),IFERROR($Y2<>"",FALSE()),IFERROR(AND(ISNUMBER($Z2),$Z2>=DATE(2020,1,1),$Z2<=DATE(2100,12,31)),FALSE()))),FALSE()),IF(IFERROR(IF(OR($E2="Blocker",$E2="Major",$E2="Moderate",$E2="Minor"),$F2<IF($AD2="Blocker",Lookups!$B$8,IF($AD2="Major",Lookups!$B$9,IF($AD2="Moderate",Lookups!$B$10,Lookups!$B$11))),FALSE()),FALSE()),NOT(AND(IFERROR($T2<>"",FALSE()),IFERROR($Y2<>"",FALSE()),IF(IFERROR($Z2<>"",FALSE()),IFERROR(AND(ISNUMBER($Z2),$Z2>=DATE(2020,1,1),$Z2<=DATE(2100,12,31)),FALSE()),NOT(ISERROR($Z2))))),FALSE())),1,0) -> 0 | AG2: =IF(OR(ISERROR($E2),ISERROR($G2),ISERROR($H2),ISERROR($J2),ISERROR($K2),ISERROR($O2),ISERROR($P2),ISERROR($Q2),ISERROR($R2),ISERROR($S2),ISERROR($T2),ISERROR($X2),ISERROR($Y2),ISERROR($Z2)),1,0) -> 0 | AH2: =IF($AF2>0,$A2&" ("&$AV2&")","") | AI2: =IFERROR("Yes","Yes") -> Yes | AJ2: =IF(IFERROR(NOT(OR($K2="",$K2="Yes",$K2="Partial",$K2="No",$K2="N/A")),TRUE()),1,0) -> 0 | AK2: =IF(OR(IFERROR(IF($G2="",AND($I2="Yes",$K2<>""),IF(ISNUMBER($G2),OR($G2<1,$G2>5,$G2<>INT($G2)),TRUE())),TRUE()),IFERROR(IF($H2="",AND($I2="Yes",$K2<>""),IF(ISNUMBER($H2),OR($H2<1,$H2>5,$H2<>INT($H2)),TRUE())),TRUE())),1,0) -> 0 | AL2: =IF(IFERROR(NOT(OR($S2="",$S2="Open",$S2="In progress",$S2="Remediated",$S2="Accepted Risk",$S2="Not applicable")),TRUE()),1,0) -> 0 | AM2: =IF(OR(IFERROR(IF($S2="Accepted Risk",OR($X2="",$Y2="",$Z2=""),FALSE()),TRUE()),IF(IFERROR($Z2<>"",FALSE()),NOT(IFERROR(AND(ISNUMBER($Z2),$Z2>=DATE(2020,1,1),$Z2<=DATE(2100,12,31)),FALSE())),ISERROR($Z2))),1,0) -> 0 | AN2: =IF(IFERROR(AND($I2="Yes",$K2="N/A"),FALSE()),1,0) -> 0 | AO2: =IF(IFERROR(IF($J2<>"",$T2="",FALSE()),TRUE()),1,0) -> 0 | AP2: =IF(IFERROR(IF($I2="Yes",IF(OR($K2="Yes",$K2="Partial"),IF(ISERROR($O2),TRUE(),$O2=""),FALSE()),FALSE()),FALSE()),1,0) -> 0 | AQ2: =IF(OR($AF2>0,$AG2>0,$AJ2>0,$AK2>0,$AL2>0,$AM2>0,$AN2>0,$AO2>0),1,0) -> 0 | AR2: =IF(IFERROR(AND($I2="Yes",OR($K2="Yes",$K2="Partial",$K2="No")),FALSE()),1,0) -> 0 | AS2: =IFERROR(IF($AR2=1,$F2*$L2,0),0) -> 0 | AT2: =IFERROR(IF($AR2=1,$F2,0),0) -> 0 | AU2: =_xlfn.TEXTJOIN(", ",TRUE(),IF(ISERROR($E2),"E2",""),IF(ISERROR($G2),"G2",""),IF(ISERROR($H2),"H2",""),IF(ISERROR($J2),"J2",""),IF(ISERROR($K2),"K2",""),IF(ISERROR($O2),"O2",""),IF(ISERROR($P2),"P2",""),IF(ISERROR($Q2),"Q2",""),IF(ISERROR($R2),"R2",""),IF(ISERROR($S2),"S2",""),IF(ISERROR($T2),"T2",""),IF(ISERROR($X2),"X2",""),IF(ISERROR($Y2),"Y2",""),IF(ISERROR($Z2),"Z2","")) | AV2: =_xlfn.TEXTJOIN("; ",TRUE(),IF(IFERROR(NOT(OR($J2="",$J2="Yes",$J2="No")),TRUE()),"Invalid override value (J)",""),IF(IFERROR(IF($E2="",$I2="Yes",NOT(OR($E2="Blocker",$E2="Major",$E2="Moderate",$E2="Minor"))),TRUE()),"Invalid or missing criticality (E)",""),IF(IFERROR(IF($J2<>"",$T2="",FALSE()),TRUE()),"Override rationale missing / invalid (T)",""),IF(IFERROR(IF(AND($A2="2.7",$I2="Yes",p_confidential="Yes"),$E2<>"Blocker",FALSE()),TRUE()),"2.7 must be Blocker when S4 = Yes",""),IF(IFERROR(IF(AND($A2="5.8",$I2="Yes"),OR($E2="Moderate",$E2="Minor"),FALSE()),TRUE()),"5.8 should be at least Major",""),IF(IF(IFERROR(AND($J2="No",$AI2="Yes",OR($AD2="Blocker",AND($A2="2.7",p_confidential="Yes"))),FALSE()),NOT(AND(IFERROR($X2<>"",FALSE()),IFERROR($Y2<>"",FALSE()),IFERROR(AND(ISNUMBER($Z2),$Z2>=DATE(2020,1,1),$Z2<=DATE(2100,12,31)),FALSE()))),FALSE()),"Blocker de-scope review missing / invalid (X-Z)",""),IF(IF(IFERROR(IF(OR($E2="Blocker",$E2="Major",$E2="Moderate",$E2="Minor"),$F2<IF($AD2="Blocker",Lookups!$B$8,IF($AD2="Major",Lookups!$B$9,IF($AD2="Moderate",Lookups!$B$10,Lookups!$B$11))),FALSE()),FALSE()),NOT(AND(IFERROR($T2<>"",FALSE()),IFERROR($Y2<>"",FALSE()),IF(IFERROR($Z2<>"",FALSE()),IFERROR(AND(ISNUMBER($Z2),$Z2>=DATE(2020,1,1),$Z2<=DATE(2100,12,31)),FALSE()),NOT(ISERROR($Z2))))),FALSE()),"Criticality below baseline: review missing / invalid (T,Y,Z)","")) | AW2: =_xlfn.TEXTJOIN("; ",TRUE(),IF($AJ2>0,"Invalid response value (K)",""),IF($AK2>0,"Likelihood/Impact missing or not integer 1-5 (G,H)",""),IF($AL2>0,"Invalid status value (S)",""),IF($AM2>0,_xlfn.TEXTJOIN("; ",TRUE(),IF(IFERROR(AND($S2="Accepted Risk",$X2=""),FALSE()),"Exemption reference (X) missing",""),IF(IFERROR(AND($S2="Accepted Risk",$Y2=""),FALSE()),"Exemption approver (Y) missing",""),IF(IFERROR(AND($S2="Accepted Risk",$Z2=""),FALSE()),"Exemption date (Z) missing",""),IF(ISERROR($Z2),"Exemption date (Z) invalid - error value",IF(IFERROR(AND($Z2<>"",NOT(AND(ISNUMBER($Z2),$Z2>=DATE(2020,1,1),$Z2<=DATE(2100,12,31)))),FALSE()),"Exemption date (Z) invalid - enter a real date","")),IF(OR(ISERROR($S2),ISERROR($X2),ISERROR($Y2)),"Exemption inputs contain an error value (S,X,Y)","")),""),IF($AG2>0,"Input/calculation fault at "&$AU2,""),IF($AN2>0,"N/A on applicable row",""))
A3: 1.2 | B3: Use Case & Data | C3: Auto: always | D3: Data classification is defined, including personal, confidential, regulated, and export-controlled data. | E3: Blocker | F3: =IFERROR(IF($E3="Blocker",Lookups!$B$8,IF($E3="Major",Lookups!$B$9,IF($E3="Moderate",Lookups!$B$10,IF($E3="Minor",Lookups!$B$11,0)))),0) -> 5 | G3: 4 | H3: 5 | I3: =IFERROR(IF(OR($J3="Yes",$J3="No"),$J3,"Yes"),"Yes") -> Yes | L3: =IFERROR(IF(OR($I3="No",$K3="N/A"),"",IF($K3="Yes",1,IF($K3="Partial",0.5,IF($K3="No",0,"")))),"") | M3: =IFERROR(IF(OR($I3="No",$K3="N/A"),"",$F3*IF(OR($G3="",NOT(ISNUMBER($G3))),3,$G3)*IF(OR($H3="",NOT(ISNUMBER($H3))),3,$H3)*IF($K3="",1,1-$L3)),"") -> 100 | N3: =IFERROR(IF(OR($I3="No",$K3="N/A",$K3=""),"",IF(AND(IFERROR(AND($S3="Accepted Risk",$AM3=0),FALSE()),OR(AND($E3="Blocker",OR($K3="No",$K3="Partial")),AND($E3="Major",$K3="No"))),IF(AND($E3="Blocker",$K3="No"),"BLOCK",IF(AND($E3="Blocker",$K3="Partial"),IF(p_stage="Pilot / PoC","ESCALATE","BLOCK"),IF(AND($E3="Major",$K3="No"),"ESCALATE","")))&" (exempted)",IF(AND($E3="Blocker",$K3="No"),"BLOCK",IF(AND($E3="Blocker",$K3="Partial"),IF(p_stage="Pilot / PoC","ESCALATE","BLOCK"),IF(AND($E3="Major",$K3="No"),"ESCALATE",""))))),"") | U3: =_xlfn.TEXTJOIN("; ",TRUE(),$AV3,$AW3,IF($AP3>0,"Evidence missing or unusable","")) | W3: Good: classification scheme (personal / confidential / regulated / export-controlled) applied to all LLM inputs, outputs, prompts, logs, and retrieval corpora. Evidence: policy + data inventory. Partial: scheme exists but not applied to LLM data flows. Advisory map (partial): AI Act Art. 10. | AA3: =IF($AN3>0,$A3,"") | AB3: =IF($AO3>0,$A3,"") | AC3: =IF($AQ3>0,$A3&" ("&$U3&")","") | AD3: Blocker | AF3: =IF(OR(IFERROR(NOT(OR($J3="",$J3="Yes",$J3="No")),TRUE()),IFERROR(IF($E3="",$I3="Yes",NOT(OR($E3="Blocker",$E3="Major",$E3="Moderate",$E3="Minor"))),TRUE()),IFERROR(IF($J3<>"",$T3="",FALSE()),TRUE()),IFERROR(IF(AND($A3="2.7",$I3="Yes",p_confidential="Yes"),$E3<>"Blocker",FALSE()),TRUE()),IFERROR(IF(AND($A3="5.8",$I3="Yes"),OR($E3="Moderate",$E3="Minor"),FALSE()),TRUE()),IF(IFERROR(AND($J3="No",$AI3="Yes",OR($AD3="Blocker",AND($A3="2.7",p_confidential="Yes"))),FALSE()),NOT(AND(IFERROR($X3<>"",FALSE()),IFERROR($Y3<>"",FALSE()),IFERROR(AND(ISNUMBER($Z3),$Z3>=DATE(2020,1,1),$Z3<=DATE(2100,12,31)),FALSE()))),FALSE()),IF(IFERROR(IF(OR($E3="Blocker",$E3="Major",$E3="Moderate",$E3="Minor"),$F3<IF($AD3="Blocker",Lookups!$B$8,IF($AD3="Major",Lookups!$B$9,IF($AD3="Moderate",Lookups!$B$10,Lookups!$B$11))),FALSE()),FALSE()),NOT(AND(IFERROR($T3<>"",FALSE()),IFERROR($Y3<>"",FALSE()),IF(IFERROR($Z3<>"",FALSE()),IFERROR(AND(ISNUMBER($Z3),$Z3>=DATE(2020,1,1),$Z3<=DATE(2100,12,31)),FALSE()),NOT(ISERROR($Z3))))),FALSE())),1,0) -> 0 | AG3: =IF(OR(ISERROR($E3),ISERROR($G3),ISERROR($H3),ISERROR($J3),ISERROR($K3),ISERROR($O3),ISERROR($P3),ISERROR($Q3),ISERROR($R3),ISERROR($S3),ISERROR($T3),ISERROR($X3),ISERROR($Y3),ISERROR($Z3)),1,0) -> 0 | AH3: =IF($AF3>0,$A3&" ("&$AV3&")","") | AI3: =IFERROR("Yes","Yes") -> Yes | AJ3: =IF(IFERROR(NOT(OR($K3="",$K3="Yes",$K3="Partial",$K3="No",$K3="N/A")),TRUE()),1,0) -> 0 | AK3: =IF(OR(IFERROR(IF($G3="",AND($I3="Yes",$K3<>""),IF(ISNUMBER($G3),OR($G3<1,$G3>5,$G3<>INT($G3)),TRUE())),TRUE()),IFERROR(IF($H3="",AND($I3="Yes",$K3<>""),IF(ISNUMBER($H3),OR($H3<1,$H3>5,$H3<>INT($H3)),TRUE())),TRUE())),1,0) -> 0 | AL3: =IF(IFERROR(NOT(OR($S3="",$S3="Open",$S3="In progress",$S3="Remediated",$S3="Accepted Risk",$S3="Not applicable")),TRUE()),1,0) -> 0 | AM3: =IF(OR(IFERROR(IF($S3="Accepted Risk",OR($X3="",$Y3="",$Z3=""),FALSE()),TRUE()),IF(IFERROR($Z3<>"",FALSE()),NOT(IFERROR(AND(ISNUMBER($Z3),$Z3>=DATE(2020,1,1),$Z3<=DATE(2100,12,31)),FALSE())),ISERROR($Z3))),1,0) -> 0 | AN3: =IF(IFERROR(AND($I3="Yes",$K3="N/A"),FALSE()),1,0) -> 0 | AO3: =IF(IFERROR(IF($J3<>"",$T3="",FALSE()),TRUE()),1,0) -> 0 | AP3: =IF(IFERROR(IF($I3="Yes",IF(OR($K3="Yes",$K3="Partial"),IF(ISERROR($O3),TRUE(),$O3=""),FALSE()),FALSE()),FALSE()),1,0) -> 0 | AQ3: =IF(OR($AF3>0,$AG3>0,$AJ3>0,$AK3>0,$AL3>0,$AM3>0,$AN3>0,$AO3>0),1,0) -> 0 | AR3: =IF(IFERROR(AND($I3="Yes",OR($K3="Yes",$K3="Partial",$K3="No")),FALSE()),1,0) -> 0 | AS3: =IFERROR(IF($AR3=1,$F3*$L3,0),0) -> 0 | AT3: =IFERROR(IF($AR3=1,$F3,0),0) -> 0 | AU3: =_xlfn.TEXTJOIN(", ",TRUE(),IF(ISERROR($E3),"E3",""),IF(ISERROR($G3),"G3",""),IF(ISERROR($H3),"H3",""),IF(ISERROR($J3),"J3",""),IF(ISERROR($K3),"K3",""),IF(ISERROR($O3),"O3",""),IF(ISERROR($P3),"P3",""),IF(ISERROR($Q3),"Q3",""),IF(ISERROR($R3),"R3",""),IF(ISERROR($S3),"S3",""),IF(ISERROR($T3),"T3",""),IF(ISERROR($X3),"X3",""),IF(ISERROR($Y3),"Y3",""),IF(ISERROR($Z3),"Z3","")) | AV3: =_xlfn.TEXTJOIN("; ",TRUE(),IF(IFERROR(NOT(OR($J3="",$J3="Yes",$J3="No")),TRUE()),"Invalid override value (J)",""),IF(IFERROR(IF($E3="",$I3="Yes",NOT(OR($E3="Blocker",$E3="Major",$E3="Moderate",$E3="Minor"))),TRUE()),"Invalid or missing criticality (E)",""),IF(IFERROR(IF($J3<>"",$T3="",FALSE()),TRUE()),"Override rationale missing / invalid (T)",""),IF(IFERROR(IF(AND($A3="2.7",$I3="Yes",p_confidential="Yes"),$E3<>"Blocker",FALSE()),TRUE()),"2.7 must be Blocker when S4 = Yes",""),IF(IFERROR(IF(AND($A3="5.8",$I3="Yes"),OR($E3="Moderate",$E3="Minor"),FALSE()),TRUE()),"5.8 should be at least Major",""),IF(IF(IFERROR(AND($J3="No",$AI3="Yes",OR($AD3="Blocker",AND($A3="2.7",p_confidential="Yes"))),FALSE()),NOT(AND(IFERROR($X3<>"",FALSE()),IFERROR($Y3<>"",FALSE()),IFERROR(AND(ISNUMBER($Z3),$Z3>=DATE(2020,1,1),$Z3<=DATE(2100,12,31)),FALSE()))),FALSE()),"Blocker de-scope review missing / invalid (X-Z)",""),IF(IF(IFERROR(IF(OR($E3="Blocker",$E3="Major",$E3="Moderate",$E3="Minor"),$F3<IF($AD3="Blocker",Lookups!$B$8,IF($AD3="Major",Lookups!$B$9,IF($AD3="Moderate",Lookups!$B$10,Lookups!$B$11))),FALSE()),FALSE()),NOT(AND(IFERROR($T3<>"",FALSE()),IFERROR($Y3<>"",FALSE()),IF(IFERROR($Z3<>"",FALSE()),IFERROR(AND(ISNUMBER($Z3),$Z3>=DATE(2020,1,1),$Z3<=DATE(2100,12,31)),FALSE()),NOT(ISERROR($Z3))))),FALSE()),"Criticality below baseline: review missing / invalid (T,Y,Z)","")) | AW3: =_xlfn.TEXTJOIN("; ",TRUE(),IF($AJ3>0,"Invalid response value (K)",""),IF($AK3>0,"Likelihood/Impact missing or not integer 1-5 (G,H)",""),IF($AL3>0,"Invalid status value (S)",""),IF($AM3>0,_xlfn.TEXTJOIN("; ",TRUE(),IF(IFERROR(AND($S3="Accepted Risk",$X3=""),FALSE()),"Exemption reference (X) missing",""),IF(IFERROR(AND($S3="Accepted Risk",$Y3=""),FALSE()),"Exemption approver (Y) missing",""),IF(IFERROR(AND($S3="Accepted Risk",$Z3=""),FALSE()),"Exemption date (Z) missing",""),IF(ISERROR($Z3),"Exemption date (Z) invalid - error value",IF(IFERROR(AND($Z3<>"",NOT(AND(ISNUMBER($Z3),$Z3>=DATE(2020,1,1),$Z3<=DATE(2100,12,31)))),FALSE()),"Exemption date (Z) invalid - enter a real date","")),IF(OR(ISERROR($S3),ISERROR($X3),ISERROR($Y3)),"Exemption inputs contain an error value (S,X,Y)","")),""),IF($AG3>0,"Input/calculation fault at "&$AU3,""),IF($AN3>0,"N/A on applicable row",""))
A4: 1.3 | B4: Use Case & Data | C4: Auto: unless S5 = No | D4: AI Act classification is completed: prohibited, high-risk, GPAI dependency, deployer/provider role, and transparency obligations. | E4: Blocker | F4: =IFERROR(IF($E4="Blocker",Lookups!$B$8,IF($E4="Major",Lookups!$B$9,IF($E4="Moderate",Lookups!$B$10,IF($E4="Minor",Lookups!$B$11,0)))),0) -> 5 | G4: 3 | H4: 5 | I4: =IFERROR(IF(OR($J4="Yes",$J4="No"),$J4,IF(p_eu="No","No","Yes")),"Yes") -> Yes | L4: =IFERROR(IF(OR($I4="No",$K4="N/A"),"",IF($K4="Yes",1,IF($K4="Partial",0.5,IF($K4="No",0,"")))),"") | M4: =IFERROR(IF(OR($I4="No",$K4="N/A"),"",$F4*IF(OR($G4="",NOT(ISNUMBER($G4))),3,$G4)*IF(OR($H4="",NOT(ISNUMBER($H4))),3,$H4)*IF($K4="",1,1-$L4)),"") -> 75 | N4: =IFERROR(IF(OR($I4="No",$K4="N/A",$K4=""),"",IF(AND(IFERROR(AND($S4="Accepted Risk",$AM4=0),FALSE()),OR(AND($E4="Blocker",OR($K4="No",$K4="Partial")),AND($E4="Major",$K4="No"))),IF(AND($E4="Blocker",$K4="No"),"BLOCK",IF(AND($E4="Blocker",$K4="Partial"),IF(p_stage="Pilot / PoC","ESCALATE","BLOCK"),IF(AND($E4="Major",$K4="No"),"ESCALATE","")))&" (exempted)",IF(AND($E4="Blocker",$K4="No"),"BLOCK",IF(AND($E4="Blocker",$K4="Partial"),IF(p_stage="Pilot / PoC","ESCALATE","BLOCK"),IF(AND($E4="Major",$K4="No"),"ESCALATE",""))))),"") | U4: =_xlfn.TEXTJOIN("; ",TRUE(),$AV4,$AW4,IF($AP4>0,"Evidence missing or unusable","")) | W4: Good: documented AI Act classification with rationale: prohibited-practices screen, Annex III high-risk check, GPAI dependency, deployer/provider role, transparency duties. Evidence: legal assessment memo. Partial: classification done, rationale or role unclear. Advisory map (partial): AI Act Art. 5, 6, Annex III. | AA4: =IF($AN4>0,$A4,"") | AB4: =IF($AO4>0,$A4,"") | AC4: =IF($AQ4>0,$A4&" ("&$U4&")","") | AD4: Blocker | AF4: =IF(OR(IFERROR(NOT(OR($J4="",$J4="Yes",$J4="No")),TRUE()),IFERROR(IF($E4="",$I4="Yes",NOT(OR($E4="Blocker",$E4="Major",$E4="Moderate",$E4="Minor"))),TRUE()),IFERROR(IF($J4<>"",$T4="",FALSE()),TRUE()),IFERROR(IF(AND($A4="2.7",$I4="Yes",p_confidential="Yes"),$E4<>"Blocker",FALSE()),TRUE()),IFERROR(IF(AND($A4="5.8",$I4="Yes"),OR($E4="Moderate",$E4="Minor"),FALSE()),TRUE()),IF(IFERROR(AND($J4="No",$AI4="Yes",OR($AD4="Blocker",AND($A4="2.7",p_confidential="Yes"))),FALSE()),NOT(AND(IFERROR($X4<>"",FALSE()),IFERROR($Y4<>"",FALSE()),IFERROR(AND(ISNUMBER($Z4),$Z4>=DATE(2020,1,1),$Z4<=DATE(2100,12,31)),FALSE()))),FALSE()),IF(IFERROR(IF(OR($E4="Blocker",$E4="Major",$E4="Moderate",$E4="Minor"),$F4<IF($AD4="Blocker",Lookups!$B$8,IF($AD4="Major",Lookups!$B$9,IF($AD4="Moderate",Lookups!$B$10,Lookups!$B$11))),FALSE()),FALSE()),NOT(AND(IFERROR($T4<>"",FALSE()),IFERROR($Y4<>"",FALSE()),IF(IFERROR($Z4<>"",FALSE()),IFERROR(AND(ISNUMBER($Z4),$Z4>=DATE(2020,1,1),$Z4<=DATE(2100,12,31)),FALSE()),NOT(ISERROR($Z4))))),FALSE())),1,0) -> 0 | AG4: =IF(OR(ISERROR($E4),ISERROR($G4),ISERROR($H4),ISERROR($J4),ISERROR($K4),ISERROR($O4),ISERROR($P4),ISERROR($Q4),ISERROR($R4),ISERROR($S4),ISERROR($T4),ISERROR($X4),ISERROR($Y4),ISERROR($Z4)),1,0) -> 0 | AH4: =IF($AF4>0,$A4&" ("&$AV4&")","") | AI4: =IFERROR(IF(p_eu="No","No","Yes"),"Yes") -> Yes | AJ4: =IF(IFERROR(NOT(OR($K4="",$K4="Yes",$K4="Partial",$K4="No",$K4="N/A")),TRUE()),1,0) -> 0 | AK4: =IF(OR(IFERROR(IF($G4="",AND($I4="Yes",$K4<>""),IF(ISNUMBER($G4),OR($G4<1,$G4>5,$G4<>INT($G4)),TRUE())),TRUE()),IFERROR(IF($H4="",AND($I4="Yes",$K4<>""),IF(ISNUMBER($H4),OR($H4<1,$H4>5,$H4<>INT($H4)),TRUE())),TRUE())),1,0) -> 0 | AL4: =IF(IFERROR(NOT(OR($S4="",$S4="Open",$S4="In progress",$S4="Remediated",$S4="Accepted Risk",$S4="Not applicable")),TRUE()),1,0) -> 0 | AM4: =IF(OR(IFERROR(IF($S4="Accepted Risk",OR($X4="",$Y4="",$Z4=""),FALSE()),TRUE()),IF(IFERROR($Z4<>"",FALSE()),NOT(IFERROR(AND(ISNUMBER($Z4),$Z4>=DATE(2020,1,1),$Z4<=DATE(2100,12,31)),FALSE())),ISERROR($Z4))),1,0) -> 0 | AN4: =IF(IFERROR(AND($I4="Yes",$K4="N/A"),FALSE()),1,0) -> 0 | AO4: =IF(IFERROR(IF($J4<>"",$T4="",FALSE()),TRUE()),1,0) -> 0 | AP4: =IF(IFERROR(IF($I4="Yes",IF(OR($K4="Yes",$K4="Partial"),IF(ISERROR($O4),TRUE(),$O4=""),FALSE()),FALSE()),FALSE()),1,0) -> 0 | AQ4: =IF(OR($AF4>0,$AG4>0,$AJ4>0,$AK4>0,$AL4>0,$AM4>0,$AN4>0,$AO4>0),1,0) -> 0 | AR4: =IF(IFERROR(AND($I4="Yes",OR($K4="Yes",$K4="Partial",$K4="No")),FALSE()),1,0) -> 0 | AS4: =IFERROR(IF($AR4=1,$F4*$L4,0),0) -> 0 | AT4: =IFERROR(IF($AR4=1,$F4,0),0) -> 0 | AU4: =_xlfn.TEXTJOIN(", ",TRUE(),IF(ISERROR($E4),"E4",""),IF(ISERROR($G4),"G4",""),IF(ISERROR($H4),"H4",""),IF(ISERROR($J4),"J4",""),IF(ISERROR($K4),"K4",""),IF(ISERROR($O4),"O4",""),IF(ISERROR($P4),"P4",""),IF(ISERROR($Q4),"Q4",""),IF(ISERROR($R4),"R4",""),IF(ISERROR($S4),"S4",""),IF(ISERROR($T4),"T4",""),IF(ISERROR($X4),"X4",""),IF(ISERROR($Y4),"Y4",""),IF(ISERROR($Z4),"Z4","")) | AV4: =_xlfn.TEXTJOIN("; ",TRUE(),IF(IFERROR(NOT(OR($J4="",$J4="Yes",$J4="No")),TRUE()),"Invalid override value (J)",""),IF(IFERROR(IF($E4="",$I4="Yes",NOT(OR($E4="Blocker",$E4="Major",$E4="Moderate",$E4="Minor"))),TRUE()),"Invalid or missing criticality (E)",""),IF(IFERROR(IF($J4<>"",$T4="",FALSE()),TRUE()),"Override rationale missing / invalid (T)",""),IF(IFERROR(IF(AND($A4="2.7",$I4="Yes",p_confidential="Yes"),$E4<>"Blocker",FALSE()),TRUE()),"2.7 must be Blocker when S4 = Yes",""),IF(IFERROR(IF(AND($A4="5.8",$I4="Yes"),OR($E4="Moderate",$E4="Minor"),FALSE()),TRUE()),"5.8 should be at least Major",""),IF(IF(IFERROR(AND($J4="No",$AI4="Yes",OR($AD4="Blocker",AND($A4="2.7",p_confidential="Yes"))),FALSE()),NOT(AND(IFERROR($X4<>"",FALSE()),IFERROR($Y4<>"",FALSE()),IFERROR(AND(ISNUMBER($Z4),$Z4>=DATE(2020,1,1),$Z4<=DATE(2100,12,31)),FALSE()))),FALSE()),"Blocker de-scope review missing / invalid (X-Z)",""),IF(IF(IFERROR(IF(OR($E4="Blocker",$E4="Major",$E4="Moderate",$E4="Minor"),$F4<IF($AD4="Blocker",Lookups!$B$8,IF($AD4="Major",Lookups!$B$9,IF($AD4="Moderate",Lookups!$B$10,Lookups!$B$11))),FALSE()),FALSE()),NOT(AND(IFERROR($T4<>"",FALSE()),IFERROR($Y4<>"",FALSE()),IF(IFERROR($Z4<>"",FALSE()),IFERROR(AND(ISNUMBER($Z4),$Z4>=DATE(2020,1,1),$Z4<=DATE(2100,12,31)),FALSE()),NOT(ISERROR($Z4))))),FALSE()),"Criticality below baseline: review missing / invalid (T,Y,Z)","")) | AW4: =_xlfn.TEXTJOIN("; ",TRUE(),IF($AJ4>0,"Invalid response value (K)",""),IF($AK4>0,"Likelihood/Impact missing or not integer 1-5 (G,H)",""),IF($AL4>0,"Invalid status value (S)",""),IF($AM4>0,_xlfn.TEXTJOIN("; ",TRUE(),IF(IFERROR(AND($S4="Accepted Risk",$X4=""),FALSE()),"Exemption reference (X) missing",""),IF(IFERROR(AND($S4="Accepted Risk",$Y4=""),FALSE()),"Exemption approver (Y) missing",""),IF(IFERROR(AND($S4="Accepted Risk",$Z4=""),FALSE()),"Exemption date (Z) missing",""),IF(ISERROR($Z4),"Exemption date (Z) invalid - error value",IF(IFERROR(AND($Z4<>"",NOT(AND(ISNUMBER($Z4),$Z4>=DATE(2020,1,1),$Z4<=DATE(2100,12,31)))),FALSE()),"Exemption date (Z) invalid - enter a real date","")),IF(OR(ISERROR($S4),ISERROR($X4),ISERROR($Y4)),"Exemption inputs contain an error value (S,X,Y)","")),""),IF($AG4>0,"Input/calculation fault at "&$AU4,""),IF($AN4>0,"N/A on applicable row",""))
A5: 1.4 | B5: Use Case & Data | C5: Auto: unless S8 = No and S18 = Assist | D5: Human oversight, accountability, escalation, and override are defined for consequential outputs. | E5: Major | F5: =IFERROR(IF($E5="Blocker",Lookups!$B$8,IF($E5="Major",Lookups!$B$9,IF($E5="Moderate",Lookups!$B$10,IF($E5="Minor",Lookups!$B$11,0)))),0) -> 4 | G5: 3 | H5: 5 | I5: =IFERROR(IF(OR($J5="Yes",$J5="No"),$J5,IF(AND(p_decisions="No",p_role="Assist (informs a human)"),"No","Yes")),"Yes") -> Yes | L5: =IFERROR(IF(OR($I5="No",$K5="N/A"),"",IF($K5="Yes",1,IF($K5="Partial",0.5,IF($K5="No",0,"")))),"") | M5: =IFERROR(IF(OR($I5="No",$K5="N/A"),"",$F5*IF(OR($G5="",NOT(ISNUMBER($G5))),3,$G5)*IF(OR($H5="",NOT(ISNUMBER($H5))),3,$H5)*IF($K5="",1,1-$L5)),"") -> 60 | N5: =IFERROR(IF(OR($I5="No",$K5="N/A",$K5=""),"",IF(AND(IFERROR(AND($S5="Accepted Risk",$AM5=0),FALSE()),OR(AND($E5="Blocker",OR($K5="No",$K5="Partial")),AND($E5="Major",$K5="No"))),IF(AND($E5="Blocker",$K5="No"),"BLOCK",IF(AND($E5="Blocker",$K5="Partial"),IF(p_stage="Pilot / PoC","ESCALATE","BLOCK"),IF(AND($E5="Major",$K5="No"),"ESCALATE","")))&" (exempted)",IF(AND($E5="Blocker",$K5="No"),"BLOCK",IF(AND($E5="Blocker",$K5="Partial"),IF(p_stage="Pilot / PoC","ESCALATE","BLOCK"),IF(AND($E5="Major",$K5="No"),"ESCALATE",""))))),"") | U5: =_xlfn.TEXTJOIN("; ",TRUE(),$AV5,$AW5,IF($AP5>0,"Evidence missing or unusable","")) | W5: Good: named human owner for consequential outputs, escalation path, tested ability to override or disable. Evidence: operating procedure, RACI, override test. Partial: oversight defined but override untested. Advisory map (partial): AI Act Art. 14. | AA5: =IF($AN5>0,$A5,"") | AB5: =IF($AO5>0,$A5,"") | AC5: =IF($AQ5>0,$A5&" ("&$U5&")","") | AD5: Major | AF5: =IF(OR(IFERROR(NOT(OR($J5="",$J5="Yes",$J5="No")),TRUE()),IFERROR(IF($E5="",$I5="Yes",NOT(OR($E5="Blocker",$E5="Major",$E5="Moderate",$E5="Minor"))),TRUE()),IFERROR(IF($J5<>"",$T5="",FALSE()),TRUE()),IFERROR(IF(AND($A5="2.7",$I5="Yes",p_confidential="Yes"),$E5<>"Blocker",FALSE()),TRUE()),IFERROR(IF(AND($A5="5.8",$I5="Yes"),OR($E5="Moderate",$E5="Minor"),FALSE()),TRUE()),IF(IFERROR(AND($J5="No",$AI5="Yes",OR($AD5="Blocker",AND($A5="2.7",p_confidential="Yes"))),FALSE()),NOT(AND(IFERROR($X5<>"",FALSE()),IFERROR($Y5<>"",FALSE()),IFERROR(AND(ISNUMBER($Z5),$Z5>=DATE(2020,1,1),$Z5<=DATE(2100,12,31)),FALSE()))),FALSE()),IF(IFERROR(IF(OR($E5="Blocker",$E5="Major",$E5="Moderate",$E5="Minor"),$F5<IF($AD5="Blocker",Lookups!$B$8,IF($AD5="Major",Lookups!$B$9,IF($AD5="Moderate",Lookups!$B$10,Lookups!$B$11))),FALSE()),FALSE()),NOT(AND(IFERROR($T5<>"",FALSE()),IFERROR($Y5<>"",FALSE()),IF(IFERROR($Z5<>"",FALSE()),IFERROR(AND(ISNUMBER($Z5),$Z5>=DATE(2020,1,1),$Z5<=DATE(2100,12,31)),FALSE()),NOT(ISERROR($Z5))))),FALSE())),1,0) -> 0 | AG5: =IF(OR(ISERROR($E5),ISERROR($G5),ISERROR($H5),ISERROR($J5),ISERROR($K5),ISERROR($O5),ISERROR($P5),ISERROR($Q5),ISERROR($R5),ISERROR($S5),ISERROR($T5),ISERROR($X5),ISERROR($Y5),ISERROR($Z5)),1,0) -> 0 | AH5: =IF($AF5>0,$A5&" ("&$AV5&")","") | AI5: =IFERROR(IF(AND(p_decisions="No",p_role="Assist (informs a human)"),"No","Yes"),"Yes") -> Yes | AJ5: =IF(IFERROR(NOT(OR($K5="",$K5="Yes",$K5="Partial",$K5="No",$K5="N/A")),TRUE()),1,0) -> 0 | AK5: =IF(OR(IFERROR(IF($G5="",AND($I5="Yes",$K5<>""),IF(ISNUMBER($G5),OR($G5<1,$G5>5,$G5<>INT($G5)),TRUE())),TRUE()),IFERROR(IF($H5="",AND($I5="Yes",$K5<>""),IF(ISNUMBER($H5),OR($H5<1,$H5>5,$H5<>INT($H5)),TRUE())),TRUE())),1,0) -> 0 | AL5: =IF(IFERROR(NOT(OR($S5="",$S5="Open",$S5="In progress",$S5="Remediated",$S5="Accepted Risk",$S5="Not applicable")),TRUE()),1,0) -> 0 | AM5: =IF(OR(IFERROR(IF($S5="Accepted Risk",OR($X5="",$Y5="",$Z5=""),FALSE()),TRUE()),IF(IFERROR($Z5<>"",FALSE()),NOT(IFERROR(AND(ISNUMBER($Z5),$Z5>=DATE(2020,1,1),$Z5<=DATE(2100,12,31)),FALSE())),ISERROR($Z5))),1,0) -> 0 | AN5: =IF(IFERROR(AND($I5="Yes",$K5="N/A"),FALSE()),1,0) -> 0 | AO5: =IF(IFERROR(IF($J5<>"",$T5="",FALSE()),TRUE()),1,0) -> 0 | AP5: =IF(IFERROR(IF($I5="Yes",IF(OR($K5="Yes",$K5="Partial"),IF(ISERROR($O5),TRUE(),$O5=""),FALSE()),FALSE()),FALSE()),1,0) -> 0 | AQ5: =IF(OR($AF5>0,$AG5>0,$AJ5>0,$AK5>0,$AL5>0,$AM5>0,$AN5>0,$AO5>0),1,0) -> 0 | AR5: =IF(IFERROR(AND($I5="Yes",OR($K5="Yes",$K5="Partial",$K5="No")),FALSE()),1,0) -> 0 | AS5: =IFERROR(IF($AR5=1,$F5*$L5,0),0) -> 0 | AT5: =IFERROR(IF($AR5=1,$F5,0),0) -> 0 | AU5: =_xlfn.TEXTJOIN(", ",TRUE(),IF(ISERROR($E5),"E5",""),IF(ISERROR($G5),"G5",""),IF(ISERROR($H5),"H5",""),IF(ISERROR($J5),"J5",""),IF(ISERROR($K5),"K5",""),IF(ISERROR($O5),"O5",""),IF(ISERROR($P5),"P5",""),IF(ISERROR($Q5),"Q5",""),IF(ISERROR($R5),"R5",""),IF(ISERROR($S5),"S5",""),IF(ISERROR($T5),"T5",""),IF(ISERROR($X5),"X5",""),IF(ISERROR($Y5),"Y5",""),IF(ISERROR($Z5),"Z5","")) | AV5: =_xlfn.TEXTJOIN("; ",TRUE(),IF(IFERROR(NOT(OR($J5="",$J5="Yes",$J5="No")),TRUE()),"Invalid override value (J)",""),IF(IFERROR(IF($E5="",$I5="Yes",NOT(OR($E5="Blocker",$E5="Major",$E5="Moderate",$E5="Minor"))),TRUE()),"Invalid or missing criticality (E)",""),IF(IFERROR(IF($J5<>"",$T5="",FALSE()),TRUE()),"Override rationale missing / invalid (T)",""),IF(IFERROR(IF(AND($A5="2.7",$I5="Yes",p_confidential="Yes"),$E5<>"Blocker",FALSE()),TRUE()),"2.7 must be Blocker when S4 = Yes",""),IF(IFERROR(IF(AND($A5="5.8",$I5="Yes"),OR($E5="Moderate",$E5="Minor"),FALSE()),TRUE()),"5.8 should be at least Major",""),IF(IF(IFERROR(AND($J5="No",$AI5="Yes",OR($AD5="Blocker",AND($A5="2.7",p_confidential="Yes"))),FALSE()),NOT(AND(IFERROR($X5<>"",FALSE()),IFERROR($Y5<>"",FALSE()),IFERROR(AND(ISNUMBER($Z5),$Z5>=DATE(2020,1,1),$Z5<=DATE(2100,12,31)),FALSE()))),FALSE()),"Blocker de-scope review missing / invalid (X-Z)",""),IF(IF(IFERROR(IF(OR($E5="Blocker",$E5="Major",$E5="Moderate",$E5="Minor"),$F5<IF($AD5="Blocker",Lookups!$B$8,IF($AD5="Major",Lookups!$B$9,IF($AD5="Moderate",Lookups!$B$10,Lookups!$B$11))),FALSE()),FALSE()),NOT(AND(IFERROR($T5<>"",FALSE()),IFERROR($Y5<>"",FALSE()),IF(IFERROR($Z5<>"",FALSE()),IFERROR(AND(ISNUMBER($Z5),$Z5>=DATE(2020,1,1),$Z5<=DATE(2100,12,31)),FALSE()),NOT(ISERROR($Z5))))),FALSE()),"Criticality below baseline: review missing / invalid (T,Y,Z)","")) | AW5: =_xlfn.TEXTJOIN("; ",TRUE(),IF($AJ5>0,"Invalid response value (K)",""),IF($AK5>0,"Likelihood/Impact missing or not integer 1-5 (G,H)",""),IF($AL5>0,"Invalid status value (S)",""),IF($AM5>0,_xlfn.TEXTJOIN("; ",TRUE(),IF(IFERROR(AND($S5="Accepted Risk",$X5=""),FALSE()),"Exemption reference (X) missing",""),IF(IFERROR(AND($S5="Accepted Risk",$Y5=""),FALSE()),"Exemption approver (Y) missing",""),IF(IFERROR(AND($S5="Accepted Risk",$Z5=""),FALSE()),"Exemption date (Z) missing",""),IF(ISERROR($Z5),"Exemption date (Z) invalid - error value",IF(IFERROR(AND($Z5<>"",NOT(AND(ISNUMBER($Z5),$Z5>=DATE(2020,1,1),$Z5<=DATE(2100,12,31)))),FALSE()),"Exemption date (Z) invalid - enter a real date","")),IF(OR(ISERROR($S5),ISERROR($X5),ISERROR($Y5)),"Exemption inputs contain an error value (S,X,Y)","")),""),IF($AG5>0,"Input/calculation fault at "&$AU5,""),IF($AN5>0,"N/A on applicable row",""))
A6: 1.5 | B6: Use Case & Data | C6: Auto: unless S12 = None | D6: The system does not execute high-impact actions autonomously without policy, validation, and approval controls. | E6: Blocker | F6: =IFERROR(IF($E6="Blocker",Lookups!$B$8,IF($E6="Major",Lookups!$B$9,IF($E6="Moderate",Lookups!$B$10,IF($E6="Minor",Lookups!$B$11,0)))),0) -> 5 | G6: 3 | H6: 5 | I6: =IFERROR(IF(OR($J6="Yes",$J6="No"),$J6,IF(p_autonomy="None (chat or single completions)","No","Yes")),"Yes") -> Yes | L6: =IFERROR(IF(OR($I6="No",$K6="N/A"),"",IF($K6="Yes",1,IF($K6="Partial",0.5,IF($K6="No",0,"")))),"") | M6: =IFERROR(IF(OR($I6="No",$K6="N/A"),"",$F6*IF(OR($G6="",NOT(ISNUMBER($G6))),3,$G6)*IF(OR($H6="",NOT(ISNUMBER($H6))),3,$H6)*IF($K6="",1,1-$L6)),"") -> 75 | N6: =IFERROR(IF(OR($I6="No",$K6="N/A",$K6=""),"",IF(AND(IFERROR(AND($S6="Accepted Risk",$AM6=0),FALSE()),OR(AND($E6="Blocker",OR($K6="No",$K6="Partial")),AND($E6="Major",$K6="No"))),IF(AND($E6="Blocker",$K6="No"),"BLOCK",IF(AND($E6="Blocker",$K6="Partial"),IF(p_stage="Pilot / PoC","ESCALATE","BLOCK"),IF(AND($E6="Major",$K6="No"),"ESCALATE","")))&" (exempted)",IF(AND($E6="Blocker",$K6="No"),"BLOCK",IF(AND($E6="Blocker",$K6="Partial"),IF(p_stage="Pilot / PoC","ESCALATE","BLOCK"),IF(AND($E6="Major",$K6="No"),"ESCALATE",""))))),"") | U6: =_xlfn.TEXTJOIN("; ",TRUE(),$AV6,$AW6,IF($AP6>0,"Evidence missing or unusable","")) | V6: 4.6, 9.2, 9.4 — 1.5 is the policy-level autonomy gate; 4.6 runtime constraint/logging; 9.2 approval for high-impact actions; 9.4 tool allowlist/sandbox. | W6: Good: written policy of permitted autonomous actions, enforced technically (approval gates, validation, dry-run). Evidence: policy + enforcement config. Partial: policy exists, enforcement incomplete. Advisory map (partial): OWASP LLM06 Excessive Agency; OWASP Agentic ASI01. | AA6: =IF($AN6>0,$A6,"") | AB6: =IF($AO6>0,$A6,"") | AC6: =IF($AQ6>0,$A6&" ("&$U6&")","") | AD6: Blocker | AF6: =IF(OR(IFERROR(NOT(OR($J6="",$J6="Yes",$J6="No")),TRUE()),IFERROR(IF($E6="",$I6="Yes",NOT(OR($E6="Blocker",$E6="Major",$E6="Moderate",$E6="Minor"))),TRUE()),IFERROR(IF($J6<>"",$T6="",FALSE()),TRUE()),IFERROR(IF(AND($A6="2.7",$I6="Yes",p_confidential="Yes"),$E6<>"Blocker",FALSE()),TRUE()),IFERROR(IF(AND($A6="5.8",$I6="Yes"),OR($E6="Moderate",$E6="Minor"),FALSE()),TRUE()),IF(IFERROR(AND($J6="No",$AI6="Yes",OR($AD6="Blocker",AND($A6="2.7",p_confidential="Yes"))),FALSE()),NOT(AND(IFERROR($X6<>"",FALSE()),IFERROR($Y6<>"",FALSE()),IFERROR(AND(ISNUMBER($Z6),$Z6>=DATE(2020,1,1),$Z6<=DATE(2100,12,31)),FALSE()))),FALSE()),IF(IFERROR(IF(OR($E6="Blocker",$E6="Major",$E6="Moderate",$E6="Minor"),$F6<IF($AD6="Blocker",Lookups!$B$8,IF($AD6="Major",Lookups!$B$9,IF($AD6="Moderate",Lookups!$B$10,Lookups!$B$11))),FALSE()),FALSE()),NOT(AND(IFERROR($T6<>"",FALSE()),IFERROR($Y6<>"",FALSE()),IF(IFERROR($Z6<>"",FALSE()),IFERROR(AND(ISNUMBER($Z6),$Z6>=DATE(2020,1,1),$Z6<=DATE(2100,12,31)),FALSE()),NOT(ISERROR($Z6))))),FALSE())),1,0) -> 0 | AG6: =IF(OR(ISERROR($E6),ISERROR($G6),ISERROR($H6),ISERROR($J6),ISERROR($K6),ISERROR($O6),ISERROR($P6),ISERROR($Q6),ISERROR($R6),ISERROR($S6),ISERROR($T6),ISERROR($X6),ISERROR($Y6),ISERROR($Z6)),1,0) -> 0 | AH6: =IF($AF6>0,$A6&" ("&$AV6&")","") | AI6: =IFERROR(IF(p_autonomy="None (chat or single completions)","No","Yes"),"Yes") -> Yes | AJ6: =IF(IFERROR(NOT(OR($K6="",$K6="Yes",$K6="Partial",$K6="No",$K6="N/A")),TRUE()),1,0) -> 0 | AK6: =IF(OR(IFERROR(IF($G6="",AND($I6="Yes",$K6<>""),IF(ISNUMBER($G6),OR($G6<1,$G6>5,$G6<>INT($G6)),TRUE())),TRUE()),IFERROR(IF($H6="",AND($I6="Yes",$K6<>""),IF(ISNUMBER($H6),OR($H6<1,$H6>5,$H6<>INT($H6)),TRUE())),TRUE())),1,0) -> 0 | AL6: =IF(IFERROR(NOT(OR($S6="",$S6="Open",$S6="In progress",$S6="Remediated",$S6="Accepted Risk",$S6="Not applicable")),TRUE()),1,0) -> 0 | AM6: =IF(OR(IFERROR(IF($S6="Accepted Risk",OR($X6="",$Y6="",$Z6=""),FALSE()),TRUE()),IF(IFERROR($Z6<>"",FALSE()),NOT(IFERROR(AND(ISNUMBER($Z6),$Z6>=DATE(2020,1,1),$Z6<=DATE(2100,12,31)),FALSE())),ISERROR($Z6))),1,0) -> 0 | AN6: =IF(IFERROR(AND($I6="Yes",$K6="N/A"),FALSE()),1,0) -> 0 | AO6: =IF(IFERROR(IF($J6<>"",$T6="",FALSE()),TRUE()),1,0) -> 0 | AP6: =IF(IFERROR(IF($I6="Yes",IF(OR($K6="Yes",$K6="Partial"),IF(ISERROR($O6),TRUE(),$O6=""),FALSE()),FALSE()),FALSE()),1,0) -> 0 | AQ6: =IF(OR($AF6>0,$AG6>0,$AJ6>0,$AK6>0,$AL6>0,$AM6>0,$AN6>0,$AO6>0),1,0) -> 0 | AR6: =IF(IFERROR(AND($I6="Yes",OR($K6="Yes",$K6="Partial",$K6="No")),FALSE()),1,0) -> 0 | AS6: =IFERROR(IF($AR6=1,$F6*$L6,0),0) -> 0 | AT6: =IFERROR(IF($AR6=1,$F6,0),0) -> 0 | AU6: =_xlfn.TEXTJOIN(", ",TRUE(),IF(ISERROR($E6),"E6",""),IF(ISERROR($G6),"G6",""),IF(ISERROR($H6),"H6",""),IF(ISERROR($J6),"J6",""),IF(ISERROR($K6),"K6",""),IF(ISERROR($O6),"O6",""),IF(ISERROR($P6),"P6",""),IF(ISERROR($Q6),"Q6",""),IF(ISERROR($R6),"R6",""),IF(ISERROR($S6),"S6",""),IF(ISERROR($T6),"T6",""),IF(ISERROR($X6),"X6",""),IF(ISERROR($Y6),"Y6",""),IF(ISERROR($Z6),"Z6","")) | AV6: =_xlfn.TEXTJOIN("; ",TRUE(),IF(IFERROR(NOT(OR($J6="",$J6="Yes",$J6="No")),TRUE()),"Invalid override value (J)",""),IF(IFERROR(IF($E6="",$I6="Yes",NOT(OR($E6="Blocker",$E6="Major",$E6="Moderate",$E6="Minor"))),TRUE()),"Invalid or missing criticality (E)",""),IF(IFERROR(IF($J6<>"",$T6="",FALSE()),TRUE()),"Override rationale missing / invalid (T)",""),IF(IFERROR(IF(AND($A6="2.7",$I6="Yes",p_confidential="Yes"),$E6<>"Blocker",FALSE()),TRUE()),"2.7 must be Blocker when S4 = Yes",""),IF(IFERROR(IF(AND($A6="5.8",$I6="Yes"),OR($E6="Moderate",$E6="Minor"),FALSE()),TRUE()),"5.8 should be at least Major",""),IF(IF(IFERROR(AND($J6="No",$AI6="Yes",OR($AD6="Blocker",AND($A6="2.7",p_confidential="Yes"))),FALSE()),NOT(AND(IFERROR($X6<>"",FALSE()),IFERROR($Y6<>"",FALSE()),IFERROR(AND(ISNUMBER($Z6),$Z6>=DATE(2020,1,1),$Z6<=DATE(2100,12,31)),FALSE()))),FALSE()),"Blocker de-scope review missing / invalid (X-Z)",""),IF(IF(IFERROR(IF(OR($E6="Blocker",$E6="Major",$E6="Moderate",$E6="Minor"),$F6<IF($AD6="Blocker",Lookups!$B$8,IF($AD6="Major",Lookups!$B$9,IF($AD6="Moderate",Lookups!$B$10,Lookups!$B$11))),FALSE()),FALSE()),NOT(AND(IFERROR($T6<>"",FALSE()),IFERROR($Y6<>"",FALSE()),IF(IFERROR($Z6<>"",FALSE()),IFERROR(AND(ISNUMBER($Z6),$Z6>=DATE(2020,1,1),$Z6<=DATE(2100,12,31)),FALSE()),NOT(ISERROR($Z6))))),FALSE()),"Criticality below baseline: review missing / invalid (T,Y,Z)","")) | AW6: =_xlfn.TEXTJOIN("; ",TRUE(),IF($AJ6>0,"Invalid response value (K)",""),IF($AK6>0,"Likelihood/Impact missing or not integer 1-5 (G,H)",""),IF($AL6>0,"Invalid status value (S)",""),IF($AM6>0,_xlfn.TEXTJOIN("; ",TRUE(),IF(IFERROR(AND($S6="Accepted Risk",$X6=""),FALSE()),"Exemption reference (X) missing",""),IF(IFERROR(AND($S6="Accepted Risk",$Y6=""),FALSE()),"Exemption approver (Y) missing",""),IF(IFERROR(AND($S6="Accepted Risk",$Z6=""),FALSE()),"Exemption date (Z) missing",""),IF(ISERROR($Z6),"Exemption date (Z) invalid - error value",IF(IFERROR(AND($Z6<>"",NOT(AND(ISNUMBER($Z6),$Z6>=DATE(2020,1,1),$Z6<=DATE(2100,12,31)))),FALSE()),"Exemption date (Z) invalid - enter a real date","")),IF(OR(ISERROR($S6),ISERROR($X6),ISERROR($Y6)),"Exemption inputs contain an error value (S,X,Y)","")),""),IF($AG6>0,"Input/calculation fault at "&$AU6,""),IF($AN6>0,"N/A on applicable row",""))
A7: 2.1 | B7: Model & Provider | C7: Auto: always | D7: Model card/system card or equivalent documentation describes intended use, limitations, training/evaluation approach, and known risks. | E7: Major | F7: =IFERROR(IF($E7="Blocker",Lookups!$B$8,IF($E7="Major",Lookups!$B$9,IF($E7="Moderate",Lookups!$B$10,IF($E7="Minor",Lookups!$B$11,0)))),0) -> 4 | G7: 3 | H7: 4 | I7: =IFERROR(IF(OR($J7="Yes",$J7="No"),$J7,"Yes"),"Yes") -> Yes | L7: =IFERROR(IF(OR($I7="No",$K7="N/A"),"",IF($K7="Yes",1,IF($K7="Partial",0.5,IF($K7="No",0,"")))),"") | M7: =IFERROR(IF(OR($I7="No",$K7="N/A"),"",$F7*IF(OR($G7="",NOT(ISNUMBER($G7))),3,$G7)*IF(OR($H7="",NOT(ISNUMBER($H7))),3,$H7)*IF($K7="",1,1-$L7)),"") -> 48 | N7: =IFERROR(IF(OR($I7="No",$K7="N/A",$K7=""),"",IF(AND(IFERROR(AND($S7="Accepted Risk",$AM7=0),FALSE()),OR(AND($E7="Blocker",OR($K7="No",$K7="Partial")),AND($E7="Major",$K7="No"))),IF(AND($E7="Blocker",$K7="No"),"BLOCK",IF(AND($E7="Blocker",$K7="Partial"),IF(p_stage="Pilot / PoC","ESCALATE","BLOCK"),IF(AND($E7="Major",$K7="No"),"ESCALATE","")))&" (exempted)",IF(AND($E7="Blocker",$K7="No"),"BLOCK",IF(AND($E7="Blocker",$K7="Partial"),IF(p_stage="Pilot / PoC","ESCALATE","BLOCK"),IF(AND($E7="Major",$K7="No"),"ESCALATE",""))))),"") | U7: =_xlfn.TEXTJOIN("; ",TRUE(),$AV7,$AW7,IF($AP7>0,"Evidence missing or unusable","")) | W7: Good: current model/system card covering intended use, limitations, training/eval approach, known risks. Evidence: card URL or repo. Partial: card exists but stale or generic. Advisory map (partial): NIST AI RMF Map. | AA7: =IF($AN7>0,$A7,"") | AB7: =IF($AO7>0,$A7,"") | AC7: =IF($AQ7>0,$A7&" ("&$U7&")","") | AD7: Major | AF7: =IF(OR(IFERROR(NOT(OR($J7="",$J7="Yes",$J7="No")),TRUE()),IFERROR(IF($E7="",$I7="Yes",NOT(OR($E7="Blocker",$E7="Major",$E7="Moderate",$E7="Minor"))),TRUE()),IFERROR(IF($J7<>"",$T7="",FALSE()),TRUE()),IFERROR(IF(AND($A7="2.7",$I7="Yes",p_confidential="Yes"),$E7<>"Blocker",FALSE()),TRUE()),IFERROR(IF(AND($A7="5.8",$I7="Yes"),OR($E7="Moderate",$E7="Minor"),FALSE()),TRUE()),IF(IFERROR(AND($J7="No",$AI7="Yes",OR($AD7="Blocker",AND($A7="2.7",p_confidential="Yes"))),FALSE()),NOT(AND(IFERROR($X7<>"",FALSE()),IFERROR($Y7<>"",FALSE()),IFERROR(AND(ISNUMBER($Z7),$Z7>=DATE(2020,1,1),$Z7<=DATE(2100,12,31)),FALSE()))),FALSE()),IF(IFERROR(IF(OR($E7="Blocker",$E7="Major",$E7="Moderate",$E7="Minor"),$F7<IF($AD7="Blocker",Lookups!$B$8,IF($AD7="Major",Lookups!$B$9,IF($AD7="Moderate",Lookups!$B$10,Lookups!$B$11))),FALSE()),FALSE()),NOT(AND(IFERROR($T7<>"",FALSE()),IFERROR($Y7<>"",FALSE()),IF(IFERROR($Z7<>"",FALSE()),IFERROR(AND(ISNUMBER($Z7),$Z7>=DATE(2020,1,1),$Z7<=DATE(2100,12,31)),FALSE()),NOT(ISERROR($Z7))))),FALSE())),1,0) -> 0 | AG7: =IF(OR(ISERROR($E7),ISERROR($G7),ISERROR($H7),ISERROR($J7),ISERROR($K7),ISERROR($O7),ISERROR($P7),ISERROR($Q7),ISERROR($R7),ISERROR($S7),ISERROR($T7),ISERROR($X7),ISERROR($Y7),ISERROR($Z7)),1,0) -> 0 | AH7: =IF($AF7>0,$A7&" ("&$AV7&")","") | AI7: =IFERROR("Yes","Yes") -> Yes | AJ7: =IF(IFERROR(NOT(OR($K7="",$K7="Yes",$K7="Partial",$K7="No",$K7="N/A")),TRUE()),1,0) -> 0 | AK7: =IF(OR(IFERROR(IF($G7="",AND($I7="Yes",$K7<>""),IF(ISNUMBER($G7),OR($G7<1,$G7>5,$G7<>INT($G7)),TRUE())),TRUE()),IFERROR(IF($H7="",AND($I7="Yes",$K7<>""),IF(ISNUMBER($H7),OR($H7<1,$H7>5,$H7<>INT($H7)),TRUE())),TRUE())),1,0) -> 0 | AL7: =IF(IFERROR(NOT(OR($S7="",$S7="Open",$S7="In progress",$S7="Remediated",$S7="Accepted Risk",$S7="Not applicable")),TRUE()),1,0) -> 0 | AM7: =IF(OR(IFERROR(IF($S7="Accepted Risk",OR($X7="",$Y7="",$Z7=""),FALSE()),TRUE()),IF(IFERROR($Z7<>"",FALSE()),NOT(IFERROR(AND(ISNUMBER($Z7),$Z7>=DATE(2020,1,1),$Z7<=DATE(2100,12,31)),FALSE())),ISERROR($Z7))),1,0) -> 0 | AN7: =IF(IFERROR(AND($I7="Yes",$K7="N/A"),FALSE()),1,0) -> 0 | AO7: =IF(IFERROR(IF($J7<>"",$T7="",FALSE()),TRUE()),1,0) -> 0 | AP7: =IF(IFERROR(IF($I7="Yes",IF(OR($K7="Yes",$K7="Partial"),IF(ISERROR($O7),TRUE(),$O7=""),FALSE()),FALSE()),FALSE()),1,0) -> 0 | AQ7: =IF(OR($AF7>0,$AG7>0,$AJ7>0,$AK7>0,$AL7>0,$AM7>0,$AN7>0,$AO7>0),1,0) -> 0 | AR7: =IF(IFERROR(AND($I7="Yes",OR($K7="Yes",$K7="Partial",$K7="No")),FALSE()),1,0) -> 0 | AS7: =IFERROR(IF($AR7=1,$F7*$L7,0),0) -> 0 | AT7: =IFERROR(IF($AR7=1,$F7,0),0) -> 0 | AU7: =_xlfn.TEXTJOIN(", ",TRUE(),IF(ISERROR($E7),"E7",""),IF(ISERROR($G7),"G7",""),IF(ISERROR($H7),"H7",""),IF(ISERROR($J7),"J7",""),IF(ISERROR($K7),"K7",""),IF(ISERROR($O7),"O7",""),IF(ISERROR($P7),"P7",""),IF(ISERROR($Q7),"Q7",""),IF(ISERROR($R7),"R7",""),IF(ISERROR($S7),"S7",""),IF(ISERROR($T7),"T7",""),IF(ISERROR($X7),"X7",""),IF(ISERROR($Y7),"Y7",""),IF(ISERROR($Z7),"Z7","")) | AV7: =_xlfn.TEXTJOIN("; ",TRUE(),IF(IFERROR(NOT(OR($J7="",$J7="Yes",$J7="No")),TRUE()),"Invalid override value (J)",""),IF(IFERROR(IF($E7="",$I7="Yes",NOT(OR($E7="Blocker",$E7="Major",$E7="Moderate",$E7="Minor"))),TRUE()),"Invalid or missing criticality (E)",""),IF(IFERROR(IF($J7<>"",$T7="",FALSE()),TRUE()),"Override rationale missing / invalid (T)",""),IF(IFERROR(IF(AND($A7="2.7",$I7="Yes",p_confidential="Yes"),$E7<>"Blocker",FALSE()),TRUE()),"2.7 must be Blocker when S4 = Yes",""),IF(IFERROR(IF(AND($A7="5.8",$I7="Yes"),OR($E7="Moderate",$E7="Minor"),FALSE()),TRUE()),"5.8 should be at least Major",""),IF(IF(IFERROR(AND($J7="No",$AI7="Yes",OR($AD7="Blocker",AND($A7="2.7",p_confidential="Yes"))),FALSE()),NOT(AND(IFERROR($X7<>"",FALSE()),IFERROR($Y7<>"",FALSE()),IFERROR(AND(ISNUMBER($Z7),$Z7>=DATE(2020,1,1),$Z7<=DATE(2100,12,31)),FALSE()))),FALSE()),"Blocker de-scope review missing / invalid (X-Z)",""),IF(IF(IFERROR(IF(OR($E7="Blocker",$E7="Major",$E7="Moderate",$E7="Minor"),$F7<IF($AD7="Blocker",Lookups!$B$8,IF($AD7="Major",Lookups!$B$9,IF($AD7="Moderate",Lookups!$B$10,Lookups!$B$11))),FALSE()),FALSE()),NOT(AND(IFERROR($T7<>"",FALSE()),IFERROR($Y7<>"",FALSE()),IF(IFERROR($Z7<>"",FALSE()),IFERROR(AND(ISNUMBER($Z7),$Z7>=DATE(2020,1,1),$Z7<=DATE(2100,12,31)),FALSE()),NOT(ISERROR($Z7))))),FALSE()),"Criticality below baseline: review missing / invalid (T,Y,Z)","")) | AW7: =_xlfn.TEXTJOIN("; ",TRUE(),IF($AJ7>0,"Invalid response value (K)",""),IF($AK7>0,"Likelihood/Impact missing or not integer 1-5 (G,H)",""),IF($AL7>0,"Invalid status value (S)",""),IF($AM7>0,_xlfn.TEXTJOIN("; ",TRUE(),IF(IFERROR(AND($S7="Accepted Risk",$X7=""),FALSE()),"Exemption reference (X) missing",""),IF(IFERROR(AND($S7="Accepted Risk",$Y7=""),FALSE()),"Exemption approver (Y) missing",""),IF(IFERROR(AND($S7="Accepted Risk",$Z7=""),FALSE()),"Exemption date (Z) missing",""),IF(ISERROR($Z7),"Exemption date (Z) invalid - error value",IF(IFERROR(AND($Z7<>"",NOT(AND(ISNUMBER($Z7),$Z7>=DATE(2020,1,1),$Z7<=DATE(2100,12,31)))),FALSE()),"Exemption date (Z) invalid - enter a real date","")),IF(OR(ISERROR($S7),ISERROR($X7),ISERROR($Y7)),"Exemption inputs contain an error value (S,X,Y)","")),""),IF($AG7>0,"Input/calculation fault at "&$AU7,""),IF($AN7>0,"N/A on applicable row",""))
A8: 2.2 | B8: Model & Provider | C8: Auto: unless S1 = self-hosted or internal | D8: Provider legal entity, jurisdictions, subcontractors, hosting locations, and support dependencies are documented. | E8: Major | F8: =IFERROR(IF($E8="Blocker",Lookups!$B$8,IF($E8="Major",Lookups!$B$9,IF($E8="Moderate",Lookups!$B$10,IF($E8="Minor",Lookups!$B$11,0)))),0) -> 4 | G8: 3 | H8: 4 | I8: =IFERROR(IF(OR($J8="Yes",$J8="No"),$J8,IF(OR(p_provider="Self-hosted / open weights",p_provider="Internal development"),"No","Yes")),"Yes") -> Yes | L8: =IFERROR(IF(OR($I8="No",$K8="N/A"),"",IF($K8="Yes",1,IF($K8="Partial",0.5,IF($K8="No",0,"")))),"") | M8: =IFERROR(IF(OR($I8="No",$K8="N/A"),"",$F8*IF(OR($G8="",NOT(ISNUMBER($G8))),3,$G8)*IF(OR($H8="",NOT(ISNUMBER($H8))),3,$H8)*IF($K8="",1,1-$L8)),"") -> 48 | N8: =IFERROR(IF(OR($I8="No",$K8="N/A",$K8=""),"",IF(AND(IFERROR(AND($S8="Accepted Risk",$AM8=0),FALSE()),OR(AND($E8="Blocker",OR($K8="No",$K8="Partial")),AND($E8="Major",$K8="No"))),IF(AND($E8="Blocker",$K8="No"),"BLOCK",IF(AND($E8="Blocker",$K8="Partial"),IF(p_stage="Pilot / PoC","ESCALATE","BLOCK"),IF(AND($E8="Major",$K8="No"),"ESCALATE","")))&" (exempted)",IF(AND($E8="Blocker",$K8="No"),"BLOCK",IF(AND($E8="Blocker",$K8="Partial"),IF(p_stage="Pilot / PoC","ESCALATE","BLOCK"),IF(AND($E8="Major",$K8="No"),"ESCALATE",""))))),"") | U8: =_xlfn.TEXTJOIN("; ",TRUE(),$AV8,$AW8,IF($AP8>0,"Evidence missing or unusable","")) | V8: 2.7, 7.3 — 2.2 documents entities/jurisdictions; 2.7 checks country-risk policy; 7.3 is the legal export/sanctions review. | W8: Good: provider legal entity, jurisdictions, subcontractors, hosting regions, support dependencies documented and current. Evidence: contract + subprocessor list. Partial: entity known, subcontractors or hosting unclear. | AA8: =IF($AN8>0,$A8,"") | AB8: =IF($AO8>0,$A8,"") | AC8: =IF($AQ8>0,$A8&" ("&$U8&")","") | AD8: Major | AF8: =IF(OR(IFERROR(NOT(OR($J8="",$J8="Yes",$J8="No")),TRUE()),IFERROR(IF($E8="",$I8="Yes",NOT(OR($E8="Blocker",$E8="Major",$E8="Moderate",$E8="Minor"))),TRUE()),IFERROR(IF($J8<>"",$T8="",FALSE()),TRUE()),IFERROR(IF(AND($A8="2.7",$I8="Yes",p_confidential="Yes"),$E8<>"Blocker",FALSE()),TRUE()),IFERROR(IF(AND($A8="5.8",$I8="Yes"),OR($E8="Moderate",$E8="Minor"),FALSE()),TRUE()),IF(IFERROR(AND($J8="No",$AI8="Yes",OR($AD8="Blocker",AND($A8="2.7",p_confidential="Yes"))),FALSE()),NOT(AND(IFERROR($X8<>"",FALSE()),IFERROR($Y8<>"",FALSE()),IFERROR(AND(ISNUMBER($Z8),$Z8>=DATE(2020,1,1),$Z8<=DATE(2100,12,31)),FALSE()))),FALSE()),IF(IFERROR(IF(OR($E8="Blocker",$E8="Major",$E8="Moderate",$E8="Minor"),$F8<IF($AD8="Blocker",Lookups!$B$8,IF($AD8="Major",Lookups!$B$9,IF($AD8="Moderate",Lookups!$B$10,Lookups!$B$11))),FALSE()),FALSE()),NOT(AND(IFERROR($T8<>"",FALSE()),IFERROR($Y8<>"",FALSE()),IF(IFERROR($Z8<>"",FALSE()),IFERROR(AND(ISNUMBER($Z8),$Z8>=DATE(2020,1,1),$Z8<=DATE(2100,12,31)),FALSE()),NOT(ISERROR($Z8))))),FALSE())),1,0) -> 0 | AG8: =IF(OR(ISERROR($E8),ISERROR($G8),ISERROR($H8),ISERROR($J8),ISERROR($K8),ISERROR($O8),ISERROR($P8),ISERROR($Q8),ISERROR($R8),ISERROR($S8),ISERROR($T8),ISERROR($X8),ISERROR($Y8),ISERROR($Z8)),1,0) -> 0 | AH8: =IF($AF8>0,$A8&" ("&$AV8&")","") | AI8: =IFERROR(IF(OR(p_provider="Self-hosted / open weights",p_provider="Internal development"),"No","Yes"),"Yes") -> Yes | AJ8: =IF(IFERROR(NOT(OR($K8="",$K8="Yes",$K8="Partial",$K8="No",$K8="N/A")),TRUE()),1,0) -> 0 | AK8: =IF(OR(IFERROR(IF($G8="",AND($I8="Yes",$K8<>""),IF(ISNUMBER($G8),OR($G8<1,$G8>5,$G8<>INT($G8)),TRUE())),TRUE()),IFERROR(IF($H8="",AND($I8="Yes",$K8<>""),IF(ISNUMBER($H8),OR($H8<1,$H8>5,$H8<>INT($H8)),TRUE())),TRUE())),1,0) -> 0 | AL8: =IF(IFERROR(NOT(OR($S8="",$S8="Open",$S8="In progress",$S8="Remediated",$S8="Accepted Risk",$S8="Not applicable")),TRUE()),1,0) -> 0 | AM8: =IF(OR(IFERROR(IF($S8="Accepted Risk",OR($X8="",$Y8="",$Z8=""),FALSE()),TRUE()),IF(IFERROR($Z8<>"",FALSE()),NOT(IFERROR(AND(ISNUMBER($Z8),$Z8>=DATE(2020,1,1),$Z8<=DATE(2100,12,31)),FALSE())),ISERROR($Z8))),1,0) -> 0 | AN8: =IF(IFERROR(AND($I8="Yes",$K8="N/A"),FALSE()),1,0) -> 0 | AO8: =IF(IFERROR(IF($J8<>"",$T8="",FALSE()),TRUE()),1,0) -> 0 | AP8: =IF(IFERROR(IF($I8="Yes",IF(OR($K8="Yes",$K8="Partial"),IF(ISERROR($O8),TRUE(),$O8=""),FALSE()),FALSE()),FALSE()),1,0) -> 0 | AQ8: =IF(OR($AF8>0,$AG8>0,$AJ8>0,$AK8>0,$AL8>0,$AM8>0,$AN8>0,$AO8>0),1,0) -> 0 | AR8: =IF(IFERROR(AND($I8="Yes",OR($K8="Yes",$K8="Partial",$K8="No")),FALSE()),1,0) -> 0 | AS8: =IFERROR(IF($AR8=1,$F8*$L8,0),0) -> 0 | AT8: =IFERROR(IF($AR8=1,$F8,0),0) -> 0 | AU8: =_xlfn.TEXTJOIN(", ",TRUE(),IF(ISERROR($E8),"E8",""),IF(ISERROR($G8),"G8",""),IF(ISERROR($H8),"H8",""),IF(ISERROR($J8),"J8",""),IF(ISERROR($K8),"K8",""),IF(ISERROR($O8),"O8",""),IF(ISERROR($P8),"P8",""),IF(ISERROR($Q8),"Q8",""),IF(ISERROR($R8),"R8",""),IF(ISERROR($S8),"S8",""),IF(ISERROR($T8),"T8",""),IF(ISERROR($X8),"X8",""),IF(ISERROR($Y8),"Y8",""),IF(ISERROR($Z8),"Z8","")) | AV8: =_xlfn.TEXTJOIN("; ",TRUE(),IF(IFERROR(NOT(OR($J8="",$J8="Yes",$J8="No")),TRUE()),"Invalid override value (J)",""),IF(IFERROR(IF($E8="",$I8="Yes",NOT(OR($E8="Blocker",$E8="Major",$E8="Moderate",$E8="Minor"))),TRUE()),"Invalid or missing criticality (E)",""),IF(IFERROR(IF($J8<>"",$T8="",FALSE()),TRUE()),"Override rationale missing / invalid (T)",""),IF(IFERROR(IF(AND($A8="2.7",$I8="Yes",p_confidential="Yes"),$E8<>"Blocker",FALSE()),TRUE()),"2.7 must be Blocker when S4 = Yes",""),IF(IFERROR(IF(AND($A8="5.8",$I8="Yes"),OR($E8="Moderate",$E8="Minor"),FALSE()),TRUE()),"5.8 should be at least Major",""),IF(IF(IFERROR(AND($J8="No",$AI8="Yes",OR($AD8="Blocker",AND($A8="2.7",p_confidential="Yes"))),FALSE()),NOT(AND(IFERROR($X8<>"",FALSE()),IFERROR($Y8<>"",FALSE()),IFERROR(AND(ISNUMBER($Z8),$Z8>=DATE(2020,1,1),$Z8<=DATE(2100,12,31)),FALSE()))),FALSE()),"Blocker de-scope review missing / invalid (X-Z)",""),IF(IF(IFERROR(IF(OR($E8="Blocker",$E8="Major",$E8="Moderate",$E8="Minor"),$F8<IF($AD8="Blocker",Lookups!$B$8,IF($AD8="Major",Lookups!$B$9,IF($AD8="Moderate",Lookups!$B$10,Lookups!$B$11))),FALSE()),FALSE()),NOT(AND(IFERROR($T8<>"",FALSE()),IFERROR($Y8<>"",FALSE()),IF(IFERROR($Z8<>"",FALSE()),IFERROR(AND(ISNUMBER($Z8),$Z8>=DATE(2020,1,1),$Z8<=DATE(2100,12,31)),FALSE()),NOT(ISERROR($Z8))))),FALSE()),"Criticality below baseline: review missing / invalid (T,Y,Z)","")) | AW8: =_xlfn.TEXTJOIN("; ",TRUE(),IF($AJ8>0,"Invalid response value (K)",""),IF($AK8>0,"Likelihood/Impact missing or not integer 1-5 (G,H)",""),IF($AL8>0,"Invalid status value (S)",""),IF($AM8>0,_xlfn.TEXTJOIN("; ",TRUE(),IF(IFERROR(AND($S8="Accepted Risk",$X8=""),FALSE()),"Exemption reference (X) missing",""),IF(IFERROR(AND($S8="Accepted Risk",$Y8=""),FALSE()),"Exemption approver (Y) missing",""),IF(IFERROR(AND($S8="Accepted Risk",$Z8=""),FALSE()),"Exemption date (Z) missing",""),IF(ISERROR($Z8),"Exemption date (Z) invalid - error value",IF(IFERROR(AND($Z8<>"",NOT(AND(ISNUMBER($Z8),$Z8>=DATE(2020,1,1),$Z8<=DATE(2100,12,31)))),FALSE()),"Exemption date (Z) invalid - enter a real date","")),IF(OR(ISERROR($S8),ISERROR($X8),ISERROR($Y8)),"Exemption inputs contain an error value (S,X,Y)","")),""),IF($AG8>0,"Input/calculation fault at "&$AU8,""),IF($AN8>0,"N/A on applicable row",""))
A9: 2.3 | B9: Model & Provider | C9: Auto: unless S1 = self-hosted or internal | D9: Independent assurance is available where appropriate, such as ISO 27001, SOC 2, audit report, penetration test, or equivalent. | E9: Moderate | F9: =IFERROR(IF($E9="Blocker",Lookups!$B$8,IF($E9="Major",Lookups!$B$9,IF($E9="Moderate",Lookups!$B$10,IF($E9="Minor",Lookups!$B$11,0)))),0) -> 3 | G9: 3 | H9: 4 | I9: =IFERROR(IF(OR($J9="Yes",$J9="No"),$J9,IF(OR(p_provider="Self-hosted / open weights",p_provider="Internal development"),"No","Yes")),"Yes") -> Yes | L9: =IFERROR(IF(OR($I9="No",$K9="N/A"),"",IF($K9="Yes",1,IF($K9="Partial",0.5,IF($K9="No",0,"")))),"") | M9: =IFERROR(IF(OR($I9="No",$K9="N/A"),"",$F9*IF(OR($G9="",NOT(ISNUMBER($G9))),3,$G9)*IF(OR($H9="",NOT(ISNUMBER($H9))),3,$H9)*IF($K9="",1,1-$L9)),"") -> 36 | N9: =IFERROR(IF(OR($I9="No",$K9="N/A",$K9=""),"",IF(AND(IFERROR(AND($S9="Accepted Risk",$AM9=0),FALSE()),OR(AND($E9="Blocker",OR($K9="No",$K9="Partial")),AND($E9="Major",$K9="No"))),IF(AND($E9="Blocker",$K9="No"),"BLOCK",IF(AND($E9="Blocker",$K9="Partial"),IF(p_stage="Pilot / PoC","ESCALATE","BLOCK"),IF(AND($E9="Major",$K9="No"),"ESCALATE","")))&" (exempted)",IF(AND($E9="Blocker",$K9="No"),"BLOCK",IF(AND($E9="Blocker",$K9="Partial"),IF(p_stage="Pilot / PoC","ESCALATE","BLOCK"),IF(AND($E9="Major",$K9="No"),"ESCALATE",""))))),"") | U9: =_xlfn.TEXTJOIN("; ",TRUE(),$AV9,$AW9,IF($AP9>0,"Evidence missing or unusable","")) | W9: Good: current ISO 27001 / SOC 2 Type II / pentest covering the service actually used. Evidence: certificate or report (NDA fine). Partial: assurance exists but scope excludes the LLM service. | AA9: =IF($AN9>0,$A9,"") | AB9: =IF($AO9>0,$A9,"") | AC9: =IF($AQ9>0,$A9&" ("&$U9&")","") | AD9: Moderate | AF9: =IF(OR(IFERROR(NOT(OR($J9="",$J9="Yes",$J9="No")),TRUE()),IFERROR(IF($E9="",$I9="Yes",NOT(OR($E9="Blocker",$E9="Major",$E9="Moderate",$E9="Minor"))),TRUE()),IFERROR(IF($J9<>"",$T9="",FALSE()),TRUE()),IFERROR(IF(AND($A9="2.7",$I9="Yes",p_confidential="Yes"),$E9<>"Blocker",FALSE()),TRUE()),IFERROR(IF(AND($A9="5.8",$I9="Yes"),OR($E9="Moderate",$E9="Minor"),FALSE()),TRUE()),IF(IFERROR(AND($J9="No",$AI9="Yes",OR($AD9="Blocker",AND($A9="2.7",p_confidential="Yes"))),FALSE()),NOT(AND(IFERROR($X9<>"",FALSE()),IFERROR($Y9<>"",FALSE()),IFERROR(AND(ISNUMBER($Z9),$Z9>=DATE(2020,1,1),$Z9<=DATE(2100,12,31)),FALSE()))),FALSE()),IF(IFERROR(IF(OR($E9="Blocker",$E9="Major",$E9="Moderate",$E9="Minor"),$F9<IF($AD9="Blocker",Lookups!$B$8,IF($AD9="Major",Lookups!$B$9,IF($AD9="Moderate",Lookups!$B$10,Lookups!$B$11))),FALSE()),FALSE()),NOT(AND(IFERROR($T9<>"",FALSE()),IFERROR($Y9<>"",FALSE()),IF(IFERROR($Z9<>"",FALSE()),IFERROR(AND(ISNUMBER($Z9),$Z9>=DATE(2020,1,1),$Z9<=DATE(2100,12,31)),FALSE()),NOT(ISERROR($Z9))))),FALSE())),1,0) -> 0 | AG9: =IF(OR(ISERROR($E9),ISERROR($G9),ISERROR($H9),ISERROR($J9),ISERROR($K9),ISERROR($O9),ISERROR($P9),ISERROR($Q9),ISERROR($R9),ISERROR($S9),ISERROR($T9),ISERROR($X9),ISERROR($Y9),ISERROR($Z9)),1,0) -> 0 | AH9: =IF($AF9>0,$A9&" ("&$AV9&")","") | AI9: =IFERROR(IF(OR(p_provider="Self-hosted / open weights",p_provider="Internal development"),"No","Yes"),"Yes") -> Yes | AJ9: =IF(IFERROR(NOT(OR($K9="",$K9="Yes",$K9="Partial",$K9="No",$K9="N/A")),TRUE()),1,0) -> 0 | AK9: =IF(OR(IFERROR(IF($G9="",AND($I9="Yes",$K9<>""),IF(ISNUMBER($G9),OR($G9<1,$G9>5,$G9<>INT($G9)),TRUE())),TRUE()),IFERROR(IF($H9="",AND($I9="Yes",$K9<>""),IF(ISNUMBER($H9),OR($H9<1,$H9>5,$H9<>INT($H9)),TRUE())),TRUE())),1,0) -> 0 | AL9: =IF(IFERROR(NOT(OR($S9="",$S9="Open",$S9="In progress",$S9="Remediated",$S9="Accepted Risk",$S9="Not applicable")),TRUE()),1,0) -> 0 | AM9: =IF(OR(IFERROR(IF($S9="Accepted Risk",OR($X9="",$Y9="",$Z9=""),FALSE()),TRUE()),IF(IFERROR($Z9<>"",FALSE()),NOT(IFERROR(AND(ISNUMBER($Z9),$Z9>=DATE(2020,1,1),$Z9<=DATE(2100,12,31)),FALSE())),ISERROR($Z9))),1,0) -> 0 | AN9: =IF(IFERROR(AND($I9="Yes",$K9="N/A"),FALSE()),1,0) -> 0 | AO9: =IF(IFERROR(IF($J9<>"",$T9="",FALSE()),TRUE()),1,0) -> 0 | AP9: =IF(IFERROR(IF($I9="Yes",IF(OR($K9="Yes",$K9="Partial"),IF(ISERROR($O9),TRUE(),$O9=""),FALSE()),FALSE()),FALSE()),1,0) -> 0 | AQ9: =IF(OR($AF9>0,$AG9>0,$AJ9>0,$AK9>0,$AL9>0,$AM9>0,$AN9>0,$AO9>0),1,0) -> 0 | AR9: =IF(IFERROR(AND($I9="Yes",OR($K9="Yes",$K9="Partial",$K9="No")),FALSE()),1,0) -> 0 | AS9: =IFERROR(IF($AR9=1,$F9*$L9,0),0) -> 0 | AT9: =IFERROR(IF($AR9=1,$F9,0),0) -> 0 | AU9: =_xlfn.TEXTJOIN(", ",TRUE(),IF(ISERROR($E9),"E9",""),IF(ISERROR($G9),"G9",""),IF(ISERROR($H9),"H9",""),IF(ISERROR($J9),"J9",""),IF(ISERROR($K9),"K9",""),IF(ISERROR($O9),"O9",""),IF(ISERROR($P9),"P9",""),IF(ISERROR($Q9),"Q9",""),IF(ISERROR($R9),"R9",""),IF(ISERROR($S9),"S9",""),IF(ISERROR($T9),"T9",""),IF(ISERROR($X9),"X9",""),IF(ISERROR($Y9),"Y9",""),IF(ISERROR($Z9),"Z9","")) | AV9: =_xlfn.TEXTJOIN("; ",TRUE(),IF(IFERROR(NOT(OR($J9="",$J9="Yes",$J9="No")),TRUE()),"Invalid override value (J)",""),IF(IFERROR(IF($E9="",$I9="Yes",NOT(OR($E9="Blocker",$E9="Major",$E9="Moderate",$E9="Minor"))),TRUE()),"Invalid or missing criticality (E)",""),IF(IFERROR(IF($J9<>"",$T9="",FALSE()),TRUE()),"Override rationale missing / invalid (T)",""),IF(IFERROR(IF(AND($A9="2.7",$I9="Yes",p_confidential="Yes"),$E9<>"Blocker",FALSE()),TRUE()),"2.7 must be Blocker when S4 = Yes",""),IF(IFERROR(IF(AND($A9="5.8",$I9="Yes"),OR($E9="Moderate",$E9="Minor"),FALSE()),TRUE()),"5.8 should be at least Major",""),IF(IF(IFERROR(AND($J9="No",$AI9="Yes",OR($AD9="Blocker",AND($A9="2.7",p_confidential="Yes"))),FALSE()),NOT(AND(IFERROR($X9<>"",FALSE()),IFERROR($Y9<>"",FALSE()),IFERROR(AND(ISNUMBER($Z9),$Z9>=DATE(2020,1,1),$Z9<=DATE(2100,12,31)),FALSE()))),FALSE()),"Blocker de-scope review missing / invalid (X-Z)",""),IF(IF(IFERROR(IF(OR($E9="Blocker",$E9="Major",$E9="Moderate",$E9="Minor"),$F9<IF($AD9="Blocker",Lookups!$B$8,IF($AD9="Major",Lookups!$B$9,IF($AD9="Moderate",Lookups!$B$10,Lookups!$B$11))),FALSE()),FALSE()),NOT(AND(IFERROR($T9<>"",FALSE()),IFERROR($Y9<>"",FALSE()),IF(IFERROR($Z9<>"",FALSE()),IFERROR(AND(ISNUMBER($Z9),$Z9>=DATE(2020,1,1),$Z9<=DATE(2100,12,31)),FALSE()),NOT(ISERROR($Z9))))),FALSE()),"Criticality below baseline: review missing / invalid (T,Y,Z)","")) | AW9: =_xlfn.TEXTJOIN("; ",TRUE(),IF($AJ9>0,"Invalid response value (K)",""),IF($AK9>0,"Likelihood/Impact missing or not integer 1-5 (G,H)",""),IF($AL9>0,"Invalid status value (S)",""),IF($AM9>0,_xlfn.TEXTJOIN("; ",TRUE(),IF(IFERROR(AND($S9="Accepted Risk",$X9=""),FALSE()),"Exemption reference (X) missing",""),IF(IFERROR(AND($S9="Accepted Risk",$Y9=""),FALSE()),"Exemption approver (Y) missing",""),IF(IFERROR(AND($S9="Accepted Risk",$Z9=""),FALSE()),"Exemption date (Z) missing",""),IF(ISERROR($Z9),"Exemption date (Z) invalid - error value",IF(IFERROR(AND($Z9<>"",NOT(AND(ISNUMBER($Z9),$Z9>=DATE(2020,1,1),$Z9<=DATE(2100,12,31)))),FALSE()),"Exemption date (Z) invalid - enter a real date","")),IF(OR(ISERROR($S9),ISERROR($X9),ISERROR($Y9)),"Exemption inputs contain an error value (S,X,Y)","")),""),IF($AG9>0,"Input/calculation fault at "&$AU9,""),IF($AN9>0,"N/A on applicable row",""))
A10: 2.4 | B10: Model & Provider | C10: Auto: unless S2 = Pilot/PoC | D10: Target model version has release notes, lifecycle support, change log, and update/rollback path. | E10: Major | F10: =IFERROR(IF($E10="Blocker",Lookups!$B$8,IF($E10="Major",Lookups!$B$9,IF($E10="Moderate",Lookups!$B$10,IF($E10="Minor",Lookups!$B$11,0)))),0) -> 4 | G10: 3 | H10: 4 | I10: =IFERROR(IF(OR($J10="Yes",$J10="No"),$J10,IF(p_stage="Pilot / PoC","No","Yes")),"Yes") -> Yes | L10: =IFERROR(IF(OR($I10="No",$K10="N/A"),"",IF($K10="Yes",1,IF($K10="Partial",0.5,IF($K10="No",0,"")))),"") | M10: =IFERROR(IF(OR($I10="No",$K10="N/A"),"",$F10*IF(OR($G10="",NOT(ISNUMBER($G10))),3,$G10)*IF(OR($H10="",NOT(ISNUMBER($H10))),3,$H10)*IF($K10="",1,1-$L10)),"") -> 48 | N10: =IFERROR(IF(OR($I10="No",$K10="N/A",$K10=""),"",IF(AND(IFERROR(AND($S10="Accepted Risk",$AM10=0),FALSE()),OR(AND($E10="Blocker",OR($K10="No",$K10="Partial")),AND($E10="Major",$K10="No"))),IF(AND($E10="Blocker",$K10="No"),"BLOCK",IF(AND($E10="Blocker",$K10="Partial"),IF(p_stage="Pilot / PoC","ESCALATE","BLOCK"),IF(AND($E10="Major",$K10="No"),"ESCALATE","")))&" (exempted)",IF(AND($E10="Blocker",$K10="No"),"BLOCK",IF(AND($E10="Blocker",$K10="Partial"),IF(p_stage="Pilot / PoC","ESCALATE","BLOCK"),IF(AND($E10="Major",$K10="No"),"ESCALATE",""))))),"") | U10: =_xlfn.TEXTJOIN("; ",TRUE(),$AV10,$AW10,IF($AP10>0,"Evidence missing or unusable","")) | W10: Good: target version pinned, release notes and lifecycle reviewed, update and rollback path tested. Evidence: release notes, pipeline records. Partial: version pinned, no rollback path. | AA10: =IF($AN10>0,$A10,"") | AB10: =IF($AO10>0,$A10,"") | AC10: =IF($AQ10>0,$A10&" ("&$U10&")","") | AD10: Major | AF10: =IF(OR(IFERROR(NOT(OR($J10="",$J10="Yes",$J10="No")),TRUE()),IFERROR(IF($E10="",$I10="Yes",NOT(OR($E10="Blocker",$E10="Major",$E10="Moderate",$E10="Minor"))),TRUE()),IFERROR(IF($J10<>"",$T10="",FALSE()),TRUE()),IFERROR(IF(AND($A10="2.7",$I10="Yes",p_confidential="Yes"),$E10<>"Blocker",FALSE()),TRUE()),IFERROR(IF(AND($A10="5.8",$I10="Yes"),OR($E10="Moderate",$E10="Minor"),FALSE()),TRUE()),IF(IFERROR(AND($J10="No",$AI10="Yes",OR($AD10="Blocker",AND($A10="2.7",p_confidential="Yes"))),FALSE()),NOT(AND(IFERROR($X10<>"",FALSE()),IFERROR($Y10<>"",FALSE()),IFERROR(AND(ISNUMBER($Z10),$Z10>=DATE(2020,1,1),$Z10<=DATE(2100,12,31)),FALSE()))),FALSE()),IF(IFERROR(IF(OR($E10="Blocker",$E10="Major",$E10="Moderate",$E10="Minor"),$F10<IF($AD10="Blocker",Lookups!$B$8,IF($AD10="Major",Lookups!$B$9,IF($AD10="Moderate",Lookups!$B$10,Lookups!$B$11))),FALSE()),FALSE()),NOT(AND(IFERROR($T10<>"",FALSE()),IFERROR($Y10<>"",FALSE()),IF(IFERROR($Z10<>"",FALSE()),IFERROR(AND(ISNUMBER($Z10),$Z10>=DATE(2020,1,1),$Z10<=DATE(2100,12,31)),FALSE()),NOT(ISERROR($Z10))))),FALSE())),1,0) -> 0 | AG10: =IF(OR(ISERROR($E10),ISERROR($G10),ISERROR($H10),ISERROR($J10),ISERROR($K10),ISERROR($O10),ISERROR($P10),ISERROR($Q10),ISERROR($R10),ISERROR($S10),ISERROR($T10),ISERROR($X10),ISERROR($Y10),ISERROR($Z10)),1,0) -> 0 | AH10: =IF($AF10>0,$A10&" ("&$AV10&")","") | AI10: =IFERROR(IF(p_stage="Pilot / PoC","No","Yes"),"Yes") -> Yes | AJ10: =IF(IFERROR(NOT(OR($K10="",$K10="Yes",$K10="Partial",$K10="No",$K10="N/A")),TRUE()),1,0) -> 0 | AK10: =IF(OR(IFERROR(IF($G10="",AND($I10="Yes",$K10<>""),IF(ISNUMBER($G10),OR($G10<1,$G10>5,$G10<>INT($G10)),TRUE())),TRUE()),IFERROR(IF($H10="",AND($I10="Yes",$K10<>""),IF(ISNUMBER($H10),OR($H10<1,$H10>5,$H10<>INT($H10)),TRUE())),TRUE())),1,0) -> 0 | AL10: =IF(IFERROR(NOT(OR($S10="",$S10="Open",$S10="In progress",$S10="Remediated",$S10="Accepted Risk",$S10="Not applicable")),TRUE()),1,0) -> 0 | AM10: =IF(OR(IFERROR(IF($S10="Accepted Risk",OR($X10="",$Y10="",$Z10=""),FALSE()),TRUE()),IF(IFERROR($Z10<>"",FALSE()),NOT(IFERROR(AND(ISNUMBER($Z10),$Z10>=DATE(2020,1,1),$Z10<=DATE(2100,12,31)),FALSE())),ISERROR($Z10))),1,0) -> 0 | AN10: =IF(IFERROR(AND($I10="Yes",$K10="N/A"),FALSE()),1,0) -> 0 | AO10: =IF(IFERROR(IF($J10<>"",$T10="",FALSE()),TRUE()),1,0) -> 0 | AP10: =IF(IFERROR(IF($I10="Yes",IF(OR($K10="Yes",$K10="Partial"),IF(ISERROR($O10),TRUE(),$O10=""),FALSE()),FALSE()),FALSE()),1,0) -> 0 | AQ10: =IF(OR($AF10>0,$AG10>0,$AJ10>0,$AK10>0,$AL10>0,$AM10>0,$AN10>0,$AO10>0),1,0) -> 0 | AR10: =IF(IFERROR(AND($I10="Yes",OR($K10="Yes",$K10="Partial",$K10="No")),FALSE()),1,0) -> 0 | AS10: =IFERROR(IF($AR10=1,$F10*$L10,0),0) -> 0 | AT10: =IFERROR(IF($AR10=1,$F10,0),0) -> 0 | AU10: =_xlfn.TEXTJOIN(", ",TRUE(),IF(ISERROR($E10),"E10",""),IF(ISERROR($G10),"G10",""),IF(ISERROR($H10),"H10",""),IF(ISERROR($J10),"J10",""),IF(ISERROR($K10),"K10",""),IF(ISERROR($O10),"O10",""),IF(ISERROR($P10),"P10",""),IF(ISERROR($Q10),"Q10",""),IF(ISERROR($R10),"R10",""),IF(ISERROR($S10),"S10",""),IF(ISERROR($T10),"T10",""),IF(ISERROR($X10),"X10",""),IF(ISERROR($Y10),"Y10",""),IF(ISERROR($Z10),"Z10","")) | AV10: =_xlfn.TEXTJOIN("; ",TRUE(),IF(IFERROR(NOT(OR($J10="",$J10="Yes",$J10="No")),TRUE()),"Invalid override value (J)",""),IF(IFERROR(IF($E10="",$I10="Yes",NOT(OR($E10="Blocker",$E10="Major",$E10="Moderate",$E10="Minor"))),TRUE()),"Invalid or missing criticality (E)",""),IF(IFERROR(IF($J10<>"",$T10="",FALSE()),TRUE()),"Override rationale missing / invalid (T)",""),IF(IFERROR(IF(AND($A10="2.7",$I10="Yes",p_confidential="Yes"),$E10<>"Blocker",FALSE()),TRUE()),"2.7 must be Blocker when S4 = Yes",""),IF(IFERROR(IF(AND($A10="5.8",$I10="Yes"),OR($E10="Moderate",$E10="Minor"),FALSE()),TRUE()),"5.8 should be at least Major",""),IF(IF(IFERROR(AND($J10="No",$AI10="Yes",OR($AD10="Blocker",AND($A10="2.7",p_confidential="Yes"))),FALSE()),NOT(AND(IFERROR($X10<>"",FALSE()),IFERROR($Y10<>"",FALSE()),IFERROR(AND(ISNUMBER($Z10),$Z10>=DATE(2020,1,1),$Z10<=DATE(2100,12,31)),FALSE()))),FALSE()),"Blocker de-scope review missing / invalid (X-Z)",""),IF(IF(IFERROR(IF(OR($E10="Blocker",$E10="Major",$E10="Moderate",$E10="Minor"),$F10<IF($AD10="Blocker",Lookups!$B$8,IF($AD10="Major",Lookups!$B$9,IF($AD10="Moderate",Lookups!$B$10,Lookups!$B$11))),FALSE()),FALSE()),NOT(AND(IFERROR($T10<>"",FALSE()),IFERROR($Y10<>"",FALSE()),IF(IFERROR($Z10<>"",FALSE()),IFERROR(AND(ISNUMBER($Z10),$Z10>=DATE(2020,1,1),$Z10<=DATE(2100,12,31)),FALSE()),NOT(ISERROR($Z10))))),FALSE()),"Criticality below baseline: review missing / invalid (T,Y,Z)","")) | AW10: =_xlfn.TEXTJOIN("; ",TRUE(),IF($AJ10>0,"Invalid response value (K)",""),IF($AK10>0,"Likelihood/Impact missing or not integer 1-5 (G,H)",""),IF($AL10>0,"Invalid status value (S)",""),IF($AM10>0,_xlfn.TEXTJOIN("; ",TRUE(),IF(IFERROR(AND($S10="Accepted Risk",$X10=""),FALSE()),"Exemption reference (X) missing",""),IF(IFERROR(AND($S10="Accepted Risk",$Y10=""),FALSE()),"Exemption approver (Y) missing",""),IF(IFERROR(AND($S10="Accepted Risk",$Z10=""),FALSE()),"Exemption date (Z) missing",""),IF(ISERROR($Z10),"Exemption date (Z) invalid - error value",IF(IFERROR(AND($Z10<>"",NOT(AND(ISNUMBER($Z10),$Z10>=DATE(2020,1,1),$Z10<=DATE(2100,12,31)))),FALSE()),"Exemption date (Z) invalid - enter a real date","")),IF(OR(ISERROR($S10),ISERROR($X10),ISERROR($Y10)),"Exemption inputs contain an error value (S,X,Y)","")),""),IF($AG10>0,"Input/calculation fault at "&$AU10,""),IF($AN10>0,"N/A on applicable row",""))
A11: 2.5 | B11: Model & Provider | C11: Auto: unless S1 = internal development | D11: Terms, license, retention, logging, confidentiality, IP, and acceptable use permit the intended company use. | E11: Blocker | F11: =IFERROR(IF($E11="Blocker",Lookups!$B$8,IF($E11="Major",Lookups!$B$9,IF($E11="Moderate",Lookups!$B$10,IF($E11="Minor",Lookups!$B$11,0)))),0) -> 5 | G11: 3 | H11: 5 | I11: =IFERROR(IF(OR($J11="Yes",$J11="No"),$J11,IF(p_provider="Internal development","No","Yes")),"Yes") -> Yes | L11: =IFERROR(IF(OR($I11="No",$K11="N/A"),"",IF($K11="Yes",1,IF($K11="Partial",0.5,IF($K11="No",0,"")))),"") | M11: =IFERROR(IF(OR($I11="No",$K11="N/A"),"",$F11*IF(OR($G11="",NOT(ISNUMBER($G11))),3,$G11)*IF(OR($H11="",NOT(ISNUMBER($H11))),3,$H11)*IF($K11="",1,1-$L11)),"") -> 75 | N11: =IFERROR(IF(OR($I11="No",$K11="N/A",$K11=""),"",IF(AND(IFERROR(AND($S11="Accepted Risk",$AM11=0),FALSE()),OR(AND($E11="Blocker",OR($K11="No",$K11="Partial")),AND($E11="Major",$K11="No"))),IF(AND($E11="Blocker",$K11="No"),"BLOCK",IF(AND($E11="Blocker",$K11="Partial"),IF(p_stage="Pilot / PoC","ESCALATE","BLOCK"),IF(AND($E11="Major",$K11="No"),"ESCALATE","")))&" (exempted)",IF(AND($E11="Blocker",$K11="No"),"BLOCK",IF(AND($E11="Blocker",$K11="Partial"),IF(p_stage="Pilot / PoC","ESCALATE","BLOCK"),IF(AND($E11="Major",$K11="No"),"ESCALATE",""))))),"") | U11: =_xlfn.TEXTJOIN("; ",TRUE(),$AV11,$AW11,IF($AP11>0,"Evidence missing or unusable","")) | W11: Good: legal-reviewed terms covering retention, training-on-data opt-out, logging, confidentiality, IP, acceptable use vs the intended use. Evidence: signed terms + review note. Partial: reviewed with one unresolved clause. | AA11: =IF($AN11>0,$A11,"") | AB11: =IF($AO11>0,$A11,"") | AC11: =IF($AQ11>0,$A11&" ("&$U11&")","") | AD11: Blocker | AF11: =IF(OR(IFERROR(NOT(OR($J11="",$J11="Yes",$J11="No")),TRUE()),IFERROR(IF($E11="",$I11="Yes",NOT(OR($E11="Blocker",$E11="Major",$E11="Moderate",$E11="Minor"))),TRUE()),IFERROR(IF($J11<>"",$T11="",FALSE()),TRUE()),IFERROR(IF(AND($A11="2.7",$I11="Yes",p_confidential="Yes"),$E11<>"Blocker",FALSE()),TRUE()),IFERROR(IF(AND($A11="5.8",$I11="Yes"),OR($E11="Moderate",$E11="Minor"),FALSE()),TRUE()),IF(IFERROR(AND($J11="No",$AI11="Yes",OR($AD11="Blocker",AND($A11="2.7",p_confidential="Yes"))),FALSE()),NOT(AND(IFERROR($X11<>"",FALSE()),IFERROR($Y11<>"",FALSE()),IFERROR(AND(ISNUMBER($Z11),$Z11>=DATE(2020,1,1),$Z11<=DATE(2100,12,31)),FALSE()))),FALSE()),IF(IFERROR(IF(OR($E11="Blocker",$E11="Major",$E11="Moderate",$E11="Minor"),$F11<IF($AD11="Blocker",Lookups!$B$8,IF($AD11="Major",Lookups!$B$9,IF($AD11="Moderate",Lookups!$B$10,Lookups!$B$11))),FALSE()),FALSE()),NOT(AND(IFERROR($T11<>"",FALSE()),IFERROR($Y11<>"",FALSE()),IF(IFERROR($Z11<>"",FALSE()),IFERROR(AND(ISNUMBER($Z11),$Z11>=DATE(2020,1,1),$Z11<=DATE(2100,12,31)),FALSE()),NOT(ISERROR($Z11))))),FALSE())),1,0) -> 0 | AG11: =IF(OR(ISERROR($E11),ISERROR($G11),ISERROR($H11),ISERROR($J11),ISERROR($K11),ISERROR($O11),ISERROR($P11),ISERROR($Q11),ISERROR($R11),ISERROR($S11),ISERROR($T11),ISERROR($X11),ISERROR($Y11),ISERROR($Z11)),1,0) -> 0 | AH11: =IF($AF11>0,$A11&" ("&$AV11&")","") | AI11: =IFERROR(IF(p_provider="Internal development","No","Yes"),"Yes") -> Yes | AJ11: =IF(IFERROR(NOT(OR($K11="",$K11="Yes",$K11="Partial",$K11="No",$K11="N/A")),TRUE()),1,0) -> 0 | AK11: =IF(OR(IFERROR(IF($G11="",AND($I11="Yes",$K11<>""),IF(ISNUMBER($G11),OR($G11<1,$G11>5,$G11<>INT($G11)),TRUE())),TRUE()),IFERROR(IF($H11="",AND($I11="Yes",$K11<>""),IF(ISNUMBER($H11),OR($H11<1,$H11>5,$H11<>INT($H11)),TRUE())),TRUE())),1,0) -> 0 | AL11: =IF(IFERROR(NOT(OR($S11="",$S11="Open",$S11="In progress",$S11="Remediated",$S11="Accepted Risk",$S11="Not applicable")),TRUE()),1,0) -> 0 | AM11: =IF(OR(IFERROR(IF($S11="Accepted Risk",OR($X11="",$Y11="",$Z11=""),FALSE()),TRUE()),IF(IFERROR($Z11<>"",FALSE()),NOT(IFERROR(AND(ISNUMBER($Z11),$Z11>=DATE(2020,1,1),$Z11<=DATE(2100,12,31)),FALSE())),ISERROR($Z11))),1,0) -> 0 | AN11: =IF(IFERROR(AND($I11="Yes",$K11="N/A"),FALSE()),1,0) -> 0 | AO11: =IF(IFERROR(IF($J11<>"",$T11="",FALSE()),TRUE()),1,0) -> 0 | AP11: =IF(IFERROR(IF($I11="Yes",IF(OR($K11="Yes",$K11="Partial"),IF(ISERROR($O11),TRUE(),$O11=""),FALSE()),FALSE()),FALSE()),1,0) -> 0 | AQ11: =IF(OR($AF11>0,$AG11>0,$AJ11>0,$AK11>0,$AL11>0,$AM11>0,$AN11>0,$AO11>0),1,0) -> 0 | AR11: =IF(IFERROR(AND($I11="Yes",OR($K11="Yes",$K11="Partial",$K11="No")),FALSE()),1,0) -> 0 | AS11: =IFERROR(IF($AR11=1,$F11*$L11,0),0) -> 0 | AT11: =IFERROR(IF($AR11=1,$F11,0),0) -> 0 | AU11: =_xlfn.TEXTJOIN(", ",TRUE(),IF(ISERROR($E11),"E11",""),IF(ISERROR($G11),"G11",""),IF(ISERROR($H11),"H11",""),IF(ISERROR($J11),"J11",""),IF(ISERROR($K11),"K11",""),IF(ISERROR($O11),"O11",""),IF(ISERROR($P11),"P11",""),IF(ISERROR($Q11),"Q11",""),IF(ISERROR($R11),"R11",""),IF(ISERROR($S11),"S11",""),IF(ISERROR($T11),"T11",""),IF(ISERROR($X11),"X11",""),IF(ISERROR($Y11),"Y11",""),IF(ISERROR($Z11),"Z11","")) | AV11: =_xlfn.TEXTJOIN("; ",TRUE(),IF(IFERROR(NOT(OR($J11="",$J11="Yes",$J11="No")),TRUE()),"Invalid override value (J)",""),IF(IFERROR(IF($E11="",$I11="Yes",NOT(OR($E11="Blocker",$E11="Major",$E11="Moderate",$E11="Minor"))),TRUE()),"Invalid or missing criticality (E)",""),IF(IFERROR(IF($J11<>"",$T11="",FALSE()),TRUE()),"Override rationale missing / invalid (T)",""),IF(IFERROR(IF(AND($A11="2.7",$I11="Yes",p_confidential="Yes"),$E11<>"Blocker",FALSE()),TRUE()),"2.7 must be Blocker when S4 = Yes",""),IF(IFERROR(IF(AND($A11="5.8",$I11="Yes"),OR($E11="Moderate",$E11="Minor"),FALSE()),TRUE()),"5.8 should be at least Major",""),IF(IF(IFERROR(AND($J11="No",$AI11="Yes",OR($AD11="Blocker",AND($A11="2.7",p_confidential="Yes"))),FALSE()),NOT(AND(IFERROR($X11<>"",FALSE()),IFERROR($Y11<>"",FALSE()),IFERROR(AND(ISNUMBER($Z11),$Z11>=DATE(2020,1,1),$Z11<=DATE(2100,12,31)),FALSE()))),FALSE()),"Blocker de-scope review missing / invalid (X-Z)",""),IF(IF(IFERROR(IF(OR($E11="Blocker",$E11="Major",$E11="Moderate",$E11="Minor"),$F11<IF($AD11="Blocker",Lookups!$B$8,IF($AD11="Major",Lookups!$B$9,IF($AD11="Moderate",Lookups!$B$10,Lookups!$B$11))),FALSE()),FALSE()),NOT(AND(IFERROR($T11<>"",FALSE()),IFERROR($Y11<>"",FALSE()),IF(IFERROR($Z11<>"",FALSE()),IFERROR(AND(ISNUMBER($Z11),$Z11>=DATE(2020,1,1),$Z11<=DATE(2100,12,31)),FALSE()),NOT(ISERROR($Z11))))),FALSE()),"Criticality below baseline: review missing / invalid (T,Y,Z)","")) | AW11: =_xlfn.TEXTJOIN("; ",TRUE(),IF($AJ11>0,"Invalid response value (K)",""),IF($AK11>0,"Likelihood/Impact missing or not integer 1-5 (G,H)",""),IF($AL11>0,"Invalid status value (S)",""),IF($AM11>0,_xlfn.TEXTJOIN("; ",TRUE(),IF(IFERROR(AND($S11="Accepted Risk",$X11=""),FALSE()),"Exemption reference (X) missing",""),IF(IFERROR(AND($S11="Accepted Risk",$Y11=""),FALSE()),"Exemption approver (Y) missing",""),IF(IFERROR(AND($S11="Accepted Risk",$Z11=""),FALSE()),"Exemption date (Z) missing",""),IF(ISERROR($Z11),"Exemption date (Z) invalid - error value",IF(IFERROR(AND($Z11<>"",NOT(AND(ISNUMBER($Z11),$Z11>=DATE(2020,1,1),$Z11<=DATE(2100,12,31)))),FALSE()),"Exemption date (Z) invalid - enter a real date","")),IF(OR(ISERROR($S11),ISERROR($X11),ISERROR($Y11)),"Exemption inputs contain an error value (S,X,Y)","")),""),IF($AG11>0,"Input/calculation fault at "&$AU11,""),IF($AN11>0,"N/A on applicable row",""))
A12: 2.6 | B12: Model & Provider | C12: Auto: unless S2 = Pilot/PoC | D12: Support, patching, incident notification, and end-of-life commitments match business criticality. | E12: Major | F12: =IFERROR(IF($E12="Blocker",Lookups!$B$8,IF($E12="Major",Lookups!$B$9,IF($E12="Moderate",Lookups!$B$10,IF($E12="Minor",Lookups!$B$11,0)))),0) -> 4 | G12: 3 | H12: 4 | I12: =IFERROR(IF(OR($J12="Yes",$J12="No"),$J12,IF(p_stage="Pilot / PoC","No","Yes")),"Yes") -> Yes | L12: =IFERROR(IF(OR($I12="No",$K12="N/A"),"",IF($K12="Yes",1,IF($K12="Partial",0.5,IF($K12="No",0,"")))),"") | M12: =IFERROR(IF(OR($I12="No",$K12="N/A"),"",$F12*IF(OR($G12="",NOT(ISNUMBER($G12))),3,$G12)*IF(OR($H12="",NOT(ISNUMBER($H12))),3,$H12)*IF($K12="",1,1-$L12)),"") -> 48 | N12: =IFERROR(IF(OR($I12="No",$K12="N/A",$K12=""),"",IF(AND(IFERROR(AND($S12="Accepted Risk",$AM12=0),FALSE()),OR(AND($E12="Blocker",OR($K12="No",$K12="Partial")),AND($E12="Major",$K12="No"))),IF(AND($E12="Blocker",$K12="No"),"BLOCK",IF(AND($E12="Blocker",$K12="Partial"),IF(p_stage="Pilot / PoC","ESCALATE","BLOCK"),IF(AND($E12="Major",$K12="No"),"ESCALATE","")))&" (exempted)",IF(AND($E12="Blocker",$K12="No"),"BLOCK",IF(AND($E12="Blocker",$K12="Partial"),IF(p_stage="Pilot / PoC","ESCALATE","BLOCK"),IF(AND($E12="Major",$K12="No"),"ESCALATE",""))))),"") | U12: =_xlfn.TEXTJOIN("; ",TRUE(),$AV12,$AW12,IF($AP12>0,"Evidence missing or unusable","")) | W12: Good: support, patching, incident-notification, and end-of-life commitments proportionate to business criticality. Evidence: SLA/contract clauses. Partial: SLA exists, no incident notification. | AA12: =IF($AN12>0,$A12,"") | AB12: =IF($AO12>0,$A12,"") | AC12: =IF($AQ12>0,$A12&" ("&$U12&")","") | AD12: Major | AF12: =IF(OR(IFERROR(NOT(OR($J12="",$J12="Yes",$J12="No")),TRUE()),IFERROR(IF($E12="",$I12="Yes",NOT(OR($E12="Blocker",$E12="Major",$E12="Moderate",$E12="Minor"))),TRUE()),IFERROR(IF($J12<>"",$T12="",FALSE()),TRUE()),IFERROR(IF(AND($A12="2.7",$I12="Yes",p_confidential="Yes"),$E12<>"Blocker",FALSE()),TRUE()),IFERROR(IF(AND($A12="5.8",$I12="Yes"),OR($E12="Moderate",$E12="Minor"),FALSE()),TRUE()),IF(IFERROR(AND($J12="No",$AI12="Yes",OR($AD12="Blocker",AND($A12="2.7",p_confidential="Yes"))),FALSE()),NOT(AND(IFERROR($X12<>"",FALSE()),IFERROR($Y12<>"",FALSE()),IFERROR(AND(ISNUMBER($Z12),$Z12>=DATE(2020,1,1),$Z12<=DATE(2100,12,31)),FALSE()))),FALSE()),IF(IFERROR(IF(OR($E12="Blocker",$E12="Major",$E12="Moderate",$E12="Minor"),$F12<IF($AD12="Blocker",Lookups!$B$8,IF($AD12="Major",Lookups!$B$9,IF($AD12="Moderate",Lookups!$B$10,Lookups!$B$11))),FALSE()),FALSE()),NOT(AND(IFERROR($T12<>"",FALSE()),IFERROR($Y12<>"",FALSE()),IF(IFERROR($Z12<>"",FALSE()),IFERROR(AND(ISNUMBER($Z12),$Z12>=DATE(2020,1,1),$Z12<=DATE(2100,12,31)),FALSE()),NOT(ISERROR($Z12))))),FALSE())),1,0) -> 0 | AG12: =IF(OR(ISERROR($E12),ISERROR($G12),ISERROR($H12),ISERROR($J12),ISERROR($K12),ISERROR($O12),ISERROR($P12),ISERROR($Q12),ISERROR($R12),ISERROR($S12),ISERROR($T12),ISERROR($X12),ISERROR($Y12),ISERROR($Z12)),1,0) -> 0 | AH12: =IF($AF12>0,$A12&" ("&$AV12&")","") | AI12: =IFERROR(IF(p_stage="Pilot / PoC","No","Yes"),"Yes") -> Yes | AJ12: =IF(IFERROR(NOT(OR($K12="",$K12="Yes",$K12="Partial",$K12="No",$K12="N/A")),TRUE()),1,0) -> 0 | AK12: =IF(OR(IFERROR(IF($G12="",AND($I12="Yes",$K12<>""),IF(ISNUMBER($G12),OR($G12<1,$G12>5,$G12<>INT($G12)),TRUE())),TRUE()),IFERROR(IF($H12="",AND($I12="Yes",$K12<>""),IF(ISNUMBER($H12),OR($H12<1,$H12>5,$H12<>INT($H12)),TRUE())),TRUE())),1,0) -> 0 | AL12: =IF(IFERROR(NOT(OR($S12="",$S12="Open",$S12="In progress",$S12="Remediated",$S12="Accepted Risk",$S12="Not applicable")),TRUE()),1,0) -> 0 | AM12: =IF(OR(IFERROR(IF($S12="Accepted Risk",OR($X12="",$Y12="",$Z12=""),FALSE()),TRUE()),IF(IFERROR($Z12<>"",FALSE()),NOT(IFERROR(AND(ISNUMBER($Z12),$Z12>=DATE(2020,1,1),$Z12<=DATE(2100,12,31)),FALSE())),ISERROR($Z12))),1,0) -> 0 | AN12: =IF(IFERROR(AND($I12="Yes",$K12="N/A"),FALSE()),1,0) -> 0 | AO12: =IF(IFERROR(IF($J12<>"",$T12="",FALSE()),TRUE()),1,0) -> 0 | AP12: =IF(IFERROR(IF($I12="Yes",IF(OR($K12="Yes",$K12="Partial"),IF(ISERROR($O12),TRUE(),$O12=""),FALSE()),FALSE()),FALSE()),1,0) -> 0 | AQ12: =IF(OR($AF12>0,$AG12>0,$AJ12>0,$AK12>0,$AL12>0,$AM12>0,$AN12>0,$AO12>0),1,0) -> 0 | AR12: =IF(IFERROR(AND($I12="Yes",OR($K12="Yes",$K12="Partial",$K12="No")),FALSE()),1,0) -> 0 | AS12: =IFERROR(IF($AR12=1,$F12*$L12,0),0) -> 0 | AT12: =IFERROR(IF($AR12=1,$F12,0),0) -> 0 | AU12: =_xlfn.TEXTJOIN(", ",TRUE(),IF(ISERROR($E12),"E12",""),IF(ISERROR($G12),"G12",""),IF(ISERROR($H12),"H12",""),IF(ISERROR($J12),"J12",""),IF(ISERROR($K12),"K12",""),IF(ISERROR($O12),"O12",""),IF(ISERROR($P12),"P12",""),IF(ISERROR($Q12),"Q12",""),IF(ISERROR($R12),"R12",""),IF(ISERROR($S12),"S12",""),IF(ISERROR($T12),"T12",""),IF(ISERROR($X12),"X12",""),IF(ISERROR($Y12),"Y12",""),IF(ISERROR($Z12),"Z12","")) | AV12: =_xlfn.TEXTJOIN("; ",TRUE(),IF(IFERROR(NOT(OR($J12="",$J12="Yes",$J12="No")),TRUE()),"Invalid override value (J)",""),IF(IFERROR(IF($E12="",$I12="Yes",NOT(OR($E12="Blocker",$E12="Major",$E12="Moderate",$E12="Minor"))),TRUE()),"Invalid or missing criticality (E)",""),IF(IFERROR(IF($J12<>"",$T12="",FALSE()),TRUE()),"Override rationale missing / invalid (T)",""),IF(IFERROR(IF(AND($A12="2.7",$I12="Yes",p_confidential="Yes"),$E12<>"Blocker",FALSE()),TRUE()),"2.7 must be Blocker when S4 = Yes",""),IF(IFERROR(IF(AND($A12="5.8",$I12="Yes"),OR($E12="Moderate",$E12="Minor"),FALSE()),TRUE()),"5.8 should be at least Major",""),IF(IF(IFERROR(AND($J12="No",$AI12="Yes",OR($AD12="Blocker",AND($A12="2.7",p_confidential="Yes"))),FALSE()),NOT(AND(IFERROR($X12<>"",FALSE()),IFERROR($Y12<>"",FALSE()),IFERROR(AND(ISNUMBER($Z12),$Z12>=DATE(2020,1,1),$Z12<=DATE(2100,12,31)),FALSE()))),FALSE()),"Blocker de-scope review missing / invalid (X-Z)",""),IF(IF(IFERROR(IF(OR($E12="Blocker",$E12="Major",$E12="Moderate",$E12="Minor"),$F12<IF($AD12="Blocker",Lookups!$B$8,IF($AD12="Major",Lookups!$B$9,IF($AD12="Moderate",Lookups!$B$10,Lookups!$B$11))),FALSE()),FALSE()),NOT(AND(IFERROR($T12<>"",FALSE()),IFERROR($Y12<>"",FALSE()),IF(IFERROR($Z12<>"",FALSE()),IFERROR(AND(ISNUMBER($Z12),$Z12>=DATE(2020,1,1),$Z12<=DATE(2100,12,31)),FALSE()),NOT(ISERROR($Z12))))),FALSE()),"Criticality below baseline: review missing / invalid (T,Y,Z)","")) | AW12: =_xlfn.TEXTJOIN("; ",TRUE(),IF($AJ12>0,"Invalid response value (K)",""),IF($AK12>0,"Likelihood/Impact missing or not integer 1-5 (G,H)",""),IF($AL12>0,"Invalid status value (S)",""),IF($AM12>0,_xlfn.TEXTJOIN("; ",TRUE(),IF(IFERROR(AND($S12="Accepted Risk",$X12=""),FALSE()),"Exemption reference (X) missing",""),IF(IFERROR(AND($S12="Accepted Risk",$Y12=""),FALSE()),"Exemption approver (Y) missing",""),IF(IFERROR(AND($S12="Accepted Risk",$Z12=""),FALSE()),"Exemption date (Z) missing",""),IF(ISERROR($Z12),"Exemption date (Z) invalid - error value",IF(IFERROR(AND($Z12<>"",NOT(AND(ISNUMBER($Z12),$Z12>=DATE(2020,1,1),$Z12<=DATE(2100,12,31)))),FALSE()),"Exemption date (Z) invalid - enter a real date","")),IF(OR(ISERROR($S12),ISERROR($X12),ISERROR($Y12)),"Exemption inputs contain an error value (S,X,Y)","")),""),IF($AG12>0,"Input/calculation fault at "&$AU12,""),IF($AN12>0,"N/A on applicable row",""))
A13: 2.7 | B13: Model & Provider | C13: Auto: unless S1 = internal development | D13: Model and provider entities are checked against the company country-risk / sovereignty policy (ownership, development location, substantial contributions); the depth of the review follows the data classification (S3/S4). | E13: Major | F13: =IFERROR(IF($E13="Blocker",Lookups!$B$8,IF($E13="Major",Lookups!$B$9,IF($E13="Moderate",Lookups!$B$10,IF($E13="Minor",Lookups!$B$11,0)))),0) -> 4 | G13: 3 | H13: 4 | I13: =IFERROR(IF(OR($J13="Yes",$J13="No"),$J13,IF(p_provider="Internal development","No","Yes")),"Yes") -> Yes | L13: =IFERROR(IF(OR($I13="No",$K13="N/A"),"",IF($K13="Yes",1,IF($K13="Partial",0.5,IF($K13="No",0,"")))),"") | M13: =IFERROR(IF(OR($I13="No",$K13="N/A"),"",$F13*IF(OR($G13="",NOT(ISNUMBER($G13))),3,$G13)*IF(OR($H13="",NOT(ISNUMBER($H13))),3,$H13)*IF($K13="",1,1-$L13)),"") -> 48 | N13: =IFERROR(IF(OR($I13="No",$K13="N/A",$K13=""),"",IF(AND(IFERROR(AND($S13="Accepted Risk",$AM13=0),FALSE()),OR(AND($E13="Blocker",OR($K13="No",$K13="Partial")),AND($E13="Major",$K13="No"))),IF(AND($E13="Blocker",$K13="No"),"BLOCK",IF(AND($E13="Blocker",$K13="Partial"),IF(p_stage="Pilot / PoC","ESCALATE","BLOCK"),IF(AND($E13="Major",$K13="No"),"ESCALATE","")))&" (exempted)",IF(AND($E13="Blocker",$K13="No"),"BLOCK",IF(AND($E13="Blocker",$K13="Partial"),IF(p_stage="Pilot / PoC","ESCALATE","BLOCK"),IF(AND($E13="Major",$K13="No"),"ESCALATE",""))))),"") | U13: =_xlfn.TEXTJOIN("; ",TRUE(),$AV13,$AW13,IF($AP13>0,"Evidence missing or unusable","")) | V13: 2.2, 7.3 — see 2.2. | W13: Good: review documented against the company country-risk/sovereignty policy (ownership, development, substantial contributions), scoped by data classification. Evidence: review memo referencing the policy. Partial: informal review without policy reference. Raise Criticality to Blocker where confidential/regulated data (S4 = Yes) or explicit sovereignty requirements apply; Weight follows automatically. | AA13: =IF($AN13>0,$A13,"") | AB13: =IF($AO13>0,$A13,"") | AC13: =IF($AQ13>0,$A13&" ("&$U13&")","") | AD13: Major | AF13: =IF(OR(IFERROR(NOT(OR($J13="",$J13="Yes",$J13="No")),TRUE()),IFERROR(IF($E13="",$I13="Yes",NOT(OR($E13="Blocker",$E13="Major",$E13="Moderate",$E13="Minor"))),TRUE()),IFERROR(IF($J13<>"",$T13="",FALSE()),TRUE()),IFERROR(IF(AND($A13="2.7",$I13="Yes",p_confidential="Yes"),$E13<>"Blocker",FALSE()),TRUE()),IFERROR(IF(AND($A13="5.8",$I13="Yes"),OR($E13="Moderate",$E13="Minor"),FALSE()),TRUE()),IF(IFERROR(AND($J13="No",$AI13="Yes",OR($AD13="Blocker",AND($A13="2.7",p_confidential="Yes"))),FALSE()),NOT(AND(IFERROR($X13<>"",FALSE()),IFERROR($Y13<>"",FALSE()),IFERROR(AND(ISNUMBER($Z13),$Z13>=DATE(2020,1,1),$Z13<=DATE(2100,12,31)),FALSE()))),FALSE()),IF(IFERROR(IF(OR($E13="Blocker",$E13="Major",$E13="Moderate",$E13="Minor"),$F13<IF($AD13="Blocker",Lookups!$B$8,IF($AD13="Major",Lookups!$B$9,IF($AD13="Moderate",Lookups!$B$10,Lookups!$B$11))),FALSE()),FALSE()),NOT(AND(IFERROR($T13<>"",FALSE()),IFERROR($Y13<>"",FALSE()),IF(IFERROR($Z13<>"",FALSE()),IFERROR(AND(ISNUMBER($Z13),$Z13>=DATE(2020,1,1),$Z13<=DATE(2100,12,31)),FALSE()),NOT(ISERROR($Z13))))),FALSE())),1,0) -> 0 | AG13: =IF(OR(ISERROR($E13),ISERROR($G13),ISERROR($H13),ISERROR($J13),ISERROR($K13),ISERROR($O13),ISERROR($P13),ISERROR($Q13),ISERROR($R13),ISERROR($S13),ISERROR($T13),ISERROR($X13),ISERROR($Y13),ISERROR($Z13)),1,0) -> 0 | AH13: =IF($AF13>0,$A13&" ("&$AV13&")","") | AI13: =IFERROR(IF(p_provider="Internal development","No","Yes"),"Yes") -> Yes | AJ13: =IF(IFERROR(NOT(OR($K13="",$K13="Yes",$K13="Partial",$K13="No",$K13="N/A")),TRUE()),1,0) -> 0 | AK13: =IF(OR(IFERROR(IF($G13="",AND($I13="Yes",$K13<>""),IF(ISNUMBER($G13),OR($G13<1,$G13>5,$G13<>INT($G13)),TRUE())),TRUE()),IFERROR(IF($H13="",AND($I13="Yes",$K13<>""),IF(ISNUMBER($H13),OR($H13<1,$H13>5,$H13<>INT($H13)),TRUE())),TRUE())),1,0) -> 0 | AL13: =IF(IFERROR(NOT(OR($S13="",$S13="Open",$S13="In progress",$S13="Remediated",$S13="Accepted Risk",$S13="Not applicable")),TRUE()),1,0) -> 0 | AM13: =IF(OR(IFERROR(IF($S13="Accepted Risk",OR($X13="",$Y13="",$Z13=""),FALSE()),TRUE()),IF(IFERROR($Z13<>"",FALSE()),NOT(IFERROR(AND(ISNUMBER($Z13),$Z13>=DATE(2020,1,1),$Z13<=DATE(2100,12,31)),FALSE())),ISERROR($Z13))),1,0) -> 0 | AN13: =IF(IFERROR(AND($I13="Yes",$K13="N/A"),FALSE()),1,0) -> 0 | AO13: =IF(IFERROR(IF($J13<>"",$T13="",FALSE()),TRUE()),1,0) -> 0 | AP13: =IF(IFERROR(IF($I13="Yes",IF(OR($K13="Yes",$K13="Partial"),IF(ISERROR($O13),TRUE(),$O13=""),FALSE()),FALSE()),FALSE()),1,0) -> 0 | AQ13: =IF(OR($AF13>0,$AG13>0,$AJ13>0,$AK13>0,$AL13>0,$AM13>0,$AN13>0,$AO13>0),1,0) -> 0 | AR13: =IF(IFERROR(AND($I13="Yes",OR($K13="Yes",$K13="Partial",$K13="No")),FALSE()),1,0) -> 0 | AS13: =IFERROR(IF($AR13=1,$F13*$L13,0),0) -> 0 | AT13: =IFERROR(IF($AR13=1,$F13,0),0) -> 0 | AU13: =_xlfn.TEXTJOIN(", ",TRUE(),IF(ISERROR($E13),"E13",""),IF(ISERROR($G13),"G13",""),IF(ISERROR($H13),"H13",""),IF(ISERROR($J13),"J13",""),IF(ISERROR($K13),"K13",""),IF(ISERROR($O13),"O13",""),IF(ISERROR($P13),"P13",""),IF(ISERROR($Q13),"Q13",""),IF(ISERROR($R13),"R13",""),IF(ISERROR($S13),"S13",""),IF(ISERROR($T13),"T13",""),IF(ISERROR($X13),"X13",""),IF(ISERROR($Y13),"Y13",""),IF(ISERROR($Z13),"Z13","")) | AV13: =_xlfn.TEXTJOIN("; ",TRUE(),IF(IFERROR(NOT(OR($J13="",$J13="Yes",$J13="No")),TRUE()),"Invalid override value (J)",""),IF(IFERROR(IF($E13="",$I13="Yes",NOT(OR($E13="Blocker",$E13="Major",$E13="Moderate",$E13="Minor"))),TRUE()),"Invalid or missing criticality (E)",""),IF(IFERROR(IF($J13<>"",$T13="",FALSE()),TRUE()),"Override rationale missing / invalid (T)",""),IF(IFERROR(IF(AND($A13="2.7",$I13="Yes",p_confidential="Yes"),$E13<>"Blocker",FALSE()),TRUE()),"2.7 must be Blocker when S4 = Yes",""),IF(IFERROR(IF(AND($A13="5.8",$I13="Yes"),OR($E13="Moderate",$E13="Minor"),FALSE()),TRUE()),"5.8 should be at least Major",""),IF(IF(IFERROR(AND($J13="No",$AI13="Yes",OR($AD13="Blocker",AND($A13="2.7",p_confidential="Yes"))),FALSE()),NOT(AND(IFERROR($X13<>"",FALSE()),IFERROR($Y13<>"",FALSE()),IFERROR(AND(ISNUMBER($Z13),$Z13>=DATE(2020,1,1),$Z13<=DATE(2100,12,31)),FALSE()))),FALSE()),"Blocker de-scope review missing / invalid (X-Z)",""),IF(IF(IFERROR(IF(OR($E13="Blocker",$E13="Major",$E13="Moderate",$E13="Minor"),$F13<IF($AD13="Blocker",Lookups!$B$8,IF($AD13="Major",Lookups!$B$9,IF($AD13="Moderate",Lookups!$B$10,Lookups!$B$11))),FALSE()),FALSE()),NOT(AND(IFERROR($T13<>"",FALSE()),IFERROR($Y13<>"",FALSE()),IF(IFERROR($Z13<>"",FALSE()),IFERROR(AND(ISNUMBER($Z13),$Z13>=DATE(2020,1,1),$Z13<=DATE(2100,12,31)),FALSE()),NOT(ISERROR($Z13))))),FALSE()),"Criticality below baseline: review missing / invalid (T,Y,Z)","")) | AW13: =_xlfn.TEXTJOIN("; ",TRUE(),IF($AJ13>0,"Invalid response value (K)",""),IF($AK13>0,"Likelihood/Impact missing or not integer 1-5 (G,H)",""),IF($AL13>0,"Invalid status value (S)",""),IF($AM13>0,_xlfn.TEXTJOIN("; ",TRUE(),IF(IFERROR(AND($S13="Accepted Risk",$X13=""),FALSE()),"Exemption reference (X) missing",""),IF(IFERROR(AND($S13="Accepted Risk",$Y13=""),FALSE()),"Exemption approver (Y) missing",""),IF(IFERROR(AND($S13="Accepted Risk",$Z13=""),FALSE()),"Exemption date (Z) missing",""),IF(ISERROR($Z13),"Exemption date (Z) invalid - error value",IF(IFERROR(AND($Z13<>"",NOT(AND(ISNUMBER($Z13),$Z13>=DATE(2020,1,1),$Z13<=DATE(2100,12,31)))),FALSE()),"Exemption date (Z) invalid - enter a real date","")),IF(OR(ISERROR($S13),ISERROR($X13),ISERROR($Y13)),"Exemption inputs contain an error value (S,X,Y)","")),""),IF($AG13>0,"Input/calculation fault at "&$AU13,""),IF($AN13>0,"N/A on applicable row",""))
A14: 3.1 | B14: Architecture & Integration | C14: Auto: always | D14: Deployment model, trust boundaries, network paths, data flows, and dependencies are documented and approved. | E14: Major | F14: =IFERROR(IF($E14="Blocker",Lookups!$B$8,IF($E14="Major",Lookups!$B$9,IF($E14="Moderate",Lookups!$B$10,IF($E14="Minor",Lookups!$B$11,0)))),0) -> 4 | G14: 4 | H14: 4 | I14: =IFERROR(IF(OR($J14="Yes",$J14="No"),$J14,"Yes"),"Yes") -> Yes | L14: =IFERROR(IF(OR($I14="No",$K14="N/A"),"",IF($K14="Yes",1,IF($K14="Partial",0.5,IF($K14="No",0,"")))),"") | M14: =IFERROR(IF(OR($I14="No",$K14="N/A"),"",$F14*IF(OR($G14="",NOT(ISNUMBER($G14))),3,$G14)*IF(OR($H14="",NOT(ISNUMBER($H14))),3,$H14)*IF($K14="",1,1-$L14)),"") -> 64 | N14: =IFERROR(IF(OR($I14="No",$K14="N/A",$K14=""),"",IF(AND(IFERROR(AND($S14="Accepted Risk",$AM14=0),FALSE()),OR(AND($E14="Blocker",OR($K14="No",$K14="Partial")),AND($E14="Major",$K14="No"))),IF(AND($E14="Blocker",$K14="No"),"BLOCK",IF(AND($E14="Blocker",$K14="Partial"),IF(p_stage="Pilot / PoC","ESCALATE","BLOCK"),IF(AND($E14="Major",$K14="No"),"ESCALATE","")))&" (exempted)",IF(AND($E14="Blocker",$K14="No"),"BLOCK",IF(AND($E14="Blocker",$K14="Partial"),IF(p_stage="Pilot / PoC","ESCALATE","BLOCK"),IF(AND($E14="Major",$K14="No"),"ESCALATE",""))))),"") | U14: =_xlfn.TEXTJOIN("; ",TRUE(),$AV14,$AW14,IF($AP14>0,"Evidence missing or unusable","")) | W14: Good: approved architecture documentation: deployment model, trust boundaries, network paths, data flows, dependencies. Evidence: diagram + sign-off. Partial: diagram exists, trust boundaries unmarked. | AA14: =IF($AN14>0,$A14,"") | AB14: =IF($AO14>0,$A14,"") | AC14: =IF($AQ14>0,$A14&" ("&$U14&")","") | AD14: Major | AF14: =IF(OR(IFERROR(NOT(OR($J14="",$J14="Yes",$J14="No")),TRUE()),IFERROR(IF($E14="",$I14="Yes",NOT(OR($E14="Blocker",$E14="Major",$E14="Moderate",$E14="Minor"))),TRUE()),IFERROR(IF($J14<>"",$T14="",FALSE()),TRUE()),IFERROR(IF(AND($A14="2.7",$I14="Yes",p_confidential="Yes"),$E14<>"Blocker",FALSE()),TRUE()),IFERROR(IF(AND($A14="5.8",$I14="Yes"),OR($E14="Moderate",$E14="Minor"),FALSE()),TRUE()),IF(IFERROR(AND($J14="No",$AI14="Yes",OR($AD14="Blocker",AND($A14="2.7",p_confidential="Yes"))),FALSE()),NOT(AND(IFERROR($X14<>"",FALSE()),IFERROR($Y14<>"",FALSE()),IFERROR(AND(ISNUMBER($Z14),$Z14>=DATE(2020,1,1),$Z14<=DATE(2100,12,31)),FALSE()))),FALSE()),IF(IFERROR(IF(OR($E14="Blocker",$E14="Major",$E14="Moderate",$E14="Minor"),$F14<IF($AD14="Blocker",Lookups!$B$8,IF($AD14="Major",Lookups!$B$9,IF($AD14="Moderate",Lookups!$B$10,Lookups!$B$11))),FALSE()),FALSE()),NOT(AND(IFERROR($T14<>"",FALSE()),IFERROR($Y14<>"",FALSE()),IF(IFERROR($Z14<>"",FALSE()),IFERROR(AND(ISNUMBER($Z14),$Z14>=DATE(2020,1,1),$Z14<=DATE(2100,12,31)),FALSE()),NOT(ISERROR($Z14))))),FALSE())),1,0) -> 0 | AG14: =IF(OR(ISERROR($E14),ISERROR($G14),ISERROR($H14),ISERROR($J14),ISERROR($K14),ISERROR($O14),ISERROR($P14),ISERROR($Q14),ISERROR($R14),ISERROR($S14),ISERROR($T14),ISERROR($X14),ISERROR($Y14),ISERROR($Z14)),1,0) -> 0 | AH14: =IF($AF14>0,$A14&" ("&$AV14&")","") | AI14: =IFERROR("Yes","Yes") -> Yes | AJ14: =IF(IFERROR(NOT(OR($K14="",$K14="Yes",$K14="Partial",$K14="No",$K14="N/A")),TRUE()),1,0) -> 0 | AK14: =IF(OR(IFERROR(IF($G14="",AND($I14="Yes",$K14<>""),IF(ISNUMBER($G14),OR($G14<1,$G14>5,$G14<>INT($G14)),TRUE())),TRUE()),IFERROR(IF($H14="",AND($I14="Yes",$K14<>""),IF(ISNUMBER($H14),OR($H14<1,$H14>5,$H14<>INT($H14)),TRUE())),TRUE())),1,0) -> 0 | AL14: =IF(IFERROR(NOT(OR($S14="",$S14="Open",$S14="In progress",$S14="Remediated",$S14="Accepted Risk",$S14="Not applicable")),TRUE()),1,0) -> 0 | AM14: =IF(OR(IFERROR(IF($S14="Accepted Risk",OR($X14="",$Y14="",$Z14=""),FALSE()),TRUE()),IF(IFERROR($Z14<>"",FALSE()),NOT(IFERROR(AND(ISNUMBER($Z14),$Z14>=DATE(2020,1,1),$Z14<=DATE(2100,12,31)),FALSE())),ISERROR($Z14))),1,0) -> 0 | AN14: =IF(IFERROR(AND($I14="Yes",$K14="N/A"),FALSE()),1,0) -> 0 | AO14: =IF(IFERROR(IF($J14<>"",$T14="",FALSE()),TRUE()),1,0) -> 0 | AP14: =IF(IFERROR(IF($I14="Yes",IF(OR($K14="Yes",$K14="Partial"),IF(ISERROR($O14),TRUE(),$O14=""),FALSE()),FALSE()),FALSE()),1,0) -> 0 | AQ14: =IF(OR($AF14>0,$AG14>0,$AJ14>0,$AK14>0,$AL14>0,$AM14>0,$AN14>0,$AO14>0),1,0) -> 0 | AR14: =IF(IFERROR(AND($I14="Yes",OR($K14="Yes",$K14="Partial",$K14="No")),FALSE()),1,0) -> 0 | AS14: =IFERROR(IF($AR14=1,$F14*$L14,0),0) -> 0 | AT14: =IFERROR(IF($AR14=1,$F14,0),0) -> 0 | AU14: =_xlfn.TEXTJOIN(", ",TRUE(),IF(ISERROR($E14),"E14",""),IF(ISERROR($G14),"G14",""),IF(ISERROR($H14),"H14",""),IF(ISERROR($J14),"J14",""),IF(ISERROR($K14),"K14",""),IF(ISERROR($O14),"O14",""),IF(ISERROR($P14),"P14",""),IF(ISERROR($Q14),"Q14",""),IF(ISERROR($R14),"R14",""),IF(ISERROR($S14),"S14",""),IF(ISERROR($T14),"T14",""),IF(ISERROR($X14),"X14",""),IF(ISERROR($Y14),"Y14",""),IF(ISERROR($Z14),"Z14","")) | AV14: =_xlfn.TEXTJOIN("; ",TRUE(),IF(IFERROR(NOT(OR($J14="",$J14="Yes",$J14="No")),TRUE()),"Invalid override value (J)",""),IF(IFERROR(IF($E14="",$I14="Yes",NOT(OR($E14="Blocker",$E14="Major",$E14="Moderate",$E14="Minor"))),TRUE()),"Invalid or missing criticality (E)",""),IF(IFERROR(IF($J14<>"",$T14="",FALSE()),TRUE()),"Override rationale missing / invalid (T)",""),IF(IFERROR(IF(AND($A14="2.7",$I14="Yes",p_confidential="Yes"),$E14<>"Blocker",FALSE()),TRUE()),"2.7 must be Blocker when S4 = Yes",""),IF(IFERROR(IF(AND($A14="5.8",$I14="Yes"),OR($E14="Moderate",$E14="Minor"),FALSE()),TRUE()),"5.8 should be at least Major",""),IF(IF(IFERROR(AND($J14="No",$AI14="Yes",OR($AD14="Blocker",AND($A14="2.7",p_confidential="Yes"))),FALSE()),NOT(AND(IFERROR($X14<>"",FALSE()),IFERROR($Y14<>"",FALSE()),IFERROR(AND(ISNUMBER($Z14),$Z14>=DATE(2020,1,1),$Z14<=DATE(2100,12,31)),FALSE()))),FALSE()),"Blocker de-scope review missing / invalid (X-Z)",""),IF(IF(IFERROR(IF(OR($E14="Blocker",$E14="Major",$E14="Moderate",$E14="Minor"),$F14<IF($AD14="Blocker",Lookups!$B$8,IF($AD14="Major",Lookups!$B$9,IF($AD14="Moderate",Lookups!$B$10,Lookups!$B$11))),FALSE()),FALSE()),NOT(AND(IFERROR($T14<>"",FALSE()),IFERROR($Y14<>"",FALSE()),IF(IFERROR($Z14<>"",FALSE()),IFERROR(AND(ISNUMBER($Z14),$Z14>=DATE(2020,1,1),$Z14<=DATE(2100,12,31)),FALSE()),NOT(ISERROR($Z14))))),FALSE()),"Criticality below baseline: review missing / invalid (T,Y,Z)","")) | AW14: =_xlfn.TEXTJOIN("; ",TRUE(),IF($AJ14>0,"Invalid response value (K)",""),IF($AK14>0,"Likelihood/Impact missing or not integer 1-5 (G,H)",""),IF($AL14>0,"Invalid status value (S)",""),IF($AM14>0,_xlfn.TEXTJOIN("; ",TRUE(),IF(IFERROR(AND($S14="Accepted Risk",$X14=""),FALSE()),"Exemption reference (X) missing",""),IF(IFERROR(AND($S14="Accepted Risk",$Y14=""),FALSE()),"Exemption approver (Y) missing",""),IF(IFERROR(AND($S14="Accepted Risk",$Z14=""),FALSE()),"Exemption date (Z) missing",""),IF(ISERROR($Z14),"Exemption date (Z) invalid - error value",IF(IFERROR(AND($Z14<>"",NOT(AND(ISNUMBER($Z14),$Z14>=DATE(2020,1,1),$Z14<=DATE(2100,12,31)))),FALSE()),"Exemption date (Z) invalid - enter a real date","")),IF(OR(ISERROR($S14),ISERROR($X14),ISERROR($Y14)),"Exemption inputs contain an error value (S,X,Y)","")),""),IF($AG14>0,"Input/calculation fault at "&$AU14,""),IF($AN14>0,"N/A on applicable row",""))
A15: 3.2 | B15: Architecture & Integration | C15: Auto: unless pure SaaS without tools/agents | D15: Runtime, tools, containers, and integrations follow least privilege and do not require avoidable root, broad Linux capabilities, or broad credentials. | E15: Blocker | F15: =IFERROR(IF($E15="Blocker",Lookups!$B$8,IF($E15="Major",Lookups!$B$9,IF($E15="Moderate",Lookups!$B$10,IF($E15="Minor",Lookups!$B$11,0)))),0) -> 5 | G15: 4 | H15: 5 | I15: =IFERROR(IF(OR($J15="Yes",$J15="No"),$J15,IF(AND(p_provider="External SaaS / API",p_tools="No",p_autonomy="None (chat or single completions)"),"No","Yes")),"Yes") -> Yes | L15: =IFERROR(IF(OR($I15="No",$K15="N/A"),"",IF($K15="Yes",1,IF($K15="Partial",0.5,IF($K15="No",0,"")))),"") | M15: =IFERROR(IF(OR($I15="No",$K15="N/A"),"",$F15*IF(OR($G15="",NOT(ISNUMBER($G15))),3,$G15)*IF(OR($H15="",NOT(ISNUMBER($H15))),3,$H15)*IF($K15="",1,1-$L15)),"") -> 100 | N15: =IFERROR(IF(OR($I15="No",$K15="N/A",$K15=""),"",IF(AND(IFERROR(AND($S15="Accepted Risk",$AM15=0),FALSE()),OR(AND($E15="Blocker",OR($K15="No",$K15="Partial")),AND($E15="Major",$K15="No"))),IF(AND($E15="Blocker",$K15="No"),"BLOCK",IF(AND($E15="Blocker",$K15="Partial"),IF(p_stage="Pilot / PoC","ESCALATE","BLOCK"),IF(AND($E15="Major",$K15="No"),"ESCALATE","")))&" (exempted)",IF(AND($E15="Blocker",$K15="No"),"BLOCK",IF(AND($E15="Blocker",$K15="Partial"),IF(p_stage="Pilot / PoC","ESCALATE","BLOCK"),IF(AND($E15="Major",$K15="No"),"ESCALATE",""))))),"") | U15: =_xlfn.TEXTJOIN("; ",TRUE(),$AV15,$AW15,IF($AP15>0,"Evidence missing or unusable","")) | W15: Good: non-root containers, dropped capabilities, scoped credentials, no avoidable privileges. Evidence: Dockerfile/K8s policy, config scan. Partial: least privilege except documented exceptions. | AA15: =IF($AN15>0,$A15,"") | AB15: =IF($AO15>0,$A15,"") | AC15: =IF($AQ15>0,$A15&" ("&$U15&")","") | AD15: Blocker | AF15: =IF(OR(IFERROR(NOT(OR($J15="",$J15="Yes",$J15="No")),TRUE()),IFERROR(IF($E15="",$I15="Yes",NOT(OR($E15="Blocker",$E15="Major",$E15="Moderate",$E15="Minor"))),TRUE()),IFERROR(IF($J15<>"",$T15="",FALSE()),TRUE()),IFERROR(IF(AND($A15="2.7",$I15="Yes",p_confidential="Yes"),$E15<>"Blocker",FALSE()),TRUE()),IFERROR(IF(AND($A15="5.8",$I15="Yes"),OR($E15="Moderate",$E15="Minor"),FALSE()),TRUE()),IF(IFERROR(AND($J15="No",$AI15="Yes",OR($AD15="Blocker",AND($A15="2.7",p_confidential="Yes"))),FALSE()),NOT(AND(IFERROR($X15<>"",FALSE()),IFERROR($Y15<>"",FALSE()),IFERROR(AND(ISNUMBER($Z15),$Z15>=DATE(2020,1,1),$Z15<=DATE(2100,12,31)),FALSE()))),FALSE()),IF(IFERROR(IF(OR($E15="Blocker",$E15="Major",$E15="Moderate",$E15="Minor"),$F15<IF($AD15="Blocker",Lookups!$B$8,IF($AD15="Major",Lookups!$B$9,IF($AD15="Moderate",Lookups!$B$10,Lookups!$B$11))),FALSE()),FALSE()),NOT(AND(IFERROR($T15<>"",FALSE()),IFERROR($Y15<>"",FALSE()),IF(IFERROR($Z15<>"",FALSE()),IFERROR(AND(ISNUMBER($Z15),$Z15>=DATE(2020,1,1),$Z15<=DATE(2100,12,31)),FALSE()),NOT(ISERROR($Z15))))),FALSE())),1,0) -> 0 | AG15: =IF(OR(ISERROR($E15),ISERROR($G15),ISERROR($H15),ISERROR($J15),ISERROR($K15),ISERROR($O15),ISERROR($P15),ISERROR($Q15),ISERROR($R15),ISERROR($S15),ISERROR($T15),ISERROR($X15),ISERROR($Y15),ISERROR($Z15)),1,0) -> 0 | AH15: =IF($AF15>0,$A15&" ("&$AV15&")","") | AI15: =IFERROR(IF(AND(p_provider="External SaaS / API",p_tools="No",p_autonomy="None (chat or single completions)"),"No","Yes"),"Yes") -> Yes | AJ15: =IF(IFERROR(NOT(OR($K15="",$K15="Yes",$K15="Partial",$K15="No",$K15="N/A")),TRUE()),1,0) -> 0 | AK15: =IF(OR(IFERROR(IF($G15="",AND($I15="Yes",$K15<>""),IF(ISNUMBER($G15),OR($G15<1,$G15>5,$G15<>INT($G15)),TRUE())),TRUE()),IFERROR(IF($H15="",AND($I15="Yes",$K15<>""),IF(ISNUMBER($H15),OR($H15<1,$H15>5,$H15<>INT($H15)),TRUE())),TRUE())),1,0) -> 0 | AL15: =IF(IFERROR(NOT(OR($S15="",$S15="Open",$S15="In progress",$S15="Remediated",$S15="Accepted Risk",$S15="Not applicable")),TRUE()),1,0) -> 0 | AM15: =IF(OR(IFERROR(IF($S15="Accepted Risk",OR($X15="",$Y15="",$Z15=""),FALSE()),TRUE()),IF(IFERROR($Z15<>"",FALSE()),NOT(IFERROR(AND(ISNUMBER($Z15),$Z15>=DATE(2020,1,1),$Z15<=DATE(2100,12,31)),FALSE())),ISERROR($Z15))),1,0) -> 0 | AN15: =IF(IFERROR(AND($I15="Yes",$K15="N/A"),FALSE()),1,0) -> 0 | AO15: =IF(IFERROR(IF($J15<>"",$T15="",FALSE()),TRUE()),1,0) -> 0 | AP15: =IF(IFERROR(IF($I15="Yes",IF(OR($K15="Yes",$K15="Partial"),IF(ISERROR($O15),TRUE(),$O15=""),FALSE()),FALSE()),FALSE()),1,0) -> 0 | AQ15: =IF(OR($AF15>0,$AG15>0,$AJ15>0,$AK15>0,$AL15>0,$AM15>0,$AN15>0,$AO15>0),1,0) -> 0 | AR15: =IF(IFERROR(AND($I15="Yes",OR($K15="Yes",$K15="Partial",$K15="No")),FALSE()),1,0) -> 0 | AS15: =IFERROR(IF($AR15=1,$F15*$L15,0),0) -> 0 | AT15: =IFERROR(IF($AR15=1,$F15,0),0) -> 0 | AU15: =_xlfn.TEXTJOIN(", ",TRUE(),IF(ISERROR($E15),"E15",""),IF(ISERROR($G15),"G15",""),IF(ISERROR($H15),"H15",""),IF(ISERROR($J15),"J15",""),IF(ISERROR($K15),"K15",""),IF(ISERROR($O15),"O15",""),IF(ISERROR($P15),"P15",""),IF(ISERROR($Q15),"Q15",""),IF(ISERROR($R15),"R15",""),IF(ISERROR($S15),"S15",""),IF(ISERROR($T15),"T15",""),IF(ISERROR($X15),"X15",""),IF(ISERROR($Y15),"Y15",""),IF(ISERROR($Z15),"Z15","")) | AV15: =_xlfn.TEXTJOIN("; ",TRUE(),IF(IFERROR(NOT(OR($J15="",$J15="Yes",$J15="No")),TRUE()),"Invalid override value (J)",""),IF(IFERROR(IF($E15="",$I15="Yes",NOT(OR($E15="Blocker",$E15="Major",$E15="Moderate",$E15="Minor"))),TRUE()),"Invalid or missing criticality (E)",""),IF(IFERROR(IF($J15<>"",$T15="",FALSE()),TRUE()),"Override rationale missing / invalid (T)",""),IF(IFERROR(IF(AND($A15="2.7",$I15="Yes",p_confidential="Yes"),$E15<>"Blocker",FALSE()),TRUE()),"2.7 must be Blocker when S4 = Yes",""),IF(IFERROR(IF(AND($A15="5.8",$I15="Yes"),OR($E15="Moderate",$E15="Minor"),FALSE()),TRUE()),"5.8 should be at least Major",""),IF(IF(IFERROR(AND($J15="No",$AI15="Yes",OR($AD15="Blocker",AND($A15="2.7",p_confidential="Yes"))),FALSE()),NOT(AND(IFERROR($X15<>"",FALSE()),IFERROR($Y15<>"",FALSE()),IFERROR(AND(ISNUMBER($Z15),$Z15>=DATE(2020,1,1),$Z15<=DATE(2100,12,31)),FALSE()))),FALSE()),"Blocker de-scope review missing / invalid (X-Z)",""),IF(IF(IFERROR(IF(OR($E15="Blocker",$E15="Major",$E15="Moderate",$E15="Minor"),$F15<IF($AD15="Blocker",Lookups!$B$8,IF($AD15="Major",Lookups!$B$9,IF($AD15="Moderate",Lookups!$B$10,Lookups!$B$11))),FALSE()),FALSE()),NOT(AND(IFERROR($T15<>"",FALSE()),IFERROR($Y15<>"",FALSE()),IF(IFERROR($Z15<>"",FALSE()),IFERROR(AND(ISNUMBER($Z15),$Z15>=DATE(2020,1,1),$Z15<=DATE(2100,12,31)),FALSE()),NOT(ISERROR($Z15))))),FALSE()),"Criticality below baseline: review missing / invalid (T,Y,Z)","")) | AW15: =_xlfn.TEXTJOIN("; ",TRUE(),IF($AJ15>0,"Invalid response value (K)",""),IF($AK15>0,"Likelihood/Impact missing or not integer 1-5 (G,H)",""),IF($AL15>0,"Invalid status value (S)",""),IF($AM15>0,_xlfn.TEXTJOIN("; ",TRUE(),IF(IFERROR(AND($S15="Accepted Risk",$X15=""),FALSE()),"Exemption reference (X) missing",""),IF(IFERROR(AND($S15="Accepted Risk",$Y15=""),FALSE()),"Exemption approver (Y) missing",""),IF(IFERROR(AND($S15="Accepted Risk",$Z15=""),FALSE()),"Exemption date (Z) missing",""),IF(ISERROR($Z15),"Exemption date (Z) invalid - error value",IF(IFERROR(AND($Z15<>"",NOT(AND(ISNUMBER($Z15),$Z15>=DATE(2020,1,1),$Z15<=DATE(2100,12,31)))),FALSE()),"Exemption date (Z) invalid - enter a real date","")),IF(OR(ISERROR($S15),ISERROR($X15),ISERROR($Y15)),"Exemption inputs contain an error value (S,X,Y)","")),""),IF($AG15>0,"Input/calculation fault at "&$AU15,""),IF($AN15>0,"N/A on applicable row",""))
A16: 3.3 | B16: Architecture & Integration | C16: Auto: always | D16: Authentication, authorization, tenant/user segregation, and privileged admin access are defined and tested. | E16: Blocker | F16: =IFERROR(IF($E16="Blocker",Lookups!$B$8,IF($E16="Major",Lookups!$B$9,IF($E16="Moderate",Lookups!$B$10,IF($E16="Minor",Lookups!$B$11,0)))),0) -> 5 | G16: 4 | H16: 5 | I16: =IFERROR(IF(OR($J16="Yes",$J16="No"),$J16,"Yes"),"Yes") -> Yes | L16: =IFERROR(IF(OR($I16="No",$K16="N/A"),"",IF($K16="Yes",1,IF($K16="Partial",0.5,IF($K16="No",0,"")))),"") | M16: =IFERROR(IF(OR($I16="No",$K16="N/A"),"",$F16*IF(OR($G16="",NOT(ISNUMBER($G16))),3,$G16)*IF(OR($H16="",NOT(ISNUMBER($H16))),3,$H16)*IF($K16="",1,1-$L16)),"") -> 100 | N16: =IFERROR(IF(OR($I16="No",$K16="N/A",$K16=""),"",IF(AND(IFERROR(AND($S16="Accepted Risk",$AM16=0),FALSE()),OR(AND($E16="Blocker",OR($K16="No",$K16="Partial")),AND($E16="Major",$K16="No"))),IF(AND($E16="Blocker",$K16="No"),"BLOCK",IF(AND($E16="Blocker",$K16="Partial"),IF(p_stage="Pilot / PoC","ESCALATE","BLOCK"),IF(AND($E16="Major",$K16="No"),"ESCALATE","")))&" (exempted)",IF(AND($E16="Blocker",$K16="No"),"BLOCK",IF(AND($E16="Blocker",$K16="Partial"),IF(p_stage="Pilot / PoC","ESCALATE","BLOCK"),IF(AND($E16="Major",$K16="No"),"ESCALATE",""))))),"") | U16: =_xlfn.TEXTJOIN("; ",TRUE(),$AV16,$AW16,IF($AP16>0,"Evidence missing or unusable","")) | W16: Good: authentication, authorization, tenant/user segregation, and privileged admin access defined and tested, including negative tests. Evidence: test report. Partial: implemented, untested. | AA16: =IF($AN16>0,$A16,"") | AB16: =IF($AO16>0,$A16,"") | AC16: =IF($AQ16>0,$A16&" ("&$U16&")","") | AD16: Blocker | AF16: =IF(OR(IFERROR(NOT(OR($J16="",$J16="Yes",$J16="No")),TRUE()),IFERROR(IF($E16="",$I16="Yes",NOT(OR($E16="Blocker",$E16="Major",$E16="Moderate",$E16="Minor"))),TRUE()),IFERROR(IF($J16<>"",$T16="",FALSE()),TRUE()),IFERROR(IF(AND($A16="2.7",$I16="Yes",p_confidential="Yes"),$E16<>"Blocker",FALSE()),TRUE()),IFERROR(IF(AND($A16="5.8",$I16="Yes"),OR($E16="Moderate",$E16="Minor"),FALSE()),TRUE()),IF(IFERROR(AND($J16="No",$AI16="Yes",OR($AD16="Blocker",AND($A16="2.7",p_confidential="Yes"))),FALSE()),NOT(AND(IFERROR($X16<>"",FALSE()),IFERROR($Y16<>"",FALSE()),IFERROR(AND(ISNUMBER($Z16),$Z16>=DATE(2020,1,1),$Z16<=DATE(2100,12,31)),FALSE()))),FALSE()),IF(IFERROR(IF(OR($E16="Blocker",$E16="Major",$E16="Moderate",$E16="Minor"),$F16<IF($AD16="Blocker",Lookups!$B$8,IF($AD16="Major",Lookups!$B$9,IF($AD16="Moderate",Lookups!$B$10,Lookups!$B$11))),FALSE()),FALSE()),NOT(AND(IFERROR($T16<>"",FALSE()),IFERROR($Y16<>"",FALSE()),IF(IFERROR($Z16<>"",FALSE()),IFERROR(AND(ISNUMBER($Z16),$Z16>=DATE(2020,1,1),$Z16<=DATE(2100,12,31)),FALSE()),NOT(ISERROR($Z16))))),FALSE())),1,0) -> 0 | AG16: =IF(OR(ISERROR($E16),ISERROR($G16),ISERROR($H16),ISERROR($J16),ISERROR($K16),ISERROR($O16),ISERROR($P16),ISERROR($Q16),ISERROR($R16),ISERROR($S16),ISERROR($T16),ISERROR($X16),ISERROR($Y16),ISERROR($Z16)),1,0) -> 0 | AH16: =IF($AF16>0,$A16&" ("&$AV16&")","") | AI16: =IFERROR("Yes","Yes") -> Yes | AJ16: =IF(IFERROR(NOT(OR($K16="",$K16="Yes",$K16="Partial",$K16="No",$K16="N/A")),TRUE()),1,0) -> 0 | AK16: =IF(OR(IFERROR(IF($G16="",AND($I16="Yes",$K16<>""),IF(ISNUMBER($G16),OR($G16<1,$G16>5,$G16<>INT($G16)),TRUE())),TRUE()),IFERROR(IF($H16="",AND($I16="Yes",$K16<>""),IF(ISNUMBER($H16),OR($H16<1,$H16>5,$H16<>INT($H16)),TRUE())),TRUE())),1,0) -> 0 | AL16: =IF(IFERROR(NOT(OR($S16="",$S16="Open",$S16="In progress",$S16="Remediated",$S16="Accepted Risk",$S16="Not applicable")),TRUE()),1,0) -> 0 | AM16: =IF(OR(IFERROR(IF($S16="Accepted Risk",OR($X16="",$Y16="",$Z16=""),FALSE()),TRUE()),IF(IFERROR($Z16<>"",FALSE()),NOT(IFERROR(AND(ISNUMBER($Z16),$Z16>=DATE(2020,1,1),$Z16<=DATE(2100,12,31)),FALSE())),ISERROR($Z16))),1,0) -> 0 | AN16: =IF(IFERROR(AND($I16="Yes",$K16="N/A"),FALSE()),1,0) -> 0 | AO16: =IF(IFERROR(IF($J16<>"",$T16="",FALSE()),TRUE()),1,0) -> 0 | AP16: =IF(IFERROR(IF($I16="Yes",IF(OR($K16="Yes",$K16="Partial"),IF(ISERROR($O16),TRUE(),$O16=""),FALSE()),FALSE()),FALSE()),1,0) -> 0 | AQ16: =IF(OR($AF16>0,$AG16>0,$AJ16>0,$AK16>0,$AL16>0,$AM16>0,$AN16>0,$AO16>0),1,0) -> 0 | AR16: =IF(IFERROR(AND($I16="Yes",OR($K16="Yes",$K16="Partial",$K16="No")),FALSE()),1,0) -> 0 | AS16: =IFERROR(IF($AR16=1,$F16*$L16,0),0) -> 0 | AT16: =IFERROR(IF($AR16=1,$F16,0),0) -> 0 | AU16: =_xlfn.TEXTJOIN(", ",TRUE(),IF(ISERROR($E16),"E16",""),IF(ISERROR($G16),"G16",""),IF(ISERROR($H16),"H16",""),IF(ISERROR($J16),"J16",""),IF(ISERROR($K16),"K16",""),IF(ISERROR($O16),"O16",""),IF(ISERROR($P16),"P16",""),IF(ISERROR($Q16),"Q16",""),IF(ISERROR($R16),"R16",""),IF(ISERROR($S16),"S16",""),IF(ISERROR($T16),"T16",""),IF(ISERROR($X16),"X16",""),IF(ISERROR($Y16),"Y16",""),IF(ISERROR($Z16),"Z16","")) | AV16: =_xlfn.TEXTJOIN("; ",TRUE(),IF(IFERROR(NOT(OR($J16="",$J16="Yes",$J16="No")),TRUE()),"Invalid override value (J)",""),IF(IFERROR(IF($E16="",$I16="Yes",NOT(OR($E16="Blocker",$E16="Major",$E16="Moderate",$E16="Minor"))),TRUE()),"Invalid or missing criticality (E)",""),IF(IFERROR(IF($J16<>"",$T16="",FALSE()),TRUE()),"Override rationale missing / invalid (T)",""),IF(IFERROR(IF(AND($A16="2.7",$I16="Yes",p_confidential="Yes"),$E16<>"Blocker",FALSE()),TRUE()),"2.7 must be Blocker when S4 = Yes",""),IF(IFERROR(IF(AND($A16="5.8",$I16="Yes"),OR($E16="Moderate",$E16="Minor"),FALSE()),TRUE()),"5.8 should be at least Major",""),IF(IF(IFERROR(AND($J16="No",$AI16="Yes",OR($AD16="Blocker",AND($A16="2.7",p_confidential="Yes"))),FALSE()),NOT(AND(IFERROR($X16<>"",FALSE()),IFERROR($Y16<>"",FALSE()),IFERROR(AND(ISNUMBER($Z16),$Z16>=DATE(2020,1,1),$Z16<=DATE(2100,12,31)),FALSE()))),FALSE()),"Blocker de-scope review missing / invalid (X-Z)",""),IF(IF(IFERROR(IF(OR($E16="Blocker",$E16="Major",$E16="Moderate",$E16="Minor"),$F16<IF($AD16="Blocker",Lookups!$B$8,IF($AD16="Major",Lookups!$B$9,IF($AD16="Moderate",Lookups!$B$10,Lookups!$B$11))),FALSE()),FALSE()),NOT(AND(IFERROR($T16<>"",FALSE()),IFERROR($Y16<>"",FALSE()),IF(IFERROR($Z16<>"",FALSE()),IFERROR(AND(ISNUMBER($Z16),$Z16>=DATE(2020,1,1),$Z16<=DATE(2100,12,31)),FALSE()),NOT(ISERROR($Z16))))),FALSE()),"Criticality below baseline: review missing / invalid (T,Y,Z)","")) | AW16: =_xlfn.TEXTJOIN("; ",TRUE(),IF($AJ16>0,"Invalid response value (K)",""),IF($AK16>0,"Likelihood/Impact missing or not integer 1-5 (G,H)",""),IF($AL16>0,"Invalid status value (S)",""),IF($AM16>0,_xlfn.TEXTJOIN("; ",TRUE(),IF(IFERROR(AND($S16="Accepted Risk",$X16=""),FALSE()),"Exemption reference (X) missing",""),IF(IFERROR(AND($S16="Accepted Risk",$Y16=""),FALSE()),"Exemption approver (Y) missing",""),IF(IFERROR(AND($S16="Accepted Risk",$Z16=""),FALSE()),"Exemption date (Z) missing",""),IF(ISERROR($Z16),"Exemption date (Z) invalid - error value",IF(IFERROR(AND($Z16<>"",NOT(AND(ISNUMBER($Z16),$Z16>=DATE(2020,1,1),$Z16<=DATE(2100,12,31)))),FALSE()),"Exemption date (Z) invalid - enter a real date","")),IF(OR(ISERROR($S16),ISERROR($X16),ISERROR($Y16)),"Exemption inputs contain an error value (S,X,Y)","")),""),IF($AG16>0,"Input/calculation fault at "&$AU16,""),IF($AN16>0,"N/A on applicable row",""))
A17: 3.4 | B17: Architecture & Integration | C17: Auto: always | D17: Secrets, credentials, tokens, and sensitive system prompts are not exposed to user-controllable context or model output. | E17: Blocker | F17: =IFERROR(IF($E17="Blocker",Lookups!$B$8,IF($E17="Major",Lookups!$B$9,IF($E17="Moderate",Lookups!$B$10,IF($E17="Minor",Lookups!$B$11,0)))),0) -> 5 | G17: 4 | H17: 5 | I17: =IFERROR(IF(OR($J17="Yes",$J17="No"),$J17,"Yes"),"Yes") -> Yes | L17: =IFERROR(IF(OR($I17="No",$K17="N/A"),"",IF($K17="Yes",1,IF($K17="Partial",0.5,IF($K17="No",0,"")))),"") | M17: =IFERROR(IF(OR($I17="No",$K17="N/A"),"",$F17*IF(OR($G17="",NOT(ISNUMBER($G17))),3,$G17)*IF(OR($H17="",NOT(ISNUMBER($H17))),3,$H17)*IF($K17="",1,1-$L17)),"") -> 100 | N17: =IFERROR(IF(OR($I17="No",$K17="N/A",$K17=""),"",IF(AND(IFERROR(AND($S17="Accepted Risk",$AM17=0),FALSE()),OR(AND($E17="Blocker",OR($K17="No",$K17="Partial")),AND($E17="Major",$K17="No"))),IF(AND($E17="Blocker",$K17="No"),"BLOCK",IF(AND($E17="Blocker",$K17="Partial"),IF(p_stage="Pilot / PoC","ESCALATE","BLOCK"),IF(AND($E17="Major",$K17="No"),"ESCALATE","")))&" (exempted)",IF(AND($E17="Blocker",$K17="No"),"BLOCK",IF(AND($E17="Blocker",$K17="Partial"),IF(p_stage="Pilot / PoC","ESCALATE","BLOCK"),IF(AND($E17="Major",$K17="No"),"ESCALATE",""))))),"") | U17: =_xlfn.TEXTJOIN("; ",TRUE(),$AV17,$AW17,IF($AP17>0,"Evidence missing or unusable","")) | W17: Good: secrets in a vault, system prompts segregated from user-controllable context, outputs scanned for secret leakage. Evidence: vault config, leakage tests. Partial: secrets managed, system prompts exposed. Advisory map (partial): OWASP LLM07 System Prompt Leakage. | AA17: =IF($AN17>0,$A17,"") | AB17: =IF($AO17>0,$A17,"") | AC17: =IF($AQ17>0,$A17&" ("&$U17&")","") | AD17: Blocker | AF17: =IF(OR(IFERROR(NOT(OR($J17="",$J17="Yes",$J17="No")),TRUE()),IFERROR(IF($E17="",$I17="Yes",NOT(OR($E17="Blocker",$E17="Major",$E17="Moderate",$E17="Minor"))),TRUE()),IFERROR(IF($J17<>"",$T17="",FALSE()),TRUE()),IFERROR(IF(AND($A17="2.7",$I17="Yes",p_confidential="Yes"),$E17<>"Blocker",FALSE()),TRUE()),IFERROR(IF(AND($A17="5.8",$I17="Yes"),OR($E17="Moderate",$E17="Minor"),FALSE()),TRUE()),IF(IFERROR(AND($J17="No",$AI17="Yes",OR($AD17="Blocker",AND($A17="2.7",p_confidential="Yes"))),FALSE()),NOT(AND(IFERROR($X17<>"",FALSE()),IFERROR($Y17<>"",FALSE()),IFERROR(AND(ISNUMBER($Z17),$Z17>=DATE(2020,1,1),$Z17<=DATE(2100,12,31)),FALSE()))),FALSE()),IF(IFERROR(IF(OR($E17="Blocker",$E17="Major",$E17="Moderate",$E17="Minor"),$F17<IF($AD17="Blocker",Lookups!$B$8,IF($AD17="Major",Lookups!$B$9,IF($AD17="Moderate",Lookups!$B$10,Lookups!$B$11))),FALSE()),FALSE()),NOT(AND(IFERROR($T17<>"",FALSE()),IFERROR($Y17<>"",FALSE()),IF(IFERROR($Z17<>"",FALSE()),IFERROR(AND(ISNUMBER($Z17),$Z17>=DATE(2020,1,1),$Z17<=DATE(2100,12,31)),FALSE()),NOT(ISERROR($Z17))))),FALSE())),1,0) -> 0 | AG17: =IF(OR(ISERROR($E17),ISERROR($G17),ISERROR($H17),ISERROR($J17),ISERROR($K17),ISERROR($O17),ISERROR($P17),ISERROR($Q17),ISERROR($R17),ISERROR($S17),ISERROR($T17),ISERROR($X17),ISERROR($Y17),ISERROR($Z17)),1,0) -> 0 | AH17: =IF($AF17>0,$A17&" ("&$AV17&")","") | AI17: =IFERROR("Yes","Yes") -> Yes | AJ17: =IF(IFERROR(NOT(OR($K17="",$K17="Yes",$K17="Partial",$K17="No",$K17="N/A")),TRUE()),1,0) -> 0 | AK17: =IF(OR(IFERROR(IF($G17="",AND($I17="Yes",$K17<>""),IF(ISNUMBER($G17),OR($G17<1,$G17>5,$G17<>INT($G17)),TRUE())),TRUE()),IFERROR(IF($H17="",AND($I17="Yes",$K17<>""),IF(ISNUMBER($H17),OR($H17<1,$H17>5,$H17<>INT($H17)),TRUE())),TRUE())),1,0) -> 0 | AL17: =IF(IFERROR(NOT(OR($S17="",$S17="Open",$S17="In progress",$S17="Remediated",$S17="Accepted Risk",$S17="Not applicable")),TRUE()),1,0) -> 0 | AM17: =IF(OR(IFERROR(IF($S17="Accepted Risk",OR($X17="",$Y17="",$Z17=""),FALSE()),TRUE()),IF(IFERROR($Z17<>"",FALSE()),NOT(IFERROR(AND(ISNUMBER($Z17),$Z17>=DATE(2020,1,1),$Z17<=DATE(2100,12,31)),FALSE())),ISERROR($Z17))),1,0) -> 0 | AN17: =IF(IFERROR(AND($I17="Yes",$K17="N/A"),FALSE()),1,0) -> 0 | AO17: =IF(IFERROR(IF($J17<>"",$T17="",FALSE()),TRUE()),1,0) -> 0 | AP17: =IF(IFERROR(IF($I17="Yes",IF(OR($K17="Yes",$K17="Partial"),IF(ISERROR($O17),TRUE(),$O17=""),FALSE()),FALSE()),FALSE()),1,0) -> 0 | AQ17: =IF(OR($AF17>0,$AG17>0,$AJ17>0,$AK17>0,$AL17>0,$AM17>0,$AN17>0,$AO17>0),1,0) -> 0 | AR17: =IF(IFERROR(AND($I17="Yes",OR($K17="Yes",$K17="Partial",$K17="No")),FALSE()),1,0) -> 0 | AS17: =IFERROR(IF($AR17=1,$F17*$L17,0),0) -> 0 | AT17: =IFERROR(IF($AR17=1,$F17,0),0) -> 0 | AU17: =_xlfn.TEXTJOIN(", ",TRUE(),IF(ISERROR($E17),"E17",""),IF(ISERROR($G17),"G17",""),IF(ISERROR($H17),"H17",""),IF(ISERROR($J17),"J17",""),IF(ISERROR($K17),"K17",""),IF(ISERROR($O17),"O17",""),IF(ISERROR($P17),"P17",""),IF(ISERROR($Q17),"Q17",""),IF(ISERROR($R17),"R17",""),IF(ISERROR($S17),"S17",""),IF(ISERROR($T17),"T17",""),IF(ISERROR($X17),"X17",""),IF(ISERROR($Y17),"Y17",""),IF(ISERROR($Z17),"Z17","")) | AV17: =_xlfn.TEXTJOIN("; ",TRUE(),IF(IFERROR(NOT(OR($J17="",$J17="Yes",$J17="No")),TRUE()),"Invalid override value (J)",""),IF(IFERROR(IF($E17="",$I17="Yes",NOT(OR($E17="Blocker",$E17="Major",$E17="Moderate",$E17="Minor"))),TRUE()),"Invalid or missing criticality (E)",""),IF(IFERROR(IF($J17<>"",$T17="",FALSE()),TRUE()),"Override rationale missing / invalid (T)",""),IF(IFERROR(IF(AND($A17="2.7",$I17="Yes",p_confidential="Yes"),$E17<>"Blocker",FALSE()),TRUE()),"2.7 must be Blocker when S4 = Yes",""),IF(IFERROR(IF(AND($A17="5.8",$I17="Yes"),OR($E17="Moderate",$E17="Minor"),FALSE()),TRUE()),"5.8 should be at least Major",""),IF(IF(IFERROR(AND($J17="No",$AI17="Yes",OR($AD17="Blocker",AND($A17="2.7",p_confidential="Yes"))),FALSE()),NOT(AND(IFERROR($X17<>"",FALSE()),IFERROR($Y17<>"",FALSE()),IFERROR(AND(ISNUMBER($Z17),$Z17>=DATE(2020,1,1),$Z17<=DATE(2100,12,31)),FALSE()))),FALSE()),"Blocker de-scope review missing / invalid (X-Z)",""),IF(IF(IFERROR(IF(OR($E17="Blocker",$E17="Major",$E17="Moderate",$E17="Minor"),$F17<IF($AD17="Blocker",Lookups!$B$8,IF($AD17="Major",Lookups!$B$9,IF($AD17="Moderate",Lookups!$B$10,Lookups!$B$11))),FALSE()),FALSE()),NOT(AND(IFERROR($T17<>"",FALSE()),IFERROR($Y17<>"",FALSE()),IF(IFERROR($Z17<>"",FALSE()),IFERROR(AND(ISNUMBER($Z17),$Z17>=DATE(2020,1,1),$Z17<=DATE(2100,12,31)),FALSE()),NOT(ISERROR($Z17))))),FALSE()),"Criticality below baseline: review missing / invalid (T,Y,Z)","")) | AW17: =_xlfn.TEXTJOIN("; ",TRUE(),IF($AJ17>0,"Invalid response value (K)",""),IF($AK17>0,"Likelihood/Impact missing or not integer 1-5 (G,H)",""),IF($AL17>0,"Invalid status value (S)",""),IF($AM17>0,_xlfn.TEXTJOIN("; ",TRUE(),IF(IFERROR(AND($S17="Accepted Risk",$X17=""),FALSE()),"Exemption reference (X) missing",""),IF(IFERROR(AND($S17="Accepted Risk",$Y17=""),FALSE()),"Exemption approver (Y) missing",""),IF(IFERROR(AND($S17="Accepted Risk",$Z17=""),FALSE()),"Exemption date (Z) missing",""),IF(ISERROR($Z17),"Exemption date (Z) invalid - error value",IF(IFERROR(AND($Z17<>"",NOT(AND(ISNUMBER($Z17),$Z17>=DATE(2020,1,1),$Z17<=DATE(2100,12,31)))),FALSE()),"Exemption date (Z) invalid - enter a real date","")),IF(OR(ISERROR($S17),ISERROR($X17),ISERROR($Y17)),"Exemption inputs contain an error value (S,X,Y)","")),""),IF($AG17>0,"Input/calculation fault at "&$AU17,""),IF($AN17>0,"N/A on applicable row",""))
A18: 3.5 | B18: Architecture & Integration | C18: Auto: unless S9 = No | D18: Retrieval data is scoped to user entitlements and protected against cross-tenant or cross-project leakage. | E18: Blocker | F18: =IFERROR(IF($E18="Blocker",Lookups!$B$8,IF($E18="Major",Lookups!$B$9,IF($E18="Moderate",Lookups!$B$10,IF($E18="Minor",Lookups!$B$11,0)))),0) -> 5 | G18: 4 | H18: 5 | I18: =IFERROR(IF(OR($J18="Yes",$J18="No"),$J18,IF(p_rag="No","No","Yes")),"Yes") -> Yes | L18: =IFERROR(IF(OR($I18="No",$K18="N/A"),"",IF($K18="Yes",1,IF($K18="Partial",0.5,IF($K18="No",0,"")))),"") | M18: =IFERROR(IF(OR($I18="No",$K18="N/A"),"",$F18*IF(OR($G18="",NOT(ISNUMBER($G18))),3,$G18)*IF(OR($H18="",NOT(ISNUMBER($H18))),3,$H18)*IF($K18="",1,1-$L18)),"") -> 100 | N18: =IFERROR(IF(OR($I18="No",$K18="N/A",$K18=""),"",IF(AND(IFERROR(AND($S18="Accepted Risk",$AM18=0),FALSE()),OR(AND($E18="Blocker",OR($K18="No",$K18="Partial")),AND($E18="Major",$K18="No"))),IF(AND($E18="Blocker",$K18="No"),"BLOCK",IF(AND($E18="Blocker",$K18="Partial"),IF(p_stage="Pilot / PoC","ESCALATE","BLOCK"),IF(AND($E18="Major",$K18="No"),"ESCALATE","")))&" (exempted)",IF(AND($E18="Blocker",$K18="No"),"BLOCK",IF(AND($E18="Blocker",$K18="Partial"),IF(p_stage="Pilot / PoC","ESCALATE","BLOCK"),IF(AND($E18="Major",$K18="No"),"ESCALATE",""))))),"") | U18: =_xlfn.TEXTJOIN("; ",TRUE(),$AV18,$AW18,IF($AP18>0,"Evidence missing or unusable","")) | W18: Good: retrieval filtered by user entitlements at query time; cross-tenant/cross-project leakage tested. Evidence: filter code + test cases. Partial: filtering exists, no leakage tests. Advisory map (partial): OWASP LLM08 Vector & Embedding Weaknesses. | AA18: =IF($AN18>0,$A18,"") | AB18: =IF($AO18>0,$A18,"") | AC18: =IF($AQ18>0,$A18&" ("&$U18&")","") | AD18: Blocker | AF18: =IF(OR(IFERROR(NOT(OR($J18="",$J18="Yes",$J18="No")),TRUE()),IFERROR(IF($E18="",$I18="Yes",NOT(OR($E18="Blocker",$E18="Major",$E18="Moderate",$E18="Minor"))),TRUE()),IFERROR(IF($J18<>"",$T18="",FALSE()),TRUE()),IFERROR(IF(AND($A18="2.7",$I18="Yes",p_confidential="Yes"),$E18<>"Blocker",FALSE()),TRUE()),IFERROR(IF(AND($A18="5.8",$I18="Yes"),OR($E18="Moderate",$E18="Minor"),FALSE()),TRUE()),IF(IFERROR(AND($J18="No",$AI18="Yes",OR($AD18="Blocker",AND($A18="2.7",p_confidential="Yes"))),FALSE()),NOT(AND(IFERROR($X18<>"",FALSE()),IFERROR($Y18<>"",FALSE()),IFERROR(AND(ISNUMBER($Z18),$Z18>=DATE(2020,1,1),$Z18<=DATE(2100,12,31)),FALSE()))),FALSE()),IF(IFERROR(IF(OR($E18="Blocker",$E18="Major",$E18="Moderate",$E18="Minor"),$F18<IF($AD18="Blocker",Lookups!$B$8,IF($AD18="Major",Lookups!$B$9,IF($AD18="Moderate",Lookups!$B$10,Lookups!$B$11))),FALSE()),FALSE()),NOT(AND(IFERROR($T18<>"",FALSE()),IFERROR($Y18<>"",FALSE()),IF(IFERROR($Z18<>"",FALSE()),IFERROR(AND(ISNUMBER($Z18),$Z18>=DATE(2020,1,1),$Z18<=DATE(2100,12,31)),FALSE()),NOT(ISERROR($Z18))))),FALSE())),1,0) -> 0 | AG18: =IF(OR(ISERROR($E18),ISERROR($G18),ISERROR($H18),ISERROR($J18),ISERROR($K18),ISERROR($O18),ISERROR($P18),ISERROR($Q18),ISERROR($R18),ISERROR($S18),ISERROR($T18),ISERROR($X18),ISERROR($Y18),ISERROR($Z18)),1,0) -> 0 | AH18: =IF($AF18>0,$A18&" ("&$AV18&")","") | AI18: =IFERROR(IF(p_rag="No","No","Yes"),"Yes") -> Yes | AJ18: =IF(IFERROR(NOT(OR($K18="",$K18="Yes",$K18="Partial",$K18="No",$K18="N/A")),TRUE()),1,0) -> 0 | AK18: =IF(OR(IFERROR(IF($G18="",AND($I18="Yes",$K18<>""),IF(ISNUMBER($G18),OR($G18<1,$G18>5,$G18<>INT($G18)),TRUE())),TRUE()),IFERROR(IF($H18="",AND($I18="Yes",$K18<>""),IF(ISNUMBER($H18),OR($H18<1,$H18>5,$H18<>INT($H18)),TRUE())),TRUE())),1,0) -> 0 | AL18: =IF(IFERROR(NOT(OR($S18="",$S18="Open",$S18="In progress",$S18="Remediated",$S18="Accepted Risk",$S18="Not applicable")),TRUE()),1,0) -> 0 | AM18: =IF(OR(IFERROR(IF($S18="Accepted Risk",OR($X18="",$Y18="",$Z18=""),FALSE()),TRUE()),IF(IFERROR($Z18<>"",FALSE()),NOT(IFERROR(AND(ISNUMBER($Z18),$Z18>=DATE(2020,1,1),$Z18<=DATE(2100,12,31)),FALSE())),ISERROR($Z18))),1,0) -> 0 | AN18: =IF(IFERROR(AND($I18="Yes",$K18="N/A"),FALSE()),1,0) -> 0 | AO18: =IF(IFERROR(IF($J18<>"",$T18="",FALSE()),TRUE()),1,0) -> 0 | AP18: =IF(IFERROR(IF($I18="Yes",IF(OR($K18="Yes",$K18="Partial"),IF(ISERROR($O18),TRUE(),$O18=""),FALSE()),FALSE()),FALSE()),1,0) -> 0 | AQ18: =IF(OR($AF18>0,$AG18>0,$AJ18>0,$AK18>0,$AL18>0,$AM18>0,$AN18>0,$AO18>0),1,0) -> 0 | AR18: =IF(IFERROR(AND($I18="Yes",OR($K18="Yes",$K18="Partial",$K18="No")),FALSE()),1,0) -> 0 | AS18: =IFERROR(IF($AR18=1,$F18*$L18,0),0) -> 0 | AT18: =IFERROR(IF($AR18=1,$F18,0),0) -> 0 | AU18: =_xlfn.TEXTJOIN(", ",TRUE(),IF(ISERROR($E18),"E18",""),IF(ISERROR($G18),"G18",""),IF(ISERROR($H18),"H18",""),IF(ISERROR($J18),"J18",""),IF(ISERROR($K18),"K18",""),IF(ISERROR($O18),"O18",""),IF(ISERROR($P18),"P18",""),IF(ISERROR($Q18),"Q18",""),IF(ISERROR($R18),"R18",""),IF(ISERROR($S18),"S18",""),IF(ISERROR($T18),"T18",""),IF(ISERROR($X18),"X18",""),IF(ISERROR($Y18),"Y18",""),IF(ISERROR($Z18),"Z18","")) | AV18: =_xlfn.TEXTJOIN("; ",TRUE(),IF(IFERROR(NOT(OR($J18="",$J18="Yes",$J18="No")),TRUE()),"Invalid override value (J)",""),IF(IFERROR(IF($E18="",$I18="Yes",NOT(OR($E18="Blocker",$E18="Major",$E18="Moderate",$E18="Minor"))),TRUE()),"Invalid or missing criticality (E)",""),IF(IFERROR(IF($J18<>"",$T18="",FALSE()),TRUE()),"Override rationale missing / invalid (T)",""),IF(IFERROR(IF(AND($A18="2.7",$I18="Yes",p_confidential="Yes"),$E18<>"Blocker",FALSE()),TRUE()),"2.7 must be Blocker when S4 = Yes",""),IF(IFERROR(IF(AND($A18="5.8",$I18="Yes"),OR($E18="Moderate",$E18="Minor"),FALSE()),TRUE()),"5.8 should be at least Major",""),IF(IF(IFERROR(AND($J18="No",$AI18="Yes",OR($AD18="Blocker",AND($A18="2.7",p_confidential="Yes"))),FALSE()),NOT(AND(IFERROR($X18<>"",FALSE()),IFERROR($Y18<>"",FALSE()),IFERROR(AND(ISNUMBER($Z18),$Z18>=DATE(2020,1,1),$Z18<=DATE(2100,12,31)),FALSE()))),FALSE()),"Blocker de-scope review missing / invalid (X-Z)",""),IF(IF(IFERROR(IF(OR($E18="Blocker",$E18="Major",$E18="Moderate",$E18="Minor"),$F18<IF($AD18="Blocker",Lookups!$B$8,IF($AD18="Major",Lookups!$B$9,IF($AD18="Moderate",Lookups!$B$10,Lookups!$B$11))),FALSE()),FALSE()),NOT(AND(IFERROR($T18<>"",FALSE()),IFERROR($Y18<>"",FALSE()),IF(IFERROR($Z18<>"",FALSE()),IFERROR(AND(ISNUMBER($Z18),$Z18>=DATE(2020,1,1),$Z18<=DATE(2100,12,31)),FALSE()),NOT(ISERROR($Z18))))),FALSE()),"Criticality below baseline: review missing / invalid (T,Y,Z)","")) | AW18: =_xlfn.TEXTJOIN("; ",TRUE(),IF($AJ18>0,"Invalid response value (K)",""),IF($AK18>0,"Likelihood/Impact missing or not integer 1-5 (G,H)",""),IF($AL18>0,"Invalid status value (S)",""),IF($AM18>0,_xlfn.TEXTJOIN("; ",TRUE(),IF(IFERROR(AND($S18="Accepted Risk",$X18=""),FALSE()),"Exemption reference (X) missing",""),IF(IFERROR(AND($S18="Accepted Risk",$Y18=""),FALSE()),"Exemption approver (Y) missing",""),IF(IFERROR(AND($S18="Accepted Risk",$Z18=""),FALSE()),"Exemption date (Z) missing",""),IF(ISERROR($Z18),"Exemption date (Z) invalid - error value",IF(IFERROR(AND($Z18<>"",NOT(AND(ISNUMBER($Z18),$Z18>=DATE(2020,1,1),$Z18<=DATE(2100,12,31)))),FALSE()),"Exemption date (Z) invalid - enter a real date","")),IF(OR(ISERROR($S18),ISERROR($X18),ISERROR($Y18)),"Exemption inputs contain an error value (S,X,Y)","")),""),IF($AG18>0,"Input/calculation fault at "&$AU18,""),IF($AN18>0,"N/A on applicable row",""))
A19: 3.6 | B19: Architecture & Integration | C19: Auto: unless S7 = No and S11 = No | D19: Outputs are treated as untrusted and validated/sandboxed before execution, rendering, or downstream action. | E19: Blocker | F19: =IFERROR(IF($E19="Blocker",Lookups!$B$8,IF($E19="Major",Lookups!$B$9,IF($E19="Moderate",Lookups!$B$10,IF($E19="Minor",Lookups!$B$11,0)))),0) -> 5 | G19: 4 | H19: 5 | I19: =IFERROR(IF(OR($J19="Yes",$J19="No"),$J19,IF(AND(p_downstream="No",p_tools="No"),"No","Yes")),"Yes") -> Yes | L19: =IFERROR(IF(OR($I19="No",$K19="N/A"),"",IF($K19="Yes",1,IF($K19="Partial",0.5,IF($K19="No",0,"")))),"") | M19: =IFERROR(IF(OR($I19="No",$K19="N/A"),"",$F19*IF(OR($G19="",NOT(ISNUMBER($G19))),3,$G19)*IF(OR($H19="",NOT(ISNUMBER($H19))),3,$H19)*IF($K19="",1,1-$L19)),"") -> 100 | N19: =IFERROR(IF(OR($I19="No",$K19="N/A",$K19=""),"",IF(AND(IFERROR(AND($S19="Accepted Risk",$AM19=0),FALSE()),OR(AND($E19="Blocker",OR($K19="No",$K19="Partial")),AND($E19="Major",$K19="No"))),IF(AND($E19="Blocker",$K19="No"),"BLOCK",IF(AND($E19="Blocker",$K19="Partial"),IF(p_stage="Pilot / PoC","ESCALATE","BLOCK"),IF(AND($E19="Major",$K19="No"),"ESCALATE","")))&" (exempted)",IF(AND($E19="Blocker",$K19="No"),"BLOCK",IF(AND($E19="Blocker",$K19="Partial"),IF(p_stage="Pilot / PoC","ESCALATE","BLOCK"),IF(AND($E19="Major",$K19="No"),"ESCALATE",""))))),"") | U19: =_xlfn.TEXTJOIN("; ",TRUE(),$AV19,$AW19,IF($AP19>0,"Evidence missing or unusable","")) | V19: 4.2, 4.9 — 3.6 gates downstream execution/rendering; 4.2 covers output content handling; 4.9 covers generated code artefacts. | W19: Good: every output channel (execution, rendering, downstream action) passes validation/sandboxing. Evidence: code + tests per channel. Partial: some channels validated. Advisory map (partial): OWASP LLM05 Improper Output Handling. | AA19: =IF($AN19>0,$A19,"") | AB19: =IF($AO19>0,$A19,"") | AC19: =IF($AQ19>0,$A19&" ("&$U19&")","") | AD19: Blocker | AF19: =IF(OR(IFERROR(NOT(OR($J19="",$J19="Yes",$J19="No")),TRUE()),IFERROR(IF($E19="",$I19="Yes",NOT(OR($E19="Blocker",$E19="Major",$E19="Moderate",$E19="Minor"))),TRUE()),IFERROR(IF($J19<>"",$T19="",FALSE()),TRUE()),IFERROR(IF(AND($A19="2.7",$I19="Yes",p_confidential="Yes"),$E19<>"Blocker",FALSE()),TRUE()),IFERROR(IF(AND($A19="5.8",$I19="Yes"),OR($E19="Moderate",$E19="Minor"),FALSE()),TRUE()),IF(IFERROR(AND($J19="No",$AI19="Yes",OR($AD19="Blocker",AND($A19="2.7",p_confidential="Yes"))),FALSE()),NOT(AND(IFERROR($X19<>"",FALSE()),IFERROR($Y19<>"",FALSE()),IFERROR(AND(ISNUMBER($Z19),$Z19>=DATE(2020,1,1),$Z19<=DATE(2100,12,31)),FALSE()))),FALSE()),IF(IFERROR(IF(OR($E19="Blocker",$E19="Major",$E19="Moderate",$E19="Minor"),$F19<IF($AD19="Blocker",Lookups!$B$8,IF($AD19="Major",Lookups!$B$9,IF($AD19="Moderate",Lookups!$B$10,Lookups!$B$11))),FALSE()),FALSE()),NOT(AND(IFERROR($T19<>"",FALSE()),IFERROR($Y19<>"",FALSE()),IF(IFERROR($Z19<>"",FALSE()),IFERROR(AND(ISNUMBER($Z19),$Z19>=DATE(2020,1,1),$Z19<=DATE(2100,12,31)),FALSE()),NOT(ISERROR($Z19))))),FALSE())),1,0) -> 0 | AG19: =IF(OR(ISERROR($E19),ISERROR($G19),ISERROR($H19),ISERROR($J19),ISERROR($K19),ISERROR($O19),ISERROR($P19),ISERROR($Q19),ISERROR($R19),ISERROR($S19),ISERROR($T19),ISERROR($X19),ISERROR($Y19),ISERROR($Z19)),1,0) -> 0 | AH19: =IF($AF19>0,$A19&" ("&$AV19&")","") | AI19: =IFERROR(IF(AND(p_downstream="No",p_tools="No"),"No","Yes"),"Yes") -> Yes | AJ19: =IF(IFERROR(NOT(OR($K19="",$K19="Yes",$K19="Partial",$K19="No",$K19="N/A")),TRUE()),1,0) -> 0 | AK19: =IF(OR(IFERROR(IF($G19="",AND($I19="Yes",$K19<>""),IF(ISNUMBER($G19),OR($G19<1,$G19>5,$G19<>INT($G19)),TRUE())),TRUE()),IFERROR(IF($H19="",AND($I19="Yes",$K19<>""),IF(ISNUMBER($H19),OR($H19<1,$H19>5,$H19<>INT($H19)),TRUE())),TRUE())),1,0) -> 0 | AL19: =IF(IFERROR(NOT(OR($S19="",$S19="Open",$S19="In progress",$S19="Remediated",$S19="Accepted Risk",$S19="Not applicable")),TRUE()),1,0) -> 0 | AM19: =IF(OR(IFERROR(IF($S19="Accepted Risk",OR($X19="",$Y19="",$Z19=""),FALSE()),TRUE()),IF(IFERROR($Z19<>"",FALSE()),NOT(IFERROR(AND(ISNUMBER($Z19),$Z19>=DATE(2020,1,1),$Z19<=DATE(2100,12,31)),FALSE())),ISERROR($Z19))),1,0) -> 0 | AN19: =IF(IFERROR(AND($I19="Yes",$K19="N/A"),FALSE()),1,0) -> 0 | AO19: =IF(IFERROR(IF($J19<>"",$T19="",FALSE()),TRUE()),1,0) -> 0 | AP19: =IF(IFERROR(IF($I19="Yes",IF(OR($K19="Yes",$K19="Partial"),IF(ISERROR($O19),TRUE(),$O19=""),FALSE()),FALSE()),FALSE()),1,0) -> 0 | AQ19: =IF(OR($AF19>0,$AG19>0,$AJ19>0,$AK19>0,$AL19>0,$AM19>0,$AN19>0,$AO19>0),1,0) -> 0 | AR19: =IF(IFERROR(AND($I19="Yes",OR($K19="Yes",$K19="Partial",$K19="No")),FALSE()),1,0) -> 0 | AS19: =IFERROR(IF($AR19=1,$F19*$L19,0),0) -> 0 | AT19: =IFERROR(IF($AR19=1,$F19,0),0) -> 0 | AU19: =_xlfn.TEXTJOIN(", ",TRUE(),IF(ISERROR($E19),"E19",""),IF(ISERROR($G19),"G19",""),IF(ISERROR($H19),"H19",""),IF(ISERROR($J19),"J19",""),IF(ISERROR($K19),"K19",""),IF(ISERROR($O19),"O19",""),IF(ISERROR($P19),"P19",""),IF(ISERROR($Q19),"Q19",""),IF(ISERROR($R19),"R19",""),IF(ISERROR($S19),"S19",""),IF(ISERROR($T19),"T19",""),IF(ISERROR($X19),"X19",""),IF(ISERROR($Y19),"Y19",""),IF(ISERROR($Z19),"Z19","")) | AV19: =_xlfn.TEXTJOIN("; ",TRUE(),IF(IFERROR(NOT(OR($J19="",$J19="Yes",$J19="No")),TRUE()),"Invalid override value (J)",""),IF(IFERROR(IF($E19="",$I19="Yes",NOT(OR($E19="Blocker",$E19="Major",$E19="Moderate",$E19="Minor"))),TRUE()),"Invalid or missing criticality (E)",""),IF(IFERROR(IF($J19<>"",$T19="",FALSE()),TRUE()),"Override rationale missing / invalid (T)",""),IF(IFERROR(IF(AND($A19="2.7",$I19="Yes",p_confidential="Yes"),$E19<>"Blocker",FALSE()),TRUE()),"2.7 must be Blocker when S4 = Yes",""),IF(IFERROR(IF(AND($A19="5.8",$I19="Yes"),OR($E19="Moderate",$E19="Minor"),FALSE()),TRUE()),"5.8 should be at least Major",""),IF(IF(IFERROR(AND($J19="No",$AI19="Yes",OR($AD19="Blocker",AND($A19="2.7",p_confidential="Yes"))),FALSE()),NOT(AND(IFERROR($X19<>"",FALSE()),IFERROR($Y19<>"",FALSE()),IFERROR(AND(ISNUMBER($Z19),$Z19>=DATE(2020,1,1),$Z19<=DATE(2100,12,31)),FALSE()))),FALSE()),"Blocker de-scope review missing / invalid (X-Z)",""),IF(IF(IFERROR(IF(OR($E19="Blocker",$E19="Major",$E19="Moderate",$E19="Minor"),$F19<IF($AD19="Blocker",Lookups!$B$8,IF($AD19="Major",Lookups!$B$9,IF($AD19="Moderate",Lookups!$B$10,Lookups!$B$11))),FALSE()),FALSE()),NOT(AND(IFERROR($T19<>"",FALSE()),IFERROR($Y19<>"",FALSE()),IF(IFERROR($Z19<>"",FALSE()),IFERROR(AND(ISNUMBER($Z19),$Z19>=DATE(2020,1,1),$Z19<=DATE(2100,12,31)),FALSE()),NOT(ISERROR($Z19))))),FALSE()),"Criticality below baseline: review missing / invalid (T,Y,Z)","")) | AW19: =_xlfn.TEXTJOIN("; ",TRUE(),IF($AJ19>0,"Invalid response value (K)",""),IF($AK19>0,"Likelihood/Impact missing or not integer 1-5 (G,H)",""),IF($AL19>0,"Invalid status value (S)",""),IF($AM19>0,_xlfn.TEXTJOIN("; ",TRUE(),IF(IFERROR(AND($S19="Accepted Risk",$X19=""),FALSE()),"Exemption reference (X) missing",""),IF(IFERROR(AND($S19="Accepted Risk",$Y19=""),FALSE()),"Exemption approver (Y) missing",""),IF(IFERROR(AND($S19="Accepted Risk",$Z19=""),FALSE()),"Exemption date (Z) missing",""),IF(ISERROR($Z19),"Exemption date (Z) invalid - error value",IF(IFERROR(AND($Z19<>"",NOT(AND(ISNUMBER($Z19),$Z19>=DATE(2020,1,1),$Z19<=DATE(2100,12,31)))),FALSE()),"Exemption date (Z) invalid - enter a real date","")),IF(OR(ISERROR($S19),ISERROR($X19),ISERROR($Y19)),"Exemption inputs contain an error value (S,X,Y)","")),""),IF($AG19>0,"Input/calculation fault at "&$AU19,""),IF($AN19>0,"N/A on applicable row",""))
A20: 3.7 | B20: Architecture & Integration | C20: Auto: only if S17 = Production / OT proximity | D20: If deployed in or adjacent to production/OT environments: OT networks and safety functions are segregated, and the system has no unvalidated write path into control systems. | E20: Blocker | F20: =IFERROR(IF($E20="Blocker",Lookups!$B$8,IF($E20="Major",Lookups!$B$9,IF($E20="Moderate",Lookups!$B$10,IF($E20="Minor",Lookups!$B$11,0)))),0) -> 5 | G20: 3 | H20: 5 | I20: =IFERROR(IF(OR($J20="Yes",$J20="No"),$J20,IF(OR(p_locus="End user client / endpoint",p_locus="Cloud or SaaS tenant",p_locus="Own data center / servers",p_locus="Network or gateway (inline)"),"No","Yes")),"Yes") -> Yes | L20: =IFERROR(IF(OR($I20="No",$K20="N/A"),"",IF($K20="Yes",1,IF($K20="Partial",0.5,IF($K20="No",0,"")))),"") | M20: =IFERROR(IF(OR($I20="No",$K20="N/A"),"",$F20*IF(OR($G20="",NOT(ISNUMBER($G20))),3,$G20)*IF(OR($H20="",NOT(ISNUMBER($H20))),3,$H20)*IF($K20="",1,1-$L20)),"") -> 75 | N20: =IFERROR(IF(OR($I20="No",$K20="N/A",$K20=""),"",IF(AND(IFERROR(AND($S20="Accepted Risk",$AM20=0),FALSE()),OR(AND($E20="Blocker",OR($K20="No",$K20="Partial")),AND($E20="Major",$K20="No"))),IF(AND($E20="Blocker",$K20="No"),"BLOCK",IF(AND($E20="Blocker",$K20="Partial"),IF(p_stage="Pilot / PoC","ESCALATE","BLOCK"),IF(AND($E20="Major",$K20="No"),"ESCALATE","")))&" (exempted)",IF(AND($E20="Blocker",$K20="No"),"BLOCK",IF(AND($E20="Blocker",$K20="Partial"),IF(p_stage="Pilot / PoC","ESCALATE","BLOCK"),IF(AND($E20="Major",$K20="No"),"ESCALATE",""))))),"") | U20: =_xlfn.TEXTJOIN("; ",TRUE(),$AV20,$AW20,IF($AP20>0,"Evidence missing or unusable","")) | W20: Good: OT/safety segregation documented; no unvalidated write path into control systems. Evidence: network diagram, pentest or architecture review. Partial: segmented, write path unreviewed. | AA20: =IF($AN20>0,$A20,"") | AB20: =IF($AO20>0,$A20,"") | AC20: =IF($AQ20>0,$A20&" ("&$U20&")","") | AD20: Blocker | AF20: =IF(OR(IFERROR(NOT(OR($J20="",$J20="Yes",$J20="No")),TRUE()),IFERROR(IF($E20="",$I20="Yes",NOT(OR($E20="Blocker",$E20="Major",$E20="Moderate",$E20="Minor"))),TRUE()),IFERROR(IF($J20<>"",$T20="",FALSE()),TRUE()),IFERROR(IF(AND($A20="2.7",$I20="Yes",p_confidential="Yes"),$E20<>"Blocker",FALSE()),TRUE()),IFERROR(IF(AND($A20="5.8",$I20="Yes"),OR($E20="Moderate",$E20="Minor"),FALSE()),TRUE()),IF(IFERROR(AND($J20="No",$AI20="Yes",OR($AD20="Blocker",AND($A20="2.7",p_confidential="Yes"))),FALSE()),NOT(AND(IFERROR($X20<>"",FALSE()),IFERROR($Y20<>"",FALSE()),IFERROR(AND(ISNUMBER($Z20),$Z20>=DATE(2020,1,1),$Z20<=DATE(2100,12,31)),FALSE()))),FALSE()),IF(IFERROR(IF(OR($E20="Blocker",$E20="Major",$E20="Moderate",$E20="Minor"),$F20<IF($AD20="Blocker",Lookups!$B$8,IF($AD20="Major",Lookups!$B$9,IF($AD20="Moderate",Lookups!$B$10,Lookups!$B$11))),FALSE()),FALSE()),NOT(AND(IFERROR($T20<>"",FALSE()),IFERROR($Y20<>"",FALSE()),IF(IFERROR($Z20<>"",FALSE()),IFERROR(AND(ISNUMBER($Z20),$Z20>=DATE(2020,1,1),$Z20<=DATE(2100,12,31)),FALSE()),NOT(ISERROR($Z20))))),FALSE())),1,0) -> 0 | AG20: =IF(OR(ISERROR($E20),ISERROR($G20),ISERROR($H20),ISERROR($J20),ISERROR($K20),ISERROR($O20),ISERROR($P20),ISERROR($Q20),ISERROR($R20),ISERROR($S20),ISERROR($T20),ISERROR($X20),ISERROR($Y20),ISERROR($Z20)),1,0) -> 0 | AH20: =IF($AF20>0,$A20&" ("&$AV20&")","") | AI20: =IFERROR(IF(OR(p_locus="End user client / endpoint",p_locus="Cloud or SaaS tenant",p_locus="Own data center / servers",p_locus="Network or gateway (inline)"),"No","Yes"),"Yes") -> Yes | AJ20: =IF(IFERROR(NOT(OR($K20="",$K20="Yes",$K20="Partial",$K20="No",$K20="N/A")),TRUE()),1,0) -> 0 | AK20: =IF(OR(IFERROR(IF($G20="",AND($I20="Yes",$K20<>""),IF(ISNUMBER($G20),OR($G20<1,$G20>5,$G20<>INT($G20)),TRUE())),TRUE()),IFERROR(IF($H20="",AND($I20="Yes",$K20<>""),IF(ISNUMBER($H20),OR($H20<1,$H20>5,$H20<>INT($H20)),TRUE())),TRUE())),1,0) -> 0 | AL20: =IF(IFERROR(NOT(OR($S20="",$S20="Open",$S20="In progress",$S20="Remediated",$S20="Accepted Risk",$S20="Not applicable")),TRUE()),1,0) -> 0 | AM20: =IF(OR(IFERROR(IF($S20="Accepted Risk",OR($X20="",$Y20="",$Z20=""),FALSE()),TRUE()),IF(IFERROR($Z20<>"",FALSE()),NOT(IFERROR(AND(ISNUMBER($Z20),$Z20>=DATE(2020,1,1),$Z20<=DATE(2100,12,31)),FALSE())),ISERROR($Z20))),1,0) -> 0 | AN20: =IF(IFERROR(AND($I20="Yes",$K20="N/A"),FALSE()),1,0) -> 0 | AO20: =IF(IFERROR(IF($J20<>"",$T20="",FALSE()),TRUE()),1,0) -> 0 | AP20: =IF(IFERROR(IF($I20="Yes",IF(OR($K20="Yes",$K20="Partial"),IF(ISERROR($O20),TRUE(),$O20=""),FALSE()),FALSE()),FALSE()),1,0) -> 0 | AQ20: =IF(OR($AF20>0,$AG20>0,$AJ20>0,$AK20>0,$AL20>0,$AM20>0,$AN20>0,$AO20>0),1,0) -> 0 | AR20: =IF(IFERROR(AND($I20="Yes",OR($K20="Yes",$K20="Partial",$K20="No")),FALSE()),1,0) -> 0 | AS20: =IFERROR(IF($AR20=1,$F20*$L20,0),0) -> 0 | AT20: =IFERROR(IF($AR20=1,$F20,0),0) -> 0 | AU20: =_xlfn.TEXTJOIN(", ",TRUE(),IF(ISERROR($E20),"E20",""),IF(ISERROR($G20),"G20",""),IF(ISERROR($H20),"H20",""),IF(ISERROR($J20),"J20",""),IF(ISERROR($K20),"K20",""),IF(ISERROR($O20),"O20",""),IF(ISERROR($P20),"P20",""),IF(ISERROR($Q20),"Q20",""),IF(ISERROR($R20),"R20",""),IF(ISERROR($S20),"S20",""),IF(ISERROR($T20),"T20",""),IF(ISERROR($X20),"X20",""),IF(ISERROR($Y20),"Y20",""),IF(ISERROR($Z20),"Z20","")) | AV20: =_xlfn.TEXTJOIN("; ",TRUE(),IF(IFERROR(NOT(OR($J20="",$J20="Yes",$J20="No")),TRUE()),"Invalid override value (J)",""),IF(IFERROR(IF($E20="",$I20="Yes",NOT(OR($E20="Blocker",$E20="Major",$E20="Moderate",$E20="Minor"))),TRUE()),"Invalid or missing criticality (E)",""),IF(IFERROR(IF($J20<>"",$T20="",FALSE()),TRUE()),"Override rationale missing / invalid (T)",""),IF(IFERROR(IF(AND($A20="2.7",$I20="Yes",p_confidential="Yes"),$E20<>"Blocker",FALSE()),TRUE()),"2.7 must be Blocker when S4 = Yes",""),IF(IFERROR(IF(AND($A20="5.8",$I20="Yes"),OR($E20="Moderate",$E20="Minor"),FALSE()),TRUE()),"5.8 should be at least Major",""),IF(IF(IFERROR(AND($J20="No",$AI20="Yes",OR($AD20="Blocker",AND($A20="2.7",p_confidential="Yes"))),FALSE()),NOT(AND(IFERROR($X20<>"",FALSE()),IFERROR($Y20<>"",FALSE()),IFERROR(AND(ISNUMBER($Z20),$Z20>=DATE(2020,1,1),$Z20<=DATE(2100,12,31)),FALSE()))),FALSE()),"Blocker de-scope review missing / invalid (X-Z)",""),IF(IF(IFERROR(IF(OR($E20="Blocker",$E20="Major",$E20="Moderate",$E20="Minor"),$F20<IF($AD20="Blocker",Lookups!$B$8,IF($AD20="Major",Lookups!$B$9,IF($AD20="Moderate",Lookups!$B$10,Lookups!$B$11))),FALSE()),FALSE()),NOT(AND(IFERROR($T20<>"",FALSE()),IFERROR($Y20<>"",FALSE()),IF(IFERROR($Z20<>"",FALSE()),IFERROR(AND(ISNUMBER($Z20),$Z20>=DATE(2020,1,1),$Z20<=DATE(2100,12,31)),FALSE()),NOT(ISERROR($Z20))))),FALSE()),"Criticality below baseline: review missing / invalid (T,Y,Z)","")) | AW20: =_xlfn.TEXTJOIN("; ",TRUE(),IF($AJ20>0,"Invalid response value (K)",""),IF($AK20>0,"Likelihood/Impact missing or not integer 1-5 (G,H)",""),IF($AL20>0,"Invalid status value (S)",""),IF($AM20>0,_xlfn.TEXTJOIN("; ",TRUE(),IF(IFERROR(AND($S20="Accepted Risk",$X20=""),FALSE()),"Exemption reference (X) missing",""),IF(IFERROR(AND($S20="Accepted Risk",$Y20=""),FALSE()),"Exemption approver (Y) missing",""),IF(IFERROR(AND($S20="Accepted Risk",$Z20=""),FALSE()),"Exemption date (Z) missing",""),IF(ISERROR($Z20),"Exemption date (Z) invalid - error value",IF(IFERROR(AND($Z20<>"",NOT(AND(ISNUMBER($Z20),$Z20>=DATE(2020,1,1),$Z20<=DATE(2100,12,31)))),FALSE()),"Exemption date (Z) invalid - enter a real date","")),IF(OR(ISERROR($S20),ISERROR($X20),ISERROR($Y20)),"Exemption inputs contain an error value (S,X,Y)","")),""),IF($AG20>0,"Input/calculation fault at "&$AU20,""),IF($AN20>0,"N/A on applicable row",""))
A21: 3.8 | B21: Architecture & Integration | C21: Auto: always | D21: Conversational context and session state are isolated between users, sessions, and tenants; no cross-session leakage of prompts, history, or retrieved content. | E21: Blocker | F21: =IFERROR(IF($E21="Blocker",Lookups!$B$8,IF($E21="Major",Lookups!$B$9,IF($E21="Moderate",Lookups!$B$10,IF($E21="Minor",Lookups!$B$11,0)))),0) -> 5 | G21: 4 | H21: 5 | I21: =IFERROR(IF(OR($J21="Yes",$J21="No"),$J21,"Yes"),"Yes") -> Yes | L21: =IFERROR(IF(OR($I21="No",$K21="N/A"),"",IF($K21="Yes",1,IF($K21="Partial",0.5,IF($K21="No",0,"")))),"") | M21: =IFERROR(IF(OR($I21="No",$K21="N/A"),"",$F21*IF(OR($G21="",NOT(ISNUMBER($G21))),3,$G21)*IF(OR($H21="",NOT(ISNUMBER($H21))),3,$H21)*IF($K21="",1,1-$L21)),"") -> 100 | N21: =IFERROR(IF(OR($I21="No",$K21="N/A",$K21=""),"",IF(AND(IFERROR(AND($S21="Accepted Risk",$AM21=0),FALSE()),OR(AND($E21="Blocker",OR($K21="No",$K21="Partial")),AND($E21="Major",$K21="No"))),IF(AND($E21="Blocker",$K21="No"),"BLOCK",IF(AND($E21="Blocker",$K21="Partial"),IF(p_stage="Pilot / PoC","ESCALATE","BLOCK"),IF(AND($E21="Major",$K21="No"),"ESCALATE","")))&" (exempted)",IF(AND($E21="Blocker",$K21="No"),"BLOCK",IF(AND($E21="Blocker",$K21="Partial"),IF(p_stage="Pilot / PoC","ESCALATE","BLOCK"),IF(AND($E21="Major",$K21="No"),"ESCALATE",""))))),"") | U21: =_xlfn.TEXTJOIN("; ",TRUE(),$AV21,$AW21,IF($AP21>0,"Evidence missing or unusable","")) | W21: Good: session/conversation state isolated per user, session, tenant; tested for cross-session leakage. Evidence: design doc + test results. Partial: isolation implemented, untested. | AA21: =IF($AN21>0,$A21,"") | AB21: =IF($AO21>0,$A21,"") | AC21: =IF($AQ21>0,$A21&" ("&$U21&")","") | AD21: Blocker | AF21: =IF(OR(IFERROR(NOT(OR($J21="",$J21="Yes",$J21="No")),TRUE()),IFERROR(IF($E21="",$I21="Yes",NOT(OR($E21="Blocker",$E21="Major",$E21="Moderate",$E21="Minor"))),TRUE()),IFERROR(IF($J21<>"",$T21="",FALSE()),TRUE()),IFERROR(IF(AND($A21="2.7",$I21="Yes",p_confidential="Yes"),$E21<>"Blocker",FALSE()),TRUE()),IFERROR(IF(AND($A21="5.8",$I21="Yes"),OR($E21="Moderate",$E21="Minor"),FALSE()),TRUE()),IF(IFERROR(AND($J21="No",$AI21="Yes",OR($AD21="Blocker",AND($A21="2.7",p_confidential="Yes"))),FALSE()),NOT(AND(IFERROR($X21<>"",FALSE()),IFERROR($Y21<>"",FALSE()),IFERROR(AND(ISNUMBER($Z21),$Z21>=DATE(2020,1,1),$Z21<=DATE(2100,12,31)),FALSE()))),FALSE()),IF(IFERROR(IF(OR($E21="Blocker",$E21="Major",$E21="Moderate",$E21="Minor"),$F21<IF($AD21="Blocker",Lookups!$B$8,IF($AD21="Major",Lookups!$B$9,IF($AD21="Moderate",Lookups!$B$10,Lookups!$B$11))),FALSE()),FALSE()),NOT(AND(IFERROR($T21<>"",FALSE()),IFERROR($Y21<>"",FALSE()),IF(IFERROR($Z21<>"",FALSE()),IFERROR(AND(ISNUMBER($Z21),$Z21>=DATE(2020,1,1),$Z21<=DATE(2100,12,31)),FALSE()),NOT(ISERROR($Z21))))),FALSE())),1,0) -> 0 | AG21: =IF(OR(ISERROR($E21),ISERROR($G21),ISERROR($H21),ISERROR($J21),ISERROR($K21),ISERROR($O21),ISERROR($P21),ISERROR($Q21),ISERROR($R21),ISERROR($S21),ISERROR($T21),ISERROR($X21),ISERROR($Y21),ISERROR($Z21)),1,0) -> 0 | AH21: =IF($AF21>0,$A21&" ("&$AV21&")","") | AI21: =IFERROR("Yes","Yes") -> Yes | AJ21: =IF(IFERROR(NOT(OR($K21="",$K21="Yes",$K21="Partial",$K21="No",$K21="N/A")),TRUE()),1,0) -> 0 | AK21: =IF(OR(IFERROR(IF($G21="",AND($I21="Yes",$K21<>""),IF(ISNUMBER($G21),OR($G21<1,$G21>5,$G21<>INT($G21)),TRUE())),TRUE()),IFERROR(IF($H21="",AND($I21="Yes",$K21<>""),IF(ISNUMBER($H21),OR($H21<1,$H21>5,$H21<>INT($H21)),TRUE())),TRUE())),1,0) -> 0 | AL21: =IF(IFERROR(NOT(OR($S21="",$S21="Open",$S21="In progress",$S21="Remediated",$S21="Accepted Risk",$S21="Not applicable")),TRUE()),1,0) -> 0 | AM21: =IF(OR(IFERROR(IF($S21="Accepted Risk",OR($X21="",$Y21="",$Z21=""),FALSE()),TRUE()),IF(IFERROR($Z21<>"",FALSE()),NOT(IFERROR(AND(ISNUMBER($Z21),$Z21>=DATE(2020,1,1),$Z21<=DATE(2100,12,31)),FALSE())),ISERROR($Z21))),1,0) -> 0 | AN21: =IF(IFERROR(AND($I21="Yes",$K21="N/A"),FALSE()),1,0) -> 0 | AO21: =IF(IFERROR(IF($J21<>"",$T21="",FALSE()),TRUE()),1,0) -> 0 | AP21: =IF(IFERROR(IF($I21="Yes",IF(OR($K21="Yes",$K21="Partial"),IF(ISERROR($O21),TRUE(),$O21=""),FALSE()),FALSE()),FALSE()),1,0) -> 0 | AQ21: =IF(OR($AF21>0,$AG21>0,$AJ21>0,$AK21>0,$AL21>0,$AM21>0,$AN21>0,$AO21>0),1,0) -> 0 | AR21: =IF(IFERROR(AND($I21="Yes",OR($K21="Yes",$K21="Partial",$K21="No")),FALSE()),1,0) -> 0 | AS21: =IFERROR(IF($AR21=1,$F21*$L21,0),0) -> 0 | AT21: =IFERROR(IF($AR21=1,$F21,0),0) -> 0 | AU21: =_xlfn.TEXTJOIN(", ",TRUE(),IF(ISERROR($E21),"E21",""),IF(ISERROR($G21),"G21",""),IF(ISERROR($H21),"H21",""),IF(ISERROR($J21),"J21",""),IF(ISERROR($K21),"K21",""),IF(ISERROR($O21),"O21",""),IF(ISERROR($P21),"P21",""),IF(ISERROR($Q21),"Q21",""),IF(ISERROR($R21),"R21",""),IF(ISERROR($S21),"S21",""),IF(ISERROR($T21),"T21",""),IF(ISERROR($X21),"X21",""),IF(ISERROR($Y21),"Y21",""),IF(ISERROR($Z21),"Z21","")) | AV21: =_xlfn.TEXTJOIN("; ",TRUE(),IF(IFERROR(NOT(OR($J21="",$J21="Yes",$J21="No")),TRUE()),"Invalid override value (J)",""),IF(IFERROR(IF($E21="",$I21="Yes",NOT(OR($E21="Blocker",$E21="Major",$E21="Moderate",$E21="Minor"))),TRUE()),"Invalid or missing criticality (E)",""),IF(IFERROR(IF($J21<>"",$T21="",FALSE()),TRUE()),"Override rationale missing / invalid (T)",""),IF(IFERROR(IF(AND($A21="2.7",$I21="Yes",p_confidential="Yes"),$E21<>"Blocker",FALSE()),TRUE()),"2.7 must be Blocker when S4 = Yes",""),IF(IFERROR(IF(AND($A21="5.8",$I21="Yes"),OR($E21="Moderate",$E21="Minor"),FALSE()),TRUE()),"5.8 should be at least Major",""),IF(IF(IFERROR(AND($J21="No",$AI21="Yes",OR($AD21="Blocker",AND($A21="2.7",p_confidential="Yes"))),FALSE()),NOT(AND(IFERROR($X21<>"",FALSE()),IFERROR($Y21<>"",FALSE()),IFERROR(AND(ISNUMBER($Z21),$Z21>=DATE(2020,1,1),$Z21<=DATE(2100,12,31)),FALSE()))),FALSE()),"Blocker de-scope review missing / invalid (X-Z)",""),IF(IF(IFERROR(IF(OR($E21="Blocker",$E21="Major",$E21="Moderate",$E21="Minor"),$F21<IF($AD21="Blocker",Lookups!$B$8,IF($AD21="Major",Lookups!$B$9,IF($AD21="Moderate",Lookups!$B$10,Lookups!$B$11))),FALSE()),FALSE()),NOT(AND(IFERROR($T21<>"",FALSE()),IFERROR($Y21<>"",FALSE()),IF(IFERROR($Z21<>"",FALSE()),IFERROR(AND(ISNUMBER($Z21),$Z21>=DATE(2020,1,1),$Z21<=DATE(2100,12,31)),FALSE()),NOT(ISERROR($Z21))))),FALSE()),"Criticality below baseline: review missing / invalid (T,Y,Z)","")) | AW21: =_xlfn.TEXTJOIN("; ",TRUE(),IF($AJ21>0,"Invalid response value (K)",""),IF($AK21>0,"Likelihood/Impact missing or not integer 1-5 (G,H)",""),IF($AL21>0,"Invalid status value (S)",""),IF($AM21>0,_xlfn.TEXTJOIN("; ",TRUE(),IF(IFERROR(AND($S21="Accepted Risk",$X21=""),FALSE()),"Exemption reference (X) missing",""),IF(IFERROR(AND($S21="Accepted Risk",$Y21=""),FALSE()),"Exemption approver (Y) missing",""),IF(IFERROR(AND($S21="Accepted Risk",$Z21=""),FALSE()),"Exemption date (Z) missing",""),IF(ISERROR($Z21),"Exemption date (Z) invalid - error value",IF(IFERROR(AND($Z21<>"",NOT(AND(ISNUMBER($Z21),$Z21>=DATE(2020,1,1),$Z21<=DATE(2100,12,31)))),FALSE()),"Exemption date (Z) invalid - enter a real date","")),IF(OR(ISERROR($S21),ISERROR($X21),ISERROR($Y21)),"Exemption inputs contain an error value (S,X,Y)","")),""),IF($AG21>0,"Input/calculation fault at "&$AU21,""),IF($AN21>0,"N/A on applicable row",""))
A22: 3.9 | B22: Architecture & Integration | C22: Auto: if external provider or tools | D22: Sensitive data is technically redacted, tokenized, or minimized (PII/secret scrubbing, DLP rules) before content leaves the trust boundary toward external providers or tools. | E22: Major | F22: =IFERROR(IF($E22="Blocker",Lookups!$B$8,IF($E22="Major",Lookups!$B$9,IF($E22="Moderate",Lookups!$B$10,IF($E22="Minor",Lookups!$B$11,0)))),0) -> 4 | G22: 3 | H22: 4 | I22: =IFERROR(IF(OR($J22="Yes",$J22="No"),$J22,IF(AND(OR(p_provider="Internal development",p_provider="Self-hosted / open weights"),p_tools="No"),"No","Yes")),"Yes") -> Yes | L22: =IFERROR(IF(OR($I22="No",$K22="N/A"),"",IF($K22="Yes",1,IF($K22="Partial",0.5,IF($K22="No",0,"")))),"") | M22: =IFERROR(IF(OR($I22="No",$K22="N/A"),"",$F22*IF(OR($G22="",NOT(ISNUMBER($G22))),3,$G22)*IF(OR($H22="",NOT(ISNUMBER($H22))),3,$H22)*IF($K22="",1,1-$L22)),"") -> 48 | N22: =IFERROR(IF(OR($I22="No",$K22="N/A",$K22=""),"",IF(AND(IFERROR(AND($S22="Accepted Risk",$AM22=0),FALSE()),OR(AND($E22="Blocker",OR($K22="No",$K22="Partial")),AND($E22="Major",$K22="No"))),IF(AND($E22="Blocker",$K22="No"),"BLOCK",IF(AND($E22="Blocker",$K22="Partial"),IF(p_stage="Pilot / PoC","ESCALATE","BLOCK"),IF(AND($E22="Major",$K22="No"),"ESCALATE","")))&" (exempted)",IF(AND($E22="Blocker",$K22="No"),"BLOCK",IF(AND($E22="Blocker",$K22="Partial"),IF(p_stage="Pilot / PoC","ESCALATE","BLOCK"),IF(AND($E22="Major",$K22="No"),"ESCALATE",""))))),"") | U22: =_xlfn.TEXTJOIN("; ",TRUE(),$AV22,$AW22,IF($AP22>0,"Evidence missing or unusable","")) | V22: 6.2, 7.1 — 3.9 is the technical redaction mechanism; 6.2 logging minimization; 7.1 the privacy assessment. | W22: Good: automated redaction/tokenization (PII, secrets) applied before content leaves the trust boundary to external providers or tools; rules tuned and tested. Evidence: DLP/filter config, test logs. Partial: some fields or channels covered. Advisory map (partial): OWASP LLM02 Sensitive Information Disclosure. | AA22: =IF($AN22>0,$A22,"") | AB22: =IF($AO22>0,$A22,"") | AC22: =IF($AQ22>0,$A22&" ("&$U22&")","") | AD22: Major | AF22: =IF(OR(IFERROR(NOT(OR($J22="",$J22="Yes",$J22="No")),TRUE()),IFERROR(IF($E22="",$I22="Yes",NOT(OR($E22="Blocker",$E22="Major",$E22="Moderate",$E22="Minor"))),TRUE()),IFERROR(IF($J22<>"",$T22="",FALSE()),TRUE()),IFERROR(IF(AND($A22="2.7",$I22="Yes",p_confidential="Yes"),$E22<>"Blocker",FALSE()),TRUE()),IFERROR(IF(AND($A22="5.8",$I22="Yes"),OR($E22="Moderate",$E22="Minor"),FALSE()),TRUE()),IF(IFERROR(AND($J22="No",$AI22="Yes",OR($AD22="Blocker",AND($A22="2.7",p_confidential="Yes"))),FALSE()),NOT(AND(IFERROR($X22<>"",FALSE()),IFERROR($Y22<>"",FALSE()),IFERROR(AND(ISNUMBER($Z22),$Z22>=DATE(2020,1,1),$Z22<=DATE(2100,12,31)),FALSE()))),FALSE()),IF(IFERROR(IF(OR($E22="Blocker",$E22="Major",$E22="Moderate",$E22="Minor"),$F22<IF($AD22="Blocker",Lookups!$B$8,IF($AD22="Major",Lookups!$B$9,IF($AD22="Moderate",Lookups!$B$10,Lookups!$B$11))),FALSE()),FALSE()),NOT(AND(IFERROR($T22<>"",FALSE()),IFERROR($Y22<>"",FALSE()),IF(IFERROR($Z22<>"",FALSE()),IFERROR(AND(ISNUMBER($Z22),$Z22>=DATE(2020,1,1),$Z22<=DATE(2100,12,31)),FALSE()),NOT(ISERROR($Z22))))),FALSE())),1,0) -> 0 | AG22: =IF(OR(ISERROR($E22),ISERROR($G22),ISERROR($H22),ISERROR($J22),ISERROR($K22),ISERROR($O22),ISERROR($P22),ISERROR($Q22),ISERROR($R22),ISERROR($S22),ISERROR($T22),ISERROR($X22),ISERROR($Y22),ISERROR($Z22)),1,0) -> 0 | AH22: =IF($AF22>0,$A22&" ("&$AV22&")","") | AI22: =IFERROR(IF(AND(OR(p_provider="Internal development",p_provider="Self-hosted / open weights"),p_tools="No"),"No","Yes"),"Yes") -> Yes | AJ22: =IF(IFERROR(NOT(OR($K22="",$K22="Yes",$K22="Partial",$K22="No",$K22="N/A")),TRUE()),1,0) -> 0 | AK22: =IF(OR(IFERROR(IF($G22="",AND($I22="Yes",$K22<>""),IF(ISNUMBER($G22),OR($G22<1,$G22>5,$G22<>INT($G22)),TRUE())),TRUE()),IFERROR(IF($H22="",AND($I22="Yes",$K22<>""),IF(ISNUMBER($H22),OR($H22<1,$H22>5,$H22<>INT($H22)),TRUE())),TRUE())),1,0) -> 0 | AL22: =IF(IFERROR(NOT(OR($S22="",$S22="Open",$S22="In progress",$S22="Remediated",$S22="Accepted Risk",$S22="Not applicable")),TRUE()),1,0) -> 0 | AM22: =IF(OR(IFERROR(IF($S22="Accepted Risk",OR($X22="",$Y22="",$Z22=""),FALSE()),TRUE()),IF(IFERROR($Z22<>"",FALSE()),NOT(IFERROR(AND(ISNUMBER($Z22),$Z22>=DATE(2020,1,1),$Z22<=DATE(2100,12,31)),FALSE())),ISERROR($Z22))),1,0) -> 0 | AN22: =IF(IFERROR(AND($I22="Yes",$K22="N/A"),FALSE()),1,0) -> 0 | AO22: =IF(IFERROR(IF($J22<>"",$T22="",FALSE()),TRUE()),1,0) -> 0 | AP22: =IF(IFERROR(IF($I22="Yes",IF(OR($K22="Yes",$K22="Partial"),IF(ISERROR($O22),TRUE(),$O22=""),FALSE()),FALSE()),FALSE()),1,0) -> 0 | AQ22: =IF(OR($AF22>0,$AG22>0,$AJ22>0,$AK22>0,$AL22>0,$AM22>0,$AN22>0,$AO22>0),1,0) -> 0 | AR22: =IF(IFERROR(AND($I22="Yes",OR($K22="Yes",$K22="Partial",$K22="No")),FALSE()),1,0) -> 0 | AS22: =IFERROR(IF($AR22=1,$F22*$L22,0),0) -> 0 | AT22: =IFERROR(IF($AR22=1,$F22,0),0) -> 0 | AU22: =_xlfn.TEXTJOIN(", ",TRUE(),IF(ISERROR($E22),"E22",""),IF(ISERROR($G22),"G22",""),IF(ISERROR($H22),"H22",""),IF(ISERROR($J22),"J22",""),IF(ISERROR($K22),"K22",""),IF(ISERROR($O22),"O22",""),IF(ISERROR($P22),"P22",""),IF(ISERROR($Q22),"Q22",""),IF(ISERROR($R22),"R22",""),IF(ISERROR($S22),"S22",""),IF(ISERROR($T22),"T22",""),IF(ISERROR($X22),"X22",""),IF(ISERROR($Y22),"Y22",""),IF(ISERROR($Z22),"Z22","")) | AV22: =_xlfn.TEXTJOIN("; ",TRUE(),IF(IFERROR(NOT(OR($J22="",$J22="Yes",$J22="No")),TRUE()),"Invalid override value (J)",""),IF(IFERROR(IF($E22="",$I22="Yes",NOT(OR($E22="Blocker",$E22="Major",$E22="Moderate",$E22="Minor"))),TRUE()),"Invalid or missing criticality (E)",""),IF(IFERROR(IF($J22<>"",$T22="",FALSE()),TRUE()),"Override rationale missing / invalid (T)",""),IF(IFERROR(IF(AND($A22="2.7",$I22="Yes",p_confidential="Yes"),$E22<>"Blocker",FALSE()),TRUE()),"2.7 must be Blocker when S4 = Yes",""),IF(IFERROR(IF(AND($A22="5.8",$I22="Yes"),OR($E22="Moderate",$E22="Minor"),FALSE()),TRUE()),"5.8 should be at least Major",""),IF(IF(IFERROR(AND($J22="No",$AI22="Yes",OR($AD22="Blocker",AND($A22="2.7",p_confidential="Yes"))),FALSE()),NOT(AND(IFERROR($X22<>"",FALSE()),IFERROR($Y22<>"",FALSE()),IFERROR(AND(ISNUMBER($Z22),$Z22>=DATE(2020,1,1),$Z22<=DATE(2100,12,31)),FALSE()))),FALSE()),"Blocker de-scope review missing / invalid (X-Z)",""),IF(IF(IFERROR(IF(OR($E22="Blocker",$E22="Major",$E22="Moderate",$E22="Minor"),$F22<IF($AD22="Blocker",Lookups!$B$8,IF($AD22="Major",Lookups!$B$9,IF($AD22="Moderate",Lookups!$B$10,Lookups!$B$11))),FALSE()),FALSE()),NOT(AND(IFERROR($T22<>"",FALSE()),IFERROR($Y22<>"",FALSE()),IF(IFERROR($Z22<>"",FALSE()),IFERROR(AND(ISNUMBER($Z22),$Z22>=DATE(2020,1,1),$Z22<=DATE(2100,12,31)),FALSE()),NOT(ISERROR($Z22))))),FALSE()),"Criticality below baseline: review missing / invalid (T,Y,Z)","")) | AW22: =_xlfn.TEXTJOIN("; ",TRUE(),IF($AJ22>0,"Invalid response value (K)",""),IF($AK22>0,"Likelihood/Impact missing or not integer 1-5 (G,H)",""),IF($AL22>0,"Invalid status value (S)",""),IF($AM22>0,_xlfn.TEXTJOIN("; ",TRUE(),IF(IFERROR(AND($S22="Accepted Risk",$X22=""),FALSE()),"Exemption reference (X) missing",""),IF(IFERROR(AND($S22="Accepted Risk",$Y22=""),FALSE()),"Exemption approver (Y) missing",""),IF(IFERROR(AND($S22="Accepted Risk",$Z22=""),FALSE()),"Exemption date (Z) missing",""),IF(ISERROR($Z22),"Exemption date (Z) invalid - error value",IF(IFERROR(AND($Z22<>"",NOT(AND(ISNUMBER($Z22),$Z22>=DATE(2020,1,1),$Z22<=DATE(2100,12,31)))),FALSE()),"Exemption date (Z) invalid - enter a real date","")),IF(OR(ISERROR($S22),ISERROR($X22),ISERROR($Y22)),"Exemption inputs contain an error value (S,X,Y)","")),""),IF($AG22>0,"Input/calculation fault at "&$AU22,""),IF($AN22>0,"N/A on applicable row",""))
A23: 4.1 | B23: LLM-Specific Threats | C23: Auto: always | D23: Prompt injection and jailbreak testing is performed against the actual use case, prompts, tools, and data. | E23: Major | F23: =IFERROR(IF($E23="Blocker",Lookups!$B$8,IF($E23="Major",Lookups!$B$9,IF($E23="Moderate",Lookups!$B$10,IF($E23="Minor",Lookups!$B$11,0)))),0) -> 4 | G23: 4 | H23: 4 | I23: =IFERROR(IF(OR($J23="Yes",$J23="No"),$J23,"Yes"),"Yes") -> Yes | L23: =IFERROR(IF(OR($I23="No",$K23="N/A"),"",IF($K23="Yes",1,IF($K23="Partial",0.5,IF($K23="No",0,"")))),"") | M23: =IFERROR(IF(OR($I23="No",$K23="N/A"),"",$F23*IF(OR($G23="",NOT(ISNUMBER($G23))),3,$G23)*IF(OR($H23="",NOT(ISNUMBER($H23))),3,$H23)*IF($K23="",1,1-$L23)),"") -> 64 | N23: =IFERROR(IF(OR($I23="No",$K23="N/A",$K23=""),"",IF(AND(IFERROR(AND($S23="Accepted Risk",$AM23=0),FALSE()),OR(AND($E23="Blocker",OR($K23="No",$K23="Partial")),AND($E23="Major",$K23="No"))),IF(AND($E23="Blocker",$K23="No"),"BLOCK",IF(AND($E23="Blocker",$K23="Partial"),IF(p_stage="Pilot / PoC","ESCALATE","BLOCK"),IF(AND($E23="Major",$K23="No"),"ESCALATE","")))&" (exempted)",IF(AND($E23="Blocker",$K23="No"),"BLOCK",IF(AND($E23="Blocker",$K23="Partial"),IF(p_stage="Pilot / PoC","ESCALATE","BLOCK"),IF(AND($E23="Major",$K23="No"),"ESCALATE",""))))),"") | U23: =_xlfn.TEXTJOIN("; ",TRUE(),$AV23,$AW23,IF($AP23>0,"Evidence missing or unusable","")) | V23: 4.10 — 4.1 is the initial adversarial test; 4.10 is the repeatable regression suite on every change. | W23: Good: prompt-injection and jailbreak tests against the actual prompts, tools, and data of this use case, with documented results. Evidence: test report, attack corpus. Partial: generic or one-off tests only. Advisory map (partial): OWASP LLM01; MITRE ATLAS AML.T0051. | AA23: =IF($AN23>0,$A23,"") | AB23: =IF($AO23>0,$A23,"") | AC23: =IF($AQ23>0,$A23&" ("&$U23&")","") | AD23: Major | AF23: =IF(OR(IFERROR(NOT(OR($J23="",$J23="Yes",$J23="No")),TRUE()),IFERROR(IF($E23="",$I23="Yes",NOT(OR($E23="Blocker",$E23="Major",$E23="Moderate",$E23="Minor"))),TRUE()),IFERROR(IF($J23<>"",$T23="",FALSE()),TRUE()),IFERROR(IF(AND($A23="2.7",$I23="Yes",p_confidential="Yes"),$E23<>"Blocker",FALSE()),TRUE()),IFERROR(IF(AND($A23="5.8",$I23="Yes"),OR($E23="Moderate",$E23="Minor"),FALSE()),TRUE()),IF(IFERROR(AND($J23="No",$AI23="Yes",OR($AD23="Blocker",AND($A23="2.7",p_confidential="Yes"))),FALSE()),NOT(AND(IFERROR($X23<>"",FALSE()),IFERROR($Y23<>"",FALSE()),IFERROR(AND(ISNUMBER($Z23),$Z23>=DATE(2020,1,1),$Z23<=DATE(2100,12,31)),FALSE()))),FALSE()),IF(IFERROR(IF(OR($E23="Blocker",$E23="Major",$E23="Moderate",$E23="Minor"),$F23<IF($AD23="Blocker",Lookups!$B$8,IF($AD23="Major",Lookups!$B$9,IF($AD23="Moderate",Lookups!$B$10,Lookups!$B$11))),FALSE()),FALSE()),NOT(AND(IFERROR($T23<>"",FALSE()),IFERROR($Y23<>"",FALSE()),IF(IFERROR($Z23<>"",FALSE()),IFERROR(AND(ISNUMBER($Z23),$Z23>=DATE(2020,1,1),$Z23<=DATE(2100,12,31)),FALSE()),NOT(ISERROR($Z23))))),FALSE())),1,0) -> 0 | AG23: =IF(OR(ISERROR($E23),ISERROR($G23),ISERROR($H23),ISERROR($J23),ISERROR($K23),ISERROR($O23),ISERROR($P23),ISERROR($Q23),ISERROR($R23),ISERROR($S23),ISERROR($T23),ISERROR($X23),ISERROR($Y23),ISERROR($Z23)),1,0) -> 0 | AH23: =IF($AF23>0,$A23&" ("&$AV23&")","") | AI23: =IFERROR("Yes","Yes") -> Yes | AJ23: =IF(IFERROR(NOT(OR($K23="",$K23="Yes",$K23="Partial",$K23="No",$K23="N/A")),TRUE()),1,0) -> 0 | AK23: =IF(OR(IFERROR(IF($G23="",AND($I23="Yes",$K23<>""),IF(ISNUMBER($G23),OR($G23<1,$G23>5,$G23<>INT($G23)),TRUE())),TRUE()),IFERROR(IF($H23="",AND($I23="Yes",$K23<>""),IF(ISNUMBER($H23),OR($H23<1,$H23>5,$H23<>INT($H23)),TRUE())),TRUE())),1,0) -> 0 | AL23: =IF(IFERROR(NOT(OR($S23="",$S23="Open",$S23="In progress",$S23="Remediated",$S23="Accepted Risk",$S23="Not applicable")),TRUE()),1,0) -> 0 | AM23: =IF(OR(IFERROR(IF($S23="Accepted Risk",OR($X23="",$Y23="",$Z23=""),FALSE()),TRUE()),IF(IFERROR($Z23<>"",FALSE()),NOT(IFERROR(AND(ISNUMBER($Z23),$Z23>=DATE(2020,1,1),$Z23<=DATE(2100,12,31)),FALSE())),ISERROR($Z23))),1,0) -> 0 | AN23: =IF(IFERROR(AND($I23="Yes",$K23="N/A"),FALSE()),1,0) -> 0 | AO23: =IF(IFERROR(IF($J23<>"",$T23="",FALSE()),TRUE()),1,0) -> 0 | AP23: =IF(IFERROR(IF($I23="Yes",IF(OR($K23="Yes",$K23="Partial"),IF(ISERROR($O23),TRUE(),$O23=""),FALSE()),FALSE()),FALSE()),1,0) -> 0 | AQ23: =IF(OR($AF23>0,$AG23>0,$AJ23>0,$AK23>0,$AL23>0,$AM23>0,$AN23>0,$AO23>0),1,0) -> 0 | AR23: =IF(IFERROR(AND($I23="Yes",OR($K23="Yes",$K23="Partial",$K23="No")),FALSE()),1,0) -> 0 | AS23: =IFERROR(IF($AR23=1,$F23*$L23,0),0) -> 0 | AT23: =IFERROR(IF($AR23=1,$F23,0),0) -> 0 | AU23: =_xlfn.TEXTJOIN(", ",TRUE(),IF(ISERROR($E23),"E23",""),IF(ISERROR($G23),"G23",""),IF(ISERROR($H23),"H23",""),IF(ISERROR($J23),"J23",""),IF(ISERROR($K23),"K23",""),IF(ISERROR($O23),"O23",""),IF(ISERROR($P23),"P23",""),IF(ISERROR($Q23),"Q23",""),IF(ISERROR($R23),"R23",""),IF(ISERROR($S23),"S23",""),IF(ISERROR($T23),"T23",""),IF(ISERROR($X23),"X23",""),IF(ISERROR($Y23),"Y23",""),IF(ISERROR($Z23),"Z23","")) | AV23: =_xlfn.TEXTJOIN("; ",TRUE(),IF(IFERROR(NOT(OR($J23="",$J23="Yes",$J23="No")),TRUE()),"Invalid override value (J)",""),IF(IFERROR(IF($E23="",$I23="Yes",NOT(OR($E23="Blocker",$E23="Major",$E23="Moderate",$E23="Minor"))),TRUE()),"Invalid or missing criticality (E)",""),IF(IFERROR(IF($J23<>"",$T23="",FALSE()),TRUE()),"Override rationale missing / invalid (T)",""),IF(IFERROR(IF(AND($A23="2.7",$I23="Yes",p_confidential="Yes"),$E23<>"Blocker",FALSE()),TRUE()),"2.7 must be Blocker when S4 = Yes",""),IF(IFERROR(IF(AND($A23="5.8",$I23="Yes"),OR($E23="Moderate",$E23="Minor"),FALSE()),TRUE()),"5.8 should be at least Major",""),IF(IF(IFERROR(AND($J23="No",$AI23="Yes",OR($AD23="Blocker",AND($A23="2.7",p_confidential="Yes"))),FALSE()),NOT(AND(IFERROR($X23<>"",FALSE()),IFERROR($Y23<>"",FALSE()),IFERROR(AND(ISNUMBER($Z23),$Z23>=DATE(2020,1,1),$Z23<=DATE(2100,12,31)),FALSE()))),FALSE()),"Blocker de-scope review missing / invalid (X-Z)",""),IF(IF(IFERROR(IF(OR($E23="Blocker",$E23="Major",$E23="Moderate",$E23="Minor"),$F23<IF($AD23="Blocker",Lookups!$B$8,IF($AD23="Major",Lookups!$B$9,IF($AD23="Moderate",Lookups!$B$10,Lookups!$B$11))),FALSE()),FALSE()),NOT(AND(IFERROR($T23<>"",FALSE()),IFERROR($Y23<>"",FALSE()),IF(IFERROR($Z23<>"",FALSE()),IFERROR(AND(ISNUMBER($Z23),$Z23>=DATE(2020,1,1),$Z23<=DATE(2100,12,31)),FALSE()),NOT(ISERROR($Z23))))),FALSE()),"Criticality below baseline: review missing / invalid (T,Y,Z)","")) | AW23: =_xlfn.TEXTJOIN("; ",TRUE(),IF($AJ23>0,"Invalid response value (K)",""),IF($AK23>0,"Likelihood/Impact missing or not integer 1-5 (G,H)",""),IF($AL23>0,"Invalid status value (S)",""),IF($AM23>0,_xlfn.TEXTJOIN("; ",TRUE(),IF(IFERROR(AND($S23="Accepted Risk",$X23=""),FALSE()),"Exemption reference (X) missing",""),IF(IFERROR(AND($S23="Accepted Risk",$Y23=""),FALSE()),"Exemption approver (Y) missing",""),IF(IFERROR(AND($S23="Accepted Risk",$Z23=""),FALSE()),"Exemption date (Z) missing",""),IF(ISERROR($Z23),"Exemption date (Z) invalid - error value",IF(IFERROR(AND($Z23<>"",NOT(AND(ISNUMBER($Z23),$Z23>=DATE(2020,1,1),$Z23<=DATE(2100,12,31)))),FALSE()),"Exemption date (Z) invalid - enter a real date","")),IF(OR(ISERROR($S23),ISERROR($X23),ISERROR($Y23)),"Exemption inputs contain an error value (S,X,Y)","")),""),IF($AG23>0,"Input/calculation fault at "&$AU23,""),IF($AN23>0,"N/A on applicable row",""))
A24: 4.2 | B24: LLM-Specific Threats | C24: Auto: always | D24: Insecure output handling controls are implemented for code, markup, links, files, commands, and structured data. | E24: Blocker | F24: =IFERROR(IF($E24="Blocker",Lookups!$B$8,IF($E24="Major",Lookups!$B$9,IF($E24="Moderate",Lookups!$B$10,IF($E24="Minor",Lookups!$B$11,0)))),0) -> 5 | G24: 4 | H24: 5 | I24: =IFERROR(IF(OR($J24="Yes",$J24="No"),$J24,"Yes"),"Yes") -> Yes | L24: =IFERROR(IF(OR($I24="No",$K24="N/A"),"",IF($K24="Yes",1,IF($K24="Partial",0.5,IF($K24="No",0,"")))),"") | M24: =IFERROR(IF(OR($I24="No",$K24="N/A"),"",$F24*IF(OR($G24="",NOT(ISNUMBER($G24))),3,$G24)*IF(OR($H24="",NOT(ISNUMBER($H24))),3,$H24)*IF($K24="",1,1-$L24)),"") -> 100 | N24: =IFERROR(IF(OR($I24="No",$K24="N/A",$K24=""),"",IF(AND(IFERROR(AND($S24="Accepted Risk",$AM24=0),FALSE()),OR(AND($E24="Blocker",OR($K24="No",$K24="Partial")),AND($E24="Major",$K24="No"))),IF(AND($E24="Blocker",$K24="No"),"BLOCK",IF(AND($E24="Blocker",$K24="Partial"),IF(p_stage="Pilot / PoC","ESCALATE","BLOCK"),IF(AND($E24="Major",$K24="No"),"ESCALATE","")))&" (exempted)",IF(AND($E24="Blocker",$K24="No"),"BLOCK",IF(AND($E24="Blocker",$K24="Partial"),IF(p_stage="Pilot / PoC","ESCALATE","BLOCK"),IF(AND($E24="Major",$K24="No"),"ESCALATE",""))))),"") | U24: =_xlfn.TEXTJOIN("; ",TRUE(),$AV24,$AW24,IF($AP24>0,"Evidence missing or unusable","")) | V24: 3.6, 4.9 — see 3.6. | W24: Good: output handling controls for code, markup, links, files, commands, structured data. Evidence: code review + tests. Partial: subset of output types covered. Advisory map (partial): OWASP LLM05. | AA24: =IF($AN24>0,$A24,"") | AB24: =IF($AO24>0,$A24,"") | AC24: =IF($AQ24>0,$A24&" ("&$U24&")","") | AD24: Blocker | AF24: =IF(OR(IFERROR(NOT(OR($J24="",$J24="Yes",$J24="No")),TRUE()),IFERROR(IF($E24="",$I24="Yes",NOT(OR($E24="Blocker",$E24="Major",$E24="Moderate",$E24="Minor"))),TRUE()),IFERROR(IF($J24<>"",$T24="",FALSE()),TRUE()),IFERROR(IF(AND($A24="2.7",$I24="Yes",p_confidential="Yes"),$E24<>"Blocker",FALSE()),TRUE()),IFERROR(IF(AND($A24="5.8",$I24="Yes"),OR($E24="Moderate",$E24="Minor"),FALSE()),TRUE()),IF(IFERROR(AND($J24="No",$AI24="Yes",OR($AD24="Blocker",AND($A24="2.7",p_confidential="Yes"))),FALSE()),NOT(AND(IFERROR($X24<>"",FALSE()),IFERROR($Y24<>"",FALSE()),IFERROR(AND(ISNUMBER($Z24),$Z24>=DATE(2020,1,1),$Z24<=DATE(2100,12,31)),FALSE()))),FALSE()),IF(IFERROR(IF(OR($E24="Blocker",$E24="Major",$E24="Moderate",$E24="Minor"),$F24<IF($AD24="Blocker",Lookups!$B$8,IF($AD24="Major",Lookups!$B$9,IF($AD24="Moderate",Lookups!$B$10,Lookups!$B$11))),FALSE()),FALSE()),NOT(AND(IFERROR($T24<>"",FALSE()),IFERROR($Y24<>"",FALSE()),IF(IFERROR($Z24<>"",FALSE()),IFERROR(AND(ISNUMBER($Z24),$Z24>=DATE(2020,1,1),$Z24<=DATE(2100,12,31)),FALSE()),NOT(ISERROR($Z24))))),FALSE())),1,0) -> 0 | AG24: =IF(OR(ISERROR($E24),ISERROR($G24),ISERROR($H24),ISERROR($J24),ISERROR($K24),ISERROR($O24),ISERROR($P24),ISERROR($Q24),ISERROR($R24),ISERROR($S24),ISERROR($T24),ISERROR($X24),ISERROR($Y24),ISERROR($Z24)),1,0) -> 0 | AH24: =IF($AF24>0,$A24&" ("&$AV24&")","") | AI24: =IFERROR("Yes","Yes") -> Yes | AJ24: =IF(IFERROR(NOT(OR($K24="",$K24="Yes",$K24="Partial",$K24="No",$K24="N/A")),TRUE()),1,0) -> 0 | AK24: =IF(OR(IFERROR(IF($G24="",AND($I24="Yes",$K24<>""),IF(ISNUMBER($G24),OR($G24<1,$G24>5,$G24<>INT($G24)),TRUE())),TRUE()),IFERROR(IF($H24="",AND($I24="Yes",$K24<>""),IF(ISNUMBER($H24),OR($H24<1,$H24>5,$H24<>INT($H24)),TRUE())),TRUE())),1,0) -> 0 | AL24: =IF(IFERROR(NOT(OR($S24="",$S24="Open",$S24="In progress",$S24="Remediated",$S24="Accepted Risk",$S24="Not applicable")),TRUE()),1,0) -> 0 | AM24: =IF(OR(IFERROR(IF($S24="Accepted Risk",OR($X24="",$Y24="",$Z24=""),FALSE()),TRUE()),IF(IFERROR($Z24<>"",FALSE()),NOT(IFERROR(AND(ISNUMBER($Z24),$Z24>=DATE(2020,1,1),$Z24<=DATE(2100,12,31)),FALSE())),ISERROR($Z24))),1,0) -> 0 | AN24: =IF(IFERROR(AND($I24="Yes",$K24="N/A"),FALSE()),1,0) -> 0 | AO24: =IF(IFERROR(IF($J24<>"",$T24="",FALSE()),TRUE()),1,0) -> 0 | AP24: =IF(IFERROR(IF($I24="Yes",IF(OR($K24="Yes",$K24="Partial"),IF(ISERROR($O24),TRUE(),$O24=""),FALSE()),FALSE()),FALSE()),1,0) -> 0 | AQ24: =IF(OR($AF24>0,$AG24>0,$AJ24>0,$AK24>0,$AL24>0,$AM24>0,$AN24>0,$AO24>0),1,0) -> 0 | AR24: =IF(IFERROR(AND($I24="Yes",OR($K24="Yes",$K24="Partial",$K24="No")),FALSE()),1,0) -> 0 | AS24: =IFERROR(IF($AR24=1,$F24*$L24,0),0) -> 0 | AT24: =IFERROR(IF($AR24=1,$F24,0),0) -> 0 | AU24: =_xlfn.TEXTJOIN(", ",TRUE(),IF(ISERROR($E24),"E24",""),IF(ISERROR($G24),"G24",""),IF(ISERROR($H24),"H24",""),IF(ISERROR($J24),"J24",""),IF(ISERROR($K24),"K24",""),IF(ISERROR($O24),"O24",""),IF(ISERROR($P24),"P24",""),IF(ISERROR($Q24),"Q24",""),IF(ISERROR($R24),"R24",""),IF(ISERROR($S24),"S24",""),IF(ISERROR($T24),"T24",""),IF(ISERROR($X24),"X24",""),IF(ISERROR($Y24),"Y24",""),IF(ISERROR($Z24),"Z24","")) | AV24: =_xlfn.TEXTJOIN("; ",TRUE(),IF(IFERROR(NOT(OR($J24="",$J24="Yes",$J24="No")),TRUE()),"Invalid override value (J)",""),IF(IFERROR(IF($E24="",$I24="Yes",NOT(OR($E24="Blocker",$E24="Major",$E24="Moderate",$E24="Minor"))),TRUE()),"Invalid or missing criticality (E)",""),IF(IFERROR(IF($J24<>"",$T24="",FALSE()),TRUE()),"Override rationale missing / invalid (T)",""),IF(IFERROR(IF(AND($A24="2.7",$I24="Yes",p_confidential="Yes"),$E24<>"Blocker",FALSE()),TRUE()),"2.7 must be Blocker when S4 = Yes",""),IF(IFERROR(IF(AND($A24="5.8",$I24="Yes"),OR($E24="Moderate",$E24="Minor"),FALSE()),TRUE()),"5.8 should be at least Major",""),IF(IF(IFERROR(AND($J24="No",$AI24="Yes",OR($AD24="Blocker",AND($A24="2.7",p_confidential="Yes"))),FALSE()),NOT(AND(IFERROR($X24<>"",FALSE()),IFERROR($Y24<>"",FALSE()),IFERROR(AND(ISNUMBER($Z24),$Z24>=DATE(2020,1,1),$Z24<=DATE(2100,12,31)),FALSE()))),FALSE()),"Blocker de-scope review missing / invalid (X-Z)",""),IF(IF(IFERROR(IF(OR($E24="Blocker",$E24="Major",$E24="Moderate",$E24="Minor"),$F24<IF($AD24="Blocker",Lookups!$B$8,IF($AD24="Major",Lookups!$B$9,IF($AD24="Moderate",Lookups!$B$10,Lookups!$B$11))),FALSE()),FALSE()),NOT(AND(IFERROR($T24<>"",FALSE()),IFERROR($Y24<>"",FALSE()),IF(IFERROR($Z24<>"",FALSE()),IFERROR(AND(ISNUMBER($Z24),$Z24>=DATE(2020,1,1),$Z24<=DATE(2100,12,31)),FALSE()),NOT(ISERROR($Z24))))),FALSE()),"Criticality below baseline: review missing / invalid (T,Y,Z)","")) | AW24: =_xlfn.TEXTJOIN("; ",TRUE(),IF($AJ24>0,"Invalid response value (K)",""),IF($AK24>0,"Likelihood/Impact missing or not integer 1-5 (G,H)",""),IF($AL24>0,"Invalid status value (S)",""),IF($AM24>0,_xlfn.TEXTJOIN("; ",TRUE(),IF(IFERROR(AND($S24="Accepted Risk",$X24=""),FALSE()),"Exemption reference (X) missing",""),IF(IFERROR(AND($S24="Accepted Risk",$Y24=""),FALSE()),"Exemption approver (Y) missing",""),IF(IFERROR(AND($S24="Accepted Risk",$Z24=""),FALSE()),"Exemption date (Z) missing",""),IF(ISERROR($Z24),"Exemption date (Z) invalid - error value",IF(IFERROR(AND($Z24<>"",NOT(AND(ISNUMBER($Z24),$Z24>=DATE(2020,1,1),$Z24<=DATE(2100,12,31)))),FALSE()),"Exemption date (Z) invalid - enter a real date","")),IF(OR(ISERROR($S24),ISERROR($X24),ISERROR($Y24)),"Exemption inputs contain an error value (S,X,Y)","")),""),IF($AG24>0,"Input/calculation fault at "&$AU24,""),IF($AN24>0,"N/A on applicable row",""))
A25: 4.3 | B25: LLM-Specific Threats | C25: Auto: unless S9 = No and S10 = No | D25: Training, fine-tuning, embedding, and retrieval data poisoning risks are assessed and mitigated. | E25: Major | F25: =IFERROR(IF($E25="Blocker",Lookups!$B$8,IF($E25="Major",Lookups!$B$9,IF($E25="Moderate",Lookups!$B$10,IF($E25="Minor",Lookups!$B$11,0)))),0) -> 4 | G25: 3 | H25: 4 | I25: =IFERROR(IF(OR($J25="Yes",$J25="No"),$J25,IF(AND(p_finetune="No",p_rag="No"),"No","Yes")),"Yes") -> Yes | L25: =IFERROR(IF(OR($I25="No",$K25="N/A"),"",IF($K25="Yes",1,IF($K25="Partial",0.5,IF($K25="No",0,"")))),"") | M25: =IFERROR(IF(OR($I25="No",$K25="N/A"),"",$F25*IF(OR($G25="",NOT(ISNUMBER($G25))),3,$G25)*IF(OR($H25="",NOT(ISNUMBER($H25))),3,$H25)*IF($K25="",1,1-$L25)),"") -> 48 | N25: =IFERROR(IF(OR($I25="No",$K25="N/A",$K25=""),"",IF(AND(IFERROR(AND($S25="Accepted Risk",$AM25=0),FALSE()),OR(AND($E25="Blocker",OR($K25="No",$K25="Partial")),AND($E25="Major",$K25="No"))),IF(AND($E25="Blocker",$K25="No"),"BLOCK",IF(AND($E25="Blocker",$K25="Partial"),IF(p_stage="Pilot / PoC","ESCALATE","BLOCK"),IF(AND($E25="Major",$K25="No"),"ESCALATE","")))&" (exempted)",IF(AND($E25="Blocker",$K25="No"),"BLOCK",IF(AND($E25="Blocker",$K25="Partial"),IF(p_stage="Pilot / PoC","ESCALATE","BLOCK"),IF(AND($E25="Major",$K25="No"),"ESCALATE",""))))),"") | U25: =_xlfn.TEXTJOIN("; ",TRUE(),$AV25,$AW25,IF($AP25>0,"Evidence missing or unusable","")) | W25: Good: poisoning risk assessed and mitigated across training, fine-tuning, embedding, and retrieval data; provenance and review gates. Evidence: data lineage + review records. Partial: assessed, mitigations incomplete. Advisory map (partial): OWASP LLM04; ATLAS AML.T0020. | AA25: =IF($AN25>0,$A25,"") | AB25: =IF($AO25>0,$A25,"") | AC25: =IF($AQ25>0,$A25&" ("&$U25&")","") | AD25: Major | AF25: =IF(OR(IFERROR(NOT(OR($J25="",$J25="Yes",$J25="No")),TRUE()),IFERROR(IF($E25="",$I25="Yes",NOT(OR($E25="Blocker",$E25="Major",$E25="Moderate",$E25="Minor"))),TRUE()),IFERROR(IF($J25<>"",$T25="",FALSE()),TRUE()),IFERROR(IF(AND($A25="2.7",$I25="Yes",p_confidential="Yes"),$E25<>"Blocker",FALSE()),TRUE()),IFERROR(IF(AND($A25="5.8",$I25="Yes"),OR($E25="Moderate",$E25="Minor"),FALSE()),TRUE()),IF(IFERROR(AND($J25="No",$AI25="Yes",OR($AD25="Blocker",AND($A25="2.7",p_confidential="Yes"))),FALSE()),NOT(AND(IFERROR($X25<>"",FALSE()),IFERROR($Y25<>"",FALSE()),IFERROR(AND(ISNUMBER($Z25),$Z25>=DATE(2020,1,1),$Z25<=DATE(2100,12,31)),FALSE()))),FALSE()),IF(IFERROR(IF(OR($E25="Blocker",$E25="Major",$E25="Moderate",$E25="Minor"),$F25<IF($AD25="Blocker",Lookups!$B$8,IF($AD25="Major",Lookups!$B$9,IF($AD25="Moderate",Lookups!$B$10,Lookups!$B$11))),FALSE()),FALSE()),NOT(AND(IFERROR($T25<>"",FALSE()),IFERROR($Y25<>"",FALSE()),IF(IFERROR($Z25<>"",FALSE()),IFERROR(AND(ISNUMBER($Z25),$Z25>=DATE(2020,1,1),$Z25<=DATE(2100,12,31)),FALSE()),NOT(ISERROR($Z25))))),FALSE())),1,0) -> 0 | AG25: =IF(OR(ISERROR($E25),ISERROR($G25),ISERROR($H25),ISERROR($J25),ISERROR($K25),ISERROR($O25),ISERROR($P25),ISERROR($Q25),ISERROR($R25),ISERROR($S25),ISERROR($T25),ISERROR($X25),ISERROR($Y25),ISERROR($Z25)),1,0) -> 0 | AH25: =IF($AF25>0,$A25&" ("&$AV25&")","") | AI25: =IFERROR(IF(AND(p_finetune="No",p_rag="No"),"No","Yes"),"Yes") -> Yes | AJ25: =IF(IFERROR(NOT(OR($K25="",$K25="Yes",$K25="Partial",$K25="No",$K25="N/A")),TRUE()),1,0) -> 0 | AK25: =IF(OR(IFERROR(IF($G25="",AND($I25="Yes",$K25<>""),IF(ISNUMBER($G25),OR($G25<1,$G25>5,$G25<>INT($G25)),TRUE())),TRUE()),IFERROR(IF($H25="",AND($I25="Yes",$K25<>""),IF(ISNUMBER($H25),OR($H25<1,$H25>5,$H25<>INT($H25)),TRUE())),TRUE())),1,0) -> 0 | AL25: =IF(IFERROR(NOT(OR($S25="",$S25="Open",$S25="In progress",$S25="Remediated",$S25="Accepted Risk",$S25="Not applicable")),TRUE()),1,0) -> 0 | AM25: =IF(OR(IFERROR(IF($S25="Accepted Risk",OR($X25="",$Y25="",$Z25=""),FALSE()),TRUE()),IF(IFERROR($Z25<>"",FALSE()),NOT(IFERROR(AND(ISNUMBER($Z25),$Z25>=DATE(2020,1,1),$Z25<=DATE(2100,12,31)),FALSE())),ISERROR($Z25))),1,0) -> 0 | AN25: =IF(IFERROR(AND($I25="Yes",$K25="N/A"),FALSE()),1,0) -> 0 | AO25: =IF(IFERROR(IF($J25<>"",$T25="",FALSE()),TRUE()),1,0) -> 0 | AP25: =IF(IFERROR(IF($I25="Yes",IF(OR($K25="Yes",$K25="Partial"),IF(ISERROR($O25),TRUE(),$O25=""),FALSE()),FALSE()),FALSE()),1,0) -> 0 | AQ25: =IF(OR($AF25>0,$AG25>0,$AJ25>0,$AK25>0,$AL25>0,$AM25>0,$AN25>0,$AO25>0),1,0) -> 0 | AR25: =IF(IFERROR(AND($I25="Yes",OR($K25="Yes",$K25="Partial",$K25="No")),FALSE()),1,0) -> 0 | AS25: =IFERROR(IF($AR25=1,$F25*$L25,0),0) -> 0 | AT25: =IFERROR(IF($AR25=1,$F25,0),0) -> 0 | AU25: =_xlfn.TEXTJOIN(", ",TRUE(),IF(ISERROR($E25),"E25",""),IF(ISERROR($G25),"G25",""),IF(ISERROR($H25),"H25",""),IF(ISERROR($J25),"J25",""),IF(ISERROR($K25),"K25",""),IF(ISERROR($O25),"O25",""),IF(ISERROR($P25),"P25",""),IF(ISERROR($Q25),"Q25",""),IF(ISERROR($R25),"R25",""),IF(ISERROR($S25),"S25",""),IF(ISERROR($T25),"T25",""),IF(ISERROR($X25),"X25",""),IF(ISERROR($Y25),"Y25",""),IF(ISERROR($Z25),"Z25","")) | AV25: =_xlfn.TEXTJOIN("; ",TRUE(),IF(IFERROR(NOT(OR($J25="",$J25="Yes",$J25="No")),TRUE()),"Invalid override value (J)",""),IF(IFERROR(IF($E25="",$I25="Yes",NOT(OR($E25="Blocker",$E25="Major",$E25="Moderate",$E25="Minor"))),TRUE()),"Invalid or missing criticality (E)",""),IF(IFERROR(IF($J25<>"",$T25="",FALSE()),TRUE()),"Override rationale missing / invalid (T)",""),IF(IFERROR(IF(AND($A25="2.7",$I25="Yes",p_confidential="Yes"),$E25<>"Blocker",FALSE()),TRUE()),"2.7 must be Blocker when S4 = Yes",""),IF(IFERROR(IF(AND($A25="5.8",$I25="Yes"),OR($E25="Moderate",$E25="Minor"),FALSE()),TRUE()),"5.8 should be at least Major",""),IF(IF(IFERROR(AND($J25="No",$AI25="Yes",OR($AD25="Blocker",AND($A25="2.7",p_confidential="Yes"))),FALSE()),NOT(AND(IFERROR($X25<>"",FALSE()),IFERROR($Y25<>"",FALSE()),IFERROR(AND(ISNUMBER($Z25),$Z25>=DATE(2020,1,1),$Z25<=DATE(2100,12,31)),FALSE()))),FALSE()),"Blocker de-scope review missing / invalid (X-Z)",""),IF(IF(IFERROR(IF(OR($E25="Blocker",$E25="Major",$E25="Moderate",$E25="Minor"),$F25<IF($AD25="Blocker",Lookups!$B$8,IF($AD25="Major",Lookups!$B$9,IF($AD25="Moderate",Lookups!$B$10,Lookups!$B$11))),FALSE()),FALSE()),NOT(AND(IFERROR($T25<>"",FALSE()),IFERROR($Y25<>"",FALSE()),IF(IFERROR($Z25<>"",FALSE()),IFERROR(AND(ISNUMBER($Z25),$Z25>=DATE(2020,1,1),$Z25<=DATE(2100,12,31)),FALSE()),NOT(ISERROR($Z25))))),FALSE()),"Criticality below baseline: review missing / invalid (T,Y,Z)","")) | AW25: =_xlfn.TEXTJOIN("; ",TRUE(),IF($AJ25>0,"Invalid response value (K)",""),IF($AK25>0,"Likelihood/Impact missing or not integer 1-5 (G,H)",""),IF($AL25>0,"Invalid status value (S)",""),IF($AM25>0,_xlfn.TEXTJOIN("; ",TRUE(),IF(IFERROR(AND($S25="Accepted Risk",$X25=""),FALSE()),"Exemption reference (X) missing",""),IF(IFERROR(AND($S25="Accepted Risk",$Y25=""),FALSE()),"Exemption approver (Y) missing",""),IF(IFERROR(AND($S25="Accepted Risk",$Z25=""),FALSE()),"Exemption date (Z) missing",""),IF(ISERROR($Z25),"Exemption date (Z) invalid - error value",IF(IFERROR(AND($Z25<>"",NOT(AND(ISNUMBER($Z25),$Z25>=DATE(2020,1,1),$Z25<=DATE(2100,12,31)))),FALSE()),"Exemption date (Z) invalid - enter a real date","")),IF(OR(ISERROR($S25),ISERROR($X25),ISERROR($Y25)),"Exemption inputs contain an error value (S,X,Y)","")),""),IF($AG25>0,"Input/calculation fault at "&$AU25,""),IF($AN25>0,"N/A on applicable row",""))
A26: 4.4 | B26: LLM-Specific Threats | C26: Auto: unless S6 = internal limited | D26: Rate limiting, quota, token/cost controls, abuse throttling, and model denial-of-service protections exist. | E26: Major | F26: =IFERROR(IF($E26="Blocker",Lookups!$B$8,IF($E26="Major",Lookups!$B$9,IF($E26="Moderate",Lookups!$B$10,IF($E26="Minor",Lookups!$B$11,0)))),0) -> 4 | G26: 4 | H26: 4 | I26: =IFERROR(IF(OR($J26="Yes",$J26="No"),$J26,IF(p_users="Internal (limited group)","No","Yes")),"Yes") -> Yes | L26: =IFERROR(IF(OR($I26="No",$K26="N/A"),"",IF($K26="Yes",1,IF($K26="Partial",0.5,IF($K26="No",0,"")))),"") | M26: =IFERROR(IF(OR($I26="No",$K26="N/A"),"",$F26*IF(OR($G26="",NOT(ISNUMBER($G26))),3,$G26)*IF(OR($H26="",NOT(ISNUMBER($H26))),3,$H26)*IF($K26="",1,1-$L26)),"") -> 64 | N26: =IFERROR(IF(OR($I26="No",$K26="N/A",$K26=""),"",IF(AND(IFERROR(AND($S26="Accepted Risk",$AM26=0),FALSE()),OR(AND($E26="Blocker",OR($K26="No",$K26="Partial")),AND($E26="Major",$K26="No"))),IF(AND($E26="Blocker",$K26="No"),"BLOCK",IF(AND($E26="Blocker",$K26="Partial"),IF(p_stage="Pilot / PoC","ESCALATE","BLOCK"),IF(AND($E26="Major",$K26="No"),"ESCALATE","")))&" (exempted)",IF(AND($E26="Blocker",$K26="No"),"BLOCK",IF(AND($E26="Blocker",$K26="Partial"),IF(p_stage="Pilot / PoC","ESCALATE","BLOCK"),IF(AND($E26="Major",$K26="No"),"ESCALATE",""))))),"") | U26: =_xlfn.TEXTJOIN("; ",TRUE(),$AV26,$AW26,IF($AP26>0,"Evidence missing or unusable","")) | W26: Good: per-user/tenant rate limits, quotas, token/cost caps, abuse throttling, DoS playbook. Evidence: gateway config + test. Partial: global limits only. Advisory map (partial): OWASP LLM10 Unbounded Consumption. | AA26: =IF($AN26>0,$A26,"") | AB26: =IF($AO26>0,$A26,"") | AC26: =IF($AQ26>0,$A26&" ("&$U26&")","") | AD26: Major | AF26: =IF(OR(IFERROR(NOT(OR($J26="",$J26="Yes",$J26="No")),TRUE()),IFERROR(IF($E26="",$I26="Yes",NOT(OR($E26="Blocker",$E26="Major",$E26="Moderate",$E26="Minor"))),TRUE()),IFERROR(IF($J26<>"",$T26="",FALSE()),TRUE()),IFERROR(IF(AND($A26="2.7",$I26="Yes",p_confidential="Yes"),$E26<>"Blocker",FALSE()),TRUE()),IFERROR(IF(AND($A26="5.8",$I26="Yes"),OR($E26="Moderate",$E26="Minor"),FALSE()),TRUE()),IF(IFERROR(AND($J26="No",$AI26="Yes",OR($AD26="Blocker",AND($A26="2.7",p_confidential="Yes"))),FALSE()),NOT(AND(IFERROR($X26<>"",FALSE()),IFERROR($Y26<>"",FALSE()),IFERROR(AND(ISNUMBER($Z26),$Z26>=DATE(2020,1,1),$Z26<=DATE(2100,12,31)),FALSE()))),FALSE()),IF(IFERROR(IF(OR($E26="Blocker",$E26="Major",$E26="Moderate",$E26="Minor"),$F26<IF($AD26="Blocker",Lookups!$B$8,IF($AD26="Major",Lookups!$B$9,IF($AD26="Moderate",Lookups!$B$10,Lookups!$B$11))),FALSE()),FALSE()),NOT(AND(IFERROR($T26<>"",FALSE()),IFERROR($Y26<>"",FALSE()),IF(IFERROR($Z26<>"",FALSE()),IFERROR(AND(ISNUMBER($Z26),$Z26>=DATE(2020,1,1),$Z26<=DATE(2100,12,31)),FALSE()),NOT(ISERROR($Z26))))),FALSE())),1,0) -> 0 | AG26: =IF(OR(ISERROR($E26),ISERROR($G26),ISERROR($H26),ISERROR($J26),ISERROR($K26),ISERROR($O26),ISERROR($P26),ISERROR($Q26),ISERROR($R26),ISERROR($S26),ISERROR($T26),ISERROR($X26),ISERROR($Y26),ISERROR($Z26)),1,0) -> 0 | AH26: =IF($AF26>0,$A26&" ("&$AV26&")","") | AI26: =IFERROR(IF(p_users="Internal (limited group)","No","Yes"),"Yes") -> Yes | AJ26: =IF(IFERROR(NOT(OR($K26="",$K26="Yes",$K26="Partial",$K26="No",$K26="N/A")),TRUE()),1,0) -> 0 | AK26: =IF(OR(IFERROR(IF($G26="",AND($I26="Yes",$K26<>""),IF(ISNUMBER($G26),OR($G26<1,$G26>5,$G26<>INT($G26)),TRUE())),TRUE()),IFERROR(IF($H26="",AND($I26="Yes",$K26<>""),IF(ISNUMBER($H26),OR($H26<1,$H26>5,$H26<>INT($H26)),TRUE())),TRUE())),1,0) -> 0 | AL26: =IF(IFERROR(NOT(OR($S26="",$S26="Open",$S26="In progress",$S26="Remediated",$S26="Accepted Risk",$S26="Not applicable")),TRUE()),1,0) -> 0 | AM26: =IF(OR(IFERROR(IF($S26="Accepted Risk",OR($X26="",$Y26="",$Z26=""),FALSE()),TRUE()),IF(IFERROR($Z26<>"",FALSE()),NOT(IFERROR(AND(ISNUMBER($Z26),$Z26>=DATE(2020,1,1),$Z26<=DATE(2100,12,31)),FALSE())),ISERROR($Z26))),1,0) -> 0 | AN26: =IF(IFERROR(AND($I26="Yes",$K26="N/A"),FALSE()),1,0) -> 0 | AO26: =IF(IFERROR(IF($J26<>"",$T26="",FALSE()),TRUE()),1,0) -> 0 | AP26: =IF(IFERROR(IF($I26="Yes",IF(OR($K26="Yes",$K26="Partial"),IF(ISERROR($O26),TRUE(),$O26=""),FALSE()),FALSE()),FALSE()),1,0) -> 0 | AQ26: =IF(OR($AF26>0,$AG26>0,$AJ26>0,$AK26>0,$AL26>0,$AM26>0,$AN26>0,$AO26>0),1,0) -> 0 | AR26: =IF(IFERROR(AND($I26="Yes",OR($K26="Yes",$K26="Partial",$K26="No")),FALSE()),1,0) -> 0 | AS26: =IFERROR(IF($AR26=1,$F26*$L26,0),0) -> 0 | AT26: =IFERROR(IF($AR26=1,$F26,0),0) -> 0 | AU26: =_xlfn.TEXTJOIN(", ",TRUE(),IF(ISERROR($E26),"E26",""),IF(ISERROR($G26),"G26",""),IF(ISERROR($H26),"H26",""),IF(ISERROR($J26),"J26",""),IF(ISERROR($K26),"K26",""),IF(ISERROR($O26),"O26",""),IF(ISERROR($P26),"P26",""),IF(ISERROR($Q26),"Q26",""),IF(ISERROR($R26),"R26",""),IF(ISERROR($S26),"S26",""),IF(ISERROR($T26),"T26",""),IF(ISERROR($X26),"X26",""),IF(ISERROR($Y26),"Y26",""),IF(ISERROR($Z26),"Z26","")) | AV26: =_xlfn.TEXTJOIN("; ",TRUE(),IF(IFERROR(NOT(OR($J26="",$J26="Yes",$J26="No")),TRUE()),"Invalid override value (J)",""),IF(IFERROR(IF($E26="",$I26="Yes",NOT(OR($E26="Blocker",$E26="Major",$E26="Moderate",$E26="Minor"))),TRUE()),"Invalid or missing criticality (E)",""),IF(IFERROR(IF($J26<>"",$T26="",FALSE()),TRUE()),"Override rationale missing / invalid (T)",""),IF(IFERROR(IF(AND($A26="2.7",$I26="Yes",p_confidential="Yes"),$E26<>"Blocker",FALSE()),TRUE()),"2.7 must be Blocker when S4 = Yes",""),IF(IFERROR(IF(AND($A26="5.8",$I26="Yes"),OR($E26="Moderate",$E26="Minor"),FALSE()),TRUE()),"5.8 should be at least Major",""),IF(IF(IFERROR(AND($J26="No",$AI26="Yes",OR($AD26="Blocker",AND($A26="2.7",p_confidential="Yes"))),FALSE()),NOT(AND(IFERROR($X26<>"",FALSE()),IFERROR($Y26<>"",FALSE()),IFERROR(AND(ISNUMBER($Z26),$Z26>=DATE(2020,1,1),$Z26<=DATE(2100,12,31)),FALSE()))),FALSE()),"Blocker de-scope review missing / invalid (X-Z)",""),IF(IF(IFERROR(IF(OR($E26="Blocker",$E26="Major",$E26="Moderate",$E26="Minor"),$F26<IF($AD26="Blocker",Lookups!$B$8,IF($AD26="Major",Lookups!$B$9,IF($AD26="Moderate",Lookups!$B$10,Lookups!$B$11))),FALSE()),FALSE()),NOT(AND(IFERROR($T26<>"",FALSE()),IFERROR($Y26<>"",FALSE()),IF(IFERROR($Z26<>"",FALSE()),IFERROR(AND(ISNUMBER($Z26),$Z26>=DATE(2020,1,1),$Z26<=DATE(2100,12,31)),FALSE()),NOT(ISERROR($Z26))))),FALSE()),"Criticality below baseline: review missing / invalid (T,Y,Z)","")) | AW26: =_xlfn.TEXTJOIN("; ",TRUE(),IF($AJ26>0,"Invalid response value (K)",""),IF($AK26>0,"Likelihood/Impact missing or not integer 1-5 (G,H)",""),IF($AL26>0,"Invalid status value (S)",""),IF($AM26>0,_xlfn.TEXTJOIN("; ",TRUE(),IF(IFERROR(AND($S26="Accepted Risk",$X26=""),FALSE()),"Exemption reference (X) missing",""),IF(IFERROR(AND($S26="Accepted Risk",$Y26=""),FALSE()),"Exemption approver (Y) missing",""),IF(IFERROR(AND($S26="Accepted Risk",$Z26=""),FALSE()),"Exemption date (Z) missing",""),IF(ISERROR($Z26),"Exemption date (Z) invalid - error value",IF(IFERROR(AND($Z26<>"",NOT(AND(ISNUMBER($Z26),$Z26>=DATE(2020,1,1),$Z26<=DATE(2100,12,31)))),FALSE()),"Exemption date (Z) invalid - enter a real date","")),IF(OR(ISERROR($S26),ISERROR($X26),ISERROR($Y26)),"Exemption inputs contain an error value (S,X,Y)","")),""),IF($AG26>0,"Input/calculation fault at "&$AU26,""),IF($AN26>0,"N/A on applicable row",""))
