Workbook
Name Conf_Adjust: Scales!$B$39:$C$41
Name Conf_Check: Scales!$B$39:$D$41
Name GateTab: 'Readiness gate'!$A$7:$K$36
Name List_Appetite: Policy!$C$4:$E$4
Name List_Blast: Scales!$B$31:$B$33
Name List_Confidence: Scales!$B$39:$B$41
Name List_Levels: Scales!$B$6:$B$10
Name List_Reversibility: Scales!$B$24:$B$27
Name List_Steps: Scales!$B$15:$B$20
Name List_YesNo: Scales!$B$54:$B$55

Sheet Guide
A1: Guide
A2: Working tool for the briefing "Auf dem Weg zum autonomen SOC" (M. Muhlert). Version 1.4.3, merged from three prototypes (SOC-Autonomy-Map as the base, SOC-Autonomie-Steuerungstool, Autonomy Decision Planner) and hardened through four independent validation reviews; the change log at the end of this sheet lists what the last two changed. Design law: less evidence must never produce more autonomy.
B4: The logic
B5: 1 | C5: Every use case is split into six process steps: Enrich, Triage, Contain, Eradicate, Recover, Notify. Autonomy belongs to an action in a step, not to a whole use case.
B6: 2 | C6: Each action is rated on reversibility (the guiding principle) and on blast radius. An action is only as reversible as its least reversible element.
B7: 3 | C7: The policy matrix turns that rating into the recommended level for each risk appetite. The recommendation is pure policy - the target picture. The appetite applies by default; a use case can carry its own appetite (its delegation profile).
B8: 4 | C8: You follow the recommendation or choose differently per step. A more cautious choice applies at once. A choice above policy stays visible as a target and releases with a recorded approval: Exception approved = Yes.
B9: 5 | C9: Three constraints decide the release candidate, what may run today: model confidence (High sets no ceiling; Medium and Low cap one or two levels below the policy level; floor L1; read-only steps are exempt), the readiness gate (not passed: hold at current; passed: state-changing steps climb one level, read-only steps release fully), and the non-waivable human-signature guardrail (state-changing irreversible or high-blast actions never release above L3, referenced to the Scales labels).
B10: 6 | C10: 'Limited by' names the binding constraint: readiness gate, model confidence, exception not approved, human-signature guardrail, own choice - or none. When several bind at the same level, all are named, joined by +. A row with missing inputs says Incomplete assessment and computes no candidate.
B11: 7 | C11: The scenario view puts target and today side by side: Standard assets (target) and Critical assets (target) are target pictures (critical re-rates every row at High blast radius), Released today shows release candidates. A target can sit above Released today; that gap is the point of the comparison.
B13: How to use it
B14: Autonomy map | C14: Choose the default risk appetite and the scenario view in the two yellow cells. The heatmap, counters and chart recalculate. All counters follow the selected view.
B15: Use cases | C15: Set a different appetite for single use cases (yellow column). IDs must stay unique; the Integrity column warns about duplicates, and a duplicate key blanks the affected register rows.
B16: Register | C16: Check action, reversibility, blast radius and model confidence for each step (blue). Your decisions sit in the yellow columns: your choice, exception approval, current level. Action, both ratings, confidence and current level are required: until all five are filled the row reads Incomplete assessment and no target and no release candidate is computed (the policy level in column J shows as soon as reversibility and blast radius are set). Columns I, K and L are grouped; the outline buttons above the columns collapse them.
B17: Readiness gate | C17: Answer the six criteria per use case with Yes or No. IDs are stable keys with uniqueness enforced: a duplicated key produces Incomplete, never an uplift. Only six explicit Yes answers pass. The yellow setting in row 4 decides what read-only steps need (default: all six criteria).
B18: Policy | C18: Change the matrix if none of the three profiles fits your organisation (whole levels 0 to 4). The guardrail column warns above L3 for irreversible or high-blast state changes; the release guardrail in the Register is non-waivable. A configuration-integrity cell checks the matrix.
B19: Scales | C19: Definitions of levels, steps, reversibility, blast radius, model confidence, gate criteria and verdicts. The confidence adjustments are editable governance conventions; a config check marks missing or invalid values, which then cap at L1.
B21: How to read it
B22: Autonomy levels | C22: The briefing assigns L0 to L5 per use case. Here the same scale is read per process step, as the split of work between human and system in that step.
B23: Recommended level | C23: Pure policy: risk appetite, reversibility, blast radius. This is the target picture. Confidence does not lower it - an ambitious target stays visible as a target.
B24: Model confidence | C24: Rated per task type. High means proven and calibrated and sets no ceiling; Medium and Low cap the release candidate below the policy level. A missing or unknown rating, or a broken adjustment on Scales, caps at L1: less evidence never produces more autonomy.
B25: Release candidate | C25: What may run today in the standard context, after confidence ceiling, gate allowance and the human-signature guardrail. Read-only steps are exempt from confidence and from one-level staging: once the gate passes, they release fully (briefing, slide 7). It remains a candidate: formal authorization stays with the Control Tower (slide 17), and the tool assumes actions, accesses and data uses are already permitted.
B26: Critical assets | C26: A target sensitivity view: production and business-critical services, board and VIP accounts, OT, supplier connections. Every row counts as High blast radius and shows the lower level.
B27: First human gate | C27: The first step in the chain that needs a human in this view. It assumes a linear path; a runtime response may branch or notify earlier.
B28: L5 | C28: Self-improving is not part of the map. It stays in test and detection engineering.
B30: Cell colours
B31: Yellow fill | C31: Your decisions: risk appetite, scenario view, appetite per use case, your own level, exception approval, current level.
B32: Blue text | C32: Pre-filled content that you can edit: actions, ratings, confidence, policy values, definitions, gate answers.
B33: Black text | C33: Calculated. Do not overwrite. Colour reinforces the text; it never carries the meaning alone.
B35: Extending
B36: New use case | C36: Rows are prepared for UC21 to UC30: add name and domain on Use cases, fill the six prepared Register rows (action, ratings, confidence, current level) and answer the gate. The map fills itself.
B37: Capacity | C37: Supported capacity is 30 use cases. Beyond UC30, add rows on all four sheets and extend every named range and row bound - copying rows alone is not enough.
B38: Renaming | C38: Change a class or step name on Scales and reselect it where used. Calculations reference the Scales cells, so renaming is safe everywhere, including the guardrail. The map marks duplicate use-case-step pairs as Dup. instead of summing levels.
B40: Pre-filled content and sources
B41: Ratings | C41: All actions and ratings are a starting proposal built from the twenty playbooks of the briefing (slides 11 and 15). They assume standard assets and are not a standard.
B42: Three corrections | C42: UC01 and UC02 Contain read blast radius Medium: quarantine across all mailboxes is not 'one mailbox' by the tool's own definition. UC02 carries Progressive, same as UC01: the briefing gives the whole mail class a high delegation profile and says quarantine and mass remediation can run fully automatically (slides 9, 15, 16).
B43: Confidence | C43: Model confidence is an illustrative starting point and a chosen governance rule, not a measurement. Replace it with evidence: precision and false-positive rates per detection, and calibration checks after every model or prompt change (briefing, slide 14).
B44: Policy values | C44: The matrix follows the briefing: L3 to L4 for common incidents, L2 to L3 for highly critical ones; irreversible and business-critical actions need a human signature (slides 3, 4 and 15).
B45: Appetite examples | C45: UC01 and UC02 are set to Progressive and UC20 to Conservative, following the briefing's delegation intents (slide 16).
B46: Readiness criteria | C46: The six gate criteria come from the readiness gate of the briefing (slide 16). Criterion 2 asks for a documented and tested rollback path; reversibility itself is already rated per step.
B47: Current levels | C47: The current level today is an illustrative starting point, not an assessment - replace it with your own baseline. Rows where current exceeds the permitted level are flagged red; invalid pasted values are treated as 0 and flagged; a missing value makes the row an incomplete assessment.
B48: Known next step | C48: Reversibility is still a label, not a demonstrated property. A recovery field - detection plus halt plus recovery within the business tolerance window, with an evidence reference - is the deliberate next iteration.
B50: Change log v1.4.2
B51: Policy gate | C51: Recommended level (J) and Level on critical assets (Q) require the Policy integrity check (Policy!B24) to read OK. Before, a blank policy cell fell through as L0, and a blank or text cell in a High blast radius row let the critical-assets level fall back to the standard level, because MIN ignores blank and text references. A broken matrix now reads Config error on every row and the line above the heatmap names the error.
B52: Current level | C52: A missing Current level today (R) reads Incomplete assessment in Check and Limited by, computes no release candidate and counts under Incomplete rows. Before, a blank cell was treated as 0 and Limited by named the readiness gate as the cause.
B53: Check column | C53: Check (P) reads Incomplete assessment whenever Limited by does, so a partly filled row no longer shows As recommended beside Incomplete assessment. The target (O) still needed only reversibility and blast radius; v1.4.3 applies one rule to the whole row.
B54: Map counters | C54: The three KPI cards and the level distribution count from the heatmap grid instead of the Register, so they match the map exactly: duplicate (ID, Step) rows that the map shows as Dup. are no longer counted, and the Released today share can no longer divide by zero.
B55: Scenario labels | C55: The scenario view reads Standard assets (target), Critical assets (target) and Released today, so the two target pictures are not mistaken for what may run today.
B56: Configuration | C56: The line above the heatmap turns red and names the error when the policy matrix or the confidence adjustments fail their integrity check on Policy or Scales.
B57: Register layout | C57: Columns I (Appetite), K (Confidence adjustment) and L (Confidence ceiling) are grouped; the outline buttons above the columns collapse them so inputs and verdicts sit side by side.
B58: Content | C58: UC07 and UC09 Eradicate cover standard remediation (Reversible with effort); reimaging is noted as a separate manual escalation, since bundling it pinned the whole step at L1. UC14 Notify confidence reads Medium, in line with the other regulatory notifications; its level is unchanged, the policy level is already L1.
B59: Review input | C59: The changes follow the third independent validation review of v1.4.1. Not adopted: a step-order constraint (a human-approved verdict followed by autonomous containment is coherent, and the inversions in the review's examples come from the Current level inputs) and reclassifying Triage as read-only (an autonomous verdict closes or escalates cases, a real state change). Open decision: a reduced readiness gate for read-only steps (Signal, Cost and Resilience only), which would release auto-enrichment in the nine use cases whose gate has not passed.
B61: Change log v1.4.3
B62: Completeness rule | C62: One rule for the whole row: Level applied (O) stays blank until action, reversibility, blast radius, confidence and current level are all filled, and Check, Level on critical assets, Release candidate and Limited by follow O. Before, the target computed from reversibility and blast radius alone, so an above-policy choice on a half-filled row appeared on the target map while Check read Incomplete assessment and the above-policy counters stayed at 0. The policy level in J still shows as soon as reversibility and blast radius are set.
B63: Conditional formats | C63: Scales C43 and D39:D41 turn red when the confidence adjustments fail their check, as Policy B24 already did; Check (P) shows Incomplete assessment in grey, as Limited by does.
B64: Read-only gate setting | C64: The Readiness gate sheet carries a setting (row 4) for what read-only steps need to pass: All six criteria (default, behaviour unchanged), Signal + cost + resilience, or Signal + cost. The column Result (read-only steps) holds that verdict; the Register uses it for No state change rows only, state-changing steps always need all six. With the pre-filled answers, Signal + cost + resilience changes nothing (Resilience & degraded mode is No in every use case whose gate has not passed) and Signal + cost releases Enrich to L4 in UC05, UC10, UC11, UC12 and UC16.
B65: File | C65: The workbook no longer forces a full recalculation on opening. Cached values are verified against a fresh calculation, so Excel asks to save only when something was edited.
B66: Review input | C66: The changes follow the fourth independent validation review (of v1.4.2). The scroll position reported there (Register opening at row 95) was not in the delivered file; a later save while scrolled wrote it.

Sheet Autonomy map
A1: SOC Autonomy Map
A2: Autonomy level per use case and process step. The target is pure policy: risk appetite, reversibility, blast radius. Model confidence, the readiness gate and the human-signature guardrail decide the release candidate. Version 1.4.3.
A4: Risk appetite (default) | C4: Progressive | E4: Runs autonomously (L4) | G4: Human approves (L3) | I4: Human decides (L0 to L2) | K4: Choices above policy | M4: Readiness gates passed | O4: Steps not fully released | Q4: Incomplete rows | S4: Current above permitted
A5: Scenario view | C5: Released today | E5: =IF(COUNT($E$8:$J$37)=0,0,COUNTIF($E$8:$J$37,4)/COUNT($E$8:$J$37)) -> 0.11666667 | G5: =IF(COUNT($E$8:$J$37)=0,0,COUNTIF($E$8:$J$37,3)/COUNT($E$8:$J$37)) -> 0.091666667 | I5: =IF(COUNT($E$8:$J$37)=0,0,COUNTIF($E$8:$J$37,"<3")/COUNT($E$8:$J$37)) -> 0.79166667 | K5: =COUNTIF(Register!$P$6:$P$185,"Above policy*") -> 0 | M5: =COUNTIF('Readiness gate'!$I$7:$I$36,"Passed")&" of "&COUNTA('Use cases'!$B$5:$B$34) -> 11 of 20 | O5: =SUMPRODUCT((Register!$O$6:$O$185<>"")*(Register!$T$6:$T$185<>"")*(Register!$T$6:$T$185<Register!$O$6:$O$185)) -> 105 | Q5: =SUMPRODUCT((Register!$B$6:$B$185<>"")*(Register!$O$6:$O$185="")) -> 0 | S5: =SUMPRODUCT((Register!$R$6:$R$185<>"")*(Register!$T$6:$T$185<>"")*(Register!$R$6:$R$185>Register!$T$6:$T$185)) -> 0
A6: =IF(OR(Policy!$B$24<>"OK",Scales!$C$43<>"OK"),"Configuration error: "&IF(Policy!$B$24<>"OK",Policy!$B$24&" (Policy sheet; no level is computed until it reads OK)","")&IF(AND(Policy!$B$24<>"OK",Scales!$C$43<>"OK"),"; ","")&IF(Scales!$C$43<>"OK",Scales!$C$43&" (Scales sheet; affected ratings cap at L1 until it reads OK)","")&".","This view: "&$C$5&" - "&IF($C$5="Released today","release candidates in the standard context (what may run today)","target picture (what the policy allows)")&". Formal authorization stays with the Control Tower.") -> This view: Released today - release candidates in the standard context (what may run today). Formal authorization stays with the Control Tower.
A7: ID | B7: Use case | C7: Domain | D7: Appetite | E7: =Scales!$B$15 -> Enrich | F7: =Scales!$B$16 -> Triage | G7: =Scales!$B$17 -> Contain | H7: =Scales!$B$18 -> Eradicate | I7: =Scales!$B$19 -> Recover | J7: =Scales!$B$20 -> Notify | K7: ="First human gate ("&IF($C$5="Released today","released","target")&")" -> First human gate (released) | L7: Above policy | M7: Readiness gate | N7: Steps not fully released
A8: =IF('Use cases'!$B$5="","",'Use cases'!$A$5) -> UC01 | B8: =IF($A8="","",'Use cases'!$B$5) -> Phishing campaign containment | C8: =IF($A8="","",'Use cases'!$C$5) -> Email and collaboration | D8: =IF($A8="","",'Use cases'!$E$5) -> Progressive | E8: =IF($A8="","",IF(COUNTIFS(Register!$A$6:$A$185,$A8,Register!$D$6:$D$185,E$7)>1,"Dup.",IF($C$5="Critical assets (target)",IF(COUNTIFS(Register!$A$6:$A$185,$A8,Register!$D$6:$D$185,E$7,Register!$Q$6:$Q$185,">=0")=0,"",SUMIFS(Register!$Q$6:$Q$185,Register!$A$6:$A$185,$A8,Register!$D$6:$D$185,E$7)),IF($C$5="Released today",IF(COUNTIFS(Register!$A$6:$A$185,$A8,Register!$D$6:$D$185,E$7,Register!$T$6:$T$185,">=0")=0,"",SUMIFS(Register!$T$6:$T$185,Register!$A$6:$A$185,$A8,Register!$D$6:$D$185,E$7)),IF(COUNTIFS(Register!$A$6:$A$185,$A8,Register!$D$6:$D$185,E$7,Register!$O$6:$O$185,">=0")=0,"",SUMIFS(Register!$O$6:$O$185,Register!$A$6:$A$185,$A8,Register!$D$6:$D$185,E$7)))))) -> 4 | F8: =IF($A8="","",IF(COUNTIFS(Register!$A$6:$A$185,$A8,Register!$D$6:$D$185,F$7)>1,"Dup.",IF($C$5="Critical assets (target)",IF(COUNTIFS(Register!$A$6:$A$185,$A8,Register!$D$6:$D$185,F$7,Register!$Q$6:$Q$185,">=0")=0,"",SUMIFS(Register!$Q$6:$Q$185,Register!$A$6:$A$185,$A8,Register!$D$6:$D$185,F$7)),IF($C$5="Released today",IF(COUNTIFS(Register!$A$6:$A$185,$A8,Register!$D$6:$D$185,F$7,Register!$T$6:$T$185,">=0")=0,"",SUMIFS(Register!$T$6:$T$185,Register!$A$6:$A$185,$A8,Register!$D$6:$D$185,F$7)),IF(COUNTIFS(Register!$A$6:$A$185,$A8,Register!$D$6:$D$185,F$7,Register!$O$6:$O$185,">=0")=0,"",SUMIFS(Register!$O$6:$O$185,Register!$A$6:$A$185,$A8,Register!$D$6:$D$185,F$7)))))) -> 3 | G8: =IF($A8="","",IF(COUNTIFS(Register!$A$6:$A$185,$A8,Register!$D$6:$D$185,G$7)>1,"Dup.",IF($C$5="Critical assets (target)",IF(COUNTIFS(Register!$A$6:$A$185,$A8,Register!$D$6:$D$185,G$7,Register!$Q$6:$Q$185,">=0")=0,"",SUMIFS(Register!$Q$6:$Q$185,Register!$A$6:$A$185,$A8,Register!$D$6:$D$185,G$7)),IF($C$5="Released today",IF(COUNTIFS(Register!$A$6:$A$185,$A8,Register!$D$6:$D$185,G$7,Register!$T$6:$T$185,">=0")=0,"",SUMIFS(Register!$T$6:$T$185,Register!$A$6:$A$185,$A8,Register!$D$6:$D$185,G$7)),IF(COUNTIFS(Register!$A$6:$A$185,$A8,Register!$D$6:$D$185,G$7,Register!$O$6:$O$185,">=0")=0,"",SUMIFS(Register!$O$6:$O$185,Register!$A$6:$A$185,$A8,Register!$D$6:$D$185,G$7)))))) -> 4 | H8: =IF($A8="","",IF(COUNTIFS(Register!$A$6:$A$185,$A8,Register!$D$6:$D$185,H$7)>1,"Dup.",IF($C$5="Critical assets (target)",IF(COUNTIFS(Register!$A$6:$A$185,$A8,Register!$D$6:$D$185,H$7,Register!$Q$6:$Q$185,">=0")=0,"",SUMIFS(Register!$Q$6:$Q$185,Register!$A$6:$A$185,$A8,Register!$D$6:$D$185,H$7)),IF($C$5="Released today",IF(COUNTIFS(Register!$A$6:$A$185,$A8,Register!$D$6:$D$185,H$7,Register!$T$6:$T$185,">=0")=0,"",SUMIFS(Register!$T$6:$T$185,Register!$A$6:$A$185,$A8,Register!$D$6:$D$185,H$7)),IF(COUNTIFS(Register!$A$6:$A$185,$A8,Register!$D$6:$D$185,H$7,Register!$O$6:$O$185,">=0")=0,"",SUMIFS(Register!$O$6:$O$185,Register!$A$6:$A$185,$A8,Register!$D$6:$D$185,H$7)))))) -> 3 | I8: =IF($A8="","",IF(COUNTIFS(Register!$A$6:$A$185,$A8,Register!$D$6:$D$185,I$7)>1,"Dup.",IF($C$5="Critical assets (target)",IF(COUNTIFS(Register!$A$6:$A$185,$A8,Register!$D$6:$D$185,I$7,Register!$Q$6:$Q$185,">=0")=0,"",SUMIFS(Register!$Q$6:$Q$185,Register!$A$6:$A$185,$A8,Register!$D$6:$D$185,I$7)),IF($C$5="Released today",IF(COUNTIFS(Register!$A$6:$A$185,$A8,Register!$D$6:$D$185,I$7,Register!$T$6:$T$185,">=0")=0,"",SUMIFS(Register!$T$6:$T$185,Register!$A$6:$A$185,$A8,Register!$D$6:$D$185,I$7)),IF(COUNTIFS(Register!$A$6:$A$185,$A8,Register!$D$6:$D$185,I$7,Register!$O$6:$O$185,">=0")=0,"",SUMIFS(Register!$O$6:$O$185,Register!$A$6:$A$185,$A8,Register!$D$6:$D$185,I$7)))))) -> 2 | J8: =IF($A8="","",IF(COUNTIFS(Register!$A$6:$A$185,$A8,Register!$D$6:$D$185,J$7)>1,"Dup.",IF($C$5="Critical assets (target)",IF(COUNTIFS(Register!$A$6:$A$185,$A8,Register!$D$6:$D$185,J$7,Register!$Q$6:$Q$185,">=0")=0,"",SUMIFS(Register!$Q$6:$Q$185,Register!$A$6:$A$185,$A8,Register!$D$6:$D$185,J$7)),IF($C$5="Released today",IF(COUNTIFS(Register!$A$6:$A$185,$A8,Register!$D$6:$D$185,J$7,Register!$T$6:$T$185,">=0")=0,"",SUMIFS(Register!$T$6:$T$185,Register!$A$6:$A$185,$A8,Register!$D$6:$D$185,J$7)),IF(COUNTIFS(Register!$A$6:$A$185,$A8,Register!$D$6:$D$185,J$7,Register!$O$6:$O$185,">=0")=0,"",SUMIFS(Register!$O$6:$O$185,Register!$A$6:$A$185,$A8,Register!$D$6:$D$185,J$7)))))) -> 3 | K8: =IF($A8="","",IF(COUNT(E8:J8)<6,"Incomplete",IF(AND(ISNUMBER(E8),E8<4),E$7,IF(AND(ISNUMBER(F8),F8<4),F$7,IF(AND(ISNUMBER(G8),G8<4),G$7,IF(AND(ISNUMBER(H8),H8<4),H$7,IF(AND(ISNUMBER(I8),I8<4),I$7,IF(AND(ISNUMBER(J8),J8<4),J$7,"None")))))))) -> Triage | L8: =IF($A8="","",COUNTIFS(Register!$A$6:$A$185,$A8,Register!$P$6:$P$185,"Above policy*")) -> 0 | M8: =IF($A8="","",IF(COUNTIF('Readiness gate'!$A$7:$A$36,$A8)<>1,"Incomplete",IFERROR(IF(VLOOKUP($A8,GateTab,9,FALSE())="","Incomplete",VLOOKUP($A8,GateTab,9,FALSE())),"Incomplete"))) -> Passed | N8: =IF($A8="","",SUMPRODUCT((Register!$A$6:$A$185=$A8)*(Register!$T$6:$T$185<>"")*(Register!$O$6:$O$185<>"")*(Register!$T$6:$T$185<Register!$O$6:$O$185))) -> 4
A9: =IF('Use cases'!$B$6="","",'Use cases'!$A$6) -> UC02 | B9: =IF($A9="","",'Use cases'!$B$6) -> Malicious attachment detonation and mailbox clean-up | C9: =IF($A9="","",'Use cases'!$C$6) -> Email and collaboration | D9: =IF($A9="","",'Use cases'!$E$6) -> Progressive | E9: =IF($A9="","",IF(COUNTIFS(Register!$A$6:$A$185,$A9,Register!$D$6:$D$185,E$7)>1,"Dup.",IF($C$5="Critical assets (target)",IF(COUNTIFS(Register!$A$6:$A$185,$A9,Register!$D$6:$D$185,E$7,Register!$Q$6:$Q$185,">=0")=0,"",SUMIFS(Register!$Q$6:$Q$185,Register!$A$6:$A$185,$A9,Register!$D$6:$D$185,E$7)),IF($C$5="Released today",IF(COUNTIFS(Register!$A$6:$A$185,$A9,Register!$D$6:$D$185,E$7,Register!$T$6:$T$185,">=0")=0,"",SUMIFS(Register!$T$6:$T$185,Register!$A$6:$A$185,$A9,Register!$D$6:$D$185,E$7)),IF(COUNTIFS(Register!$A$6:$A$185,$A9,Register!$D$6:$D$185,E$7,Register!$O$6:$O$185,">=0")=0,"",SUMIFS(Register!$O$6:$O$185,Register!$A$6:$A$185,$A9,Register!$D$6:$D$185,E$7)))))) -> 4 | F9: =IF($A9="","",IF(COUNTIFS(Register!$A$6:$A$185,$A9,Register!$D$6:$D$185,F$7)>1,"Dup.",IF($C$5="Critical assets (target)",IF(COUNTIFS(Register!$A$6:$A$185,$A9,Register!$D$6:$D$185,F$7,Register!$Q$6:$Q$185,">=0")=0,"",SUMIFS(Register!$Q$6:$Q$185,Register!$A$6:$A$185,$A9,Register!$D$6:$D$185,F$7)),IF($C$5="Released today",IF(COUNTIFS(Register!$A$6:$A$185,$A9,Register!$D$6:$D$185,F$7,Register!$T$6:$T$185,">=0")=0,"",SUMIFS(Register!$T$6:$T$185,Register!$A$6:$A$185,$A9,Register!$D$6:$D$185,F$7)),IF(COUNTIFS(Register!$A$6:$A$185,$A9,Register!$D$6:$D$185,F$7,Register!$O$6:$O$185,">=0")=0,"",SUMIFS(Register!$O$6:$O$185,Register!$A$6:$A$185,$A9,Register!$D$6:$D$185,F$7)))))) -> 2 | G9: =IF($A9="","",IF(COUNTIFS(Register!$A$6:$A$185,$A9,Register!$D$6:$D$185,G$7)>1,"Dup.",IF($C$5="Critical assets (target)",IF(COUNTIFS(Register!$A$6:$A$185,$A9,Register!$D$6:$D$185,G$7,Register!$Q$6:$Q$185,">=0")=0,"",SUMIFS(Register!$Q$6:$Q$185,Register!$A$6:$A$185,$A9,Register!$D$6:$D$185,G$7)),IF($C$5="Released today",IF(COUNTIFS(Register!$A$6:$A$185,$A9,Register!$D$6:$D$185,G$7,Register!$T$6:$T$185,">=0")=0,"",SUMIFS(Register!$T$6:$T$185,Register!$A$6:$A$185,$A9,Register!$D$6:$D$185,G$7)),IF(COUNTIFS(Register!$A$6:$A$185,$A9,Register!$D$6:$D$185,G$7,Register!$O$6:$O$185,">=0")=0,"",SUMIFS(Register!$O$6:$O$185,Register!$A$6:$A$185,$A9,Register!$D$6:$D$185,G$7)))))) -> 3 | H9: =IF($A9="","",IF(COUNTIFS(Register!$A$6:$A$185,$A9,Register!$D$6:$D$185,H$7)>1,"Dup.",IF($C$5="Critical assets (target)",IF(COUNTIFS(Register!$A$6:$A$185,$A9,Register!$D$6:$D$185,H$7,Register!$Q$6:$Q$185,">=0")=0,"",SUMIFS(Register!$Q$6:$Q$185,Register!$A$6:$A$185,$A9,Register!$D$6:$D$185,H$7)),IF($C$5="Released today",IF(COUNTIFS(Register!$A$6:$A$185,$A9,Register!$D$6:$D$185,H$7,Register!$T$6:$T$185,">=0")=0,"",SUMIFS(Register!$T$6:$T$185,Register!$A$6:$A$185,$A9,Register!$D$6:$D$185,H$7)),IF(COUNTIFS(Register!$A$6:$A$185,$A9,Register!$D$6:$D$185,H$7,Register!$O$6:$O$185,">=0")=0,"",SUMIFS(Register!$O$6:$O$185,Register!$A$6:$A$185,$A9,Register!$D$6:$D$185,H$7)))))) -> 2 | I9: =IF($A9="","",IF(COUNTIFS(Register!$A$6:$A$185,$A9,Register!$D$6:$D$185,I$7)>1,"Dup.",IF($C$5="Critical assets (target)",IF(COUNTIFS(Register!$A$6:$A$185,$A9,Register!$D$6:$D$185,I$7,Register!$Q$6:$Q$185,">=0")=0,"",SUMIFS(Register!$Q$6:$Q$185,Register!$A$6:$A$185,$A9,Register!$D$6:$D$185,I$7)),IF($C$5="Released today",IF(COUNTIFS(Register!$A$6:$A$185,$A9,Register!$D$6:$D$185,I$7,Register!$T$6:$T$185,">=0")=0,"",SUMIFS(Register!$T$6:$T$185,Register!$A$6:$A$185,$A9,Register!$D$6:$D$185,I$7)),IF(COUNTIFS(Register!$A$6:$A$185,$A9,Register!$D$6:$D$185,I$7,Register!$O$6:$O$185,">=0")=0,"",SUMIFS(Register!$O$6:$O$185,Register!$A$6:$A$185,$A9,Register!$D$6:$D$185,I$7)))))) -> 2 | J9: =IF($A9="","",IF(COUNTIFS(Register!$A$6:$A$185,$A9,Register!$D$6:$D$185,J$7)>1,"Dup.",IF($C$5="Critical assets (target)",IF(COUNTIFS(Register!$A$6:$A$185,$A9,Register!$D$6:$D$185,J$7,Register!$Q$6:$Q$185,">=0")=0,"",SUMIFS(Register!$Q$6:$Q$185,Register!$A$6:$A$185,$A9,Register!$D$6:$D$185,J$7)),IF($C$5="Released today",IF(COUNTIFS(Register!$A$6:$A$185,$A9,Register!$D$6:$D$185,J$7,Register!$T$6:$T$185,">=0")=0,"",SUMIFS(Register!$T$6:$T$185,Register!$A$6:$A$185,$A9,Register!$D$6:$D$185,J$7)),IF(COUNTIFS(Register!$A$6:$A$185,$A9,Register!$D$6:$D$185,J$7,Register!$O$6:$O$185,">=0")=0,"",SUMIFS(Register!$O$6:$O$185,Register!$A$6:$A$185,$A9,Register!$D$6:$D$185,J$7)))))) -> 2 | K9: =IF($A9="","",IF(COUNT(E9:J9)<6,"Incomplete",IF(AND(ISNUMBER(E9),E9<4),E$7,IF(AND(ISNUMBER(F9),F9<4),F$7,IF(AND(ISNUMBER(G9),G9<4),G$7,IF(AND(ISNUMBER(H9),H9<4),H$7,IF(AND(ISNUMBER(I9),I9<4),I$7,IF(AND(ISNUMBER(J9),J9<4),J$7,"None")))))))) -> Triage | L9: =IF($A9="","",COUNTIFS(Register!$A$6:$A$185,$A9,Register!$P$6:$P$185,"Above policy*")) -> 0 | M9: =IF($A9="","",IF(COUNTIF('Readiness gate'!$A$7:$A$36,$A9)<>1,"Incomplete",IFERROR(IF(VLOOKUP($A9,GateTab,9,FALSE())="","Incomplete",VLOOKUP($A9,GateTab,9,FALSE())),"Incomplete"))) -> Passed | N9: =IF($A9="","",SUMPRODUCT((Register!$A$6:$A$185=$A9)*(Register!$T$6:$T$185<>"")*(Register!$O$6:$O$185<>"")*(Register!$T$6:$T$185<Register!$O$6:$O$185))) -> 5
A10: =IF('Use cases'!$B$7="","",'Use cases'!$A$7) -> UC03 | B10: =IF($A10="","",'Use cases'!$B$7) -> OAuth consent abuse | C10: =IF($A10="","",'Use cases'!$C$7) -> Identity | D10: =IF($A10="","",'Use cases'!$E$7) -> Progressive | E10: =IF($A10="","",IF(COUNTIFS(Register!$A$6:$A$185,$A10,Register!$D$6:$D$185,E$7)>1,"Dup.",IF($C$5="Critical assets (target)",IF(COUNTIFS(Register!$A$6:$A$185,$A10,Register!$D$6:$D$185,E$7,Register!$Q$6:$Q$185,">=0")=0,"",SUMIFS(Register!$Q$6:$Q$185,Register!$A$6:$A$185,$A10,Register!$D$6:$D$185,E$7)),IF($C$5="Released today",IF(COUNTIFS(Register!$A$6:$A$185,$A10,Register!$D$6:$D$185,E$7,Register!$T$6:$T$185,">=0")=0,"",SUMIFS(Register!$T$6:$T$185,Register!$A$6:$A$185,$A10,Register!$D$6:$D$185,E$7)),IF(COUNTIFS(Register!$A$6:$A$185,$A10,Register!$D$6:$D$185,E$7,Register!$O$6:$O$185,">=0")=0,"",SUMIFS(Register!$O$6:$O$185,Register!$A$6:$A$185,$A10,Register!$D$6:$D$185,E$7)))))) -> 4 | F10: =IF($A10="","",IF(COUNTIFS(Register!$A$6:$A$185,$A10,Register!$D$6:$D$185,F$7)>1,"Dup.",IF($C$5="Critical assets (target)",IF(COUNTIFS(Register!$A$6:$A$185,$A10,Register!$D$6:$D$185,F$7,Register!$Q$6:$Q$185,">=0")=0,"",SUMIFS(Register!$Q$6:$Q$185,Register!$A$6:$A$185,$A10,Register!$D$6:$D$185,F$7)),IF($C$5="Released today",IF(COUNTIFS(Register!$A$6:$A$185,$A10,Register!$D$6:$D$185,F$7,Register!$T$6:$T$185,">=0")=0,"",SUMIFS(Register!$T$6:$T$185,Register!$A$6:$A$185,$A10,Register!$D$6:$D$185,F$7)),IF(COUNTIFS(Register!$A$6:$A$185,$A10,Register!$D$6:$D$185,F$7,Register!$O$6:$O$185,">=0")=0,"",SUMIFS(Register!$O$6:$O$185,Register!$A$6:$A$185,$A10,Register!$D$6:$D$185,F$7)))))) -> 2 | G10: =IF($A10="","",IF(COUNTIFS(Register!$A$6:$A$185,$A10,Register!$D$6:$D$185,G$7)>1,"Dup.",IF($C$5="Critical assets (target)",IF(COUNTIFS(Register!$A$6:$A$185,$A10,Register!$D$6:$D$185,G$7,Register!$Q$6:$Q$185,">=0")=0,"",SUMIFS(Register!$Q$6:$Q$185,Register!$A$6:$A$185,$A10,Register!$D$6:$D$185,G$7)),IF($C$5="Released today",IF(COUNTIFS(Register!$A$6:$A$185,$A10,Register!$D$6:$D$185,G$7,Register!$T$6:$T$185,">=0")=0,"",SUMIFS(Register!$T$6:$T$185,Register!$A$6:$A$185,$A10,Register!$D$6:$D$185,G$7)),IF(COUNTIFS(Register!$A$6:$A$185,$A10,Register!$D$6:$D$185,G$7,Register!$O$6:$O$185,">=0")=0,"",SUMIFS(Register!$O$6:$O$185,Register!$A$6:$A$185,$A10,Register!$D$6:$D$185,G$7)))))) -> 3 | H10: =IF($A10="","",IF(COUNTIFS(Register!$A$6:$A$185,$A10,Register!$D$6:$D$185,H$7)>1,"Dup.",IF($C$5="Critical assets (target)",IF(COUNTIFS(Register!$A$6:$A$185,$A10,Register!$D$6:$D$185,H$7,Register!$Q$6:$Q$185,">=0")=0,"",SUMIFS(Register!$Q$6:$Q$185,Register!$A$6:$A$185,$A10,Register!$D$6:$D$185,H$7)),IF($C$5="Released today",IF(COUNTIFS(Register!$A$6:$A$185,$A10,Register!$D$6:$D$185,H$7,Register!$T$6:$T$185,">=0")=0,"",SUMIFS(Register!$T$6:$T$185,Register!$A$6:$A$185,$A10,Register!$D$6:$D$185,H$7)),IF(COUNTIFS(Register!$A$6:$A$185,$A10,Register!$D$6:$D$185,H$7,Register!$O$6:$O$185,">=0")=0,"",SUMIFS(Register!$O$6:$O$185,Register!$A$6:$A$185,$A10,Register!$D$6:$D$185,H$7)))))) -> 2 | I10: =IF($A10="","",IF(COUNTIFS(Register!$A$6:$A$185,$A10,Register!$D$6:$D$185,I$7)>1,"Dup.",IF($C$5="Critical assets (target)",IF(COUNTIFS(Register!$A$6:$A$185,$A10,Register!$D$6:$D$185,I$7,Register!$Q$6:$Q$185,">=0")=0,"",SUMIFS(Register!$Q$6:$Q$185,Register!$A$6:$A$185,$A10,Register!$D$6:$D$185,I$7)),IF($C$5="Released today",IF(COUNTIFS(Register!$A$6:$A$185,$A10,Register!$D$6:$D$185,I$7,Register!$T$6:$T$185,">=0")=0,"",SUMIFS(Register!$T$6:$T$185,Register!$A$6:$A$185,$A10,Register!$D$6:$D$185,I$7)),IF(COUNTIFS(Register!$A$6:$A$185,$A10,Register!$D$6:$D$185,I$7,Register!$O$6:$O$185,">=0")=0,"",SUMIFS(Register!$O$6:$O$185,Register!$A$6:$A$185,$A10,Register!$D$6:$D$185,I$7)))))) -> 2 | J10: =IF($A10="","",IF(COUNTIFS(Register!$A$6:$A$185,$A10,Register!$D$6:$D$185,J$7)>1,"Dup.",IF($C$5="Critical assets (target)",IF(COUNTIFS(Register!$A$6:$A$185,$A10,Register!$D$6:$D$185,J$7,Register!$Q$6:$Q$185,">=0")=0,"",SUMIFS(Register!$Q$6:$Q$185,Register!$A$6:$A$185,$A10,Register!$D$6:$D$185,J$7)),IF($C$5="Released today",IF(COUNTIFS(Register!$A$6:$A$185,$A10,Register!$D$6:$D$185,J$7,Register!$T$6:$T$185,">=0")=0,"",SUMIFS(Register!$T$6:$T$185,Register!$A$6:$A$185,$A10,Register!$D$6:$D$185,J$7)),IF(COUNTIFS(Register!$A$6:$A$185,$A10,Register!$D$6:$D$185,J$7,Register!$O$6:$O$185,">=0")=0,"",SUMIFS(Register!$O$6:$O$185,Register!$A$6:$A$185,$A10,Register!$D$6:$D$185,J$7)))))) -> 2 | K10: =IF($A10="","",IF(COUNT(E10:J10)<6,"Incomplete",IF(AND(ISNUMBER(E10),E10<4),E$7,IF(AND(ISNUMBER(F10),F10<4),F$7,IF(AND(ISNUMBER(G10),G10<4),G$7,IF(AND(ISNUMBER(H10),H10<4),H$7,IF(AND(ISNUMBER(I10),I10<4),I$7,IF(AND(ISNUMBER(J10),J10<4),J$7,"None")))))))) -> Triage | L10: =IF($A10="","",COUNTIFS(Register!$A$6:$A$185,$A10,Register!$P$6:$P$185,"Above policy*")) -> 0 | M10: =IF($A10="","",IF(COUNTIF('Readiness gate'!$A$7:$A$36,$A10)<>1,"Incomplete",IFERROR(IF(VLOOKUP($A10,GateTab,9,FALSE())="","Incomplete",VLOOKUP($A10,GateTab,9,FALSE())),"Incomplete"))) -> Passed | N10: =IF($A10="","",SUMPRODUCT((Register!$A$6:$A$185=$A10)*(Register!$T$6:$T$185<>"")*(Register!$O$6:$O$185<>"")*(Register!$T$6:$T$185<Register!$O$6:$O$185))) -> 5
A11: =IF('Use cases'!$B$8="","",'Use cases'!$A$8) -> UC04 | B11: =IF($A11="","",'Use cases'!$B$8) -> Suspicious MFA registration | C11: =IF($A11="","",'Use cases'!$C$8) -> Identity | D11: =IF($A11="","",'Use cases'!$E$8) -> Progressive | E11: =IF($A11="","",IF(COUNTIFS(Register!$A$6:$A$185,$A11,Register!$D$6:$D$185,E$7)>1,"Dup.",IF($C$5="Critical assets (target)",IF(COUNTIFS(Register!$A$6:$A$185,$A11,Register!$D$6:$D$185,E$7,Register!$Q$6:$Q$185,">=0")=0,"",SUMIFS(Register!$Q$6:$Q$185,Register!$A$6:$A$185,$A11,Register!$D$6:$D$185,E$7)),IF($C$5="Released today",IF(COUNTIFS(Register!$A$6:$A$185,$A11,Register!$D$6:$D$185,E$7,Register!$T$6:$T$185,">=0")=0,"",SUMIFS(Register!$T$6:$T$185,Register!$A$6:$A$185,$A11,Register!$D$6:$D$185,E$7)),IF(COUNTIFS(Register!$A$6:$A$185,$A11,Register!$D$6:$D$185,E$7,Register!$O$6:$O$185,">=0")=0,"",SUMIFS(Register!$O$6:$O$185,Register!$A$6:$A$185,$A11,Register!$D$6:$D$185,E$7)))))) -> 4 | F11: =IF($A11="","",IF(COUNTIFS(Register!$A$6:$A$185,$A11,Register!$D$6:$D$185,F$7)>1,"Dup.",IF($C$5="Critical assets (target)",IF(COUNTIFS(Register!$A$6:$A$185,$A11,Register!$D$6:$D$185,F$7,Register!$Q$6:$Q$185,">=0")=0,"",SUMIFS(Register!$Q$6:$Q$185,Register!$A$6:$A$185,$A11,Register!$D$6:$D$185,F$7)),IF($C$5="Released today",IF(COUNTIFS(Register!$A$6:$A$185,$A11,Register!$D$6:$D$185,F$7,Register!$T$6:$T$185,">=0")=0,"",SUMIFS(Register!$T$6:$T$185,Register!$A$6:$A$185,$A11,Register!$D$6:$D$185,F$7)),IF(COUNTIFS(Register!$A$6:$A$185,$A11,Register!$D$6:$D$185,F$7,Register!$O$6:$O$185,">=0")=0,"",SUMIFS(Register!$O$6:$O$185,Register!$A$6:$A$185,$A11,Register!$D$6:$D$185,F$7)))))) -> 2 | G11: =IF($A11="","",IF(COUNTIFS(Register!$A$6:$A$185,$A11,Register!$D$6:$D$185,G$7)>1,"Dup.",IF($C$5="Critical assets (target)",IF(COUNTIFS(Register!$A$6:$A$185,$A11,Register!$D$6:$D$185,G$7,Register!$Q$6:$Q$185,">=0")=0,"",SUMIFS(Register!$Q$6:$Q$185,Register!$A$6:$A$185,$A11,Register!$D$6:$D$185,G$7)),IF($C$5="Released today",IF(COUNTIFS(Register!$A$6:$A$185,$A11,Register!$D$6:$D$185,G$7,Register!$T$6:$T$185,">=0")=0,"",SUMIFS(Register!$T$6:$T$185,Register!$A$6:$A$185,$A11,Register!$D$6:$D$185,G$7)),IF(COUNTIFS(Register!$A$6:$A$185,$A11,Register!$D$6:$D$185,G$7,Register!$O$6:$O$185,">=0")=0,"",SUMIFS(Register!$O$6:$O$185,Register!$A$6:$A$185,$A11,Register!$D$6:$D$185,G$7)))))) -> 3 | H11: =IF($A11="","",IF(COUNTIFS(Register!$A$6:$A$185,$A11,Register!$D$6:$D$185,H$7)>1,"Dup.",IF($C$5="Critical assets (target)",IF(COUNTIFS(Register!$A$6:$A$185,$A11,Register!$D$6:$D$185,H$7,Register!$Q$6:$Q$185,">=0")=0,"",SUMIFS(Register!$Q$6:$Q$185,Register!$A$6:$A$185,$A11,Register!$D$6:$D$185,H$7)),IF($C$5="Released today",IF(COUNTIFS(Register!$A$6:$A$185,$A11,Register!$D$6:$D$185,H$7,Register!$T$6:$T$185,">=0")=0,"",SUMIFS(Register!$T$6:$T$185,Register!$A$6:$A$185,$A11,Register!$D$6:$D$185,H$7)),IF(COUNTIFS(Register!$A$6:$A$185,$A11,Register!$D$6:$D$185,H$7,Register!$O$6:$O$185,">=0")=0,"",SUMIFS(Register!$O$6:$O$185,Register!$A$6:$A$185,$A11,Register!$D$6:$D$185,H$7)))))) -> 2 | I11: =IF($A11="","",IF(COUNTIFS(Register!$A$6:$A$185,$A11,Register!$D$6:$D$185,I$7)>1,"Dup.",IF($C$5="Critical assets (target)",IF(COUNTIFS(Register!$A$6:$A$185,$A11,Register!$D$6:$D$185,I$7,Register!$Q$6:$Q$185,">=0")=0,"",SUMIFS(Register!$Q$6:$Q$185,Register!$A$6:$A$185,$A11,Register!$D$6:$D$185,I$7)),IF($C$5="Released today",IF(COUNTIFS(Register!$A$6:$A$185,$A11,Register!$D$6:$D$185,I$7,Register!$T$6:$T$185,">=0")=0,"",SUMIFS(Register!$T$6:$T$185,Register!$A$6:$A$185,$A11,Register!$D$6:$D$185,I$7)),IF(COUNTIFS(Register!$A$6:$A$185,$A11,Register!$D$6:$D$185,I$7,Register!$O$6:$O$185,">=0")=0,"",SUMIFS(Register!$O$6:$O$185,Register!$A$6:$A$185,$A11,Register!$D$6:$D$185,I$7)))))) -> 2 | J11: =IF($A11="","",IF(COUNTIFS(Register!$A$6:$A$185,$A11,Register!$D$6:$D$185,J$7)>1,"Dup.",IF($C$5="Critical assets (target)",IF(COUNTIFS(Register!$A$6:$A$185,$A11,Register!$D$6:$D$185,J$7,Register!$Q$6:$Q$185,">=0")=0,"",SUMIFS(Register!$Q$6:$Q$185,Register!$A$6:$A$185,$A11,Register!$D$6:$D$185,J$7)),IF($C$5="Released today",IF(COUNTIFS(Register!$A$6:$A$185,$A11,Register!$D$6:$D$185,J$7,Register!$T$6:$T$185,">=0")=0,"",SUMIFS(Register!$T$6:$T$185,Register!$A$6:$A$185,$A11,Register!$D$6:$D$185,J$7)),IF(COUNTIFS(Register!$A$6:$A$185,$A11,Register!$D$6:$D$185,J$7,Register!$O$6:$O$185,">=0")=0,"",SUMIFS(Register!$O$6:$O$185,Register!$A$6:$A$185,$A11,Register!$D$6:$D$185,J$7)))))) -> 2 | K11: =IF($A11="","",IF(COUNT(E11:J11)<6,"Incomplete",IF(AND(ISNUMBER(E11),E11<4),E$7,IF(AND(ISNUMBER(F11),F11<4),F$7,IF(AND(ISNUMBER(G11),G11<4),G$7,IF(AND(ISNUMBER(H11),H11<4),H$7,IF(AND(ISNUMBER(I11),I11<4),I$7,IF(AND(ISNUMBER(J11),J11<4),J$7,"None")))))))) -> Triage | L11: =IF($A11="","",COUNTIFS(Register!$A$6:$A$185,$A11,Register!$P$6:$P$185,"Above policy*")) -> 0 | M11: =IF($A11="","",IF(COUNTIF('Readiness gate'!$A$7:$A$36,$A11)<>1,"Incomplete",IFERROR(IF(VLOOKUP($A11,GateTab,9,FALSE())="","Incomplete",VLOOKUP($A11,GateTab,9,FALSE())),"Incomplete"))) -> Passed | N11: =IF($A11="","",SUMPRODUCT((Register!$A$6:$A$185=$A11)*(Register!$T$6:$T$185<>"")*(Register!$O$6:$O$185<>"")*(Register!$T$6:$T$185<Register!$O$6:$O$185))) -> 5
A12: =IF('Use cases'!$B$9="","",'Use cases'!$A$9) -> UC05 | B12: =IF($A12="","",'Use cases'!$B$9) -> Privileged account anomaly | C12: =IF($A12="","",'Use cases'!$C$9) -> Identity | D12: =IF($A12="","",'Use cases'!$E$9) -> Progressive | E12: =IF($A12="","",IF(COUNTIFS(Register!$A$6:$A$185,$A12,Register!$D$6:$D$185,E$7)>1,"Dup.",IF($C$5="Critical assets (target)",IF(COUNTIFS(Register!$A$6:$A$185,$A12,Register!$D$6:$D$185,E$7,Register!$Q$6:$Q$185,">=0")=0,"",SUMIFS(Register!$Q$6:$Q$185,Register!$A$6:$A$185,$A12,Register!$D$6:$D$185,E$7)),IF($C$5="Released today",IF(COUNTIFS(Register!$A$6:$A$185,$A12,Register!$D$6:$D$185,E$7,Register!$T$6:$T$185,">=0")=0,"",SUMIFS(Register!$T$6:$T$185,Register!$A$6:$A$185,$A12,Register!$D$6:$D$185,E$7)),IF(COUNTIFS(Register!$A$6:$A$185,$A12,Register!$D$6:$D$185,E$7,Register!$O$6:$O$185,">=0")=0,"",SUMIFS(Register!$O$6:$O$185,Register!$A$6:$A$185,$A12,Register!$D$6:$D$185,E$7)))))) -> 1 | F12: =IF($A12="","",IF(COUNTIFS(Register!$A$6:$A$185,$A12,Register!$D$6:$D$185,F$7)>1,"Dup.",IF($C$5="Critical assets (target)",IF(COUNTIFS(Register!$A$6:$A$185,$A12,Register!$D$6:$D$185,F$7,Register!$Q$6:$Q$185,">=0")=0,"",SUMIFS(Register!$Q$6:$Q$185,Register!$A$6:$A$185,$A12,Register!$D$6:$D$185,F$7)),IF($C$5="Released today",IF(COUNTIFS(Register!$A$6:$A$185,$A12,Register!$D$6:$D$185,F$7,Register!$T$6:$T$185,">=0")=0,"",SUMIFS(Register!$T$6:$T$185,Register!$A$6:$A$185,$A12,Register!$D$6:$D$185,F$7)),IF(COUNTIFS(Register!$A$6:$A$185,$A12,Register!$D$6:$D$185,F$7,Register!$O$6:$O$185,">=0")=0,"",SUMIFS(Register!$O$6:$O$185,Register!$A$6:$A$185,$A12,Register!$D$6:$D$185,F$7)))))) -> 1 | G12: =IF($A12="","",IF(COUNTIFS(Register!$A$6:$A$185,$A12,Register!$D$6:$D$185,G$7)>1,"Dup.",IF($C$5="Critical assets (target)",IF(COUNTIFS(Register!$A$6:$A$185,$A12,Register!$D$6:$D$185,G$7,Register!$Q$6:$Q$185,">=0")=0,"",SUMIFS(Register!$Q$6:$Q$185,Register!$A$6:$A$185,$A12,Register!$D$6:$D$185,G$7)),IF($C$5="Released today",IF(COUNTIFS(Register!$A$6:$A$185,$A12,Register!$D$6:$D$185,G$7,Register!$T$6:$T$185,">=0")=0,"",SUMIFS(Register!$T$6:$T$185,Register!$A$6:$A$185,$A12,Register!$D$6:$D$185,G$7)),IF(COUNTIFS(Register!$A$6:$A$185,$A12,Register!$D$6:$D$185,G$7,Register!$O$6:$O$185,">=0")=0,"",SUMIFS(Register!$O$6:$O$185,Register!$A$6:$A$185,$A12,Register!$D$6:$D$185,G$7)))))) -> 2 | H12: =IF($A12="","",IF(COUNTIFS(Register!$A$6:$A$185,$A12,Register!$D$6:$D$185,H$7)>1,"Dup.",IF($C$5="Critical assets (target)",IF(COUNTIFS(Register!$A$6:$A$185,$A12,Register!$D$6:$D$185,H$7,Register!$Q$6:$Q$185,">=0")=0,"",SUMIFS(Register!$Q$6:$Q$185,Register!$A$6:$A$185,$A12,Register!$D$6:$D$185,H$7)),IF($C$5="Released today",IF(COUNTIFS(Register!$A$6:$A$185,$A12,Register!$D$6:$D$185,H$7,Register!$T$6:$T$185,">=0")=0,"",SUMIFS(Register!$T$6:$T$185,Register!$A$6:$A$185,$A12,Register!$D$6:$D$185,H$7)),IF(COUNTIFS(Register!$A$6:$A$185,$A12,Register!$D$6:$D$185,H$7,Register!$O$6:$O$185,">=0")=0,"",SUMIFS(Register!$O$6:$O$185,Register!$A$6:$A$185,$A12,Register!$D$6:$D$185,H$7)))))) -> 1 | I12: =IF($A12="","",IF(COUNTIFS(Register!$A$6:$A$185,$A12,Register!$D$6:$D$185,I$7)>1,"Dup.",IF($C$5="Critical assets (target)",IF(COUNTIFS(Register!$A$6:$A$185,$A12,Register!$D$6:$D$185,I$7,Register!$Q$6:$Q$185,">=0")=0,"",SUMIFS(Register!$Q$6:$Q$185,Register!$A$6:$A$185,$A12,Register!$D$6:$D$185,I$7)),IF($C$5="Released today",IF(COUNTIFS(Register!$A$6:$A$185,$A12,Register!$D$6:$D$185,I$7,Register!$T$6:$T$185,">=0")=0,"",SUMIFS(Register!$T$6:$T$185,Register!$A$6:$A$185,$A12,Register!$D$6:$D$185,I$7)),IF(COUNTIFS(Register!$A$6:$A$185,$A12,Register!$D$6:$D$185,I$7,Register!$O$6:$O$185,">=0")=0,"",SUMIFS(Register!$O$6:$O$185,Register!$A$6:$A$185,$A12,Register!$D$6:$D$185,I$7)))))) -> 1 | J12: =IF($A12="","",IF(COUNTIFS(Register!$A$6:$A$185,$A12,Register!$D$6:$D$185,J$7)>1,"Dup.",IF($C$5="Critical assets (target)",IF(COUNTIFS(Register!$A$6:$A$185,$A12,Register!$D$6:$D$185,J$7,Register!$Q$6:$Q$185,">=0")=0,"",SUMIFS(Register!$Q$6:$Q$185,Register!$A$6:$A$185,$A12,Register!$D$6:$D$185,J$7)),IF($C$5="Released today",IF(COUNTIFS(Register!$A$6:$A$185,$A12,Register!$D$6:$D$185,J$7,Register!$T$6:$T$185,">=0")=0,"",SUMIFS(Register!$T$6:$T$185,Register!$A$6:$A$185,$A12,Register!$D$6:$D$185,J$7)),IF(COUNTIFS(Register!$A$6:$A$185,$A12,Register!$D$6:$D$185,J$7,Register!$O$6:$O$185,">=0")=0,"",SUMIFS(Register!$O$6:$O$185,Register!$A$6:$A$185,$A12,Register!$D$6:$D$185,J$7)))))) -> 1 | K12: =IF($A12="","",IF(COUNT(E12:J12)<6,"Incomplete",IF(AND(ISNUMBER(E12),E12<4),E$7,IF(AND(ISNUMBER(F12),F12<4),F$7,IF(AND(ISNUMBER(G12),G12<4),G$7,IF(AND(ISNUMBER(H12),H12<4),H$7,IF(AND(ISNUMBER(I12),I12<4),I$7,IF(AND(ISNUMBER(J12),J12<4),J$7,"None")))))))) -> Enrich | L12: =IF($A12="","",COUNTIFS(Register!$A$6:$A$185,$A12,Register!$P$6:$P$185,"Above policy*")) -> 0 | M12: =IF($A12="","",IF(COUNTIF('Readiness gate'!$A$7:$A$36,$A12)<>1,"Incomplete",IFERROR(IF(VLOOKUP($A12,GateTab,9,FALSE())="","Incomplete",VLOOKUP($A12,GateTab,9,FALSE())),"Incomplete"))) -> Not passed | N12: =IF($A12="","",SUMPRODUCT((Register!$A$6:$A$185=$A12)*(Register!$T$6:$T$185<>"")*(Register!$O$6:$O$185<>"")*(Register!$T$6:$T$185<Register!$O$6:$O$185))) -> 6
A13: =IF('Use cases'!$B$10="","",'Use cases'!$A$10) -> UC06 | B13: =IF($A13="","",'Use cases'!$B$10) -> Token theft and replay | C13: =IF($A13="","",'Use cases'!$C$10) -> Identity | D13: =IF($A13="","",'Use cases'!$E$10) -> Progressive | E13: =IF($A13="","",IF(COUNTIFS(Register!$A$6:$A$185,$A13,Register!$D$6:$D$185,E$7)>1,"Dup.",IF($C$5="Critical assets (target)",IF(COUNTIFS(Register!$A$6:$A$185,$A13,Register!$D$6:$D$185,E$7,Register!$Q$6:$Q$185,">=0")=0,"",SUMIFS(Register!$Q$6:$Q$185,Register!$A$6:$A$185,$A13,Register!$D$6:$D$185,E$7)),IF($C$5="Released today",IF(COUNTIFS(Register!$A$6:$A$185,$A13,Register!$D$6:$D$185,E$7,Register!$T$6:$T$185,">=0")=0,"",SUMIFS(Register!$T$6:$T$185,Register!$A$6:$A$185,$A13,Register!$D$6:$D$185,E$7)),IF(COUNTIFS(Register!$A$6:$A$185,$A13,Register!$D$6:$D$185,E$7,Register!$O$6:$O$185,">=0")=0,"",SUMIFS(Register!$O$6:$O$185,Register!$A$6:$A$185,$A13,Register!$D$6:$D$185,E$7)))))) -> 4 | F13: =IF($A13="","",IF(COUNTIFS(Register!$A$6:$A$185,$A13,Register!$D$6:$D$185,F$7)>1,"Dup.",IF($C$5="Critical assets (target)",IF(COUNTIFS(Register!$A$6:$A$185,$A13,Register!$D$6:$D$185,F$7,Register!$Q$6:$Q$185,">=0")=0,"",SUMIFS(Register!$Q$6:$Q$185,Register!$A$6:$A$185,$A13,Register!$D$6:$D$185,F$7)),IF($C$5="Released today",IF(COUNTIFS(Register!$A$6:$A$185,$A13,Register!$D$6:$D$185,F$7,Register!$T$6:$T$185,">=0")=0,"",SUMIFS(Register!$T$6:$T$185,Register!$A$6:$A$185,$A13,Register!$D$6:$D$185,F$7)),IF(COUNTIFS(Register!$A$6:$A$185,$A13,Register!$D$6:$D$185,F$7,Register!$O$6:$O$185,">=0")=0,"",SUMIFS(Register!$O$6:$O$185,Register!$A$6:$A$185,$A13,Register!$D$6:$D$185,F$7)))))) -> 2 | G13: =IF($A13="","",IF(COUNTIFS(Register!$A$6:$A$185,$A13,Register!$D$6:$D$185,G$7)>1,"Dup.",IF($C$5="Critical assets (target)",IF(COUNTIFS(Register!$A$6:$A$185,$A13,Register!$D$6:$D$185,G$7,Register!$Q$6:$Q$185,">=0")=0,"",SUMIFS(Register!$Q$6:$Q$185,Register!$A$6:$A$185,$A13,Register!$D$6:$D$185,G$7)),IF($C$5="Released today",IF(COUNTIFS(Register!$A$6:$A$185,$A13,Register!$D$6:$D$185,G$7,Register!$T$6:$T$185,">=0")=0,"",SUMIFS(Register!$T$6:$T$185,Register!$A$6:$A$185,$A13,Register!$D$6:$D$185,G$7)),IF(COUNTIFS(Register!$A$6:$A$185,$A13,Register!$D$6:$D$185,G$7,Register!$O$6:$O$185,">=0")=0,"",SUMIFS(Register!$O$6:$O$185,Register!$A$6:$A$185,$A13,Register!$D$6:$D$185,G$7)))))) -> 3 | H13: =IF($A13="","",IF(COUNTIFS(Register!$A$6:$A$185,$A13,Register!$D$6:$D$185,H$7)>1,"Dup.",IF($C$5="Critical assets (target)",IF(COUNTIFS(Register!$A$6:$A$185,$A13,Register!$D$6:$D$185,H$7,Register!$Q$6:$Q$185,">=0")=0,"",SUMIFS(Register!$Q$6:$Q$185,Register!$A$6:$A$185,$A13,Register!$D$6:$D$185,H$7)),IF($C$5="Released today",IF(COUNTIFS(Register!$A$6:$A$185,$A13,Register!$D$6:$D$185,H$7,Register!$T$6:$T$185,">=0")=0,"",SUMIFS(Register!$T$6:$T$185,Register!$A$6:$A$185,$A13,Register!$D$6:$D$185,H$7)),IF(COUNTIFS(Register!$A$6:$A$185,$A13,Register!$D$6:$D$185,H$7,Register!$O$6:$O$185,">=0")=0,"",SUMIFS(Register!$O$6:$O$185,Register!$A$6:$A$185,$A13,Register!$D$6:$D$185,H$7)))))) -> 2 | I13: =IF($A13="","",IF(COUNTIFS(Register!$A$6:$A$185,$A13,Register!$D$6:$D$185,I$7)>1,"Dup.",IF($C$5="Critical assets (target)",IF(COUNTIFS(Register!$A$6:$A$185,$A13,Register!$D$6:$D$185,I$7,Register!$Q$6:$Q$185,">=0")=0,"",SUMIFS(Register!$Q$6:$Q$185,Register!$A$6:$A$185,$A13,Register!$D$6:$D$185,I$7)),IF($C$5="Released today",IF(COUNTIFS(Register!$A$6:$A$185,$A13,Register!$D$6:$D$185,I$7,Register!$T$6:$T$185,">=0")=0,"",SUMIFS(Register!$T$6:$T$185,Register!$A$6:$A$185,$A13,Register!$D$6:$D$185,I$7)),IF(COUNTIFS(Register!$A$6:$A$185,$A13,Register!$D$6:$D$185,I$7,Register!$O$6:$O$185,">=0")=0,"",SUMIFS(Register!$O$6:$O$185,Register!$A$6:$A$185,$A13,Register!$D$6:$D$185,I$7)))))) -> 2 | J13: =IF($A13="","",IF(COUNTIFS(Register!$A$6:$A$185,$A13,Register!$D$6:$D$185,J$7)>1,"Dup.",IF($C$5="Critical assets (target)",IF(COUNTIFS(Register!$A$6:$A$185,$A13,Register!$D$6:$D$185,J$7,Register!$Q$6:$Q$185,">=0")=0,"",SUMIFS(Register!$Q$6:$Q$185,Register!$A$6:$A$185,$A13,Register!$D$6:$D$185,J$7)),IF($C$5="Released today",IF(COUNTIFS(Register!$A$6:$A$185,$A13,Register!$D$6:$D$185,J$7,Register!$T$6:$T$185,">=0")=0,"",SUMIFS(Register!$T$6:$T$185,Register!$A$6:$A$185,$A13,Register!$D$6:$D$185,J$7)),IF(COUNTIFS(Register!$A$6:$A$185,$A13,Register!$D$6:$D$185,J$7,Register!$O$6:$O$185,">=0")=0,"",SUMIFS(Register!$O$6:$O$185,Register!$A$6:$A$185,$A13,Register!$D$6:$D$185,J$7)))))) -> 2 | K13: =IF($A13="","",IF(COUNT(E13:J13)<6,"Incomplete",IF(AND(ISNUMBER(E13),E13<4),E$7,IF(AND(ISNUMBER(F13),F13<4),F$7,IF(AND(ISNUMBER(G13),G13<4),G$7,IF(AND(ISNUMBER(H13),H13<4),H$7,IF(AND(ISNUMBER(I13),I13<4),I$7,IF(AND(ISNUMBER(J13),J13<4),J$7,"None")))))))) -> Triage | L13: =IF($A13="","",COUNTIFS(Register!$A$6:$A$185,$A13,Register!$P$6:$P$185,"Above policy*")) -> 0 | M13: =IF($A13="","",IF(COUNTIF('Readiness gate'!$A$7:$A$36,$A13)<>1,"Incomplete",IFERROR(IF(VLOOKUP($A13,GateTab,9,FALSE())="","Incomplete",VLOOKUP($A13,GateTab,9,FALSE())),"Incomplete"))) -> Passed | N13: =IF($A13="","",SUMPRODUCT((Register!$A$6:$A$185=$A13)*(Register!$T$6:$T$185<>"")*(Register!$O$6:$O$185<>"")*(Register!$T$6:$T$185<Register!$O$6:$O$185))) -> 5
A14: =IF('Use cases'!$B$11="","",'Use cases'!$A$11) -> UC07 | B14: =IF($A14="","",'Use cases'!$B$11) -> Endpoint malware containment | C14: =IF($A14="","",'Use cases'!$C$11) -> Endpoint | D14: =IF($A14="","",'Use cases'!$E$11) -> Progressive | E14: =IF($A14="","",IF(COUNTIFS(Register!$A$6:$A$185,$A14,Register!$D$6:$D$185,E$7)>1,"Dup.",IF($C$5="Critical assets (target)",IF(COUNTIFS(Register!$A$6:$A$185,$A14,Register!$D$6:$D$185,E$7,Register!$Q$6:$Q$185,">=0")=0,"",SUMIFS(Register!$Q$6:$Q$185,Register!$A$6:$A$185,$A14,Register!$D$6:$D$185,E$7)),IF($C$5="Released today",IF(COUNTIFS(Register!$A$6:$A$185,$A14,Register!$D$6:$D$185,E$7,Register!$T$6:$T$185,">=0")=0,"",SUMIFS(Register!$T$6:$T$185,Register!$A$6:$A$185,$A14,Register!$D$6:$D$185,E$7)),IF(COUNTIFS(Register!$A$6:$A$185,$A14,Register!$D$6:$D$185,E$7,Register!$O$6:$O$185,">=0")=0,"",SUMIFS(Register!$O$6:$O$185,Register!$A$6:$A$185,$A14,Register!$D$6:$D$185,E$7)))))) -> 4 | F14: =IF($A14="","",IF(COUNTIFS(Register!$A$6:$A$185,$A14,Register!$D$6:$D$185,F$7)>1,"Dup.",IF($C$5="Critical assets (target)",IF(COUNTIFS(Register!$A$6:$A$185,$A14,Register!$D$6:$D$185,F$7,Register!$Q$6:$Q$185,">=0")=0,"",SUMIFS(Register!$Q$6:$Q$185,Register!$A$6:$A$185,$A14,Register!$D$6:$D$185,F$7)),IF($C$5="Released today",IF(COUNTIFS(Register!$A$6:$A$185,$A14,Register!$D$6:$D$185,F$7,Register!$T$6:$T$185,">=0")=0,"",SUMIFS(Register!$T$6:$T$185,Register!$A$6:$A$185,$A14,Register!$D$6:$D$185,F$7)),IF(COUNTIFS(Register!$A$6:$A$185,$A14,Register!$D$6:$D$185,F$7,Register!$O$6:$O$185,">=0")=0,"",SUMIFS(Register!$O$6:$O$185,Register!$A$6:$A$185,$A14,Register!$D$6:$D$185,F$7)))))) -> 2 | G14: =IF($A14="","",IF(COUNTIFS(Register!$A$6:$A$185,$A14,Register!$D$6:$D$185,G$7)>1,"Dup.",IF($C$5="Critical assets (target)",IF(COUNTIFS(Register!$A$6:$A$185,$A14,Register!$D$6:$D$185,G$7,Register!$Q$6:$Q$185,">=0")=0,"",SUMIFS(Register!$Q$6:$Q$185,Register!$A$6:$A$185,$A14,Register!$D$6:$D$185,G$7)),IF($C$5="Released today",IF(COUNTIFS(Register!$A$6:$A$185,$A14,Register!$D$6:$D$185,G$7,Register!$T$6:$T$185,">=0")=0,"",SUMIFS(Register!$T$6:$T$185,Register!$A$6:$A$185,$A14,Register!$D$6:$D$185,G$7)),IF(COUNTIFS(Register!$A$6:$A$185,$A14,Register!$D$6:$D$185,G$7,Register!$O$6:$O$185,">=0")=0,"",SUMIFS(Register!$O$6:$O$185,Register!$A$6:$A$185,$A14,Register!$D$6:$D$185,G$7)))))) -> 4 | H14: =IF($A14="","",IF(COUNTIFS(Register!$A$6:$A$185,$A14,Register!$D$6:$D$185,H$7)>1,"Dup.",IF($C$5="Critical assets (target)",IF(COUNTIFS(Register!$A$6:$A$185,$A14,Register!$D$6:$D$185,H$7,Register!$Q$6:$Q$185,">=0")=0,"",SUMIFS(Register!$Q$6:$Q$185,Register!$A$6:$A$185,$A14,Register!$D$6:$D$185,H$7)),IF($C$5="Released today",IF(COUNTIFS(Register!$A$6:$A$185,$A14,Register!$D$6:$D$185,H$7,Register!$T$6:$T$185,">=0")=0,"",SUMIFS(Register!$T$6:$T$185,Register!$A$6:$A$185,$A14,Register!$D$6:$D$185,H$7)),IF(COUNTIFS(Register!$A$6:$A$185,$A14,Register!$D$6:$D$185,H$7,Register!$O$6:$O$185,">=0")=0,"",SUMIFS(Register!$O$6:$O$185,Register!$A$6:$A$185,$A14,Register!$D$6:$D$185,H$7)))))) -> 2 | I14: =IF($A14="","",IF(COUNTIFS(Register!$A$6:$A$185,$A14,Register!$D$6:$D$185,I$7)>1,"Dup.",IF($C$5="Critical assets (target)",IF(COUNTIFS(Register!$A$6:$A$185,$A14,Register!$D$6:$D$185,I$7,Register!$Q$6:$Q$185,">=0")=0,"",SUMIFS(Register!$Q$6:$Q$185,Register!$A$6:$A$185,$A14,Register!$D$6:$D$185,I$7)),IF($C$5="Released today",IF(COUNTIFS(Register!$A$6:$A$185,$A14,Register!$D$6:$D$185,I$7,Register!$T$6:$T$185,">=0")=0,"",SUMIFS(Register!$T$6:$T$185,Register!$A$6:$A$185,$A14,Register!$D$6:$D$185,I$7)),IF(COUNTIFS(Register!$A$6:$A$185,$A14,Register!$D$6:$D$185,I$7,Register!$O$6:$O$185,">=0")=0,"",SUMIFS(Register!$O$6:$O$185,Register!$A$6:$A$185,$A14,Register!$D$6:$D$185,I$7)))))) -> 2 | J14: =IF($A14="","",IF(COUNTIFS(Register!$A$6:$A$185,$A14,Register!$D$6:$D$185,J$7)>1,"Dup.",IF($C$5="Critical assets (target)",IF(COUNTIFS(Register!$A$6:$A$185,$A14,Register!$D$6:$D$185,J$7,Register!$Q$6:$Q$185,">=0")=0,"",SUMIFS(Register!$Q$6:$Q$185,Register!$A$6:$A$185,$A14,Register!$D$6:$D$185,J$7)),IF($C$5="Released today",IF(COUNTIFS(Register!$A$6:$A$185,$A14,Register!$D$6:$D$185,J$7,Register!$T$6:$T$185,">=0")=0,"",SUMIFS(Register!$T$6:$T$185,Register!$A$6:$A$185,$A14,Register!$D$6:$D$185,J$7)),IF(COUNTIFS(Register!$A$6:$A$185,$A14,Register!$D$6:$D$185,J$7,Register!$O$6:$O$185,">=0")=0,"",SUMIFS(Register!$O$6:$O$185,Register!$A$6:$A$185,$A14,Register!$D$6:$D$185,J$7)))))) -> 2 | K14: =IF($A14="","",IF(COUNT(E14:J14)<6,"Incomplete",IF(AND(ISNUMBER(E14),E14<4),E$7,IF(AND(ISNUMBER(F14),F14<4),F$7,IF(AND(ISNUMBER(G14),G14<4),G$7,IF(AND(ISNUMBER(H14),H14<4),H$7,IF(AND(ISNUMBER(I14),I14<4),I$7,IF(AND(ISNUMBER(J14),J14<4),J$7,"None")))))))) -> Triage | L14: =IF($A14="","",COUNTIFS(Register!$A$6:$A$185,$A14,Register!$P$6:$P$185,"Above policy*")) -> 0 | M14: =IF($A14="","",IF(COUNTIF('Readiness gate'!$A$7:$A$36,$A14)<>1,"Incomplete",IFERROR(IF(VLOOKUP($A14,GateTab,9,FALSE())="","Incomplete",VLOOKUP($A14,GateTab,9,FALSE())),"Incomplete"))) -> Passed | N14: =IF($A14="","",SUMPRODUCT((Register!$A$6:$A$185=$A14)*(Register!$T$6:$T$185<>"")*(Register!$O$6:$O$185<>"")*(Register!$T$6:$T$185<Register!$O$6:$O$185))) -> 4
A15: =IF('Use cases'!$B$12="","",'Use cases'!$A$12) -> UC08 | B15: =IF($A15="","",'Use cases'!$B$12) -> Early ransomware indicators | C15: =IF($A15="","",'Use cases'!$C$12) -> Endpoint | D15: =IF($A15="","",'Use cases'!$E$12) -> Progressive | E15: =IF($A15="","",IF(COUNTIFS(Register!$A$6:$A$185,$A15,Register!$D$6:$D$185,E$7)>1,"Dup.",IF($C$5="Critical assets (target)",IF(COUNTIFS(Register!$A$6:$A$185,$A15,Register!$D$6:$D$185,E$7,Register!$Q$6:$Q$185,">=0")=0,"",SUMIFS(Register!$Q$6:$Q$185,Register!$A$6:$A$185,$A15,Register!$D$6:$D$185,E$7)),IF($C$5="Released today",IF(COUNTIFS(Register!$A$6:$A$185,$A15,Register!$D$6:$D$185,E$7,Register!$T$6:$T$185,">=0")=0,"",SUMIFS(Register!$T$6:$T$185,Register!$A$6:$A$185,$A15,Register!$D$6:$D$185,E$7)),IF(COUNTIFS(Register!$A$6:$A$185,$A15,Register!$D$6:$D$185,E$7,Register!$O$6:$O$185,">=0")=0,"",SUMIFS(Register!$O$6:$O$185,Register!$A$6:$A$185,$A15,Register!$D$6:$D$185,E$7)))))) -> 1 | F15: =IF($A15="","",IF(COUNTIFS(Register!$A$6:$A$185,$A15,Register!$D$6:$D$185,F$7)>1,"Dup.",IF($C$5="Critical assets (target)",IF(COUNTIFS(Register!$A$6:$A$185,$A15,Register!$D$6:$D$185,F$7,Register!$Q$6:$Q$185,">=0")=0,"",SUMIFS(Register!$Q$6:$Q$185,Register!$A$6:$A$185,$A15,Register!$D$6:$D$185,F$7)),IF($C$5="Released today",IF(COUNTIFS(Register!$A$6:$A$185,$A15,Register!$D$6:$D$185,F$7,Register!$T$6:$T$185,">=0")=0,"",SUMIFS(Register!$T$6:$T$185,Register!$A$6:$A$185,$A15,Register!$D$6:$D$185,F$7)),IF(COUNTIFS(Register!$A$6:$A$185,$A15,Register!$D$6:$D$185,F$7,Register!$O$6:$O$185,">=0")=0,"",SUMIFS(Register!$O$6:$O$185,Register!$A$6:$A$185,$A15,Register!$D$6:$D$185,F$7)))))) -> 1 | G15: =IF($A15="","",IF(COUNTIFS(Register!$A$6:$A$185,$A15,Register!$D$6:$D$185,G$7)>1,"Dup.",IF($C$5="Critical assets (target)",IF(COUNTIFS(Register!$A$6:$A$185,$A15,Register!$D$6:$D$185,G$7,Register!$Q$6:$Q$185,">=0")=0,"",SUMIFS(Register!$Q$6:$Q$185,Register!$A$6:$A$185,$A15,Register!$D$6:$D$185,G$7)),IF($C$5="Released today",IF(COUNTIFS(Register!$A$6:$A$185,$A15,Register!$D$6:$D$185,G$7,Register!$T$6:$T$185,">=0")=0,"",SUMIFS(Register!$T$6:$T$185,Register!$A$6:$A$185,$A15,Register!$D$6:$D$185,G$7)),IF(COUNTIFS(Register!$A$6:$A$185,$A15,Register!$D$6:$D$185,G$7,Register!$O$6:$O$185,">=0")=0,"",SUMIFS(Register!$O$6:$O$185,Register!$A$6:$A$185,$A15,Register!$D$6:$D$185,G$7)))))) -> 2 | H15: =IF($A15="","",IF(COUNTIFS(Register!$A$6:$A$185,$A15,Register!$D$6:$D$185,H$7)>1,"Dup.",IF($C$5="Critical assets (target)",IF(COUNTIFS(Register!$A$6:$A$185,$A15,Register!$D$6:$D$185,H$7,Register!$Q$6:$Q$185,">=0")=0,"",SUMIFS(Register!$Q$6:$Q$185,Register!$A$6:$A$185,$A15,Register!$D$6:$D$185,H$7)),IF($C$5="Released today",IF(COUNTIFS(Register!$A$6:$A$185,$A15,Register!$D$6:$D$185,H$7,Register!$T$6:$T$185,">=0")=0,"",SUMIFS(Register!$T$6:$T$185,Register!$A$6:$A$185,$A15,Register!$D$6:$D$185,H$7)),IF(COUNTIFS(Register!$A$6:$A$185,$A15,Register!$D$6:$D$185,H$7,Register!$O$6:$O$185,">=0")=0,"",SUMIFS(Register!$O$6:$O$185,Register!$A$6:$A$185,$A15,Register!$D$6:$D$185,H$7)))))) -> 1 | I15: =IF($A15="","",IF(COUNTIFS(Register!$A$6:$A$185,$A15,Register!$D$6:$D$185,I$7)>1,"Dup.",IF($C$5="Critical assets (target)",IF(COUNTIFS(Register!$A$6:$A$185,$A15,Register!$D$6:$D$185,I$7,Register!$Q$6:$Q$185,">=0")=0,"",SUMIFS(Register!$Q$6:$Q$185,Register!$A$6:$A$185,$A15,Register!$D$6:$D$185,I$7)),IF($C$5="Released today",IF(COUNTIFS(Register!$A$6:$A$185,$A15,Register!$D$6:$D$185,I$7,Register!$T$6:$T$185,">=0")=0,"",SUMIFS(Register!$T$6:$T$185,Register!$A$6:$A$185,$A15,Register!$D$6:$D$185,I$7)),IF(COUNTIFS(Register!$A$6:$A$185,$A15,Register!$D$6:$D$185,I$7,Register!$O$6:$O$185,">=0")=0,"",SUMIFS(Register!$O$6:$O$185,Register!$A$6:$A$185,$A15,Register!$D$6:$D$185,I$7)))))) -> 1 | J15: =IF($A15="","",IF(COUNTIFS(Register!$A$6:$A$185,$A15,Register!$D$6:$D$185,J$7)>1,"Dup.",IF($C$5="Critical assets (target)",IF(COUNTIFS(Register!$A$6:$A$185,$A15,Register!$D$6:$D$185,J$7,Register!$Q$6:$Q$185,">=0")=0,"",SUMIFS(Register!$Q$6:$Q$185,Register!$A$6:$A$185,$A15,Register!$D$6:$D$185,J$7)),IF($C$5="Released today",IF(COUNTIFS(Register!$A$6:$A$185,$A15,Register!$D$6:$D$185,J$7,Register!$T$6:$T$185,">=0")=0,"",SUMIFS(Register!$T$6:$T$185,Register!$A$6:$A$185,$A15,Register!$D$6:$D$185,J$7)),IF(COUNTIFS(Register!$A$6:$A$185,$A15,Register!$D$6:$D$185,J$7,Register!$O$6:$O$185,">=0")=0,"",SUMIFS(Register!$O$6:$O$185,Register!$A$6:$A$185,$A15,Register!$D$6:$D$185,J$7)))))) -> 1 | K15: =IF($A15="","",IF(COUNT(E15:J15)<6,"Incomplete",IF(AND(ISNUMBER(E15),E15<4),E$7,IF(AND(ISNUMBER(F15),F15<4),F$7,IF(AND(ISNUMBER(G15),G15<4),G$7,IF(AND(ISNUMBER(H15),H15<4),H$7,IF(AND(ISNUMBER(I15),I15<4),I$7,IF(AND(ISNUMBER(J15),J15<4),J$7,"None")))))))) -> Enrich | L15: =IF($A15="","",COUNTIFS(Register!$A$6:$A$185,$A15,Register!$P$6:$P$185,"Above policy*")) -> 0 | M15: =IF($A15="","",IF(COUNTIF('Readiness gate'!$A$7:$A$36,$A15)<>1,"Incomplete",IFERROR(IF(VLOOKUP($A15,GateTab,9,FALSE())="","Incomplete",VLOOKUP($A15,GateTab,9,FALSE())),"Incomplete"))) -> Not passed | N15: =IF($A15="","",SUMPRODUCT((Register!$A$6:$A$185=$A15)*(Register!$T$6:$T$185<>"")*(Register!$O$6:$O$185<>"")*(Register!$T$6:$T$185<Register!$O$6:$O$185))) -> 6
A16: =IF('Use cases'!$B$13="","",'Use cases'!$A$13) -> UC09 | B16: =IF($A16="","",'Use cases'!$B$13) -> C2 beaconing | C16: =IF($A16="","",'Use cases'!$C$13) -> Network | D16: =IF($A16="","",'Use cases'!$E$13) -> Progressive | E16: =IF($A16="","",IF(COUNTIFS(Register!$A$6:$A$185,$A16,Register!$D$6:$D$185,E$7)>1,"Dup.",IF($C$5="Critical assets (target)",IF(COUNTIFS(Register!$A$6:$A$185,$A16,Register!$D$6:$D$185,E$7,Register!$Q$6:$Q$185,">=0")=0,"",SUMIFS(Register!$Q$6:$Q$185,Register!$A$6:$A$185,$A16,Register!$D$6:$D$185,E$7)),IF($C$5="Released today",IF(COUNTIFS(Register!$A$6:$A$185,$A16,Register!$D$6:$D$185,E$7,Register!$T$6:$T$185,">=0")=0,"",SUMIFS(Register!$T$6:$T$185,Register!$A$6:$A$185,$A16,Register!$D$6:$D$185,E$7)),IF(COUNTIFS(Register!$A$6:$A$185,$A16,Register!$D$6:$D$185,E$7,Register!$O$6:$O$185,">=0")=0,"",SUMIFS(Register!$O$6:$O$185,Register!$A$6:$A$185,$A16,Register!$D$6:$D$185,E$7)))))) -> 4 | F16: =IF($A16="","",IF(COUNTIFS(Register!$A$6:$A$185,$A16,Register!$D$6:$D$185,F$7)>1,"Dup.",IF($C$5="Critical assets (target)",IF(COUNTIFS(Register!$A$6:$A$185,$A16,Register!$D$6:$D$185,F$7,Register!$Q$6:$Q$185,">=0")=0,"",SUMIFS(Register!$Q$6:$Q$185,Register!$A$6:$A$185,$A16,Register!$D$6:$D$185,F$7)),IF($C$5="Released today",IF(COUNTIFS(Register!$A$6:$A$185,$A16,Register!$D$6:$D$185,F$7,Register!$T$6:$T$185,">=0")=0,"",SUMIFS(Register!$T$6:$T$185,Register!$A$6:$A$185,$A16,Register!$D$6:$D$185,F$7)),IF(COUNTIFS(Register!$A$6:$A$185,$A16,Register!$D$6:$D$185,F$7,Register!$O$6:$O$185,">=0")=0,"",SUMIFS(Register!$O$6:$O$185,Register!$A$6:$A$185,$A16,Register!$D$6:$D$185,F$7)))))) -> 2 | G16: =IF($A16="","",IF(COUNTIFS(Register!$A$6:$A$185,$A16,Register!$D$6:$D$185,G$7)>1,"Dup.",IF($C$5="Critical assets (target)",IF(COUNTIFS(Register!$A$6:$A$185,$A16,Register!$D$6:$D$185,G$7,Register!$Q$6:$Q$185,">=0")=0,"",SUMIFS(Register!$Q$6:$Q$185,Register!$A$6:$A$185,$A16,Register!$D$6:$D$185,G$7)),IF($C$5="Released today",IF(COUNTIFS(Register!$A$6:$A$185,$A16,Register!$D$6:$D$185,G$7,Register!$T$6:$T$185,">=0")=0,"",SUMIFS(Register!$T$6:$T$185,Register!$A$6:$A$185,$A16,Register!$D$6:$D$185,G$7)),IF(COUNTIFS(Register!$A$6:$A$185,$A16,Register!$D$6:$D$185,G$7,Register!$O$6:$O$185,">=0")=0,"",SUMIFS(Register!$O$6:$O$185,Register!$A$6:$A$185,$A16,Register!$D$6:$D$185,G$7)))))) -> 4 | H16: =IF($A16="","",IF(COUNTIFS(Register!$A$6:$A$185,$A16,Register!$D$6:$D$185,H$7)>1,"Dup.",IF($C$5="Critical assets (target)",IF(COUNTIFS(Register!$A$6:$A$185,$A16,Register!$D$6:$D$185,H$7,Register!$Q$6:$Q$185,">=0")=0,"",SUMIFS(Register!$Q$6:$Q$185,Register!$A$6:$A$185,$A16,Register!$D$6:$D$185,H$7)),IF($C$5="Released today",IF(COUNTIFS(Register!$A$6:$A$185,$A16,Register!$D$6:$D$185,H$7,Register!$T$6:$T$185,">=0")=0,"",SUMIFS(Register!$T$6:$T$185,Register!$A$6:$A$185,$A16,Register!$D$6:$D$185,H$7)),IF(COUNTIFS(Register!$A$6:$A$185,$A16,Register!$D$6:$D$185,H$7,Register!$O$6:$O$185,">=0")=0,"",SUMIFS(Register!$O$6:$O$185,Register!$A$6:$A$185,$A16,Register!$D$6:$D$185,H$7)))))) -> 2 | I16: =IF($A16="","",IF(COUNTIFS(Register!$A$6:$A$185,$A16,Register!$D$6:$D$185,I$7)>1,"Dup.",IF($C$5="Critical assets (target)",IF(COUNTIFS(Register!$A$6:$A$185,$A16,Register!$D$6:$D$185,I$7,Register!$Q$6:$Q$185,">=0")=0,"",SUMIFS(Register!$Q$6:$Q$185,Register!$A$6:$A$185,$A16,Register!$D$6:$D$185,I$7)),IF($C$5="Released today",IF(COUNTIFS(Register!$A$6:$A$185,$A16,Register!$D$6:$D$185,I$7,Register!$T$6:$T$185,">=0")=0,"",SUMIFS(Register!$T$6:$T$185,Register!$A$6:$A$185,$A16,Register!$D$6:$D$185,I$7)),IF(COUNTIFS(Register!$A$6:$A$185,$A16,Register!$D$6:$D$185,I$7,Register!$O$6:$O$185,">=0")=0,"",SUMIFS(Register!$O$6:$O$185,Register!$A$6:$A$185,$A16,Register!$D$6:$D$185,I$7)))))) -> 2 | J16: =IF($A16="","",IF(COUNTIFS(Register!$A$6:$A$185,$A16,Register!$D$6:$D$185,J$7)>1,"Dup.",IF($C$5="Critical assets (target)",IF(COUNTIFS(Register!$A$6:$A$185,$A16,Register!$D$6:$D$185,J$7,Register!$Q$6:$Q$185,">=0")=0,"",SUMIFS(Register!$Q$6:$Q$185,Register!$A$6:$A$185,$A16,Register!$D$6:$D$185,J$7)),IF($C$5="Released today",IF(COUNTIFS(Register!$A$6:$A$185,$A16,Register!$D$6:$D$185,J$7,Register!$T$6:$T$185,">=0")=0,"",SUMIFS(Register!$T$6:$T$185,Register!$A$6:$A$185,$A16,Register!$D$6:$D$185,J$7)),IF(COUNTIFS(Register!$A$6:$A$185,$A16,Register!$D$6:$D$185,J$7,Register!$O$6:$O$185,">=0")=0,"",SUMIFS(Register!$O$6:$O$185,Register!$A$6:$A$185,$A16,Register!$D$6:$D$185,J$7)))))) -> 2 | K16: =IF($A16="","",IF(COUNT(E16:J16)<6,"Incomplete",IF(AND(ISNUMBER(E16),E16<4),E$7,IF(AND(ISNUMBER(F16),F16<4),F$7,IF(AND(ISNUMBER(G16),G16<4),G$7,IF(AND(ISNUMBER(H16),H16<4),H$7,IF(AND(ISNUMBER(I16),I16<4),I$7,IF(AND(ISNUMBER(J16),J16<4),J$7,"None")))))))) -> Triage | L16: =IF($A16="","",COUNTIFS(Register!$A$6:$A$185,$A16,Register!$P$6:$P$185,"Above policy*")) -> 0 | M16: =IF($A16="","",IF(COUNTIF('Readiness gate'!$A$7:$A$36,$A16)<>1,"Incomplete",IFERROR(IF(VLOOKUP($A16,GateTab,9,FALSE())="","Incomplete",VLOOKUP($A16,GateTab,9,FALSE())),"Incomplete"))) -> Passed | N16: =IF($A16="","",SUMPRODUCT((Register!$A$6:$A$185=$A16)*(Register!$T$6:$T$185<>"")*(Register!$O$6:$O$185<>"")*(Register!$T$6:$T$185<Register!$O$6:$O$185))) -> 4
A17: =IF('Use cases'!$B$14="","",'Use cases'!$A$14) -> UC10 | B17: =IF($A17="","",'Use cases'!$B$14) -> Suspicious PowerShell or LOLBin activity | C17: =IF($A17="","",'Use cases'!$C$14) -> Endpoint | D17: =IF($A17="","",'Use cases'!$E$14) -> Progressive | E17: =IF($A17="","",IF(COUNTIFS(Register!$A$6:$A$185,$A17,Register!$D$6:$D$185,E$7)>1,"Dup.",IF($C$5="Critical assets (target)",IF(COUNTIFS(Register!$A$6:$A$185,$A17,Register!$D$6:$D$185,E$7,Register!$Q$6:$Q$185,">=0")=0,"",SUMIFS(Register!$Q$6:$Q$185,Register!$A$6:$A$185,$A17,Register!$D$6:$D$185,E$7)),IF($C$5="Released today",IF(COUNTIFS(Register!$A$6:$A$185,$A17,Register!$D$6:$D$185,E$7,Register!$T$6:$T$185,">=0")=0,"",SUMIFS(Register!$T$6:$T$185,Register!$A$6:$A$185,$A17,Register!$D$6:$D$185,E$7)),IF(COUNTIFS(Register!$A$6:$A$185,$A17,Register!$D$6:$D$185,E$7,Register!$O$6:$O$185,">=0")=0,"",SUMIFS(Register!$O$6:$O$185,Register!$A$6:$A$185,$A17,Register!$D$6:$D$185,E$7)))))) -> 1 | F17: =IF($A17="","",IF(COUNTIFS(Register!$A$6:$A$185,$A17,Register!$D$6:$D$185,F$7)>1,"Dup.",IF($C$5="Critical assets (target)",IF(COUNTIFS(Register!$A$6:$A$185,$A17,Register!$D$6:$D$185,F$7,Register!$Q$6:$Q$185,">=0")=0,"",SUMIFS(Register!$Q$6:$Q$185,Register!$A$6:$A$185,$A17,Register!$D$6:$D$185,F$7)),IF($C$5="Released today",IF(COUNTIFS(Register!$A$6:$A$185,$A17,Register!$D$6:$D$185,F$7,Register!$T$6:$T$185,">=0")=0,"",SUMIFS(Register!$T$6:$T$185,Register!$A$6:$A$185,$A17,Register!$D$6:$D$185,F$7)),IF(COUNTIFS(Register!$A$6:$A$185,$A17,Register!$D$6:$D$185,F$7,Register!$O$6:$O$185,">=0")=0,"",SUMIFS(Register!$O$6:$O$185,Register!$A$6:$A$185,$A17,Register!$D$6:$D$185,F$7)))))) -> 2 | G17: =IF($A17="","",IF(COUNTIFS(Register!$A$6:$A$185,$A17,Register!$D$6:$D$185,G$7)>1,"Dup.",IF($C$5="Critical assets (target)",IF(COUNTIFS(Register!$A$6:$A$185,$A17,Register!$D$6:$D$185,G$7,Register!$Q$6:$Q$185,">=0")=0,"",SUMIFS(Register!$Q$6:$Q$185,Register!$A$6:$A$185,$A17,Register!$D$6:$D$185,G$7)),IF($C$5="Released today",IF(COUNTIFS(Register!$A$6:$A$185,$A17,Register!$D$6:$D$185,G$7,Register!$T$6:$T$185,">=0")=0,"",SUMIFS(Register!$T$6:$T$185,Register!$A$6:$A$185,$A17,Register!$D$6:$D$185,G$7)),IF(COUNTIFS(Register!$A$6:$A$185,$A17,Register!$D$6:$D$185,G$7,Register!$O$6:$O$185,">=0")=0,"",SUMIFS(Register!$O$6:$O$185,Register!$A$6:$A$185,$A17,Register!$D$6:$D$185,G$7)))))) -> 2 | H17: =IF($A17="","",IF(COUNTIFS(Register!$A$6:$A$185,$A17,Register!$D$6:$D$185,H$7)>1,"Dup.",IF($C$5="Critical assets (target)",IF(COUNTIFS(Register!$A$6:$A$185,$A17,Register!$D$6:$D$185,H$7,Register!$Q$6:$Q$185,">=0")=0,"",SUMIFS(Register!$Q$6:$Q$185,Register!$A$6:$A$185,$A17,Register!$D$6:$D$185,H$7)),IF($C$5="Released today",IF(COUNTIFS(Register!$A$6:$A$185,$A17,Register!$D$6:$D$185,H$7,Register!$T$6:$T$185,">=0")=0,"",SUMIFS(Register!$T$6:$T$185,Register!$A$6:$A$185,$A17,Register!$D$6:$D$185,H$7)),IF(COUNTIFS(Register!$A$6:$A$185,$A17,Register!$D$6:$D$185,H$7,Register!$O$6:$O$185,">=0")=0,"",SUMIFS(Register!$O$6:$O$185,Register!$A$6:$A$185,$A17,Register!$D$6:$D$185,H$7)))))) -> 1 | I17: =IF($A17="","",IF(COUNTIFS(Register!$A$6:$A$185,$A17,Register!$D$6:$D$185,I$7)>1,"Dup.",IF($C$5="Critical assets (target)",IF(COUNTIFS(Register!$A$6:$A$185,$A17,Register!$D$6:$D$185,I$7,Register!$Q$6:$Q$185,">=0")=0,"",SUMIFS(Register!$Q$6:$Q$185,Register!$A$6:$A$185,$A17,Register!$D$6:$D$185,I$7)),IF($C$5="Released today",IF(COUNTIFS(Register!$A$6:$A$185,$A17,Register!$D$6:$D$185,I$7,Register!$T$6:$T$185,">=0")=0,"",SUMIFS(Register!$T$6:$T$185,Register!$A$6:$A$185,$A17,Register!$D$6:$D$185,I$7)),IF(COUNTIFS(Register!$A$6:$A$185,$A17,Register!$D$6:$D$185,I$7,Register!$O$6:$O$185,">=0")=0,"",SUMIFS(Register!$O$6:$O$185,Register!$A$6:$A$185,$A17,Register!$D$6:$D$185,I$7)))))) -> 1 | J17: =IF($A17="","",IF(COUNTIFS(Register!$A$6:$A$185,$A17,Register!$D$6:$D$185,J$7)>1,"Dup.",IF($C$5="Critical assets (target)",IF(COUNTIFS(Register!$A$6:$A$185,$A17,Register!$D$6:$D$185,J$7,Register!$Q$6:$Q$185,">=0")=0,"",SUMIFS(Register!$Q$6:$Q$185,Register!$A$6:$A$185,$A17,Register!$D$6:$D$185,J$7)),IF($C$5="Released today",IF(COUNTIFS(Register!$A$6:$A$185,$A17,Register!$D$6:$D$185,J$7,Register!$T$6:$T$185,">=0")=0,"",SUMIFS(Register!$T$6:$T$185,Register!$A$6:$A$185,$A17,Register!$D$6:$D$185,J$7)),IF(COUNTIFS(Register!$A$6:$A$185,$A17,Register!$D$6:$D$185,J$7,Register!$O$6:$O$185,">=0")=0,"",SUMIFS(Register!$O$6:$O$185,Register!$A$6:$A$185,$A17,Register!$D$6:$D$185,J$7)))))) -> 1 | K17: =IF($A17="","",IF(COUNT(E17:J17)<6,"Incomplete",IF(AND(ISNUMBER(E17),E17<4),E$7,IF(AND(ISNUMBER(F17),F17<4),F$7,IF(AND(ISNUMBER(G17),G17<4),G$7,IF(AND(ISNUMBER(H17),H17<4),H$7,IF(AND(ISNUMBER(I17),I17<4),I$7,IF(AND(ISNUMBER(J17),J17<4),J$7,"None")))))))) -> Enrich | L17: =IF($A17="","",COUNTIFS(Register!$A$6:$A$185,$A17,Register!$P$6:$P$185,"Above policy*")) -> 0 | M17: =IF($A17="","",IF(COUNTIF('Readiness gate'!$A$7:$A$36,$A17)<>1,"Incomplete",IFERROR(IF(VLOOKUP($A17,GateTab,9,FALSE())="","Incomplete",VLOOKUP($A17,GateTab,9,FALSE())),"Incomplete"))) -> Not passed | N17: =IF($A17="","",SUMPRODUCT((Register!$A$6:$A$185=$A17)*(Register!$T$6:$T$185<>"")*(Register!$O$6:$O$185<>"")*(Register!$T$6:$T$185<Register!$O$6:$O$185))) -> 6
A18: =IF('Use cases'!$B$15="","",'Use cases'!$A$15) -> UC11 | B18: =IF($A18="","",'Use cases'!$B$15) -> Data exfiltration via cloud storage | C18: =IF($A18="","",'Use cases'!$C$15) -> Data | D18: =IF($A18="","",'Use cases'!$E$15) -> Progressive | E18: =IF($A18="","",IF(COUNTIFS(Register!$A$6:$A$185,$A18,Register!$D$6:$D$185,E$7)>1,"Dup.",IF($C$5="Critical assets (target)",IF(COUNTIFS(Register!$A$6:$A$185,$A18,Register!$D$6:$D$185,E$7,Register!$Q$6:$Q$185,">=0")=0,"",SUMIFS(Register!$Q$6:$Q$185,Register!$A$6:$A$185,$A18,Register!$D$6:$D$185,E$7)),IF($C$5="Released today",IF(COUNTIFS(Register!$A$6:$A$185,$A18,Register!$D$6:$D$185,E$7,Register!$T$6:$T$185,">=0")=0,"",SUMIFS(Register!$T$6:$T$185,Register!$A$6:$A$185,$A18,Register!$D$6:$D$185,E$7)),IF(COUNTIFS(Register!$A$6:$A$185,$A18,Register!$D$6:$D$185,E$7,Register!$O$6:$O$185,">=0")=0,"",SUMIFS(Register!$O$6:$O$185,Register!$A$6:$A$185,$A18,Register!$D$6:$D$185,E$7)))))) -> 1 | F18: =IF($A18="","",IF(COUNTIFS(Register!$A$6:$A$185,$A18,Register!$D$6:$D$185,F$7)>1,"Dup.",IF($C$5="Critical assets (target)",IF(COUNTIFS(Register!$A$6:$A$185,$A18,Register!$D$6:$D$185,F$7,Register!$Q$6:$Q$185,">=0")=0,"",SUMIFS(Register!$Q$6:$Q$185,Register!$A$6:$A$185,$A18,Register!$D$6:$D$185,F$7)),IF($C$5="Released today",IF(COUNTIFS(Register!$A$6:$A$185,$A18,Register!$D$6:$D$185,F$7,Register!$T$6:$T$185,">=0")=0,"",SUMIFS(Register!$T$6:$T$185,Register!$A$6:$A$185,$A18,Register!$D$6:$D$185,F$7)),IF(COUNTIFS(Register!$A$6:$A$185,$A18,Register!$D$6:$D$185,F$7,Register!$O$6:$O$185,">=0")=0,"",SUMIFS(Register!$O$6:$O$185,Register!$A$6:$A$185,$A18,Register!$D$6:$D$185,F$7)))))) -> 1 | G18: =IF($A18="","",IF(COUNTIFS(Register!$A$6:$A$185,$A18,Register!$D$6:$D$185,G$7)>1,"Dup.",IF($C$5="Critical assets (target)",IF(COUNTIFS(Register!$A$6:$A$185,$A18,Register!$D$6:$D$185,G$7,Register!$Q$6:$Q$185,">=0")=0,"",SUMIFS(Register!$Q$6:$Q$185,Register!$A$6:$A$185,$A18,Register!$D$6:$D$185,G$7)),IF($C$5="Released today",IF(COUNTIFS(Register!$A$6:$A$185,$A18,Register!$D$6:$D$185,G$7,Register!$T$6:$T$185,">=0")=0,"",SUMIFS(Register!$T$6:$T$185,Register!$A$6:$A$185,$A18,Register!$D$6:$D$185,G$7)),IF(COUNTIFS(Register!$A$6:$A$185,$A18,Register!$D$6:$D$185,G$7,Register!$O$6:$O$185,">=0")=0,"",SUMIFS(Register!$O$6:$O$185,Register!$A$6:$A$185,$A18,Register!$D$6:$D$185,G$7)))))) -> 2 | H18: =IF($A18="","",IF(COUNTIFS(Register!$A$6:$A$185,$A18,Register!$D$6:$D$185,H$7)>1,"Dup.",IF($C$5="Critical assets (target)",IF(COUNTIFS(Register!$A$6:$A$185,$A18,Register!$D$6:$D$185,H$7,Register!$Q$6:$Q$185,">=0")=0,"",SUMIFS(Register!$Q$6:$Q$185,Register!$A$6:$A$185,$A18,Register!$D$6:$D$185,H$7)),IF($C$5="Released today",IF(COUNTIFS(Register!$A$6:$A$185,$A18,Register!$D$6:$D$185,H$7,Register!$T$6:$T$185,">=0")=0,"",SUMIFS(Register!$T$6:$T$185,Register!$A$6:$A$185,$A18,Register!$D$6:$D$185,H$7)),IF(COUNTIFS(Register!$A$6:$A$185,$A18,Register!$D$6:$D$185,H$7,Register!$O$6:$O$185,">=0")=0,"",SUMIFS(Register!$O$6:$O$185,Register!$A$6:$A$185,$A18,Register!$D$6:$D$185,H$7)))))) -> 1 | I18: =IF($A18="","",IF(COUNTIFS(Register!$A$6:$A$185,$A18,Register!$D$6:$D$185,I$7)>1,"Dup.",IF($C$5="Critical assets (target)",IF(COUNTIFS(Register!$A$6:$A$185,$A18,Register!$D$6:$D$185,I$7,Register!$Q$6:$Q$185,">=0")=0,"",SUMIFS(Register!$Q$6:$Q$185,Register!$A$6:$A$185,$A18,Register!$D$6:$D$185,I$7)),IF($C$5="Released today",IF(COUNTIFS(Register!$A$6:$A$185,$A18,Register!$D$6:$D$185,I$7,Register!$T$6:$T$185,">=0")=0,"",SUMIFS(Register!$T$6:$T$185,Register!$A$6:$A$185,$A18,Register!$D$6:$D$185,I$7)),IF(COUNTIFS(Register!$A$6:$A$185,$A18,Register!$D$6:$D$185,I$7,Register!$O$6:$O$185,">=0")=0,"",SUMIFS(Register!$O$6:$O$185,Register!$A$6:$A$185,$A18,Register!$D$6:$D$185,I$7)))))) -> 1 | J18: =IF($A18="","",IF(COUNTIFS(Register!$A$6:$A$185,$A18,Register!$D$6:$D$185,J$7)>1,"Dup.",IF($C$5="Critical assets (target)",IF(COUNTIFS(Register!$A$6:$A$185,$A18,Register!$D$6:$D$185,J$7,Register!$Q$6:$Q$185,">=0")=0,"",SUMIFS(Register!$Q$6:$Q$185,Register!$A$6:$A$185,$A18,Register!$D$6:$D$185,J$7)),IF($C$5="Released today",IF(COUNTIFS(Register!$A$6:$A$185,$A18,Register!$D$6:$D$185,J$7,Register!$T$6:$T$185,">=0")=0,"",SUMIFS(Register!$T$6:$T$185,Register!$A$6:$A$185,$A18,Register!$D$6:$D$185,J$7)),IF(COUNTIFS(Register!$A$6:$A$185,$A18,Register!$D$6:$D$185,J$7,Register!$O$6:$O$185,">=0")=0,"",SUMIFS(Register!$O$6:$O$185,Register!$A$6:$A$185,$A18,Register!$D$6:$D$185,J$7)))))) -> 1 | K18: =IF($A18="","",IF(COUNT(E18:J18)<6,"Incomplete",IF(AND(ISNUMBER(E18),E18<4),E$7,IF(AND(ISNUMBER(F18),F18<4),F$7,IF(AND(ISNUMBER(G18),G18<4),G$7,IF(AND(ISNUMBER(H18),H18<4),H$7,IF(AND(ISNUMBER(I18),I18<4),I$7,IF(AND(ISNUMBER(J18),J18<4),J$7,"None")))))))) -> Enrich | L18: =IF($A18="","",COUNTIFS(Register!$A$6:$A$185,$A18,Register!$P$6:$P$185,"Above policy*")) -> 0 | M18: =IF($A18="","",IF(COUNTIF('Readiness gate'!$A$7:$A$36,$A18)<>1,"Incomplete",IFERROR(IF(VLOOKUP($A18,GateTab,9,FALSE())="","Incomplete",VLOOKUP($A18,GateTab,9,FALSE())),"Incomplete"))) -> Not passed | N18: =IF($A18="","",SUMPRODUCT((Register!$A$6:$A$185=$A18)*(Register!$T$6:$T$185<>"")*(Register!$O$6:$O$185<>"")*(Register!$T$6:$T$185<Register!$O$6:$O$185))) -> 6
A19: =IF('Use cases'!$B$16="","",'Use cases'!$A$16) -> UC12 | B19: =IF($A19="","",'Use cases'!$B$16) -> Unusual SaaS sharing | C19: =IF($A19="","",'Use cases'!$C$16) -> Data | D19: =IF($A19="","",'Use cases'!$E$16) -> Progressive | E19: =IF($A19="","",IF(COUNTIFS(Register!$A$6:$A$185,$A19,Register!$D$6:$D$185,E$7)>1,"Dup.",IF($C$5="Critical assets (target)",IF(COUNTIFS(Register!$A$6:$A$185,$A19,Register!$D$6:$D$185,E$7,Register!$Q$6:$Q$185,">=0")=0,"",SUMIFS(Register!$Q$6:$Q$185,Register!$A$6:$A$185,$A19,Register!$D$6:$D$185,E$7)),IF($C$5="Released today",IF(COUNTIFS(Register!$A$6:$A$185,$A19,Register!$D$6:$D$185,E$7,Register!$T$6:$T$185,">=0")=0,"",SUMIFS(Register!$T$6:$T$185,Register!$A$6:$A$185,$A19,Register!$D$6:$D$185,E$7)),IF(COUNTIFS(Register!$A$6:$A$185,$A19,Register!$D$6:$D$185,E$7,Register!$O$6:$O$185,">=0")=0,"",SUMIFS(Register!$O$6:$O$185,Register!$A$6:$A$185,$A19,Register!$D$6:$D$185,E$7)))))) -> 1 | F19: =IF($A19="","",IF(COUNTIFS(Register!$A$6:$A$185,$A19,Register!$D$6:$D$185,F$7)>1,"Dup.",IF($C$5="Critical assets (target)",IF(COUNTIFS(Register!$A$6:$A$185,$A19,Register!$D$6:$D$185,F$7,Register!$Q$6:$Q$185,">=0")=0,"",SUMIFS(Register!$Q$6:$Q$185,Register!$A$6:$A$185,$A19,Register!$D$6:$D$185,F$7)),IF($C$5="Released today",IF(COUNTIFS(Register!$A$6:$A$185,$A19,Register!$D$6:$D$185,F$7,Register!$T$6:$T$185,">=0")=0,"",SUMIFS(Register!$T$6:$T$185,Register!$A$6:$A$185,$A19,Register!$D$6:$D$185,F$7)),IF(COUNTIFS(Register!$A$6:$A$185,$A19,Register!$D$6:$D$185,F$7,Register!$O$6:$O$185,">=0")=0,"",SUMIFS(Register!$O$6:$O$185,Register!$A$6:$A$185,$A19,Register!$D$6:$D$185,F$7)))))) -> 1 | G19: =IF($A19="","",IF(COUNTIFS(Register!$A$6:$A$185,$A19,Register!$D$6:$D$185,G$7)>1,"Dup.",IF($C$5="Critical assets (target)",IF(COUNTIFS(Register!$A$6:$A$185,$A19,Register!$D$6:$D$185,G$7,Register!$Q$6:$Q$185,">=0")=0,"",SUMIFS(Register!$Q$6:$Q$185,Register!$A$6:$A$185,$A19,Register!$D$6:$D$185,G$7)),IF($C$5="Released today",IF(COUNTIFS(Register!$A$6:$A$185,$A19,Register!$D$6:$D$185,G$7,Register!$T$6:$T$185,">=0")=0,"",SUMIFS(Register!$T$6:$T$185,Register!$A$6:$A$185,$A19,Register!$D$6:$D$185,G$7)),IF(COUNTIFS(Register!$A$6:$A$185,$A19,Register!$D$6:$D$185,G$7,Register!$O$6:$O$185,">=0")=0,"",SUMIFS(Register!$O$6:$O$185,Register!$A$6:$A$185,$A19,Register!$D$6:$D$185,G$7)))))) -> 2 | H19: =IF($A19="","",IF(COUNTIFS(Register!$A$6:$A$185,$A19,Register!$D$6:$D$185,H$7)>1,"Dup.",IF($C$5="Critical assets (target)",IF(COUNTIFS(Register!$A$6:$A$185,$A19,Register!$D$6:$D$185,H$7,Register!$Q$6:$Q$185,">=0")=0,"",SUMIFS(Register!$Q$6:$Q$185,Register!$A$6:$A$185,$A19,Register!$D$6:$D$185,H$7)),IF($C$5="Released today",IF(COUNTIFS(Register!$A$6:$A$185,$A19,Register!$D$6:$D$185,H$7,Register!$T$6:$T$185,">=0")=0,"",SUMIFS(Register!$T$6:$T$185,Register!$A$6:$A$185,$A19,Register!$D$6:$D$185,H$7)),IF(COUNTIFS(Register!$A$6:$A$185,$A19,Register!$D$6:$D$185,H$7,Register!$O$6:$O$185,">=0")=0,"",SUMIFS(Register!$O$6:$O$185,Register!$A$6:$A$185,$A19,Register!$D$6:$D$185,H$7)))))) -> 1 | I19: =IF($A19="","",IF(COUNTIFS(Register!$A$6:$A$185,$A19,Register!$D$6:$D$185,I$7)>1,"Dup.",IF($C$5="Critical assets (target)",IF(COUNTIFS(Register!$A$6:$A$185,$A19,Register!$D$6:$D$185,I$7,Register!$Q$6:$Q$185,">=0")=0,"",SUMIFS(Register!$Q$6:$Q$185,Register!$A$6:$A$185,$A19,Register!$D$6:$D$185,I$7)),IF($C$5="Released today",IF(COUNTIFS(Register!$A$6:$A$185,$A19,Register!$D$6:$D$185,I$7,Register!$T$6:$T$185,">=0")=0,"",SUMIFS(Register!$T$6:$T$185,Register!$A$6:$A$185,$A19,Register!$D$6:$D$185,I$7)),IF(COUNTIFS(Register!$A$6:$A$185,$A19,Register!$D$6:$D$185,I$7,Register!$O$6:$O$185,">=0")=0,"",SUMIFS(Register!$O$6:$O$185,Register!$A$6:$A$185,$A19,Register!$D$6:$D$185,I$7)))))) -> 1 | J19: =IF($A19="","",IF(COUNTIFS(Register!$A$6:$A$185,$A19,Register!$D$6:$D$185,J$7)>1,"Dup.",IF($C$5="Critical assets (target)",IF(COUNTIFS(Register!$A$6:$A$185,$A19,Register!$D$6:$D$185,J$7,Register!$Q$6:$Q$185,">=0")=0,"",SUMIFS(Register!$Q$6:$Q$185,Register!$A$6:$A$185,$A19,Register!$D$6:$D$185,J$7)),IF($C$5="Released today",IF(COUNTIFS(Register!$A$6:$A$185,$A19,Register!$D$6:$D$185,J$7,Register!$T$6:$T$185,">=0")=0,"",SUMIFS(Register!$T$6:$T$185,Register!$A$6:$A$185,$A19,Register!$D$6:$D$185,J$7)),IF(COUNTIFS(Register!$A$6:$A$185,$A19,Register!$D$6:$D$185,J$7,Register!$O$6:$O$185,">=0")=0,"",SUMIFS(Register!$O$6:$O$185,Register!$A$6:$A$185,$A19,Register!$D$6:$D$185,J$7)))))) -> 1 | K19: =IF($A19="","",IF(COUNT(E19:J19)<6,"Incomplete",IF(AND(ISNUMBER(E19),E19<4),E$7,IF(AND(ISNUMBER(F19),F19<4),F$7,IF(AND(ISNUMBER(G19),G19<4),G$7,IF(AND(ISNUMBER(H19),H19<4),H$7,IF(AND(ISNUMBER(I19),I19<4),I$7,IF(AND(ISNUMBER(J19),J19<4),J$7,"None")))))))) -> Enrich | L19: =IF($A19="","",COUNTIFS(Register!$A$6:$A$185,$A19,Register!$P$6:$P$185,"Above policy*")) -> 0 | M19: =IF($A19="","",IF(COUNTIF('Readiness gate'!$A$7:$A$36,$A19)<>1,"Incomplete",IFERROR(IF(VLOOKUP($A19,GateTab,9,FALSE())="","Incomplete",VLOOKUP($A19,GateTab,9,FALSE())),"Incomplete"))) -> Not passed | N19: =IF($A19="","",SUMPRODUCT((Register!$A$6:$A$185=$A19)*(Register!$T$6:$T$185<>"")*(Register!$O$6:$O$185<>"")*(Register!$T$6:$T$185<Register!$O$6:$O$185))) -> 6
A20: =IF('Use cases'!$B$17="","",'Use cases'!$A$17) -> UC13 | B20: =IF($A20="","",'Use cases'!$B$17) -> Cloud key leak | C20: =IF($A20="","",'Use cases'!$C$17) -> Cloud | D20: =IF($A20="","",'Use cases'!$E$17) -> Progressive | E20: =IF($A20="","",IF(COUNTIFS(Register!$A$6:$A$185,$A20,Register!$D$6:$D$185,E$7)>1,"Dup.",IF($C$5="Critical assets (target)",IF(COUNTIFS(Register!$A$6:$A$185,$A20,Register!$D$6:$D$185,E$7,Register!$Q$6:$Q$185,">=0")=0,"",SUMIFS(Register!$Q$6:$Q$185,Register!$A$6:$A$185,$A20,Register!$D$6:$D$185,E$7)),IF($C$5="Released today",IF(COUNTIFS(Register!$A$6:$A$185,$A20,Register!$D$6:$D$185,E$7,Register!$T$6:$T$185,">=0")=0,"",SUMIFS(Register!$T$6:$T$185,Register!$A$6:$A$185,$A20,Register!$D$6:$D$185,E$7)),IF(COUNTIFS(Register!$A$6:$A$185,$A20,Register!$D$6:$D$185,E$7,Register!$O$6:$O$185,">=0")=0,"",SUMIFS(Register!$O$6:$O$185,Register!$A$6:$A$185,$A20,Register!$D$6:$D$185,E$7)))))) -> 4 | F20: =IF($A20="","",IF(COUNTIFS(Register!$A$6:$A$185,$A20,Register!$D$6:$D$185,F$7)>1,"Dup.",IF($C$5="Critical assets (target)",IF(COUNTIFS(Register!$A$6:$A$185,$A20,Register!$D$6:$D$185,F$7,Register!$Q$6:$Q$185,">=0")=0,"",SUMIFS(Register!$Q$6:$Q$185,Register!$A$6:$A$185,$A20,Register!$D$6:$D$185,F$7)),IF($C$5="Released today",IF(COUNTIFS(Register!$A$6:$A$185,$A20,Register!$D$6:$D$185,F$7,Register!$T$6:$T$185,">=0")=0,"",SUMIFS(Register!$T$6:$T$185,Register!$A$6:$A$185,$A20,Register!$D$6:$D$185,F$7)),IF(COUNTIFS(Register!$A$6:$A$185,$A20,Register!$D$6:$D$185,F$7,Register!$O$6:$O$185,">=0")=0,"",SUMIFS(Register!$O$6:$O$185,Register!$A$6:$A$185,$A20,Register!$D$6:$D$185,F$7)))))) -> 2 | G20: =IF($A20="","",IF(COUNTIFS(Register!$A$6:$A$185,$A20,Register!$D$6:$D$185,G$7)>1,"Dup.",IF($C$5="Critical assets (target)",IF(COUNTIFS(Register!$A$6:$A$185,$A20,Register!$D$6:$D$185,G$7,Register!$Q$6:$Q$185,">=0")=0,"",SUMIFS(Register!$Q$6:$Q$185,Register!$A$6:$A$185,$A20,Register!$D$6:$D$185,G$7)),IF($C$5="Released today",IF(COUNTIFS(Register!$A$6:$A$185,$A20,Register!$D$6:$D$185,G$7,Register!$T$6:$T$185,">=0")=0,"",SUMIFS(Register!$T$6:$T$185,Register!$A$6:$A$185,$A20,Register!$D$6:$D$185,G$7)),IF(COUNTIFS(Register!$A$6:$A$185,$A20,Register!$D$6:$D$185,G$7,Register!$O$6:$O$185,">=0")=0,"",SUMIFS(Register!$O$6:$O$185,Register!$A$6:$A$185,$A20,Register!$D$6:$D$185,G$7)))))) -> 3 | H20: =IF($A20="","",IF(COUNTIFS(Register!$A$6:$A$185,$A20,Register!$D$6:$D$185,H$7)>1,"Dup.",IF($C$5="Critical assets (target)",IF(COUNTIFS(Register!$A$6:$A$185,$A20,Register!$D$6:$D$185,H$7,Register!$Q$6:$Q$185,">=0")=0,"",SUMIFS(Register!$Q$6:$Q$185,Register!$A$6:$A$185,$A20,Register!$D$6:$D$185,H$7)),IF($C$5="Released today",IF(COUNTIFS(Register!$A$6:$A$185,$A20,Register!$D$6:$D$185,H$7,Register!$T$6:$T$185,">=0")=0,"",SUMIFS(Register!$T$6:$T$185,Register!$A$6:$A$185,$A20,Register!$D$6:$D$185,H$7)),IF(COUNTIFS(Register!$A$6:$A$185,$A20,Register!$D$6:$D$185,H$7,Register!$O$6:$O$185,">=0")=0,"",SUMIFS(Register!$O$6:$O$185,Register!$A$6:$A$185,$A20,Register!$D$6:$D$185,H$7)))))) -> 2 | I20: =IF($A20="","",IF(COUNTIFS(Register!$A$6:$A$185,$A20,Register!$D$6:$D$185,I$7)>1,"Dup.",IF($C$5="Critical assets (target)",IF(COUNTIFS(Register!$A$6:$A$185,$A20,Register!$D$6:$D$185,I$7,Register!$Q$6:$Q$185,">=0")=0,"",SUMIFS(Register!$Q$6:$Q$185,Register!$A$6:$A$185,$A20,Register!$D$6:$D$185,I$7)),IF($C$5="Released today",IF(COUNTIFS(Register!$A$6:$A$185,$A20,Register!$D$6:$D$185,I$7,Register!$T$6:$T$185,">=0")=0,"",SUMIFS(Register!$T$6:$T$185,Register!$A$6:$A$185,$A20,Register!$D$6:$D$185,I$7)),IF(COUNTIFS(Register!$A$6:$A$185,$A20,Register!$D$6:$D$185,I$7,Register!$O$6:$O$185,">=0")=0,"",SUMIFS(Register!$O$6:$O$185,Register!$A$6:$A$185,$A20,Register!$D$6:$D$185,I$7)))))) -> 2 | J20: =IF($A20="","",IF(COUNTIFS(Register!$A$6:$A$185,$A20,Register!$D$6:$D$185,J$7)>1,"Dup.",IF($C$5="Critical assets (target)",IF(COUNTIFS(Register!$A$6:$A$185,$A20,Register!$D$6:$D$185,J$7,Register!$Q$6:$Q$185,">=0")=0,"",SUMIFS(Register!$Q$6:$Q$185,Register!$A$6:$A$185,$A20,Register!$D$6:$D$185,J$7)),IF($C$5="Released today",IF(COUNTIFS(Register!$A$6:$A$185,$A20,Register!$D$6:$D$185,J$7,Register!$T$6:$T$185,">=0")=0,"",SUMIFS(Register!$T$6:$T$185,Register!$A$6:$A$185,$A20,Register!$D$6:$D$185,J$7)),IF(COUNTIFS(Register!$A$6:$A$185,$A20,Register!$D$6:$D$185,J$7,Register!$O$6:$O$185,">=0")=0,"",SUMIFS(Register!$O$6:$O$185,Register!$A$6:$A$185,$A20,Register!$D$6:$D$185,J$7)))))) -> 2 | K20: =IF($A20="","",IF(COUNT(E20:J20)<6,"Incomplete",IF(AND(ISNUMBER(E20),E20<4),E$7,IF(AND(ISNUMBER(F20),F20<4),F$7,IF(AND(ISNUMBER(G20),G20<4),G$7,IF(AND(ISNUMBER(H20),H20<4),H$7,IF(AND(ISNUMBER(I20),I20<4),I$7,IF(AND(ISNUMBER(J20),J20<4),J$7,"None")))))))) -> Triage | L20: =IF($A20="","",COUNTIFS(Register!$A$6:$A$185,$A20,Register!$P$6:$P$185,"Above policy*")) -> 0 | M20: =IF($A20="","",IF(COUNTIF('Readiness gate'!$A$7:$A$36,$A20)<>1,"Incomplete",IFERROR(IF(VLOOKUP($A20,GateTab,9,FALSE())="","Incomplete",VLOOKUP($A20,GateTab,9,FALSE())),"Incomplete"))) -> Passed | N20: =IF($A20="","",SUMPRODUCT((Register!$A$6:$A$185=$A20)*(Register!$T$6:$T$185<>"")*(Register!$O$6:$O$185<>"")*(Register!$T$6:$T$185<Register!$O$6:$O$185))) -> 5
A21: =IF('Use cases'!$B$18="","",'Use cases'!$A$18) -> UC14 | B21: =IF($A21="","",'Use cases'!$B$18) -> Public S3 or blob exposure | C21: =IF($A21="","",'Use cases'!$C$18) -> Cloud | D21: =IF($A21="","",'Use cases'!$E$18) -> Progressive | E21: =IF($A21="","",IF(COUNTIFS(Register!$A$6:$A$185,$A21,Register!$D$6:$D$185,E$7)>1,"Dup.",IF($C$5="Critical assets (target)",IF(COUNTIFS(Register!$A$6:$A$185,$A21,Register!$D$6:$D$185,E$7,Register!$Q$6:$Q$185,">=0")=0,"",SUMIFS(Register!$Q$6:$Q$185,Register!$A$6:$A$185,$A21,Register!$D$6:$D$185,E$7)),IF($C$5="Released today",IF(COUNTIFS(Register!$A$6:$A$185,$A21,Register!$D$6:$D$185,E$7,Register!$T$6:$T$185,">=0")=0,"",SUMIFS(Register!$T$6:$T$185,Register!$A$6:$A$185,$A21,Register!$D$6:$D$185,E$7)),IF(COUNTIFS(Register!$A$6:$A$185,$A21,Register!$D$6:$D$185,E$7,Register!$O$6:$O$185,">=0")=0,"",SUMIFS(Register!$O$6:$O$185,Register!$A$6:$A$185,$A21,Register!$D$6:$D$185,E$7)))))) -> 4 | F21: =IF($A21="","",IF(COUNTIFS(Register!$A$6:$A$185,$A21,Register!$D$6:$D$185,F$7)>1,"Dup.",IF($C$5="Critical assets (target)",IF(COUNTIFS(Register!$A$6:$A$185,$A21,Register!$D$6:$D$185,F$7,Register!$Q$6:$Q$185,">=0")=0,"",SUMIFS(Register!$Q$6:$Q$185,Register!$A$6:$A$185,$A21,Register!$D$6:$D$185,F$7)),IF($C$5="Released today",IF(COUNTIFS(Register!$A$6:$A$185,$A21,Register!$D$6:$D$185,F$7,Register!$T$6:$T$185,">=0")=0,"",SUMIFS(Register!$T$6:$T$185,Register!$A$6:$A$185,$A21,Register!$D$6:$D$185,F$7)),IF(COUNTIFS(Register!$A$6:$A$185,$A21,Register!$D$6:$D$185,F$7,Register!$O$6:$O$185,">=0")=0,"",SUMIFS(Register!$O$6:$O$185,Register!$A$6:$A$185,$A21,Register!$D$6:$D$185,F$7)))))) -> 2 | G21: =IF($A21="","",IF(COUNTIFS(Register!$A$6:$A$185,$A21,Register!$D$6:$D$185,G$7)>1,"Dup.",IF($C$5="Critical assets (target)",IF(COUNTIFS(Register!$A$6:$A$185,$A21,Register!$D$6:$D$185,G$7,Register!$Q$6:$Q$185,">=0")=0,"",SUMIFS(Register!$Q$6:$Q$185,Register!$A$6:$A$185,$A21,Register!$D$6:$D$185,G$7)),IF($C$5="Released today",IF(COUNTIFS(Register!$A$6:$A$185,$A21,Register!$D$6:$D$185,G$7,Register!$T$6:$T$185,">=0")=0,"",SUMIFS(Register!$T$6:$T$185,Register!$A$6:$A$185,$A21,Register!$D$6:$D$185,G$7)),IF(COUNTIFS(Register!$A$6:$A$185,$A21,Register!$D$6:$D$185,G$7,Register!$O$6:$O$185,">=0")=0,"",SUMIFS(Register!$O$6:$O$185,Register!$A$6:$A$185,$A21,Register!$D$6:$D$185,G$7)))))) -> 3 | H21: =IF($A21="","",IF(COUNTIFS(Register!$A$6:$A$185,$A21,Register!$D$6:$D$185,H$7)>1,"Dup.",IF($C$5="Critical assets (target)",IF(COUNTIFS(Register!$A$6:$A$185,$A21,Register!$D$6:$D$185,H$7,Register!$Q$6:$Q$185,">=0")=0,"",SUMIFS(Register!$Q$6:$Q$185,Register!$A$6:$A$185,$A21,Register!$D$6:$D$185,H$7)),IF($C$5="Released today",IF(COUNTIFS(Register!$A$6:$A$185,$A21,Register!$D$6:$D$185,H$7,Register!$T$6:$T$185,">=0")=0,"",SUMIFS(Register!$T$6:$T$185,Register!$A$6:$A$185,$A21,Register!$D$6:$D$185,H$7)),IF(COUNTIFS(Register!$A$6:$A$185,$A21,Register!$D$6:$D$185,H$7,Register!$O$6:$O$185,">=0")=0,"",SUMIFS(Register!$O$6:$O$185,Register!$A$6:$A$185,$A21,Register!$D$6:$D$185,H$7)))))) -> 2 | I21: =IF($A21="","",IF(COUNTIFS(Register!$A$6:$A$185,$A21,Register!$D$6:$D$185,I$7)>1,"Dup.",IF($C$5="Critical assets (target)",IF(COUNTIFS(Register!$A$6:$A$185,$A21,Register!$D$6:$D$185,I$7,Register!$Q$6:$Q$185,">=0")=0,"",SUMIFS(Register!$Q$6:$Q$185,Register!$A$6:$A$185,$A21,Register!$D$6:$D$185,I$7)),IF($C$5="Released today",IF(COUNTIFS(Register!$A$6:$A$185,$A21,Register!$D$6:$D$185,I$7,Register!$T$6:$T$185,">=0")=0,"",SUMIFS(Register!$T$6:$T$185,Register!$A$6:$A$185,$A21,Register!$D$6:$D$185,I$7)),IF(COUNTIFS(Register!$A$6:$A$185,$A21,Register!$D$6:$D$185,I$7,Register!$O$6:$O$185,">=0")=0,"",SUMIFS(Register!$O$6:$O$185,Register!$A$6:$A$185,$A21,Register!$D$6:$D$185,I$7)))))) -> 2 | J21: =IF($A21="","",IF(COUNTIFS(Register!$A$6:$A$185,$A21,Register!$D$6:$D$185,J$7)>1,"Dup.",IF($C$5="Critical assets (target)",IF(COUNTIFS(Register!$A$6:$A$185,$A21,Register!$D$6:$D$185,J$7,Register!$Q$6:$Q$185,">=0")=0,"",SUMIFS(Register!$Q$6:$Q$185,Register!$A$6:$A$185,$A21,Register!$D$6:$D$185,J$7)),IF($C$5="Released today",IF(COUNTIFS(Register!$A$6:$A$185,$A21,Register!$D$6:$D$185,J$7,Register!$T$6:$T$185,">=0")=0,"",SUMIFS(Register!$T$6:$T$185,Register!$A$6:$A$185,$A21,Register!$D$6:$D$185,J$7)),IF(COUNTIFS(Register!$A$6:$A$185,$A21,Register!$D$6:$D$185,J$7,Register!$O$6:$O$185,">=0")=0,"",SUMIFS(Register!$O$6:$O$185,Register!$A$6:$A$185,$A21,Register!$D$6:$D$185,J$7)))))) -> 1 | K21: =IF($A21="","",IF(COUNT(E21:J21)<6,"Incomplete",IF(AND(ISNUMBER(E21),E21<4),E$7,IF(AND(ISNUMBER(F21),F21<4),F$7,IF(AND(ISNUMBER(G21),G21<4),G$7,IF(AND(ISNUMBER(H21),H21<4),H$7,IF(AND(ISNUMBER(I21),I21<4),I$7,IF(AND(ISNUMBER(J21),J21<4),J$7,"None")))))))) -> Triage | L21: =IF($A21="","",COUNTIFS(Register!$A$6:$A$185,$A21,Register!$P$6:$P$185,"Above policy*")) -> 0 | M21: =IF($A21="","",IF(COUNTIF('Readiness gate'!$A$7:$A$36,$A21)<>1,"Incomplete",IFERROR(IF(VLOOKUP($A21,GateTab,9,FALSE())="","Incomplete",VLOOKUP($A21,GateTab,9,FALSE())),"Incomplete"))) -> Passed | N21: =IF($A21="","",SUMPRODUCT((Register!$A$6:$A$185=$A21)*(Register!$T$6:$T$185<>"")*(Register!$O$6:$O$185<>"")*(Register!$T$6:$T$185<Register!$O$6:$O$185))) -> 5
A22: =IF('Use cases'!$B$19="","",'Use cases'!$A$19) -> UC15 | B22: =IF($A22="","",'Use cases'!$B$19) -> New internet-exposed critical CVE | C22: =IF($A22="","",'Use cases'!$C$19) -> Exposure | D22: =IF($A22="","",'Use cases'!$E$19) -> Progressive | E22: =IF($A22="","",IF(COUNTIFS(Register!$A$6:$A$185,$A22,Register!$D$6:$D$185,E$7)>1,"Dup.",IF($C$5="Critical assets (target)",IF(COUNTIFS(Register!$A$6:$A$185,$A22,Register!$D$6:$D$185,E$7,Register!$Q$6:$Q$185,">=0")=0,"",SUMIFS(Register!$Q$6:$Q$185,Register!$A$6:$A$185,$A22,Register!$D$6:$D$185,E$7)),IF($C$5="Released today",IF(COUNTIFS(Register!$A$6:$A$185,$A22,Register!$D$6:$D$185,E$7,Register!$T$6:$T$185,">=0")=0,"",SUMIFS(Register!$T$6:$T$185,Register!$A$6:$A$185,$A22,Register!$D$6:$D$185,E$7)),IF(COUNTIFS(Register!$A$6:$A$185,$A22,Register!$D$6:$D$185,E$7,Register!$O$6:$O$185,">=0")=0,"",SUMIFS(Register!$O$6:$O$185,Register!$A$6:$A$185,$A22,Register!$D$6:$D$185,E$7)))))) -> 4 | F22: =IF($A22="","",IF(COUNTIFS(Register!$A$6:$A$185,$A22,Register!$D$6:$D$185,F$7)>1,"Dup.",IF($C$5="Critical assets (target)",IF(COUNTIFS(Register!$A$6:$A$185,$A22,Register!$D$6:$D$185,F$7,Register!$Q$6:$Q$185,">=0")=0,"",SUMIFS(Register!$Q$6:$Q$185,Register!$A$6:$A$185,$A22,Register!$D$6:$D$185,F$7)),IF($C$5="Released today",IF(COUNTIFS(Register!$A$6:$A$185,$A22,Register!$D$6:$D$185,F$7,Register!$T$6:$T$185,">=0")=0,"",SUMIFS(Register!$T$6:$T$185,Register!$A$6:$A$185,$A22,Register!$D$6:$D$185,F$7)),IF(COUNTIFS(Register!$A$6:$A$185,$A22,Register!$D$6:$D$185,F$7,Register!$O$6:$O$185,">=0")=0,"",SUMIFS(Register!$O$6:$O$185,Register!$A$6:$A$185,$A22,Register!$D$6:$D$185,F$7)))))) -> 2 | G22: =IF($A22="","",IF(COUNTIFS(Register!$A$6:$A$185,$A22,Register!$D$6:$D$185,G$7)>1,"Dup.",IF($C$5="Critical assets (target)",IF(COUNTIFS(Register!$A$6:$A$185,$A22,Register!$D$6:$D$185,G$7,Register!$Q$6:$Q$185,">=0")=0,"",SUMIFS(Register!$Q$6:$Q$185,Register!$A$6:$A$185,$A22,Register!$D$6:$D$185,G$7)),IF($C$5="Released today",IF(COUNTIFS(Register!$A$6:$A$185,$A22,Register!$D$6:$D$185,G$7,Register!$T$6:$T$185,">=0")=0,"",SUMIFS(Register!$T$6:$T$185,Register!$A$6:$A$185,$A22,Register!$D$6:$D$185,G$7)),IF(COUNTIFS(Register!$A$6:$A$185,$A22,Register!$D$6:$D$185,G$7,Register!$O$6:$O$185,">=0")=0,"",SUMIFS(Register!$O$6:$O$185,Register!$A$6:$A$185,$A22,Register!$D$6:$D$185,G$7)))))) -> 3 | H22: =IF($A22="","",IF(COUNTIFS(Register!$A$6:$A$185,$A22,Register!$D$6:$D$185,H$7)>1,"Dup.",IF($C$5="Critical assets (target)",IF(COUNTIFS(Register!$A$6:$A$185,$A22,Register!$D$6:$D$185,H$7,Register!$Q$6:$Q$185,">=0")=0,"",SUMIFS(Register!$Q$6:$Q$185,Register!$A$6:$A$185,$A22,Register!$D$6:$D$185,H$7)),IF($C$5="Released today",IF(COUNTIFS(Register!$A$6:$A$185,$A22,Register!$D$6:$D$185,H$7,Register!$T$6:$T$185,">=0")=0,"",SUMIFS(Register!$T$6:$T$185,Register!$A$6:$A$185,$A22,Register!$D$6:$D$185,H$7)),IF(COUNTIFS(Register!$A$6:$A$185,$A22,Register!$D$6:$D$185,H$7,Register!$O$6:$O$185,">=0")=0,"",SUMIFS(Register!$O$6:$O$185,Register!$A$6:$A$185,$A22,Register!$D$6:$D$185,H$7)))))) -> 2 | I22: =IF($A22="","",IF(COUNTIFS(Register!$A$6:$A$185,$A22,Register!$D$6:$D$185,I$7)>1,"Dup.",IF($C$5="Critical assets (target)",IF(COUNTIFS(Register!$A$6:$A$185,$A22,Register!$D$6:$D$185,I$7,Register!$Q$6:$Q$185,">=0")=0,"",SUMIFS(Register!$Q$6:$Q$185,Register!$A$6:$A$185,$A22,Register!$D$6:$D$185,I$7)),IF($C$5="Released today",IF(COUNTIFS(Register!$A$6:$A$185,$A22,Register!$D$6:$D$185,I$7,Register!$T$6:$T$185,">=0")=0,"",SUMIFS(Register!$T$6:$T$185,Register!$A$6:$A$185,$A22,Register!$D$6:$D$185,I$7)),IF(COUNTIFS(Register!$A$6:$A$185,$A22,Register!$D$6:$D$185,I$7,Register!$O$6:$O$185,">=0")=0,"",SUMIFS(Register!$O$6:$O$185,Register!$A$6:$A$185,$A22,Register!$D$6:$D$185,I$7)))))) -> 2 | J22: =IF($A22="","",IF(COUNTIFS(Register!$A$6:$A$185,$A22,Register!$D$6:$D$185,J$7)>1,"Dup.",IF($C$5="Critical assets (target)",IF(COUNTIFS(Register!$A$6:$A$185,$A22,Register!$D$6:$D$185,J$7,Register!$Q$6:$Q$185,">=0")=0,"",SUMIFS(Register!$Q$6:$Q$185,Register!$A$6:$A$185,$A22,Register!$D$6:$D$185,J$7)),IF($C$5="Released today",IF(COUNTIFS(Register!$A$6:$A$185,$A22,Register!$D$6:$D$185,J$7,Register!$T$6:$T$185,">=0")=0,"",SUMIFS(Register!$T$6:$T$185,Register!$A$6:$A$185,$A22,Register!$D$6:$D$185,J$7)),IF(COUNTIFS(Register!$A$6:$A$185,$A22,Register!$D$6:$D$185,J$7,Register!$O$6:$O$185,">=0")=0,"",SUMIFS(Register!$O$6:$O$185,Register!$A$6:$A$185,$A22,Register!$D$6:$D$185,J$7)))))) -> 2 | K22: =IF($A22="","",IF(COUNT(E22:J22)<6,"Incomplete",IF(AND(ISNUMBER(E22),E22<4),E$7,IF(AND(ISNUMBER(F22),F22<4),F$7,IF(AND(ISNUMBER(G22),G22<4),G$7,IF(AND(ISNUMBER(H22),H22<4),H$7,IF(AND(ISNUMBER(I22),I22<4),I$7,IF(AND(ISNUMBER(J22),J22<4),J$7,"None")))))))) -> Triage | L22: =IF($A22="","",COUNTIFS(Register!$A$6:$A$185,$A22,Register!$P$6:$P$185,"Above policy*")) -> 0 | M22: =IF($A22="","",IF(COUNTIF('Readiness gate'!$A$7:$A$36,$A22)<>1,"Incomplete",IFERROR(IF(VLOOKUP($A22,GateTab,9,FALSE())="","Incomplete",VLOOKUP($A22,GateTab,9,FALSE())),"Incomplete"))) -> Passed | N22: =IF($A22="","",SUMPRODUCT((Register!$A$6:$A$185=$A22)*(Register!$T$6:$T$185<>"")*(Register!$O$6:$O$185<>"")*(Register!$T$6:$T$185<Register!$O$6:$O$185))) -> 5
A23: =IF('Use cases'!$B$20="","",'Use cases'!$A$20) -> UC16 | B23: =IF($A23="","",'Use cases'!$B$20) -> Suspicious admin creation | C23: =IF($A23="","",'Use cases'!$C$20) -> Identity | D23: =IF($A23="","",'Use cases'!$E$20) -> Progressive | E23: =IF($A23="","",IF(COUNTIFS(Register!$A$6:$A$185,$A23,Register!$D$6:$D$185,E$7)>1,"Dup.",IF($C$5="Critical assets (target)",IF(COUNTIFS(Register!$A$6:$A$185,$A23,Register!$D$6:$D$185,E$7,Register!$Q$6:$Q$185,">=0")=0,"",SUMIFS(Register!$Q$6:$Q$185,Register!$A$6:$A$185,$A23,Register!$D$6:$D$185,E$7)),IF($C$5="Released today",IF(COUNTIFS(Register!$A$6:$A$185,$A23,Register!$D$6:$D$185,E$7,Register!$T$6:$T$185,">=0")=0,"",SUMIFS(Register!$T$6:$T$185,Register!$A$6:$A$185,$A23,Register!$D$6:$D$185,E$7)),IF(COUNTIFS(Register!$A$6:$A$185,$A23,Register!$D$6:$D$185,E$7,Register!$O$6:$O$185,">=0")=0,"",SUMIFS(Register!$O$6:$O$185,Register!$A$6:$A$185,$A23,Register!$D$6:$D$185,E$7)))))) -> 1 | F23: =IF($A23="","",IF(COUNTIFS(Register!$A$6:$A$185,$A23,Register!$D$6:$D$185,F$7)>1,"Dup.",IF($C$5="Critical assets (target)",IF(COUNTIFS(Register!$A$6:$A$185,$A23,Register!$D$6:$D$185,F$7,Register!$Q$6:$Q$185,">=0")=0,"",SUMIFS(Register!$Q$6:$Q$185,Register!$A$6:$A$185,$A23,Register!$D$6:$D$185,F$7)),IF($C$5="Released today",IF(COUNTIFS(Register!$A$6:$A$185,$A23,Register!$D$6:$D$185,F$7,Register!$T$6:$T$185,">=0")=0,"",SUMIFS(Register!$T$6:$T$185,Register!$A$6:$A$185,$A23,Register!$D$6:$D$185,F$7)),IF(COUNTIFS(Register!$A$6:$A$185,$A23,Register!$D$6:$D$185,F$7,Register!$O$6:$O$185,">=0")=0,"",SUMIFS(Register!$O$6:$O$185,Register!$A$6:$A$185,$A23,Register!$D$6:$D$185,F$7)))))) -> 1 | G23: =IF($A23="","",IF(COUNTIFS(Register!$A$6:$A$185,$A23,Register!$D$6:$D$185,G$7)>1,"Dup.",IF($C$5="Critical assets (target)",IF(COUNTIFS(Register!$A$6:$A$185,$A23,Register!$D$6:$D$185,G$7,Register!$Q$6:$Q$185,">=0")=0,"",SUMIFS(Register!$Q$6:$Q$185,Register!$A$6:$A$185,$A23,Register!$D$6:$D$185,G$7)),IF($C$5="Released today",IF(COUNTIFS(Register!$A$6:$A$185,$A23,Register!$D$6:$D$185,G$7,Register!$T$6:$T$185,">=0")=0,"",SUMIFS(Register!$T$6:$T$185,Register!$A$6:$A$185,$A23,Register!$D$6:$D$185,G$7)),IF(COUNTIFS(Register!$A$6:$A$185,$A23,Register!$D$6:$D$185,G$7,Register!$O$6:$O$185,">=0")=0,"",SUMIFS(Register!$O$6:$O$185,Register!$A$6:$A$185,$A23,Register!$D$6:$D$185,G$7)))))) -> 2 | H23: =IF($A23="","",IF(COUNTIFS(Register!$A$6:$A$185,$A23,Register!$D$6:$D$185,H$7)>1,"Dup.",IF($C$5="Critical assets (target)",IF(COUNTIFS(Register!$A$6:$A$185,$A23,Register!$D$6:$D$185,H$7,Register!$Q$6:$Q$185,">=0")=0,"",SUMIFS(Register!$Q$6:$Q$185,Register!$A$6:$A$185,$A23,Register!$D$6:$D$185,H$7)),IF($C$5="Released today",IF(COUNTIFS(Register!$A$6:$A$185,$A23,Register!$D$6:$D$185,H$7,Register!$T$6:$T$185,">=0")=0,"",SUMIFS(Register!$T$6:$T$185,Register!$A$6:$A$185,$A23,Register!$D$6:$D$185,H$7)),IF(COUNTIFS(Register!$A$6:$A$185,$A23,Register!$D$6:$D$185,H$7,Register!$O$6:$O$185,">=0")=0,"",SUMIFS(Register!$O$6:$O$185,Register!$A$6:$A$185,$A23,Register!$D$6:$D$185,H$7)))))) -> 1 | I23: =IF($A23="","",IF(COUNTIFS(Register!$A$6:$A$185,$A23,Register!$D$6:$D$185,I$7)>1,"Dup.",IF($C$5="Critical assets (target)",IF(COUNTIFS(Register!$A$6:$A$185,$A23,Register!$D$6:$D$185,I$7,Register!$Q$6:$Q$185,">=0")=0,"",SUMIFS(Register!$Q$6:$Q$185,Register!$A$6:$A$185,$A23,Register!$D$6:$D$185,I$7)),IF($C$5="Released today",IF(COUNTIFS(Register!$A$6:$A$185,$A23,Register!$D$6:$D$185,I$7,Register!$T$6:$T$185,">=0")=0,"",SUMIFS(Register!$T$6:$T$185,Register!$A$6:$A$185,$A23,Register!$D$6:$D$185,I$7)),IF(COUNTIFS(Register!$A$6:$A$185,$A23,Register!$D$6:$D$185,I$7,Register!$O$6:$O$185,">=0")=0,"",SUMIFS(Register!$O$6:$O$185,Register!$A$6:$A$185,$A23,Register!$D$6:$D$185,I$7)))))) -> 1 | J23: =IF($A23="","",IF(COUNTIFS(Register!$A$6:$A$185,$A23,Register!$D$6:$D$185,J$7)>1,"Dup.",IF($C$5="Critical assets (target)",IF(COUNTIFS(Register!$A$6:$A$185,$A23,Register!$D$6:$D$185,J$7,Register!$Q$6:$Q$185,">=0")=0,"",SUMIFS(Register!$Q$6:$Q$185,Register!$A$6:$A$185,$A23,Register!$D$6:$D$185,J$7)),IF($C$5="Released today",IF(COUNTIFS(Register!$A$6:$A$185,$A23,Register!$D$6:$D$185,J$7,Register!$T$6:$T$185,">=0")=0,"",SUMIFS(Register!$T$6:$T$185,Register!$A$6:$A$185,$A23,Register!$D$6:$D$185,J$7)),IF(COUNTIFS(Register!$A$6:$A$185,$A23,Register!$D$6:$D$185,J$7,Register!$O$6:$O$185,">=0")=0,"",SUMIFS(Register!$O$6:$O$185,Register!$A$6:$A$185,$A23,Register!$D$6:$D$185,J$7)))))) -> 1 | K23: =IF($A23="","",IF(COUNT(E23:J23)<6,"Incomplete",IF(AND(ISNUMBER(E23),E23<4),E$7,IF(AND(ISNUMBER(F23),F23<4),F$7,IF(AND(ISNUMBER(G23),G23<4),G$7,IF(AND(ISNUMBER(H23),H23<4),H$7,IF(AND(ISNUMBER(I23),I23<4),I$7,IF(AND(ISNUMBER(J23),J23<4),J$7,"None")))))))) -> Enrich | L23: =IF($A23="","",COUNTIFS(Register!$A$6:$A$185,$A23,Register!$P$6:$P$185,"Above policy*")) -> 0 | M23: =IF($A23="","",IF(COUNTIF('Readiness gate'!$A$7:$A$36,$A23)<>1,"Incomplete",IFERROR(IF(VLOOKUP($A23,GateTab,9,FALSE())="","Incomplete",VLOOKUP($A23,GateTab,9,FALSE())),"Incomplete"))) -> Not passed | N23: =IF($A23="","",SUMPRODUCT((Register!$A$6:$A$185=$A23)*(Register!$T$6:$T$185<>"")*(Register!$O$6:$O$185<>"")*(Register!$T$6:$T$185<Register!$O$6:$O$185))) -> 6
A24: =IF('Use cases'!$B$21="","",'Use cases'!$A$21) -> UC17 | B24: =IF($A24="","",'Use cases'!$B$21) -> Lateral movement indicators | C24: =IF($A24="","",'Use cases'!$C$21) -> Network | D24: =IF($A24="","",'Use cases'!$E$21) -> Progressive | E24: =IF($A24="","",IF(COUNTIFS(Register!$A$6:$A$185,$A24,Register!$D$6:$D$185,E$7)>1,"Dup.",IF($C$5="Critical assets (target)",IF(COUNTIFS(Register!$A$6:$A$185,$A24,Register!$D$6:$D$185,E$7,Register!$Q$6:$Q$185,">=0")=0,"",SUMIFS(Register!$Q$6:$Q$185,Register!$A$6:$A$185,$A24,Register!$D$6:$D$185,E$7)),IF($C$5="Released today",IF(COUNTIFS(Register!$A$6:$A$185,$A24,Register!$D$6:$D$185,E$7,Register!$T$6:$T$185,">=0")=0,"",SUMIFS(Register!$T$6:$T$185,Register!$A$6:$A$185,$A24,Register!$D$6:$D$185,E$7)),IF(COUNTIFS(Register!$A$6:$A$185,$A24,Register!$D$6:$D$185,E$7,Register!$O$6:$O$185,">=0")=0,"",SUMIFS(Register!$O$6:$O$185,Register!$A$6:$A$185,$A24,Register!$D$6:$D$185,E$7)))))) -> 1 | F24: =IF($A24="","",IF(COUNTIFS(Register!$A$6:$A$185,$A24,Register!$D$6:$D$185,F$7)>1,"Dup.",IF($C$5="Critical assets (target)",IF(COUNTIFS(Register!$A$6:$A$185,$A24,Register!$D$6:$D$185,F$7,Register!$Q$6:$Q$185,">=0")=0,"",SUMIFS(Register!$Q$6:$Q$185,Register!$A$6:$A$185,$A24,Register!$D$6:$D$185,F$7)),IF($C$5="Released today",IF(COUNTIFS(Register!$A$6:$A$185,$A24,Register!$D$6:$D$185,F$7,Register!$T$6:$T$185,">=0")=0,"",SUMIFS(Register!$T$6:$T$185,Register!$A$6:$A$185,$A24,Register!$D$6:$D$185,F$7)),IF(COUNTIFS(Register!$A$6:$A$185,$A24,Register!$D$6:$D$185,F$7,Register!$O$6:$O$185,">=0")=0,"",SUMIFS(Register!$O$6:$O$185,Register!$A$6:$A$185,$A24,Register!$D$6:$D$185,F$7)))))) -> 1 | G24: =IF($A24="","",IF(COUNTIFS(Register!$A$6:$A$185,$A24,Register!$D$6:$D$185,G$7)>1,"Dup.",IF($C$5="Critical assets (target)",IF(COUNTIFS(Register!$A$6:$A$185,$A24,Register!$D$6:$D$185,G$7,Register!$Q$6:$Q$185,">=0")=0,"",SUMIFS(Register!$Q$6:$Q$185,Register!$A$6:$A$185,$A24,Register!$D$6:$D$185,G$7)),IF($C$5="Released today",IF(COUNTIFS(Register!$A$6:$A$185,$A24,Register!$D$6:$D$185,G$7,Register!$T$6:$T$185,">=0")=0,"",SUMIFS(Register!$T$6:$T$185,Register!$A$6:$A$185,$A24,Register!$D$6:$D$185,G$7)),IF(COUNTIFS(Register!$A$6:$A$185,$A24,Register!$D$6:$D$185,G$7,Register!$O$6:$O$185,">=0")=0,"",SUMIFS(Register!$O$6:$O$185,Register!$A$6:$A$185,$A24,Register!$D$6:$D$185,G$7)))))) -> 2 | H24: =IF($A24="","",IF(COUNTIFS(Register!$A$6:$A$185,$A24,Register!$D$6:$D$185,H$7)>1,"Dup.",IF($C$5="Critical assets (target)",IF(COUNTIFS(Register!$A$6:$A$185,$A24,Register!$D$6:$D$185,H$7,Register!$Q$6:$Q$185,">=0")=0,"",SUMIFS(Register!$Q$6:$Q$185,Register!$A$6:$A$185,$A24,Register!$D$6:$D$185,H$7)),IF($C$5="Released today",IF(COUNTIFS(Register!$A$6:$A$185,$A24,Register!$D$6:$D$185,H$7,Register!$T$6:$T$185,">=0")=0,"",SUMIFS(Register!$T$6:$T$185,Register!$A$6:$A$185,$A24,Register!$D$6:$D$185,H$7)),IF(COUNTIFS(Register!$A$6:$A$185,$A24,Register!$D$6:$D$185,H$7,Register!$O$6:$O$185,">=0")=0,"",SUMIFS(Register!$O$6:$O$185,Register!$A$6:$A$185,$A24,Register!$D$6:$D$185,H$7)))))) -> 1 | I24: =IF($A24="","",IF(COUNTIFS(Register!$A$6:$A$185,$A24,Register!$D$6:$D$185,I$7)>1,"Dup.",IF($C$5="Critical assets (target)",IF(COUNTIFS(Register!$A$6:$A$185,$A24,Register!$D$6:$D$185,I$7,Register!$Q$6:$Q$185,">=0")=0,"",SUMIFS(Register!$Q$6:$Q$185,Register!$A$6:$A$185,$A24,Register!$D$6:$D$185,I$7)),IF($C$5="Released today",IF(COUNTIFS(Register!$A$6:$A$185,$A24,Register!$D$6:$D$185,I$7,Register!$T$6:$T$185,">=0")=0,"",SUMIFS(Register!$T$6:$T$185,Register!$A$6:$A$185,$A24,Register!$D$6:$D$185,I$7)),IF(COUNTIFS(Register!$A$6:$A$185,$A24,Register!$D$6:$D$185,I$7,Register!$O$6:$O$185,">=0")=0,"",SUMIFS(Register!$O$6:$O$185,Register!$A$6:$A$185,$A24,Register!$D$6:$D$185,I$7)))))) -> 1 | J24: =IF($A24="","",IF(COUNTIFS(Register!$A$6:$A$185,$A24,Register!$D$6:$D$185,J$7)>1,"Dup.",IF($C$5="Critical assets (target)",IF(COUNTIFS(Register!$A$6:$A$185,$A24,Register!$D$6:$D$185,J$7,Register!$Q$6:$Q$185,">=0")=0,"",SUMIFS(Register!$Q$6:$Q$185,Register!$A$6:$A$185,$A24,Register!$D$6:$D$185,J$7)),IF($C$5="Released today",IF(COUNTIFS(Register!$A$6:$A$185,$A24,Register!$D$6:$D$185,J$7,Register!$T$6:$T$185,">=0")=0,"",SUMIFS(Register!$T$6:$T$185,Register!$A$6:$A$185,$A24,Register!$D$6:$D$185,J$7)),IF(COUNTIFS(Register!$A$6:$A$185,$A24,Register!$D$6:$D$185,J$7,Register!$O$6:$O$185,">=0")=0,"",SUMIFS(Register!$O$6:$O$185,Register!$A$6:$A$185,$A24,Register!$D$6:$D$185,J$7)))))) -> 1 | K24: =IF($A24="","",IF(COUNT(E24:J24)<6,"Incomplete",IF(AND(ISNUMBER(E24),E24<4),E$7,IF(AND(ISNUMBER(F24),F24<4),F$7,IF(AND(ISNUMBER(G24),G24<4),G$7,IF(AND(ISNUMBER(H24),H24<4),H$7,IF(AND(ISNUMBER(I24),I24<4),I$7,IF(AND(ISNUMBER(J24),J24<4),J$7,"None")))))))) -> Enrich | L24: =IF($A24="","",COUNTIFS(Register!$A$6:$A$185,$A24,Register!$P$6:$P$185,"Above policy*")) -> 0 | M24: =IF($A24="","",IF(COUNTIF('Readiness gate'!$A$7:$A$36,$A24)<>1,"Incomplete",IFERROR(IF(VLOOKUP($A24,GateTab,9,FALSE())="","Incomplete",VLOOKUP($A24,GateTab,9,FALSE())),"Incomplete"))) -> Not passed | N24: =IF($A24="","",SUMPRODUCT((Register!$A$6:$A$185=$A24)*(Register!$T$6:$T$185<>"")*(Register!$O$6:$O$185<>"")*(Register!$T$6:$T$185<Register!$O$6:$O$185))) -> 6
A25: =IF('Use cases'!$B$22="","",'Use cases'!$A$22) -> UC18 | B25: =IF($A25="","",'Use cases'!$B$22) -> DNS tunneling | C25: =IF($A25="","",'Use cases'!$C$22) -> Network | D25: =IF($A25="","",'Use cases'!$E$22) -> Progressive | E25: =IF($A25="","",IF(COUNTIFS(Register!$A$6:$A$185,$A25,Register!$D$6:$D$185,E$7)>1,"Dup.",IF($C$5="Critical assets (target)",IF(COUNTIFS(Register!$A$6:$A$185,$A25,Register!$D$6:$D$185,E$7,Register!$Q$6:$Q$185,">=0")=0,"",SUMIFS(Register!$Q$6:$Q$185,Register!$A$6:$A$185,$A25,Register!$D$6:$D$185,E$7)),IF($C$5="Released today",IF(COUNTIFS(Register!$A$6:$A$185,$A25,Register!$D$6:$D$185,E$7,Register!$T$6:$T$185,">=0")=0,"",SUMIFS(Register!$T$6:$T$185,Register!$A$6:$A$185,$A25,Register!$D$6:$D$185,E$7)),IF(COUNTIFS(Register!$A$6:$A$185,$A25,Register!$D$6:$D$185,E$7,Register!$O$6:$O$185,">=0")=0,"",SUMIFS(Register!$O$6:$O$185,Register!$A$6:$A$185,$A25,Register!$D$6:$D$185,E$7)))))) -> 4 | F25: =IF($A25="","",IF(COUNTIFS(Register!$A$6:$A$185,$A25,Register!$D$6:$D$185,F$7)>1,"Dup.",IF($C$5="Critical assets (target)",IF(COUNTIFS(Register!$A$6:$A$185,$A25,Register!$D$6:$D$185,F$7,Register!$Q$6:$Q$185,">=0")=0,"",SUMIFS(Register!$Q$6:$Q$185,Register!$A$6:$A$185,$A25,Register!$D$6:$D$185,F$7)),IF($C$5="Released today",IF(COUNTIFS(Register!$A$6:$A$185,$A25,Register!$D$6:$D$185,F$7,Register!$T$6:$T$185,">=0")=0,"",SUMIFS(Register!$T$6:$T$185,Register!$A$6:$A$185,$A25,Register!$D$6:$D$185,F$7)),IF(COUNTIFS(Register!$A$6:$A$185,$A25,Register!$D$6:$D$185,F$7,Register!$O$6:$O$185,">=0")=0,"",SUMIFS(Register!$O$6:$O$185,Register!$A$6:$A$185,$A25,Register!$D$6:$D$185,F$7)))))) -> 2 | G25: =IF($A25="","",IF(COUNTIFS(Register!$A$6:$A$185,$A25,Register!$D$6:$D$185,G$7)>1,"Dup.",IF($C$5="Critical assets (target)",IF(COUNTIFS(Register!$A$6:$A$185,$A25,Register!$D$6:$D$185,G$7,Register!$Q$6:$Q$185,">=0")=0,"",SUMIFS(Register!$Q$6:$Q$185,Register!$A$6:$A$185,$A25,Register!$D$6:$D$185,G$7)),IF($C$5="Released today",IF(COUNTIFS(Register!$A$6:$A$185,$A25,Register!$D$6:$D$185,G$7,Register!$T$6:$T$185,">=0")=0,"",SUMIFS(Register!$T$6:$T$185,Register!$A$6:$A$185,$A25,Register!$D$6:$D$185,G$7)),IF(COUNTIFS(Register!$A$6:$A$185,$A25,Register!$D$6:$D$185,G$7,Register!$O$6:$O$185,">=0")=0,"",SUMIFS(Register!$O$6:$O$185,Register!$A$6:$A$185,$A25,Register!$D$6:$D$185,G$7)))))) -> 3 | H25: =IF($A25="","",IF(COUNTIFS(Register!$A$6:$A$185,$A25,Register!$D$6:$D$185,H$7)>1,"Dup.",IF($C$5="Critical assets (target)",IF(COUNTIFS(Register!$A$6:$A$185,$A25,Register!$D$6:$D$185,H$7,Register!$Q$6:$Q$185,">=0")=0,"",SUMIFS(Register!$Q$6:$Q$185,Register!$A$6:$A$185,$A25,Register!$D$6:$D$185,H$7)),IF($C$5="Released today",IF(COUNTIFS(Register!$A$6:$A$185,$A25,Register!$D$6:$D$185,H$7,Register!$T$6:$T$185,">=0")=0,"",SUMIFS(Register!$T$6:$T$185,Register!$A$6:$A$185,$A25,Register!$D$6:$D$185,H$7)),IF(COUNTIFS(Register!$A$6:$A$185,$A25,Register!$D$6:$D$185,H$7,Register!$O$6:$O$185,">=0")=0,"",SUMIFS(Register!$O$6:$O$185,Register!$A$6:$A$185,$A25,Register!$D$6:$D$185,H$7)))))) -> 2 | I25: =IF($A25="","",IF(COUNTIFS(Register!$A$6:$A$185,$A25,Register!$D$6:$D$185,I$7)>1,"Dup.",IF($C$5="Critical assets (target)",IF(COUNTIFS(Register!$A$6:$A$185,$A25,Register!$D$6:$D$185,I$7,Register!$Q$6:$Q$185,">=0")=0,"",SUMIFS(Register!$Q$6:$Q$185,Register!$A$6:$A$185,$A25,Register!$D$6:$D$185,I$7)),IF($C$5="Released today",IF(COUNTIFS(Register!$A$6:$A$185,$A25,Register!$D$6:$D$185,I$7,Register!$T$6:$T$185,">=0")=0,"",SUMIFS(Register!$T$6:$T$185,Register!$A$6:$A$185,$A25,Register!$D$6:$D$185,I$7)),IF(COUNTIFS(Register!$A$6:$A$185,$A25,Register!$D$6:$D$185,I$7,Register!$O$6:$O$185,">=0")=0,"",SUMIFS(Register!$O$6:$O$185,Register!$A$6:$A$185,$A25,Register!$D$6:$D$185,I$7)))))) -> 2 | J25: =IF($A25="","",IF(COUNTIFS(Register!$A$6:$A$185,$A25,Register!$D$6:$D$185,J$7)>1,"Dup.",IF($C$5="Critical assets (target)",IF(COUNTIFS(Register!$A$6:$A$185,$A25,Register!$D$6:$D$185,J$7,Register!$Q$6:$Q$185,">=0")=0,"",SUMIFS(Register!$Q$6:$Q$185,Register!$A$6:$A$185,$A25,Register!$D$6:$D$185,J$7)),IF($C$5="Released today",IF(COUNTIFS(Register!$A$6:$A$185,$A25,Register!$D$6:$D$185,J$7,Register!$T$6:$T$185,">=0")=0,"",SUMIFS(Register!$T$6:$T$185,Register!$A$6:$A$185,$A25,Register!$D$6:$D$185,J$7)),IF(COUNTIFS(Register!$A$6:$A$185,$A25,Register!$D$6:$D$185,J$7,Register!$O$6:$O$185,">=0")=0,"",SUMIFS(Register!$O$6:$O$185,Register!$A$6:$A$185,$A25,Register!$D$6:$D$185,J$7)))))) -> 2 | K25: =IF($A25="","",IF(COUNT(E25:J25)<6,"Incomplete",IF(AND(ISNUMBER(E25),E25<4),E$7,IF(AND(ISNUMBER(F25),F25<4),F$7,IF(AND(ISNUMBER(G25),G25<4),G$7,IF(AND(ISNUMBER(H25),H25<4),H$7,IF(AND(ISNUMBER(I25),I25<4),I$7,IF(AND(ISNUMBER(J25),J25<4),J$7,"None")))))))) -> Triage | L25: =IF($A25="","",COUNTIFS(Register!$A$6:$A$185,$A25,Register!$P$6:$P$185,"Above policy*")) -> 0 | M25: =IF($A25="","",IF(COUNTIF('Readiness gate'!$A$7:$A$36,$A25)<>1,"Incomplete",IFERROR(IF(VLOOKUP($A25,GateTab,9,FALSE())="","Incomplete",VLOOKUP($A25,GateTab,9,FALSE())),"Incomplete"))) -> Passed | N25: =IF($A25="","",SUMPRODUCT((Register!$A$6:$A$185=$A25)*(Register!$T$6:$T$185<>"")*(Register!$O$6:$O$185<>"")*(Register!$T$6:$T$185<Register!$O$6:$O$185))) -> 5
A26: =IF('Use cases'!$B$23="","",'Use cases'!$A$23) -> UC19 | B26: =IF($A26="","",'Use cases'!$B$23) -> Shadow AI data leakage | C26: =IF($A26="","",'Use cases'!$C$23) -> Data | D26: =IF($A26="","",'Use cases'!$E$23) -> Progressive | E26: =IF($A26="","",IF(COUNTIFS(Register!$A$6:$A$185,$A26,Register!$D$6:$D$185,E$7)>1,"Dup.",IF($C$5="Critical assets (target)",IF(COUNTIFS(Register!$A$6:$A$185,$A26,Register!$D$6:$D$185,E$7,Register!$Q$6:$Q$185,">=0")=0,"",SUMIFS(Register!$Q$6:$Q$185,Register!$A$6:$A$185,$A26,Register!$D$6:$D$185,E$7)),IF($C$5="Released today",IF(COUNTIFS(Register!$A$6:$A$185,$A26,Register!$D$6:$D$185,E$7,Register!$T$6:$T$185,">=0")=0,"",SUMIFS(Register!$T$6:$T$185,Register!$A$6:$A$185,$A26,Register!$D$6:$D$185,E$7)),IF(COUNTIFS(Register!$A$6:$A$185,$A26,Register!$D$6:$D$185,E$7,Register!$O$6:$O$185,">=0")=0,"",SUMIFS(Register!$O$6:$O$185,Register!$A$6:$A$185,$A26,Register!$D$6:$D$185,E$7)))))) -> 1 | F26: =IF($A26="","",IF(COUNTIFS(Register!$A$6:$A$185,$A26,Register!$D$6:$D$185,F$7)>1,"Dup.",IF($C$5="Critical assets (target)",IF(COUNTIFS(Register!$A$6:$A$185,$A26,Register!$D$6:$D$185,F$7,Register!$Q$6:$Q$185,">=0")=0,"",SUMIFS(Register!$Q$6:$Q$185,Register!$A$6:$A$185,$A26,Register!$D$6:$D$185,F$7)),IF($C$5="Released today",IF(COUNTIFS(Register!$A$6:$A$185,$A26,Register!$D$6:$D$185,F$7,Register!$T$6:$T$185,">=0")=0,"",SUMIFS(Register!$T$6:$T$185,Register!$A$6:$A$185,$A26,Register!$D$6:$D$185,F$7)),IF(COUNTIFS(Register!$A$6:$A$185,$A26,Register!$D$6:$D$185,F$7,Register!$O$6:$O$185,">=0")=0,"",SUMIFS(Register!$O$6:$O$185,Register!$A$6:$A$185,$A26,Register!$D$6:$D$185,F$7)))))) -> 1 | G26: =IF($A26="","",IF(COUNTIFS(Register!$A$6:$A$185,$A26,Register!$D$6:$D$185,G$7)>1,"Dup.",IF($C$5="Critical assets (target)",IF(COUNTIFS(Register!$A$6:$A$185,$A26,Register!$D$6:$D$185,G$7,Register!$Q$6:$Q$185,">=0")=0,"",SUMIFS(Register!$Q$6:$Q$185,Register!$A$6:$A$185,$A26,Register!$D$6:$D$185,G$7)),IF($C$5="Released today",IF(COUNTIFS(Register!$A$6:$A$185,$A26,Register!$D$6:$D$185,G$7,Register!$T$6:$T$185,">=0")=0,"",SUMIFS(Register!$T$6:$T$185,Register!$A$6:$A$185,$A26,Register!$D$6:$D$185,G$7)),IF(COUNTIFS(Register!$A$6:$A$185,$A26,Register!$D$6:$D$185,G$7,Register!$O$6:$O$185,">=0")=0,"",SUMIFS(Register!$O$6:$O$185,Register!$A$6:$A$185,$A26,Register!$D$6:$D$185,G$7)))))) -> 2 | H26: =IF($A26="","",IF(COUNTIFS(Register!$A$6:$A$185,$A26,Register!$D$6:$D$185,H$7)>1,"Dup.",IF($C$5="Critical assets (target)",IF(COUNTIFS(Register!$A$6:$A$185,$A26,Register!$D$6:$D$185,H$7,Register!$Q$6:$Q$185,">=0")=0,"",SUMIFS(Register!$Q$6:$Q$185,Register!$A$6:$A$185,$A26,Register!$D$6:$D$185,H$7)),IF($C$5="Released today",IF(COUNTIFS(Register!$A$6:$A$185,$A26,Register!$D$6:$D$185,H$7,Register!$T$6:$T$185,">=0")=0,"",SUMIFS(Register!$T$6:$T$185,Register!$A$6:$A$185,$A26,Register!$D$6:$D$185,H$7)),IF(COUNTIFS(Register!$A$6:$A$185,$A26,Register!$D$6:$D$185,H$7,Register!$O$6:$O$185,">=0")=0,"",SUMIFS(Register!$O$6:$O$185,Register!$A$6:$A$185,$A26,Register!$D$6:$D$185,H$7)))))) -> 1 | I26: =IF($A26="","",IF(COUNTIFS(Register!$A$6:$A$185,$A26,Register!$D$6:$D$185,I$7)>1,"Dup.",IF($C$5="Critical assets (target)",IF(COUNTIFS(Register!$A$6:$A$185,$A26,Register!$D$6:$D$185,I$7,Register!$Q$6:$Q$185,">=0")=0,"",SUMIFS(Register!$Q$6:$Q$185,Register!$A$6:$A$185,$A26,Register!$D$6:$D$185,I$7)),IF($C$5="Released today",IF(COUNTIFS(Register!$A$6:$A$185,$A26,Register!$D$6:$D$185,I$7,Register!$T$6:$T$185,">=0")=0,"",SUMIFS(Register!$T$6:$T$185,Register!$A$6:$A$185,$A26,Register!$D$6:$D$185,I$7)),IF(COUNTIFS(Register!$A$6:$A$185,$A26,Register!$D$6:$D$185,I$7,Register!$O$6:$O$185,">=0")=0,"",SUMIFS(Register!$O$6:$O$185,Register!$A$6:$A$185,$A26,Register!$D$6:$D$185,I$7)))))) -> 1 | J26: =IF($A26="","",IF(COUNTIFS(Register!$A$6:$A$185,$A26,Register!$D$6:$D$185,J$7)>1,"Dup.",IF($C$5="Critical assets (target)",IF(COUNTIFS(Register!$A$6:$A$185,$A26,Register!$D$6:$D$185,J$7,Register!$Q$6:$Q$185,">=0")=0,"",SUMIFS(Register!$Q$6:$Q$185,Register!$A$6:$A$185,$A26,Register!$D$6:$D$185,J$7)),IF($C$5="Released today",IF(COUNTIFS(Register!$A$6:$A$185,$A26,Register!$D$6:$D$185,J$7,Register!$T$6:$T$185,">=0")=0,"",SUMIFS(Register!$T$6:$T$185,Register!$A$6:$A$185,$A26,Register!$D$6:$D$185,J$7)),IF(COUNTIFS(Register!$A$6:$A$185,$A26,Register!$D$6:$D$185,J$7,Register!$O$6:$O$185,">=0")=0,"",SUMIFS(Register!$O$6:$O$185,Register!$A$6:$A$185,$A26,Register!$D$6:$D$185,J$7)))))) -> 1 | K26: =IF($A26="","",IF(COUNT(E26:J26)<6,"Incomplete",IF(AND(ISNUMBER(E26),E26<4),E$7,IF(AND(ISNUMBER(F26),F26<4),F$7,IF(AND(ISNUMBER(G26),G26<4),G$7,IF(AND(ISNUMBER(H26),H26<4),H$7,IF(AND(ISNUMBER(I26),I26<4),I$7,IF(AND(ISNUMBER(J26),J26<4),J$7,"None")))))))) -> Enrich | L26: =IF($A26="","",COUNTIFS(Register!$A$6:$A$185,$A26,Register!$P$6:$P$185,"Above policy*")) -> 0 | M26: =IF($A26="","",IF(COUNTIF('Readiness gate'!$A$7:$A$36,$A26)<>1,"Incomplete",IFERROR(IF(VLOOKUP($A26,GateTab,9,FALSE())="","Incomplete",VLOOKUP($A26,GateTab,9,FALSE())),"Incomplete"))) -> Not passed | N26: =IF($A26="","",SUMPRODUCT((Register!$A$6:$A$185=$A26)*(Register!$T$6:$T$185<>"")*(Register!$O$6:$O$185<>"")*(Register!$T$6:$T$185<Register!$O$6:$O$185))) -> 6
A27: =IF('Use cases'!$B$24="","",'Use cases'!$A$24) -> UC20 | B27: =IF($A27="","",'Use cases'!$B$24) -> Supplier compromise signal | C27: =IF($A27="","",'Use cases'!$C$24) -> Third party | D27: =IF($A27="","",'Use cases'!$E$24) -> Conservative | E27: =IF($A27="","",IF(COUNTIFS(Register!$A$6:$A$185,$A27,Register!$D$6:$D$185,E$7)>1,"Dup.",IF($C$5="Critical assets (target)",IF(COUNTIFS(Register!$A$6:$A$185,$A27,Register!$D$6:$D$185,E$7,Register!$Q$6:$Q$185,">=0")=0,"",SUMIFS(Register!$Q$6:$Q$185,Register!$A$6:$A$185,$A27,Register!$D$6:$D$185,E$7)),IF($C$5="Released today",IF(COUNTIFS(Register!$A$6:$A$185,$A27,Register!$D$6:$D$185,E$7,Register!$T$6:$T$185,">=0")=0,"",SUMIFS(Register!$T$6:$T$185,Register!$A$6:$A$185,$A27,Register!$D$6:$D$185,E$7)),IF(COUNTIFS(Register!$A$6:$A$185,$A27,Register!$D$6:$D$185,E$7,Register!$O$6:$O$185,">=0")=0,"",SUMIFS(Register!$O$6:$O$185,Register!$A$6:$A$185,$A27,Register!$D$6:$D$185,E$7)))))) -> 1 | F27: =IF($A27="","",IF(COUNTIFS(Register!$A$6:$A$185,$A27,Register!$D$6:$D$185,F$7)>1,"Dup.",IF($C$5="Critical assets (target)",IF(COUNTIFS(Register!$A$6:$A$185,$A27,Register!$D$6:$D$185,F$7,Register!$Q$6:$Q$185,">=0")=0,"",SUMIFS(Register!$Q$6:$Q$185,Register!$A$6:$A$185,$A27,Register!$D$6:$D$185,F$7)),IF($C$5="Released today",IF(COUNTIFS(Register!$A$6:$A$185,$A27,Register!$D$6:$D$185,F$7,Register!$T$6:$T$185,">=0")=0,"",SUMIFS(Register!$T$6:$T$185,Register!$A$6:$A$185,$A27,Register!$D$6:$D$185,F$7)),IF(COUNTIFS(Register!$A$6:$A$185,$A27,Register!$D$6:$D$185,F$7,Register!$O$6:$O$185,">=0")=0,"",SUMIFS(Register!$O$6:$O$185,Register!$A$6:$A$185,$A27,Register!$D$6:$D$185,F$7)))))) -> 1 | G27: =IF($A27="","",IF(COUNTIFS(Register!$A$6:$A$185,$A27,Register!$D$6:$D$185,G$7)>1,"Dup.",IF($C$5="Critical assets (target)",IF(COUNTIFS(Register!$A$6:$A$185,$A27,Register!$D$6:$D$185,G$7,Register!$Q$6:$Q$185,">=0")=0,"",SUMIFS(Register!$Q$6:$Q$185,Register!$A$6:$A$185,$A27,Register!$D$6:$D$185,G$7)),IF($C$5="Released today",IF(COUNTIFS(Register!$A$6:$A$185,$A27,Register!$D$6:$D$185,G$7,Register!$T$6:$T$185,">=0")=0,"",SUMIFS(Register!$T$6:$T$185,Register!$A$6:$A$185,$A27,Register!$D$6:$D$185,G$7)),IF(COUNTIFS(Register!$A$6:$A$185,$A27,Register!$D$6:$D$185,G$7,Register!$O$6:$O$185,">=0")=0,"",SUMIFS(Register!$O$6:$O$185,Register!$A$6:$A$185,$A27,Register!$D$6:$D$185,G$7)))))) -> 0 | H27: =IF($A27="","",IF(COUNTIFS(Register!$A$6:$A$185,$A27,Register!$D$6:$D$185,H$7)>1,"Dup.",IF($C$5="Critical assets (target)",IF(COUNTIFS(Register!$A$6:$A$185,$A27,Register!$D$6:$D$185,H$7,Register!$Q$6:$Q$185,">=0")=0,"",SUMIFS(Register!$Q$6:$Q$185,Register!$A$6:$A$185,$A27,Register!$D$6:$D$185,H$7)),IF($C$5="Released today",IF(COUNTIFS(Register!$A$6:$A$185,$A27,Register!$D$6:$D$185,H$7,Register!$T$6:$T$185,">=0")=0,"",SUMIFS(Register!$T$6:$T$185,Register!$A$6:$A$185,$A27,Register!$D$6:$D$185,H$7)),IF(COUNTIFS(Register!$A$6:$A$185,$A27,Register!$D$6:$D$185,H$7,Register!$O$6:$O$185,">=0")=0,"",SUMIFS(Register!$O$6:$O$185,Register!$A$6:$A$185,$A27,Register!$D$6:$D$185,H$7)))))) -> 0 | I27: =IF($A27="","",IF(COUNTIFS(Register!$A$6:$A$185,$A27,Register!$D$6:$D$185,I$7)>1,"Dup.",IF($C$5="Critical assets (target)",IF(COUNTIFS(Register!$A$6:$A$185,$A27,Register!$D$6:$D$185,I$7,Register!$Q$6:$Q$185,">=0")=0,"",SUMIFS(Register!$Q$6:$Q$185,Register!$A$6:$A$185,$A27,Register!$D$6:$D$185,I$7)),IF($C$5="Released today",IF(COUNTIFS(Register!$A$6:$A$185,$A27,Register!$D$6:$D$185,I$7,Register!$T$6:$T$185,">=0")=0,"",SUMIFS(Register!$T$6:$T$185,Register!$A$6:$A$185,$A27,Register!$D$6:$D$185,I$7)),IF(COUNTIFS(Register!$A$6:$A$185,$A27,Register!$D$6:$D$185,I$7,Register!$O$6:$O$185,">=0")=0,"",SUMIFS(Register!$O$6:$O$185,Register!$A$6:$A$185,$A27,Register!$D$6:$D$185,I$7)))))) -> 0 | J27: =IF($A27="","",IF(COUNTIFS(Register!$A$6:$A$185,$A27,Register!$D$6:$D$185,J$7)>1,"Dup.",IF($C$5="Critical assets (target)",IF(COUNTIFS(Register!$A$6:$A$185,$A27,Register!$D$6:$D$185,J$7,Register!$Q$6:$Q$185,">=0")=0,"",SUMIFS(Register!$Q$6:$Q$185,Register!$A$6:$A$185,$A27,Register!$D$6:$D$185,J$7)),IF($C$5="Released today",IF(COUNTIFS(Register!$A$6:$A$185,$A27,Register!$D$6:$D$185,J$7,Register!$T$6:$T$185,">=0")=0,"",SUMIFS(Register!$T$6:$T$185,Register!$A$6:$A$185,$A27,Register!$D$6:$D$185,J$7)),IF(COUNTIFS(Register!$A$6:$A$185,$A27,Register!$D$6:$D$185,J$7,Register!$O$6:$O$185,">=0")=0,"",SUMIFS(Register!$O$6:$O$185,Register!$A$6:$A$185,$A27,Register!$D$6:$D$185,J$7)))))) -> 1 | K27: =IF($A27="","",IF(COUNT(E27:J27)<6,"Incomplete",IF(AND(ISNUMBER(E27),E27<4),E$7,IF(AND(ISNUMBER(F27),F27<4),F$7,IF(AND(ISNUMBER(G27),G27<4),G$7,IF(AND(ISNUMBER(H27),H27<4),H$7,IF(AND(ISNUMBER(I27),I27<4),I$7,IF(AND(ISNUMBER(J27),J27<4),J$7,"None")))))))) -> Enrich | L27: =IF($A27="","",COUNTIFS(Register!$A$6:$A$185,$A27,Register!$P$6:$P$185,"Above policy*")) -> 0 | M27: =IF($A27="","",IF(COUNTIF('Readiness gate'!$A$7:$A$36,$A27)<>1,"Incomplete",IFERROR(IF(VLOOKUP($A27,GateTab,9,FALSE())="","Incomplete",VLOOKUP($A27,GateTab,9,FALSE())),"Incomplete"))) -> Not passed | N27: =IF($A27="","",SUMPRODUCT((Register!$A$6:$A$185=$A27)*(Register!$T$6:$T$185<>"")*(Register!$O$6:$O$185<>"")*(Register!$T$6:$T$185<Register!$O$6:$O$185))) -> 5
A28: =IF('Use cases'!$B$25="","",'Use cases'!$A$25) | B28: =IF($A28="","",'Use cases'!$B$25) | C28: =IF($A28="","",'Use cases'!$C$25) | D28: =IF($A28="","",'Use cases'!$E$25) | E28: =IF($A28="","",IF(COUNTIFS(Register!$A$6:$A$185,$A28,Register!$D$6:$D$185,E$7)>1,"Dup.",IF($C$5="Critical assets (target)",IF(COUNTIFS(Register!$A$6:$A$185,$A28,Register!$D$6:$D$185,E$7,Register!$Q$6:$Q$185,">=0")=0,"",SUMIFS(Register!$Q$6:$Q$185,Register!$A$6:$A$185,$A28,Register!$D$6:$D$185,E$7)),IF($C$5="Released today",IF(COUNTIFS(Register!$A$6:$A$185,$A28,Register!$D$6:$D$185,E$7,Register!$T$6:$T$185,">=0")=0,"",SUMIFS(Register!$T$6:$T$185,Register!$A$6:$A$185,$A28,Register!$D$6:$D$185,E$7)),IF(COUNTIFS(Register!$A$6:$A$185,$A28,Register!$D$6:$D$185,E$7,Register!$O$6:$O$185,">=0")=0,"",SUMIFS(Register!$O$6:$O$185,Register!$A$6:$A$185,$A28,Register!$D$6:$D$185,E$7)))))) | F28: =IF($A28="","",IF(COUNTIFS(Register!$A$6:$A$185,$A28,Register!$D$6:$D$185,F$7)>1,"Dup.",IF($C$5="Critical assets (target)",IF(COUNTIFS(Register!$A$6:$A$185,$A28,Register!$D$6:$D$185,F$7,Register!$Q$6:$Q$185,">=0")=0,"",SUMIFS(Register!$Q$6:$Q$185,Register!$A$6:$A$185,$A28,Register!$D$6:$D$185,F$7)),IF($C$5="Released today",IF(COUNTIFS(Register!$A$6:$A$185,$A28,Register!$D$6:$D$185,F$7,Register!$T$6:$T$185,">=0")=0,"",SUMIFS(Register!$T$6:$T$185,Register!$A$6:$A$185,$A28,Register!$D$6:$D$185,F$7)),IF(COUNTIFS(Register!$A$6:$A$185,$A28,Register!$D$6:$D$185,F$7,Register!$O$6:$O$185,">=0")=0,"",SUMIFS(Register!$O$6:$O$185,Register!$A$6:$A$185,$A28,Register!$D$6:$D$185,F$7)))))) | G28: =IF($A28="","",IF(COUNTIFS(Register!$A$6:$A$185,$A28,Register!$D$6:$D$185,G$7)>1,"Dup.",IF($C$5="Critical assets (target)",IF(COUNTIFS(Register!$A$6:$A$185,$A28,Register!$D$6:$D$185,G$7,Register!$Q$6:$Q$185,">=0")=0,"",SUMIFS(Register!$Q$6:$Q$185,Register!$A$6:$A$185,$A28,Register!$D$6:$D$185,G$7)),IF($C$5="Released today",IF(COUNTIFS(Register!$A$6:$A$185,$A28,Register!$D$6:$D$185,G$7,Register!$T$6:$T$185,">=0")=0,"",SUMIFS(Register!$T$6:$T$185,Register!$A$6:$A$185,$A28,Register!$D$6:$D$185,G$7)),IF(COUNTIFS(Register!$A$6:$A$185,$A28,Register!$D$6:$D$185,G$7,Register!$O$6:$O$185,">=0")=0,"",SUMIFS(Register!$O$6:$O$185,Register!$A$6:$A$185,$A28,Register!$D$6:$D$185,G$7)))))) | H28: =IF($A28="","",IF(COUNTIFS(Register!$A$6:$A$185,$A28,Register!$D$6:$D$185,H$7)>1,"Dup.",IF($C$5="Critical assets (target)",IF(COUNTIFS(Register!$A$6:$A$185,$A28,Register!$D$6:$D$185,H$7,Register!$Q$6:$Q$185,">=0")=0,"",SUMIFS(Register!$Q$6:$Q$185,Register!$A$6:$A$185,$A28,Register!$D$6:$D$185,H$7)),IF($C$5="Released today",IF(COUNTIFS(Register!$A$6:$A$185,$A28,Register!$D$6:$D$185,H$7,Register!$T$6:$T$185,">=0")=0,"",SUMIFS(Register!$T$6:$T$185,Register!$A$6:$A$185,$A28,Register!$D$6:$D$185,H$7)),IF(COUNTIFS(Register!$A$6:$A$185,$A28,Register!$D$6:$D$185,H$7,Register!$O$6:$O$185,">=0")=0,"",SUMIFS(Register!$O$6:$O$185,Register!$A$6:$A$185,$A28,Register!$D$6:$D$185,H$7)))))) | I28: =IF($A28="","",IF(COUNTIFS(Register!$A$6:$A$185,$A28,Register!$D$6:$D$185,I$7)>1,"Dup.",IF($C$5="Critical assets (target)",IF(COUNTIFS(Register!$A$6:$A$185,$A28,Register!$D$6:$D$185,I$7,Register!$Q$6:$Q$185,">=0")=0,"",SUMIFS(Register!$Q$6:$Q$185,Register!$A$6:$A$185,$A28,Register!$D$6:$D$185,I$7)),IF($C$5="Released today",IF(COUNTIFS(Register!$A$6:$A$185,$A28,Register!$D$6:$D$185,I$7,Register!$T$6:$T$185,">=0")=0,"",SUMIFS(Register!$T$6:$T$185,Register!$A$6:$A$185,$A28,Register!$D$6:$D$185,I$7)),IF(COUNTIFS(Register!$A$6:$A$185,$A28,Register!$D$6:$D$185,I$7,Register!$O$6:$O$185,">=0")=0,"",SUMIFS(Register!$O$6:$O$185,Register!$A$6:$A$185,$A28,Register!$D$6:$D$185,I$7)))))) | J28: =IF($A28="","",IF(COUNTIFS(Register!$A$6:$A$185,$A28,Register!$D$6:$D$185,J$7)>1,"Dup.",IF($C$5="Critical assets (target)",IF(COUNTIFS(Register!$A$6:$A$185,$A28,Register!$D$6:$D$185,J$7,Register!$Q$6:$Q$185,">=0")=0,"",SUMIFS(Register!$Q$6:$Q$185,Register!$A$6:$A$185,$A28,Register!$D$6:$D$185,J$7)),IF($C$5="Released today",IF(COUNTIFS(Register!$A$6:$A$185,$A28,Register!$D$6:$D$185,J$7,Register!$T$6:$T$185,">=0")=0,"",SUMIFS(Register!$T$6:$T$185,Register!$A$6:$A$185,$A28,Register!$D$6:$D$185,J$7)),IF(COUNTIFS(Register!$A$6:$A$185,$A28,Register!$D$6:$D$185,J$7,Register!$O$6:$O$185,">=0")=0,"",SUMIFS(Register!$O$6:$O$185,Register!$A$6:$A$185,$A28,Register!$D$6:$D$185,J$7)))))) | K28: =IF($A28="","",IF(COUNT(E28:J28)<6,"Incomplete",IF(AND(ISNUMBER(E28),E28<4),E$7,IF(AND(ISNUMBER(F28),F28<4),F$7,IF(AND(ISNUMBER(G28),G28<4),G$7,IF(AND(ISNUMBER(H28),H28<4),H$7,IF(AND(ISNUMBER(I28),I28<4),I$7,IF(AND(ISNUMBER(J28),J28<4),J$7,"None")))))))) | L28: =IF($A28="","",COUNTIFS(Register!$A$6:$A$185,$A28,Register!$P$6:$P$185,"Above policy*")) | M28: =IF($A28="","",IF(COUNTIF('Readiness gate'!$A$7:$A$36,$A28)<>1,"Incomplete",IFERROR(IF(VLOOKUP($A28,GateTab,9,FALSE())="","Incomplete",VLOOKUP($A28,GateTab,9,FALSE())),"Incomplete"))) | N28: =IF($A28="","",SUMPRODUCT((Register!$A$6:$A$185=$A28)*(Register!$T$6:$T$185<>"")*(Register!$O$6:$O$185<>"")*(Register!$T$6:$T$185<Register!$O$6:$O$185)))
A29: =IF('Use cases'!$B$26="","",'Use cases'!$A$26) | B29: =IF($A29="","",'Use cases'!$B$26) | C29: =IF($A29="","",'Use cases'!$C$26) | D29: =IF($A29="","",'Use cases'!$E$26) | E29: =IF($A29="","",IF(COUNTIFS(Register!$A$6:$A$185,$A29,Register!$D$6:$D$185,E$7)>1,"Dup.",IF($C$5="Critical assets (target)",IF(COUNTIFS(Register!$A$6:$A$185,$A29,Register!$D$6:$D$185,E$7,Register!$Q$6:$Q$185,">=0")=0,"",SUMIFS(Register!$Q$6:$Q$185,Register!$A$6:$A$185,$A29,Register!$D$6:$D$185,E$7)),IF($C$5="Released today",IF(COUNTIFS(Register!$A$6:$A$185,$A29,Register!$D$6:$D$185,E$7,Register!$T$6:$T$185,">=0")=0,"",SUMIFS(Register!$T$6:$T$185,Register!$A$6:$A$185,$A29,Register!$D$6:$D$185,E$7)),IF(COUNTIFS(Register!$A$6:$A$185,$A29,Register!$D$6:$D$185,E$7,Register!$O$6:$O$185,">=0")=0,"",SUMIFS(Register!$O$6:$O$185,Register!$A$6:$A$185,$A29,Register!$D$6:$D$185,E$7)))))) | F29: =IF($A29="","",IF(COUNTIFS(Register!$A$6:$A$185,$A29,Register!$D$6:$D$185,F$7)>1,"Dup.",IF($C$5="Critical assets (target)",IF(COUNTIFS(Register!$A$6:$A$185,$A29,Register!$D$6:$D$185,F$7,Register!$Q$6:$Q$185,">=0")=0,"",SUMIFS(Register!$Q$6:$Q$185,Register!$A$6:$A$185,$A29,Register!$D$6:$D$185,F$7)),IF($C$5="Released today",IF(COUNTIFS(Register!$A$6:$A$185,$A29,Register!$D$6:$D$185,F$7,Register!$T$6:$T$185,">=0")=0,"",SUMIFS(Register!$T$6:$T$185,Register!$A$6:$A$185,$A29,Register!$D$6:$D$185,F$7)),IF(COUNTIFS(Register!$A$6:$A$185,$A29,Register!$D$6:$D$185,F$7,Register!$O$6:$O$185,">=0")=0,"",SUMIFS(Register!$O$6:$O$185,Register!$A$6:$A$185,$A29,Register!$D$6:$D$185,F$7)))))) | G29: =IF($A29="","",IF(COUNTIFS(Register!$A$6:$A$185,$A29,Register!$D$6:$D$185,G$7)>1,"Dup.",IF($C$5="Critical assets (target)",IF(COUNTIFS(Register!$A$6:$A$185,$A29,Register!$D$6:$D$185,G$7,Register!$Q$6:$Q$185,">=0")=0,"",SUMIFS(Register!$Q$6:$Q$185,Register!$A$6:$A$185,$A29,Register!$D$6:$D$185,G$7)),IF($C$5="Released today",IF(COUNTIFS(Register!$A$6:$A$185,$A29,Register!$D$6:$D$185,G$7,Register!$T$6:$T$185,">=0")=0,"",SUMIFS(Register!$T$6:$T$185,Register!$A$6:$A$185,$A29,Register!$D$6:$D$185,G$7)),IF(COUNTIFS(Register!$A$6:$A$185,$A29,Register!$D$6:$D$185,G$7,Register!$O$6:$O$185,">=0")=0,"",SUMIFS(Register!$O$6:$O$185,Register!$A$6:$A$185,$A29,Register!$D$6:$D$185,G$7)))))) | H29: =IF($A29="","",IF(COUNTIFS(Register!$A$6:$A$185,$A29,Register!$D$6:$D$185,H$7)>1,"Dup.",IF($C$5="Critical assets (target)",IF(COUNTIFS(Register!$A$6:$A$185,$A29,Register!$D$6:$D$185,H$7,Register!$Q$6:$Q$185,">=0")=0,"",SUMIFS(Register!$Q$6:$Q$185,Register!$A$6:$A$185,$A29,Register!$D$6:$D$185,H$7)),IF($C$5="Released today",IF(COUNTIFS(Register!$A$6:$A$185,$A29,Register!$D$6:$D$185,H$7,Register!$T$6:$T$185,">=0")=0,"",SUMIFS(Register!$T$6:$T$185,Register!$A$6:$A$185,$A29,Register!$D$6:$D$185,H$7)),IF(COUNTIFS(Register!$A$6:$A$185,$A29,Register!$D$6:$D$185,H$7,Register!$O$6:$O$185,">=0")=0,"",SUMIFS(Register!$O$6:$O$185,Register!$A$6:$A$185,$A29,Register!$D$6:$D$185,H$7)))))) | I29: =IF($A29="","",IF(COUNTIFS(Register!$A$6:$A$185,$A29,Register!$D$6:$D$185,I$7)>1,"Dup.",IF($C$5="Critical assets (target)",IF(COUNTIFS(Register!$A$6:$A$185,$A29,Register!$D$6:$D$185,I$7,Register!$Q$6:$Q$185,">=0")=0,"",SUMIFS(Register!$Q$6:$Q$185,Register!$A$6:$A$185,$A29,Register!$D$6:$D$185,I$7)),IF($C$5="Released today",IF(COUNTIFS(Register!$A$6:$A$185,$A29,Register!$D$6:$D$185,I$7,Register!$T$6:$T$185,">=0")=0,"",SUMIFS(Register!$T$6:$T$185,Register!$A$6:$A$185,$A29,Register!$D$6:$D$185,I$7)),IF(COUNTIFS(Register!$A$6:$A$185,$A29,Register!$D$6:$D$185,I$7,Register!$O$6:$O$185,">=0")=0,"",SUMIFS(Register!$O$6:$O$185,Register!$A$6:$A$185,$A29,Register!$D$6:$D$185,I$7)))))) | J29: =IF($A29="","",IF(COUNTIFS(Register!$A$6:$A$185,$A29,Register!$D$6:$D$185,J$7)>1,"Dup.",IF($C$5="Critical assets (target)",IF(COUNTIFS(Register!$A$6:$A$185,$A29,Register!$D$6:$D$185,J$7,Register!$Q$6:$Q$185,">=0")=0,"",SUMIFS(Register!$Q$6:$Q$185,Register!$A$6:$A$185,$A29,Register!$D$6:$D$185,J$7)),IF($C$5="Released today",IF(COUNTIFS(Register!$A$6:$A$185,$A29,Register!$D$6:$D$185,J$7,Register!$T$6:$T$185,">=0")=0,"",SUMIFS(Register!$T$6:$T$185,Register!$A$6:$A$185,$A29,Register!$D$6:$D$185,J$7)),IF(COUNTIFS(Register!$A$6:$A$185,$A29,Register!$D$6:$D$185,J$7,Register!$O$6:$O$185,">=0")=0,"",SUMIFS(Register!$O$6:$O$185,Register!$A$6:$A$185,$A29,Register!$D$6:$D$185,J$7)))))) | K29: =IF($A29="","",IF(COUNT(E29:J29)<6,"Incomplete",IF(AND(ISNUMBER(E29),E29<4),E$7,IF(AND(ISNUMBER(F29),F29<4),F$7,IF(AND(ISNUMBER(G29),G29<4),G$7,IF(AND(ISNUMBER(H29),H29<4),H$7,IF(AND(ISNUMBER(I29),I29<4),I$7,IF(AND(ISNUMBER(J29),J29<4),J$7,"None")))))))) | L29: =IF($A29="","",COUNTIFS(Register!$A$6:$A$185,$A29,Register!$P$6:$P$185,"Above policy*")) | M29: =IF($A29="","",IF(COUNTIF('Readiness gate'!$A$7:$A$36,$A29)<>1,"Incomplete",IFERROR(IF(VLOOKUP($A29,GateTab,9,FALSE())="","Incomplete",VLOOKUP($A29,GateTab,9,FALSE())),"Incomplete"))) | N29: =IF($A29="","",SUMPRODUCT((Register!$A$6:$A$185=$A29)*(Register!$T$6:$T$185<>"")*(Register!$O$6:$O$185<>"")*(Register!$T$6:$T$185<Register!$O$6:$O$185)))
A30: =IF('Use cases'!$B$27="","",'Use cases'!$A$27) | B30: =IF($A30="","",'Use cases'!$B$27) | C30: =IF($A30="","",'Use cases'!$C$27) | D30: =IF($A30="","",'Use cases'!$E$27) | E30: =IF($A30="","",IF(COUNTIFS(Register!$A$6:$A$185,$A30,Register!$D$6:$D$185,E$7)>1,"Dup.",IF($C$5="Critical assets (target)",IF(COUNTIFS(Register!$A$6:$A$185,$A30,Register!$D$6:$D$185,E$7,Register!$Q$6:$Q$185,">=0")=0,"",SUMIFS(Register!$Q$6:$Q$185,Register!$A$6:$A$185,$A30,Register!$D$6:$D$185,E$7)),IF($C$5="Released today",IF(COUNTIFS(Register!$A$6:$A$185,$A30,Register!$D$6:$D$185,E$7,Register!$T$6:$T$185,">=0")=0,"",SUMIFS(Register!$T$6:$T$185,Register!$A$6:$A$185,$A30,Register!$D$6:$D$185,E$7)),IF(COUNTIFS(Register!$A$6:$A$185,$A30,Register!$D$6:$D$185,E$7,Register!$O$6:$O$185,">=0")=0,"",SUMIFS(Register!$O$6:$O$185,Register!$A$6:$A$185,$A30,Register!$D$6:$D$185,E$7)))))) | F30: =IF($A30="","",IF(COUNTIFS(Register!$A$6:$A$185,$A30,Register!$D$6:$D$185,F$7)>1,"Dup.",IF($C$5="Critical assets (target)",IF(COUNTIFS(Register!$A$6:$A$185,$A30,Register!$D$6:$D$185,F$7,Register!$Q$6:$Q$185,">=0")=0,"",SUMIFS(Register!$Q$6:$Q$185,Register!$A$6:$A$185,$A30,Register!$D$6:$D$185,F$7)),IF($C$5="Released today",IF(COUNTIFS(Register!$A$6:$A$185,$A30,Register!$D$6:$D$185,F$7,Register!$T$6:$T$185,">=0")=0,"",SUMIFS(Register!$T$6:$T$185,Register!$A$6:$A$185,$A30,Register!$D$6:$D$185,F$7)),IF(COUNTIFS(Register!$A$6:$A$185,$A30,Register!$D$6:$D$185,F$7,Register!$O$6:$O$185,">=0")=0,"",SUMIFS(Register!$O$6:$O$185,Register!$A$6:$A$185,$A30,Register!$D$6:$D$185,F$7)))))) | G30: =IF($A30="","",IF(COUNTIFS(Register!$A$6:$A$185,$A30,Register!$D$6:$D$185,G$7)>1,"Dup.",IF($C$5="Critical assets (target)",IF(COUNTIFS(Register!$A$6:$A$185,$A30,Register!$D$6:$D$185,G$7,Register!$Q$6:$Q$185,">=0")=0,"",SUMIFS(Register!$Q$6:$Q$185,Register!$A$6:$A$185,$A30,Register!$D$6:$D$185,G$7)),IF($C$5="Released today",IF(COUNTIFS(Register!$A$6:$A$185,$A30,Register!$D$6:$D$185,G$7,Register!$T$6:$T$185,">=0")=0,"",SUMIFS(Register!$T$6:$T$185,Register!$A$6:$A$185,$A30,Register!$D$6:$D$185,G$7)),IF(COUNTIFS(Register!$A$6:$A$185,$A30,Register!$D$6:$D$185,G$7,Register!$O$6:$O$185,">=0")=0,"",SUMIFS(Register!$O$6:$O$185,Register!$A$6:$A$185,$A30,Register!$D$6:$D$185,G$7)))))) | H30: =IF($A30="","",IF(COUNTIFS(Register!$A$6:$A$185,$A30,Register!$D$6:$D$185,H$7)>1,"Dup.",IF($C$5="Critical assets (target)",IF(COUNTIFS(Register!$A$6:$A$185,$A30,Register!$D$6:$D$185,H$7,Register!$Q$6:$Q$185,">=0")=0,"",SUMIFS(Register!$Q$6:$Q$185,Register!$A$6:$A$185,$A30,Register!$D$6:$D$185,H$7)),IF($C$5="Released today",IF(COUNTIFS(Register!$A$6:$A$185,$A30,Register!$D$6:$D$185,H$7,Register!$T$6:$T$185,">=0")=0,"",SUMIFS(Register!$T$6:$T$185,Register!$A$6:$A$185,$A30,Register!$D$6:$D$185,H$7)),IF(COUNTIFS(Register!$A$6:$A$185,$A30,Register!$D$6:$D$185,H$7,Register!$O$6:$O$185,">=0")=0,"",SUMIFS(Register!$O$6:$O$185,Register!$A$6:$A$185,$A30,Register!$D$6:$D$185,H$7)))))) | I30: =IF($A30="","",IF(COUNTIFS(Register!$A$6:$A$185,$A30,Register!$D$6:$D$185,I$7)>1,"Dup.",IF($C$5="Critical assets (target)",IF(COUNTIFS(Register!$A$6:$A$185,$A30,Register!$D$6:$D$185,I$7,Register!$Q$6:$Q$185,">=0")=0,"",SUMIFS(Register!$Q$6:$Q$185,Register!$A$6:$A$185,$A30,Register!$D$6:$D$185,I$7)),IF($C$5="Released today",IF(COUNTIFS(Register!$A$6:$A$185,$A30,Register!$D$6:$D$185,I$7,Register!$T$6:$T$185,">=0")=0,"",SUMIFS(Register!$T$6:$T$185,Register!$A$6:$A$185,$A30,Register!$D$6:$D$185,I$7)),IF(COUNTIFS(Register!$A$6:$A$185,$A30,Register!$D$6:$D$185,I$7,Register!$O$6:$O$185,">=0")=0,"",SUMIFS(Register!$O$6:$O$185,Register!$A$6:$A$185,$A30,Register!$D$6:$D$185,I$7)))))) | J30: =IF($A30="","",IF(COUNTIFS(Register!$A$6:$A$185,$A30,Register!$D$6:$D$185,J$7)>1,"Dup.",IF($C$5="Critical assets (target)",IF(COUNTIFS(Register!$A$6:$A$185,$A30,Register!$D$6:$D$185,J$7,Register!$Q$6:$Q$185,">=0")=0,"",SUMIFS(Register!$Q$6:$Q$185,Register!$A$6:$A$185,$A30,Register!$D$6:$D$185,J$7)),IF($C$5="Released today",IF(COUNTIFS(Register!$A$6:$A$185,$A30,Register!$D$6:$D$185,J$7,Register!$T$6:$T$185,">=0")=0,"",SUMIFS(Register!$T$6:$T$185,Register!$A$6:$A$185,$A30,Register!$D$6:$D$185,J$7)),IF(COUNTIFS(Register!$A$6:$A$185,$A30,Register!$D$6:$D$185,J$7,Register!$O$6:$O$185,">=0")=0,"",SUMIFS(Register!$O$6:$O$185,Register!$A$6:$A$185,$A30,Register!$D$6:$D$185,J$7)))))) | K30: =IF($A30="","",IF(COUNT(E30:J30)<6,"Incomplete",IF(AND(ISNUMBER(E30),E30<4),E$7,IF(AND(ISNUMBER(F30),F30<4),F$7,IF(AND(ISNUMBER(G30),G30<4),G$7,IF(AND(ISNUMBER(H30),H30<4),H$7,IF(AND(ISNUMBER(I30),I30<4),I$7,IF(AND(ISNUMBER(J30),J30<4),J$7,"None")))))))) | L30: =IF($A30="","",COUNTIFS(Register!$A$6:$A$185,$A30,Register!$P$6:$P$185,"Above policy*")) | M30: =IF($A30="","",IF(COUNTIF('Readiness gate'!$A$7:$A$36,$A30)<>1,"Incomplete",IFERROR(IF(VLOOKUP($A30,GateTab,9,FALSE())="","Incomplete",VLOOKUP($A30,GateTab,9,FALSE())),"Incomplete"))) | N30: =IF($A30="","",SUMPRODUCT((Register!$A$6:$A$185=$A30)*(Register!$T$6:$T$185<>"")*(Register!$O$6:$O$185<>"")*(Register!$T$6:$T$185<Register!$O$6:$O$185)))
A31: =IF('Use cases'!$B$28="","",'Use cases'!$A$28) | B31: =IF($A31="","",'Use cases'!$B$28) | C31: =IF($A31="","",'Use cases'!$C$28) | D31: =IF($A31="","",'Use cases'!$E$28) | E31: =IF($A31="","",IF(COUNTIFS(Register!$A$6:$A$185,$A31,Register!$D$6:$D$185,E$7)>1,"Dup.",IF($C$5="Critical assets (target)",IF(COUNTIFS(Register!$A$6:$A$185,$A31,Register!$D$6:$D$185,E$7,Register!$Q$6:$Q$185,">=0")=0,"",SUMIFS(Register!$Q$6:$Q$185,Register!$A$6:$A$185,$A31,Register!$D$6:$D$185,E$7)),IF($C$5="Released today",IF(COUNTIFS(Register!$A$6:$A$185,$A31,Register!$D$6:$D$185,E$7,Register!$T$6:$T$185,">=0")=0,"",SUMIFS(Register!$T$6:$T$185,Register!$A$6:$A$185,$A31,Register!$D$6:$D$185,E$7)),IF(COUNTIFS(Register!$A$6:$A$185,$A31,Register!$D$6:$D$185,E$7,Register!$O$6:$O$185,">=0")=0,"",SUMIFS(Register!$O$6:$O$185,Register!$A$6:$A$185,$A31,Register!$D$6:$D$185,E$7)))))) | F31: =IF($A31="","",IF(COUNTIFS(Register!$A$6:$A$185,$A31,Register!$D$6:$D$185,F$7)>1,"Dup.",IF($C$5="Critical assets (target)",IF(COUNTIFS(Register!$A$6:$A$185,$A31,Register!$D$6:$D$185,F$7,Register!$Q$6:$Q$185,">=0")=0,"",SUMIFS(Register!$Q$6:$Q$185,Register!$A$6:$A$185,$A31,Register!$D$6:$D$185,F$7)),IF($C$5="Released today",IF(COUNTIFS(Register!$A$6:$A$185,$A31,Register!$D$6:$D$185,F$7,Register!$T$6:$T$185,">=0")=0,"",SUMIFS(Register!$T$6:$T$185,Register!$A$6:$A$185,$A31,Register!$D$6:$D$185,F$7)),IF(COUNTIFS(Register!$A$6:$A$185,$A31,Register!$D$6:$D$185,F$7,Register!$O$6:$O$185,">=0")=0,"",SUMIFS(Register!$O$6:$O$185,Register!$A$6:$A$185,$A31,Register!$D$6:$D$185,F$7)))))) | G31: =IF($A31="","",IF(COUNTIFS(Register!$A$6:$A$185,$A31,Register!$D$6:$D$185,G$7)>1,"Dup.",IF($C$5="Critical assets (target)",IF(COUNTIFS(Register!$A$6:$A$185,$A31,Register!$D$6:$D$185,G$7,Register!$Q$6:$Q$185,">=0")=0,"",SUMIFS(Register!$Q$6:$Q$185,Register!$A$6:$A$185,$A31,Register!$D$6:$D$185,G$7)),IF($C$5="Released today",IF(COUNTIFS(Register!$A$6:$A$185,$A31,Register!$D$6:$D$185,G$7,Register!$T$6:$T$185,">=0")=0,"",SUMIFS(Register!$T$6:$T$185,Register!$A$6:$A$185,$A31,Register!$D$6:$D$185,G$7)),IF(COUNTIFS(Register!$A$6:$A$185,$A31,Register!$D$6:$D$185,G$7,Register!$O$6:$O$185,">=0")=0,"",SUMIFS(Register!$O$6:$O$185,Register!$A$6:$A$185,$A31,Register!$D$6:$D$185,G$7)))))) | H31: =IF($A31="","",IF(COUNTIFS(Register!$A$6:$A$185,$A31,Register!$D$6:$D$185,H$7)>1,"Dup.",IF($C$5="Critical assets (target)",IF(COUNTIFS(Register!$A$6:$A$185,$A31,Register!$D$6:$D$185,H$7,Register!$Q$6:$Q$185,">=0")=0,"",SUMIFS(Register!$Q$6:$Q$185,Register!$A$6:$A$185,$A31,Register!$D$6:$D$185,H$7)),IF($C$5="Released today",IF(COUNTIFS(Register!$A$6:$A$185,$A31,Register!$D$6:$D$185,H$7,Register!$T$6:$T$185,">=0")=0,"",SUMIFS(Register!$T$6:$T$185,Register!$A$6:$A$185,$A31,Register!$D$6:$D$185,H$7)),IF(COUNTIFS(Register!$A$6:$A$185,$A31,Register!$D$6:$D$185,H$7,Register!$O$6:$O$185,">=0")=0,"",SUMIFS(Register!$O$6:$O$185,Register!$A$6:$A$185,$A31,Register!$D$6:$D$185,H$7)))))) | I31: =IF($A31="","",IF(COUNTIFS(Register!$A$6:$A$185,$A31,Register!$D$6:$D$185,I$7)>1,"Dup.",IF($C$5="Critical assets (target)",IF(COUNTIFS(Register!$A$6:$A$185,$A31,Register!$D$6:$D$185,I$7,Register!$Q$6:$Q$185,">=0")=0,"",SUMIFS(Register!$Q$6:$Q$185,Register!$A$6:$A$185,$A31,Register!$D$6:$D$185,I$7)),IF($C$5="Released today",IF(COUNTIFS(Register!$A$6:$A$185,$A31,Register!$D$6:$D$185,I$7,Register!$T$6:$T$185,">=0")=0,"",SUMIFS(Register!$T$6:$T$185,Register!$A$6:$A$185,$A31,Register!$D$6:$D$185,I$7)),IF(COUNTIFS(Register!$A$6:$A$185,$A31,Register!$D$6:$D$185,I$7,Register!$O$6:$O$185,">=0")=0,"",SUMIFS(Register!$O$6:$O$185,Register!$A$6:$A$185,$A31,Register!$D$6:$D$185,I$7)))))) | J31: =IF($A31="","",IF(COUNTIFS(Register!$A$6:$A$185,$A31,Register!$D$6:$D$185,J$7)>1,"Dup.",IF($C$5="Critical assets (target)",IF(COUNTIFS(Register!$A$6:$A$185,$A31,Register!$D$6:$D$185,J$7,Register!$Q$6:$Q$185,">=0")=0,"",SUMIFS(Register!$Q$6:$Q$185,Register!$A$6:$A$185,$A31,Register!$D$6:$D$185,J$7)),IF($C$5="Released today",IF(COUNTIFS(Register!$A$6:$A$185,$A31,Register!$D$6:$D$185,J$7,Register!$T$6:$T$185,">=0")=0,"",SUMIFS(Register!$T$6:$T$185,Register!$A$6:$A$185,$A31,Register!$D$6:$D$185,J$7)),IF(COUNTIFS(Register!$A$6:$A$185,$A31,Register!$D$6:$D$185,J$7,Register!$O$6:$O$185,">=0")=0,"",SUMIFS(Register!$O$6:$O$185,Register!$A$6:$A$185,$A31,Register!$D$6:$D$185,J$7)))))) | K31: =IF($A31="","",IF(COUNT(E31:J31)<6,"Incomplete",IF(AND(ISNUMBER(E31),E31<4),E$7,IF(AND(ISNUMBER(F31),F31<4),F$7,IF(AND(ISNUMBER(G31),G31<4),G$7,IF(AND(ISNUMBER(H31),H31<4),H$7,IF(AND(ISNUMBER(I31),I31<4),I$7,IF(AND(ISNUMBER(J31),J31<4),J$7,"None")))))))) | L31: =IF($A31="","",COUNTIFS(Register!$A$6:$A$185,$A31,Register!$P$6:$P$185,"Above policy*")) | M31: =IF($A31="","",IF(COUNTIF('Readiness gate'!$A$7:$A$36,$A31)<>1,"Incomplete",IFERROR(IF(VLOOKUP($A31,GateTab,9,FALSE())="","Incomplete",VLOOKUP($A31,GateTab,9,FALSE())),"Incomplete"))) | N31: =IF($A31="","",SUMPRODUCT((Register!$A$6:$A$185=$A31)*(Register!$T$6:$T$185<>"")*(Register!$O$6:$O$185<>"")*(Register!$T$6:$T$185<Register!$O$6:$O$185)))
A32: =IF('Use cases'!$B$29="","",'Use cases'!$A$29) | B32: =IF($A32="","",'Use cases'!$B$29) | C32: =IF($A32="","",'Use cases'!$C$29) | D32: =IF($A32="","",'Use cases'!$E$29) | E32: =IF($A32="","",IF(COUNTIFS(Register!$A$6:$A$185,$A32,Register!$D$6:$D$185,E$7)>1,"Dup.",IF($C$5="Critical assets (target)",IF(COUNTIFS(Register!$A$6:$A$185,$A32,Register!$D$6:$D$185,E$7,Register!$Q$6:$Q$185,">=0")=0,"",SUMIFS(Register!$Q$6:$Q$185,Register!$A$6:$A$185,$A32,Register!$D$6:$D$185,E$7)),IF($C$5="Released today",IF(COUNTIFS(Register!$A$6:$A$185,$A32,Register!$D$6:$D$185,E$7,Register!$T$6:$T$185,">=0")=0,"",SUMIFS(Register!$T$6:$T$185,Register!$A$6:$A$185,$A32,Register!$D$6:$D$185,E$7)),IF(COUNTIFS(Register!$A$6:$A$185,$A32,Register!$D$6:$D$185,E$7,Register!$O$6:$O$185,">=0")=0,"",SUMIFS(Register!$O$6:$O$185,Register!$A$6:$A$185,$A32,Register!$D$6:$D$185,E$7)))))) | F32: =IF($A32="","",IF(COUNTIFS(Register!$A$6:$A$185,$A32,Register!$D$6:$D$185,F$7)>1,"Dup.",IF($C$5="Critical assets (target)",IF(COUNTIFS(Register!$A$6:$A$185,$A32,Register!$D$6:$D$185,F$7,Register!$Q$6:$Q$185,">=0")=0,"",SUMIFS(Register!$Q$6:$Q$185,Register!$A$6:$A$185,$A32,Register!$D$6:$D$185,F$7)),IF($C$5="Released today",IF(COUNTIFS(Register!$A$6:$A$185,$A32,Register!$D$6:$D$185,F$7,Register!$T$6:$T$185,">=0")=0,"",SUMIFS(Register!$T$6:$T$185,Register!$A$6:$A$185,$A32,Register!$D$6:$D$185,F$7)),IF(COUNTIFS(Register!$A$6:$A$185,$A32,Register!$D$6:$D$185,F$7,Register!$O$6:$O$185,">=0")=0,"",SUMIFS(Register!$O$6:$O$185,Register!$A$6:$A$185,$A32,Register!$D$6:$D$185,F$7)))))) | G32: =IF($A32="","",IF(COUNTIFS(Register!$A$6:$A$185,$A32,Register!$D$6:$D$185,G$7)>1,"Dup.",IF($C$5="Critical assets (target)",IF(COUNTIFS(Register!$A$6:$A$185,$A32,Register!$D$6:$D$185,G$7,Register!$Q$6:$Q$185,">=0")=0,"",SUMIFS(Register!$Q$6:$Q$185,Register!$A$6:$A$185,$A32,Register!$D$6:$D$185,G$7)),IF($C$5="Released today",IF(COUNTIFS(Register!$A$6:$A$185,$A32,Register!$D$6:$D$185,G$7,Register!$T$6:$T$185,">=0")=0,"",SUMIFS(Register!$T$6:$T$185,Register!$A$6:$A$185,$A32,Register!$D$6:$D$185,G$7)),IF(COUNTIFS(Register!$A$6:$A$185,$A32,Register!$D$6:$D$185,G$7,Register!$O$6:$O$185,">=0")=0,"",SUMIFS(Register!$O$6:$O$185,Register!$A$6:$A$185,$A32,Register!$D$6:$D$185,G$7)))))) | H32: =IF($A32="","",IF(COUNTIFS(Register!$A$6:$A$185,$A32,Register!$D$6:$D$185,H$7)>1,"Dup.",IF($C$5="Critical assets (target)",IF(COUNTIFS(Register!$A$6:$A$185,$A32,Register!$D$6:$D$185,H$7,Register!$Q$6:$Q$185,">=0")=0,"",SUMIFS(Register!$Q$6:$Q$185,Register!$A$6:$A$185,$A32,Register!$D$6:$D$185,H$7)),IF($C$5="Released today",IF(COUNTIFS(Register!$A$6:$A$185,$A32,Register!$D$6:$D$185,H$7,Register!$T$6:$T$185,">=0")=0,"",SUMIFS(Register!$T$6:$T$185,Register!$A$6:$A$185,$A32,Register!$D$6:$D$185,H$7)),IF(COUNTIFS(Register!$A$6:$A$185,$A32,Register!$D$6:$D$185,H$7,Register!$O$6:$O$185,">=0")=0,"",SUMIFS(Register!$O$6:$O$185,Register!$A$6:$A$185,$A32,Register!$D$6:$D$185,H$7)))))) | I32: =IF($A32="","",IF(COUNTIFS(Register!$A$6:$A$185,$A32,Register!$D$6:$D$185,I$7)>1,"Dup.",IF($C$5="Critical assets (target)",IF(COUNTIFS(Register!$A$6:$A$185,$A32,Register!$D$6:$D$185,I$7,Register!$Q$6:$Q$185,">=0")=0,"",SUMIFS(Register!$Q$6:$Q$185,Register!$A$6:$A$185,$A32,Register!$D$6:$D$185,I$7)),IF($C$5="Released today",IF(COUNTIFS(Register!$A$6:$A$185,$A32,Register!$D$6:$D$185,I$7,Register!$T$6:$T$185,">=0")=0,"",SUMIFS(Register!$T$6:$T$185,Register!$A$6:$A$185,$A32,Register!$D$6:$D$185,I$7)),IF(COUNTIFS(Register!$A$6:$A$185,$A32,Register!$D$6:$D$185,I$7,Register!$O$6:$O$185,">=0")=0,"",SUMIFS(Register!$O$6:$O$185,Register!$A$6:$A$185,$A32,Register!$D$6:$D$185,I$7)))))) | J32: =IF($A32="","",IF(COUNTIFS(Register!$A$6:$A$185,$A32,Register!$D$6:$D$185,J$7)>1,"Dup.",IF($C$5="Critical assets (target)",IF(COUNTIFS(Register!$A$6:$A$185,$A32,Register!$D$6:$D$185,J$7,Register!$Q$6:$Q$185,">=0")=0,"",SUMIFS(Register!$Q$6:$Q$185,Register!$A$6:$A$185,$A32,Register!$D$6:$D$185,J$7)),IF($C$5="Released today",IF(COUNTIFS(Register!$A$6:$A$185,$A32,Register!$D$6:$D$185,J$7,Register!$T$6:$T$185,">=0")=0,"",SUMIFS(Register!$T$6:$T$185,Register!$A$6:$A$185,$A32,Register!$D$6:$D$185,J$7)),IF(COUNTIFS(Register!$A$6:$A$185,$A32,Register!$D$6:$D$185,J$7,Register!$O$6:$O$185,">=0")=0,"",SUMIFS(Register!$O$6:$O$185,Register!$A$6:$A$185,$A32,Register!$D$6:$D$185,J$7)))))) | K32: =IF($A32="","",IF(COUNT(E32:J32)<6,"Incomplete",IF(AND(ISNUMBER(E32),E32<4),E$7,IF(AND(ISNUMBER(F32),F32<4),F$7,IF(AND(ISNUMBER(G32),G32<4),G$7,IF(AND(ISNUMBER(H32),H32<4),H$7,IF(AND(ISNUMBER(I32),I32<4),I$7,IF(AND(ISNUMBER(J32),J32<4),J$7,"None")))))))) | L32: =IF($A32="","",COUNTIFS(Register!$A$6:$A$185,$A32,Register!$P$6:$P$185,"Above policy*")) | M32: =IF($A32="","",IF(COUNTIF('Readiness gate'!$A$7:$A$36,$A32)<>1,"Incomplete",IFERROR(IF(VLOOKUP($A32,GateTab,9,FALSE())="","Incomplete",VLOOKUP($A32,GateTab,9,FALSE())),"Incomplete"))) | N32: =IF($A32="","",SUMPRODUCT((Register!$A$6:$A$185=$A32)*(Register!$T$6:$T$185<>"")*(Register!$O$6:$O$185<>"")*(Register!$T$6:$T$185<Register!$O$6:$O$185)))
A33: =IF('Use cases'!$B$30="","",'Use cases'!$A$30) | B33: =IF($A33="","",'Use cases'!$B$30) | C33: =IF($A33="","",'Use cases'!$C$30) | D33: =IF($A33="","",'Use cases'!$E$30) | E33: =IF($A33="","",IF(COUNTIFS(Register!$A$6:$A$185,$A33,Register!$D$6:$D$185,E$7)>1,"Dup.",IF($C$5="Critical assets (target)",IF(COUNTIFS(Register!$A$6:$A$185,$A33,Register!$D$6:$D$185,E$7,Register!$Q$6:$Q$185,">=0")=0,"",SUMIFS(Register!$Q$6:$Q$185,Register!$A$6:$A$185,$A33,Register!$D$6:$D$185,E$7)),IF($C$5="Released today",IF(COUNTIFS(Register!$A$6:$A$185,$A33,Register!$D$6:$D$185,E$7,Register!$T$6:$T$185,">=0")=0,"",SUMIFS(Register!$T$6:$T$185,Register!$A$6:$A$185,$A33,Register!$D$6:$D$185,E$7)),IF(COUNTIFS(Register!$A$6:$A$185,$A33,Register!$D$6:$D$185,E$7,Register!$O$6:$O$185,">=0")=0,"",SUMIFS(Register!$O$6:$O$185,Register!$A$6:$A$185,$A33,Register!$D$6:$D$185,E$7)))))) | F33: =IF($A33="","",IF(COUNTIFS(Register!$A$6:$A$185,$A33,Register!$D$6:$D$185,F$7)>1,"Dup.",IF($C$5="Critical assets (target)",IF(COUNTIFS(Register!$A$6:$A$185,$A33,Register!$D$6:$D$185,F$7,Register!$Q$6:$Q$185,">=0")=0,"",SUMIFS(Register!$Q$6:$Q$185,Register!$A$6:$A$185,$A33,Register!$D$6:$D$185,F$7)),IF($C$5="Released today",IF(COUNTIFS(Register!$A$6:$A$185,$A33,Register!$D$6:$D$185,F$7,Register!$T$6:$T$185,">=0")=0,"",SUMIFS(Register!$T$6:$T$185,Register!$A$6:$A$185,$A33,Register!$D$6:$D$185,F$7)),IF(COUNTIFS(Register!$A$6:$A$185,$A33,Register!$D$6:$D$185,F$7,Register!$O$6:$O$185,">=0")=0,"",SUMIFS(Register!$O$6:$O$185,Register!$A$6:$A$185,$A33,Register!$D$6:$D$185,F$7)))))) | G33: =IF($A33="","",IF(COUNTIFS(Register!$A$6:$A$185,$A33,Register!$D$6:$D$185,G$7)>1,"Dup.",IF($C$5="Critical assets (target)",IF(COUNTIFS(Register!$A$6:$A$185,$A33,Register!$D$6:$D$185,G$7,Register!$Q$6:$Q$185,">=0")=0,"",SUMIFS(Register!$Q$6:$Q$185,Register!$A$6:$A$185,$A33,Register!$D$6:$D$185,G$7)),IF($C$5="Released today",IF(COUNTIFS(Register!$A$6:$A$185,$A33,Register!$D$6:$D$185,G$7,Register!$T$6:$T$185,">=0")=0,"",SUMIFS(Register!$T$6:$T$185,Register!$A$6:$A$185,$A33,Register!$D$6:$D$185,G$7)),IF(COUNTIFS(Register!$A$6:$A$185,$A33,Register!$D$6:$D$185,G$7,Register!$O$6:$O$185,">=0")=0,"",SUMIFS(Register!$O$6:$O$185,Register!$A$6:$A$185,$A33,Register!$D$6:$D$185,G$7)))))) | H33: =IF($A33="","",IF(COUNTIFS(Register!$A$6:$A$185,$A33,Register!$D$6:$D$185,H$7)>1,"Dup.",IF($C$5="Critical assets (target)",IF(COUNTIFS(Register!$A$6:$A$185,$A33,Register!$D$6:$D$185,H$7,Register!$Q$6:$Q$185,">=0")=0,"",SUMIFS(Register!$Q$6:$Q$185,Register!$A$6:$A$185,$A33,Register!$D$6:$D$185,H$7)),IF($C$5="Released today",IF(COUNTIFS(Register!$A$6:$A$185,$A33,Register!$D$6:$D$185,H$7,Register!$T$6:$T$185,">=0")=0,"",SUMIFS(Register!$T$6:$T$185,Register!$A$6:$A$185,$A33,Register!$D$6:$D$185,H$7)),IF(COUNTIFS(Register!$A$6:$A$185,$A33,Register!$D$6:$D$185,H$7,Register!$O$6:$O$185,">=0")=0,"",SUMIFS(Register!$O$6:$O$185,Register!$A$6:$A$185,$A33,Register!$D$6:$D$185,H$7)))))) | I33: =IF($A33="","",IF(COUNTIFS(Register!$A$6:$A$185,$A33,Register!$D$6:$D$185,I$7)>1,"Dup.",IF($C$5="Critical assets (target)",IF(COUNTIFS(Register!$A$6:$A$185,$A33,Register!$D$6:$D$185,I$7,Register!$Q$6:$Q$185,">=0")=0,"",SUMIFS(Register!$Q$6:$Q$185,Register!$A$6:$A$185,$A33,Register!$D$6:$D$185,I$7)),IF($C$5="Released today",IF(COUNTIFS(Register!$A$6:$A$185,$A33,Register!$D$6:$D$185,I$7,Register!$T$6:$T$185,">=0")=0,"",SUMIFS(Register!$T$6:$T$185,Register!$A$6:$A$185,$A33,Register!$D$6:$D$185,I$7)),IF(COUNTIFS(Register!$A$6:$A$185,$A33,Register!$D$6:$D$185,I$7,Register!$O$6:$O$185,">=0")=0,"",SUMIFS(Register!$O$6:$O$185,Register!$A$6:$A$185,$A33,Register!$D$6:$D$185,I$7)))))) | J33: =IF($A33="","",IF(COUNTIFS(Register!$A$6:$A$185,$A33,Register!$D$6:$D$185,J$7)>1,"Dup.",IF($C$5="Critical assets (target)",IF(COUNTIFS(Register!$A$6:$A$185,$A33,Register!$D$6:$D$185,J$7,Register!$Q$6:$Q$185,">=0")=0,"",SUMIFS(Register!$Q$6:$Q$185,Register!$A$6:$A$185,$A33,Register!$D$6:$D$185,J$7)),IF($C$5="Released today",IF(COUNTIFS(Register!$A$6:$A$185,$A33,Register!$D$6:$D$185,J$7,Register!$T$6:$T$185,">=0")=0,"",SUMIFS(Register!$T$6:$T$185,Register!$A$6:$A$185,$A33,Register!$D$6:$D$185,J$7)),IF(COUNTIFS(Register!$A$6:$A$185,$A33,Register!$D$6:$D$185,J$7,Register!$O$6:$O$185,">=0")=0,"",SUMIFS(Register!$O$6:$O$185,Register!$A$6:$A$185,$A33,Register!$D$6:$D$185,J$7)))))) | K33: =IF($A33="","",IF(COUNT(E33:J33)<6,"Incomplete",IF(AND(ISNUMBER(E33),E33<4),E$7,IF(AND(ISNUMBER(F33),F33<4),F$7,IF(AND(ISNUMBER(G33),G33<4),G$7,IF(AND(ISNUMBER(H33),H33<4),H$7,IF(AND(ISNUMBER(I33),I33<4),I$7,IF(AND(ISNUMBER(J33),J33<4),J$7,"None")))))))) | L33: =IF($A33="","",COUNTIFS(Register!$A$6:$A$185,$A33,Register!$P$6:$P$185,"Above policy*")) | M33: =IF($A33="","",IF(COUNTIF('Readiness gate'!$A$7:$A$36,$A33)<>1,"Incomplete",IFERROR(IF(VLOOKUP($A33,GateTab,9,FALSE())="","Incomplete",VLOOKUP($A33,GateTab,9,FALSE())),"Incomplete"))) | N33: =IF($A33="","",SUMPRODUCT((Register!$A$6:$A$185=$A33)*(Register!$T$6:$T$185<>"")*(Register!$O$6:$O$185<>"")*(Register!$T$6:$T$185<Register!$O$6:$O$185)))
A34: =IF('Use cases'!$B$31="","",'Use cases'!$A$31) | B34: =IF($A34="","",'Use cases'!$B$31) | C34: =IF($A34="","",'Use cases'!$C$31) | D34: =IF($A34="","",'Use cases'!$E$31) | E34: =IF($A34="","",IF(COUNTIFS(Register!$A$6:$A$185,$A34,Register!$D$6:$D$185,E$7)>1,"Dup.",IF($C$5="Critical assets (target)",IF(COUNTIFS(Register!$A$6:$A$185,$A34,Register!$D$6:$D$185,E$7,Register!$Q$6:$Q$185,">=0")=0,"",SUMIFS(Register!$Q$6:$Q$185,Register!$A$6:$A$185,$A34,Register!$D$6:$D$185,E$7)),IF($C$5="Released today",IF(COUNTIFS(Register!$A$6:$A$185,$A34,Register!$D$6:$D$185,E$7,Register!$T$6:$T$185,">=0")=0,"",SUMIFS(Register!$T$6:$T$185,Register!$A$6:$A$185,$A34,Register!$D$6:$D$185,E$7)),IF(COUNTIFS(Register!$A$6:$A$185,$A34,Register!$D$6:$D$185,E$7,Register!$O$6:$O$185,">=0")=0,"",SUMIFS(Register!$O$6:$O$185,Register!$A$6:$A$185,$A34,Register!$D$6:$D$185,E$7)))))) | F34: =IF($A34="","",IF(COUNTIFS(Register!$A$6:$A$185,$A34,Register!$D$6:$D$185,F$7)>1,"Dup.",IF($C$5="Critical assets (target)",IF(COUNTIFS(Register!$A$6:$A$185,$A34,Register!$D$6:$D$185,F$7,Register!$Q$6:$Q$185,">=0")=0,"",SUMIFS(Register!$Q$6:$Q$185,Register!$A$6:$A$185,$A34,Register!$D$6:$D$185,F$7)),IF($C$5="Released today",IF(COUNTIFS(Register!$A$6:$A$185,$A34,Register!$D$6:$D$185,F$7,Register!$T$6:$T$185,">=0")=0,"",SUMIFS(Register!$T$6:$T$185,Register!$A$6:$A$185,$A34,Register!$D$6:$D$185,F$7)),IF(COUNTIFS(Register!$A$6:$A$185,$A34,Register!$D$6:$D$185,F$7,Register!$O$6:$O$185,">=0")=0,"",SUMIFS(Register!$O$6:$O$185,Register!$A$6:$A$185,$A34,Register!$D$6:$D$185,F$7)))))) | G34: =IF($A34="","",IF(COUNTIFS(Register!$A$6:$A$185,$A34,Register!$D$6:$D$185,G$7)>1,"Dup.",IF($C$5="Critical assets (target)",IF(COUNTIFS(Register!$A$6:$A$185,$A34,Register!$D$6:$D$185,G$7,Register!$Q$6:$Q$185,">=0")=0,"",SUMIFS(Register!$Q$6:$Q$185,Register!$A$6:$A$185,$A34,Register!$D$6:$D$185,G$7)),IF($C$5="Released today",IF(COUNTIFS(Register!$A$6:$A$185,$A34,Register!$D$6:$D$185,G$7,Register!$T$6:$T$185,">=0")=0,"",SUMIFS(Register!$T$6:$T$185,Register!$A$6:$A$185,$A34,Register!$D$6:$D$185,G$7)),IF(COUNTIFS(Register!$A$6:$A$185,$A34,Register!$D$6:$D$185,G$7,Register!$O$6:$O$185,">=0")=0,"",SUMIFS(Register!$O$6:$O$185,Register!$A$6:$A$185,$A34,Register!$D$6:$D$185,G$7)))))) | H34: =IF($A34="","",IF(COUNTIFS(Register!$A$6:$A$185,$A34,Register!$D$6:$D$185,H$7)>1,"Dup.",IF($C$5="Critical assets (target)",IF(COUNTIFS(Register!$A$6:$A$185,$A34,Register!$D$6:$D$185,H$7,Register!$Q$6:$Q$185,">=0")=0,"",SUMIFS(Register!$Q$6:$Q$185,Register!$A$6:$A$185,$A34,Register!$D$6:$D$185,H$7)),IF($C$5="Released today",IF(COUNTIFS(Register!$A$6:$A$185,$A34,Register!$D$6:$D$185,H$7,Register!$T$6:$T$185,">=0")=0,"",SUMIFS(Register!$T$6:$T$185,Register!$A$6:$A$185,$A34,Register!$D$6:$D$185,H$7)),IF(COUNTIFS(Register!$A$6:$A$185,$A34,Register!$D$6:$D$185,H$7,Register!$O$6:$O$185,">=0")=0,"",SUMIFS(Register!$O$6:$O$185,Register!$A$6:$A$185,$A34,Register!$D$6:$D$185,H$7)))))) | I34: =IF($A34="","",IF(COUNTIFS(Register!$A$6:$A$185,$A34,Register!$D$6:$D$185,I$7)>1,"Dup.",IF($C$5="Critical assets (target)",IF(COUNTIFS(Register!$A$6:$A$185,$A34,Register!$D$6:$D$185,I$7,Register!$Q$6:$Q$185,">=0")=0,"",SUMIFS(Register!$Q$6:$Q$185,Register!$A$6:$A$185,$A34,Register!$D$6:$D$185,I$7)),IF($C$5="Released today",IF(COUNTIFS(Register!$A$6:$A$185,$A34,Register!$D$6:$D$185,I$7,Register!$T$6:$T$185,">=0")=0,"",SUMIFS(Register!$T$6:$T$185,Register!$A$6:$A$185,$A34,Register!$D$6:$D$185,I$7)),IF(COUNTIFS(Register!$A$6:$A$185,$A34,Register!$D$6:$D$185,I$7,Register!$O$6:$O$185,">=0")=0,"",SUMIFS(Register!$O$6:$O$185,Register!$A$6:$A$185,$A34,Register!$D$6:$D$185,I$7)))))) | J34: =IF($A34="","",IF(COUNTIFS(Register!$A$6:$A$185,$A34,Register!$D$6:$D$185,J$7)>1,"Dup.",IF($C$5="Critical assets (target)",IF(COUNTIFS(Register!$A$6:$A$185,$A34,Register!$D$6:$D$185,J$7,Register!$Q$6:$Q$185,">=0")=0,"",SUMIFS(Register!$Q$6:$Q$185,Register!$A$6:$A$185,$A34,Register!$D$6:$D$185,J$7)),IF($C$5="Released today",IF(COUNTIFS(Register!$A$6:$A$185,$A34,Register!$D$6:$D$185,J$7,Register!$T$6:$T$185,">=0")=0,"",SUMIFS(Register!$T$6:$T$185,Register!$A$6:$A$185,$A34,Register!$D$6:$D$185,J$7)),IF(COUNTIFS(Register!$A$6:$A$185,$A34,Register!$D$6:$D$185,J$7,Register!$O$6:$O$185,">=0")=0,"",SUMIFS(Register!$O$6:$O$185,Register!$A$6:$A$185,$A34,Register!$D$6:$D$185,J$7)))))) | K34: =IF($A34="","",IF(COUNT(E34:J34)<6,"Incomplete",IF(AND(ISNUMBER(E34),E34<4),E$7,IF(AND(ISNUMBER(F34),F34<4),F$7,IF(AND(ISNUMBER(G34),G34<4),G$7,IF(AND(ISNUMBER(H34),H34<4),H$7,IF(AND(ISNUMBER(I34),I34<4),I$7,IF(AND(ISNUMBER(J34),J34<4),J$7,"None")))))))) | L34: =IF($A34="","",COUNTIFS(Register!$A$6:$A$185,$A34,Register!$P$6:$P$185,"Above policy*")) | M34: =IF($A34="","",IF(COUNTIF('Readiness gate'!$A$7:$A$36,$A34)<>1,"Incomplete",IFERROR(IF(VLOOKUP($A34,GateTab,9,FALSE())="","Incomplete",VLOOKUP($A34,GateTab,9,FALSE())),"Incomplete"))) | N34: =IF($A34="","",SUMPRODUCT((Register!$A$6:$A$185=$A34)*(Register!$T$6:$T$185<>"")*(Register!$O$6:$O$185<>"")*(Register!$T$6:$T$185<Register!$O$6:$O$185)))
A35: =IF('Use cases'!$B$32="","",'Use cases'!$A$32) | B35: =IF($A35="","",'Use cases'!$B$32) | C35: =IF($A35="","",'Use cases'!$C$32) | D35: =IF($A35="","",'Use cases'!$E$32) | E35: =IF($A35="","",IF(COUNTIFS(Register!$A$6:$A$185,$A35,Register!$D$6:$D$185,E$7)>1,"Dup.",IF($C$5="Critical assets (target)",IF(COUNTIFS(Register!$A$6:$A$185,$A35,Register!$D$6:$D$185,E$7,Register!$Q$6:$Q$185,">=0")=0,"",SUMIFS(Register!$Q$6:$Q$185,Register!$A$6:$A$185,$A35,Register!$D$6:$D$185,E$7)),IF($C$5="Released today",IF(COUNTIFS(Register!$A$6:$A$185,$A35,Register!$D$6:$D$185,E$7,Register!$T$6:$T$185,">=0")=0,"",SUMIFS(Register!$T$6:$T$185,Register!$A$6:$A$185,$A35,Register!$D$6:$D$185,E$7)),IF(COUNTIFS(Register!$A$6:$A$185,$A35,Register!$D$6:$D$185,E$7,Register!$O$6:$O$185,">=0")=0,"",SUMIFS(Register!$O$6:$O$185,Register!$A$6:$A$185,$A35,Register!$D$6:$D$185,E$7)))))) | F35: =IF($A35="","",IF(COUNTIFS(Register!$A$6:$A$185,$A35,Register!$D$6:$D$185,F$7)>1,"Dup.",IF($C$5="Critical assets (target)",IF(COUNTIFS(Register!$A$6:$A$185,$A35,Register!$D$6:$D$185,F$7,Register!$Q$6:$Q$185,">=0")=0,"",SUMIFS(Register!$Q$6:$Q$185,Register!$A$6:$A$185,$A35,Register!$D$6:$D$185,F$7)),IF($C$5="Released today",IF(COUNTIFS(Register!$A$6:$A$185,$A35,Register!$D$6:$D$185,F$7,Register!$T$6:$T$185,">=0")=0,"",SUMIFS(Register!$T$6:$T$185,Register!$A$6:$A$185,$A35,Register!$D$6:$D$185,F$7)),IF(COUNTIFS(Register!$A$6:$A$185,$A35,Register!$D$6:$D$185,F$7,Register!$O$6:$O$185,">=0")=0,"",SUMIFS(Register!$O$6:$O$185,Register!$A$6:$A$185,$A35,Register!$D$6:$D$185,F$7)))))) | G35: =IF($A35="","",IF(COUNTIFS(Register!$A$6:$A$185,$A35,Register!$D$6:$D$185,G$7)>1,"Dup.",IF($C$5="Critical assets (target)",IF(COUNTIFS(Register!$A$6:$A$185,$A35,Register!$D$6:$D$185,G$7,Register!$Q$6:$Q$185,">=0")=0,"",SUMIFS(Register!$Q$6:$Q$185,Register!$A$6:$A$185,$A35,Register!$D$6:$D$185,G$7)),IF($C$5="Released today",IF(COUNTIFS(Register!$A$6:$A$185,$A35,Register!$D$6:$D$185,G$7,Register!$T$6:$T$185,">=0")=0,"",SUMIFS(Register!$T$6:$T$185,Register!$A$6:$A$185,$A35,Register!$D$6:$D$185,G$7)),IF(COUNTIFS(Register!$A$6:$A$185,$A35,Register!$D$6:$D$185,G$7,Register!$O$6:$O$185,">=0")=0,"",SUMIFS(Register!$O$6:$O$185,Register!$A$6:$A$185,$A35,Register!$D$6:$D$185,G$7)))))) | H35: =IF($A35="","",IF(COUNTIFS(Register!$A$6:$A$185,$A35,Register!$D$6:$D$185,H$7)>1,"Dup.",IF($C$5="Critical assets (target)",IF(COUNTIFS(Register!$A$6:$A$185,$A35,Register!$D$6:$D$185,H$7,Register!$Q$6:$Q$185,">=0")=0,"",SUMIFS(Register!$Q$6:$Q$185,Register!$A$6:$A$185,$A35,Register!$D$6:$D$185,H$7)),IF($C$5="Released today",IF(COUNTIFS(Register!$A$6:$A$185,$A35,Register!$D$6:$D$185,H$7,Register!$T$6:$T$185,">=0")=0,"",SUMIFS(Register!$T$6:$T$185,Register!$A$6:$A$185,$A35,Register!$D$6:$D$185,H$7)),IF(COUNTIFS(Register!$A$6:$A$185,$A35,Register!$D$6:$D$185,H$7,Register!$O$6:$O$185,">=0")=0,"",SUMIFS(Register!$O$6:$O$185,Register!$A$6:$A$185,$A35,Register!$D$6:$D$185,H$7)))))) | I35: =IF($A35="","",IF(COUNTIFS(Register!$A$6:$A$185,$A35,Register!$D$6:$D$185,I$7)>1,"Dup.",IF($C$5="Critical assets (target)",IF(COUNTIFS(Register!$A$6:$A$185,$A35,Register!$D$6:$D$185,I$7,Register!$Q$6:$Q$185,">=0")=0,"",SUMIFS(Register!$Q$6:$Q$185,Register!$A$6:$A$185,$A35,Register!$D$6:$D$185,I$7)),IF($C$5="Released today",IF(COUNTIFS(Register!$A$6:$A$185,$A35,Register!$D$6:$D$185,I$7,Register!$T$6:$T$185,">=0")=0,"",SUMIFS(Register!$T$6:$T$185,Register!$A$6:$A$185,$A35,Register!$D$6:$D$185,I$7)),IF(COUNTIFS(Register!$A$6:$A$185,$A35,Register!$D$6:$D$185,I$7,Register!$O$6:$O$185,">=0")=0,"",SUMIFS(Register!$O$6:$O$185,Register!$A$6:$A$185,$A35,Register!$D$6:$D$185,I$7)))))) | J35: =IF($A35="","",IF(COUNTIFS(Register!$A$6:$A$185,$A35,Register!$D$6:$D$185,J$7)>1,"Dup.",IF($C$5="Critical assets (target)",IF(COUNTIFS(Register!$A$6:$A$185,$A35,Register!$D$6:$D$185,J$7,Register!$Q$6:$Q$185,">=0")=0,"",SUMIFS(Register!$Q$6:$Q$185,Register!$A$6:$A$185,$A35,Register!$D$6:$D$185,J$7)),IF($C$5="Released today",IF(COUNTIFS(Register!$A$6:$A$185,$A35,Register!$D$6:$D$185,J$7,Register!$T$6:$T$185,">=0")=0,"",SUMIFS(Register!$T$6:$T$185,Register!$A$6:$A$185,$A35,Register!$D$6:$D$185,J$7)),IF(COUNTIFS(Register!$A$6:$A$185,$A35,Register!$D$6:$D$185,J$7,Register!$O$6:$O$185,">=0")=0,"",SUMIFS(Register!$O$6:$O$185,Register!$A$6:$A$185,$A35,Register!$D$6:$D$185,J$7)))))) | K35: =IF($A35="","",IF(COUNT(E35:J35)<6,"Incomplete",IF(AND(ISNUMBER(E35),E35<4),E$7,IF(AND(ISNUMBER(F35),F35<4),F$7,IF(AND(ISNUMBER(G35),G35<4),G$7,IF(AND(ISNUMBER(H35),H35<4),H$7,IF(AND(ISNUMBER(I35),I35<4),I$7,IF(AND(ISNUMBER(J35),J35<4),J$7,"None")))))))) | L35: =IF($A35="","",COUNTIFS(Register!$A$6:$A$185,$A35,Register!$P$6:$P$185,"Above policy*")) | M35: =IF($A35="","",IF(COUNTIF('Readiness gate'!$A$7:$A$36,$A35)<>1,"Incomplete",IFERROR(IF(VLOOKUP($A35,GateTab,9,FALSE())="","Incomplete",VLOOKUP($A35,GateTab,9,FALSE())),"Incomplete"))) | N35: =IF($A35="","",SUMPRODUCT((Register!$A$6:$A$185=$A35)*(Register!$T$6:$T$185<>"")*(Register!$O$6:$O$185<>"")*(Register!$T$6:$T$185<Register!$O$6:$O$185)))
A36: =IF('Use cases'!$B$33="","",'Use cases'!$A$33) | B36: =IF($A36="","",'Use cases'!$B$33) | C36: =IF($A36="","",'Use cases'!$C$33) | D36: =IF($A36="","",'Use cases'!$E$33) | E36: =IF($A36="","",IF(COUNTIFS(Register!$A$6:$A$185,$A36,Register!$D$6:$D$185,E$7)>1,"Dup.",IF($C$5="Critical assets (target)",IF(COUNTIFS(Register!$A$6:$A$185,$A36,Register!$D$6:$D$185,E$7,Register!$Q$6:$Q$185,">=0")=0,"",SUMIFS(Register!$Q$6:$Q$185,Register!$A$6:$A$185,$A36,Register!$D$6:$D$185,E$7)),IF($C$5="Released today",IF(COUNTIFS(Register!$A$6:$A$185,$A36,Register!$D$6:$D$185,E$7,Register!$T$6:$T$185,">=0")=0,"",SUMIFS(Register!$T$6:$T$185,Register!$A$6:$A$185,$A36,Register!$D$6:$D$185,E$7)),IF(COUNTIFS(Register!$A$6:$A$185,$A36,Register!$D$6:$D$185,E$7,Register!$O$6:$O$185,">=0")=0,"",SUMIFS(Register!$O$6:$O$185,Register!$A$6:$A$185,$A36,Register!$D$6:$D$185,E$7)))))) | F36: =IF($A36="","",IF(COUNTIFS(Register!$A$6:$A$185,$A36,Register!$D$6:$D$185,F$7)>1,"Dup.",IF($C$5="Critical assets (target)",IF(COUNTIFS(Register!$A$6:$A$185,$A36,Register!$D$6:$D$185,F$7,Register!$Q$6:$Q$185,">=0")=0,"",SUMIFS(Register!$Q$6:$Q$185,Register!$A$6:$A$185,$A36,Register!$D$6:$D$185,F$7)),IF($C$5="Released today",IF(COUNTIFS(Register!$A$6:$A$185,$A36,Register!$D$6:$D$185,F$7,Register!$T$6:$T$185,">=0")=0,"",SUMIFS(Register!$T$6:$T$185,Register!$A$6:$A$185,$A36,Register!$D$6:$D$185,F$7)),IF(COUNTIFS(Register!$A$6:$A$185,$A36,Register!$D$6:$D$185,F$7,Register!$O$6:$O$185,">=0")=0,"",SUMIFS(Register!$O$6:$O$185,Register!$A$6:$A$185,$A36,Register!$D$6:$D$185,F$7)))))) | G36: =IF($A36="","",IF(COUNTIFS(Register!$A$6:$A$185,$A36,Register!$D$6:$D$185,G$7)>1,"Dup.",IF($C$5="Critical assets (target)",IF(COUNTIFS(Register!$A$6:$A$185,$A36,Register!$D$6:$D$185,G$7,Register!$Q$6:$Q$185,">=0")=0,"",SUMIFS(Register!$Q$6:$Q$185,Register!$A$6:$A$185,$A36,Register!$D$6:$D$185,G$7)),IF($C$5="Released today",IF(COUNTIFS(Register!$A$6:$A$185,$A36,Register!$D$6:$D$185,G$7,Register!$T$6:$T$185,">=0")=0,"",SUMIFS(Register!$T$6:$T$185,Register!$A$6:$A$185,$A36,Register!$D$6:$D$185,G$7)),IF(COUNTIFS(Register!$A$6:$A$185,$A36,Register!$D$6:$D$185,G$7,Register!$O$6:$O$185,">=0")=0,"",SUMIFS(Register!$O$6:$O$185,Register!$A$6:$A$185,$A36,Register!$D$6:$D$185,G$7)))))) | H36: =IF($A36="","",IF(COUNTIFS(Register!$A$6:$A$185,$A36,Register!$D$6:$D$185,H$7)>1,"Dup.",IF($C$5="Critical assets (target)",IF(COUNTIFS(Register!$A$6:$A$185,$A36,Register!$D$6:$D$185,H$7,Register!$Q$6:$Q$185,">=0")=0,"",SUMIFS(Register!$Q$6:$Q$185,Register!$A$6:$A$185,$A36,Register!$D$6:$D$185,H$7)),IF($C$5="Released today",IF(COUNTIFS(Register!$A$6:$A$185,$A36,Register!$D$6:$D$185,H$7,Register!$T$6:$T$185,">=0")=0,"",SUMIFS(Register!$T$6:$T$185,Register!$A$6:$A$185,$A36,Register!$D$6:$D$185,H$7)),IF(COUNTIFS(Register!$A$6:$A$185,$A36,Register!$D$6:$D$185,H$7,Register!$O$6:$O$185,">=0")=0,"",SUMIFS(Register!$O$6:$O$185,Register!$A$6:$A$185,$A36,Register!$D$6:$D$185,H$7)))))) | I36: =IF($A36="","",IF(COUNTIFS(Register!$A$6:$A$185,$A36,Register!$D$6:$D$185,I$7)>1,"Dup.",IF($C$5="Critical assets (target)",IF(COUNTIFS(Register!$A$6:$A$185,$A36,Register!$D$6:$D$185,I$7,Register!$Q$6:$Q$185,">=0")=0,"",SUMIFS(Register!$Q$6:$Q$185,Register!$A$6:$A$185,$A36,Register!$D$6:$D$185,I$7)),IF($C$5="Released today",IF(COUNTIFS(Register!$A$6:$A$185,$A36,Register!$D$6:$D$185,I$7,Register!$T$6:$T$185,">=0")=0,"",SUMIFS(Register!$T$6:$T$185,Register!$A$6:$A$185,$A36,Register!$D$6:$D$185,I$7)),IF(COUNTIFS(Register!$A$6:$A$185,$A36,Register!$D$6:$D$185,I$7,Register!$O$6:$O$185,">=0")=0,"",SUMIFS(Register!$O$6:$O$185,Register!$A$6:$A$185,$A36,Register!$D$6:$D$185,I$7)))))) | J36: =IF($A36="","",IF(COUNTIFS(Register!$A$6:$A$185,$A36,Register!$D$6:$D$185,J$7)>1,"Dup.",IF($C$5="Critical assets (target)",IF(COUNTIFS(Register!$A$6:$A$185,$A36,Register!$D$6:$D$185,J$7,Register!$Q$6:$Q$185,">=0")=0,"",SUMIFS(Register!$Q$6:$Q$185,Register!$A$6:$A$185,$A36,Register!$D$6:$D$185,J$7)),IF($C$5="Released today",IF(COUNTIFS(Register!$A$6:$A$185,$A36,Register!$D$6:$D$185,J$7,Register!$T$6:$T$185,">=0")=0,"",SUMIFS(Register!$T$6:$T$185,Register!$A$6:$A$185,$A36,Register!$D$6:$D$185,J$7)),IF(COUNTIFS(Register!$A$6:$A$185,$A36,Register!$D$6:$D$185,J$7,Register!$O$6:$O$185,">=0")=0,"",SUMIFS(Register!$O$6:$O$185,Register!$A$6:$A$185,$A36,Register!$D$6:$D$185,J$7)))))) | K36: =IF($A36="","",IF(COUNT(E36:J36)<6,"Incomplete",IF(AND(ISNUMBER(E36),E36<4),E$7,IF(AND(ISNUMBER(F36),F36<4),F$7,IF(AND(ISNUMBER(G36),G36<4),G$7,IF(AND(ISNUMBER(H36),H36<4),H$7,IF(AND(ISNUMBER(I36),I36<4),I$7,IF(AND(ISNUMBER(J36),J36<4),J$7,"None")))))))) | L36: =IF($A36="","",COUNTIFS(Register!$A$6:$A$185,$A36,Register!$P$6:$P$185,"Above policy*")) | M36: =IF($A36="","",IF(COUNTIF('Readiness gate'!$A$7:$A$36,$A36)<>1,"Incomplete",IFERROR(IF(VLOOKUP($A36,GateTab,9,FALSE())="","Incomplete",VLOOKUP($A36,GateTab,9,FALSE())),"Incomplete"))) | N36: =IF($A36="","",SUMPRODUCT((Register!$A$6:$A$185=$A36)*(Register!$T$6:$T$185<>"")*(Register!$O$6:$O$185<>"")*(Register!$T$6:$T$185<Register!$O$6:$O$185)))
A37: =IF('Use cases'!$B$34="","",'Use cases'!$A$34) | B37: =IF($A37="","",'Use cases'!$B$34) | C37: =IF($A37="","",'Use cases'!$C$34) | D37: =IF($A37="","",'Use cases'!$E$34) | E37: =IF($A37="","",IF(COUNTIFS(Register!$A$6:$A$185,$A37,Register!$D$6:$D$185,E$7)>1,"Dup.",IF($C$5="Critical assets (target)",IF(COUNTIFS(Register!$A$6:$A$185,$A37,Register!$D$6:$D$185,E$7,Register!$Q$6:$Q$185,">=0")=0,"",SUMIFS(Register!$Q$6:$Q$185,Register!$A$6:$A$185,$A37,Register!$D$6:$D$185,E$7)),IF($C$5="Released today",IF(COUNTIFS(Register!$A$6:$A$185,$A37,Register!$D$6:$D$185,E$7,Register!$T$6:$T$185,">=0")=0,"",SUMIFS(Register!$T$6:$T$185,Register!$A$6:$A$185,$A37,Register!$D$6:$D$185,E$7)),IF(COUNTIFS(Register!$A$6:$A$185,$A37,Register!$D$6:$D$185,E$7,Register!$O$6:$O$185,">=0")=0,"",SUMIFS(Register!$O$6:$O$185,Register!$A$6:$A$185,$A37,Register!$D$6:$D$185,E$7)))))) | F37: =IF($A37="","",IF(COUNTIFS(Register!$A$6:$A$185,$A37,Register!$D$6:$D$185,F$7)>1,"Dup.",IF($C$5="Critical assets (target)",IF(COUNTIFS(Register!$A$6:$A$185,$A37,Register!$D$6:$D$185,F$7,Register!$Q$6:$Q$185,">=0")=0,"",SUMIFS(Register!$Q$6:$Q$185,Register!$A$6:$A$185,$A37,Register!$D$6:$D$185,F$7)),IF($C$5="Released today",IF(COUNTIFS(Register!$A$6:$A$185,$A37,Register!$D$6:$D$185,F$7,Register!$T$6:$T$185,">=0")=0,"",SUMIFS(Register!$T$6:$T$185,Register!$A$6:$A$185,$A37,Register!$D$6:$D$185,F$7)),IF(COUNTIFS(Register!$A$6:$A$185,$A37,Register!$D$6:$D$185,F$7,Register!$O$6:$O$185,">=0")=0,"",SUMIFS(Register!$O$6:$O$185,Register!$A$6:$A$185,$A37,Register!$D$6:$D$185,F$7)))))) | G37: =IF($A37="","",IF(COUNTIFS(Register!$A$6:$A$185,$A37,Register!$D$6:$D$185,G$7)>1,"Dup.",IF($C$5="Critical assets (target)",IF(COUNTIFS(Register!$A$6:$A$185,$A37,Register!$D$6:$D$185,G$7,Register!$Q$6:$Q$185,">=0")=0,"",SUMIFS(Register!$Q$6:$Q$185,Register!$A$6:$A$185,$A37,Register!$D$6:$D$185,G$7)),IF($C$5="Released today",IF(COUNTIFS(Register!$A$6:$A$185,$A37,Register!$D$6:$D$185,G$7,Register!$T$6:$T$185,">=0")=0,"",SUMIFS(Register!$T$6:$T$185,Register!$A$6:$A$185,$A37,Register!$D$6:$D$185,G$7)),IF(COUNTIFS(Register!$A$6:$A$185,$A37,Register!$D$6:$D$185,G$7,Register!$O$6:$O$185,">=0")=0,"",SUMIFS(Register!$O$6:$O$185,Register!$A$6:$A$185,$A37,Register!$D$6:$D$185,G$7)))))) | H37: =IF($A37="","",IF(COUNTIFS(Register!$A$6:$A$185,$A37,Register!$D$6:$D$185,H$7)>1,"Dup.",IF($C$5="Critical assets (target)",IF(COUNTIFS(Register!$A$6:$A$185,$A37,Register!$D$6:$D$185,H$7,Register!$Q$6:$Q$185,">=0")=0,"",SUMIFS(Register!$Q$6:$Q$185,Register!$A$6:$A$185,$A37,Register!$D$6:$D$185,H$7)),IF($C$5="Released today",IF(COUNTIFS(Register!$A$6:$A$185,$A37,Register!$D$6:$D$185,H$7,Register!$T$6:$T$185,">=0")=0,"",SUMIFS(Register!$T$6:$T$185,Register!$A$6:$A$185,$A37,Register!$D$6:$D$185,H$7)),IF(COUNTIFS(Register!$A$6:$A$185,$A37,Register!$D$6:$D$185,H$7,Register!$O$6:$O$185,">=0")=0,"",SUMIFS(Register!$O$6:$O$185,Register!$A$6:$A$185,$A37,Register!$D$6:$D$185,H$7)))))) | I37: =IF($A37="","",IF(COUNTIFS(Register!$A$6:$A$185,$A37,Register!$D$6:$D$185,I$7)>1,"Dup.",IF($C$5="Critical assets (target)",IF(COUNTIFS(Register!$A$6:$A$185,$A37,Register!$D$6:$D$185,I$7,Register!$Q$6:$Q$185,">=0")=0,"",SUMIFS(Register!$Q$6:$Q$185,Register!$A$6:$A$185,$A37,Register!$D$6:$D$185,I$7)),IF($C$5="Released today",IF(COUNTIFS(Register!$A$6:$A$185,$A37,Register!$D$6:$D$185,I$7,Register!$T$6:$T$185,">=0")=0,"",SUMIFS(Register!$T$6:$T$185,Register!$A$6:$A$185,$A37,Register!$D$6:$D$185,I$7)),IF(COUNTIFS(Register!$A$6:$A$185,$A37,Register!$D$6:$D$185,I$7,Register!$O$6:$O$185,">=0")=0,"",SUMIFS(Register!$O$6:$O$185,Register!$A$6:$A$185,$A37,Register!$D$6:$D$185,I$7)))))) | J37: =IF($A37="","",IF(COUNTIFS(Register!$A$6:$A$185,$A37,Register!$D$6:$D$185,J$7)>1,"Dup.",IF($C$5="Critical assets (target)",IF(COUNTIFS(Register!$A$6:$A$185,$A37,Register!$D$6:$D$185,J$7,Register!$Q$6:$Q$185,">=0")=0,"",SUMIFS(Register!$Q$6:$Q$185,Register!$A$6:$A$185,$A37,Register!$D$6:$D$185,J$7)),IF($C$5="Released today",IF(COUNTIFS(Register!$A$6:$A$185,$A37,Register!$D$6:$D$185,J$7,Register!$T$6:$T$185,">=0")=0,"",SUMIFS(Register!$T$6:$T$185,Register!$A$6:$A$185,$A37,Register!$D$6:$D$185,J$7)),IF(COUNTIFS(Register!$A$6:$A$185,$A37,Register!$D$6:$D$185,J$7,Register!$O$6:$O$185,">=0")=0,"",SUMIFS(Register!$O$6:$O$185,Register!$A$6:$A$185,$A37,Register!$D$6:$D$185,J$7)))))) | K37: =IF($A37="","",IF(COUNT(E37:J37)<6,"Incomplete",IF(AND(ISNUMBER(E37),E37<4),E$7,IF(AND(ISNUMBER(F37),F37<4),F$7,IF(AND(ISNUMBER(G37),G37<4),G$7,IF(AND(ISNUMBER(H37),H37<4),H$7,IF(AND(ISNUMBER(I37),I37<4),I$7,IF(AND(ISNUMBER(J37),J37<4),J$7,"None")))))))) | L37: =IF($A37="","",COUNTIFS(Register!$A$6:$A$185,$A37,Register!$P$6:$P$185,"Above policy*")) | M37: =IF($A37="","",IF(COUNTIF('Readiness gate'!$A$7:$A$36,$A37)<>1,"Incomplete",IFERROR(IF(VLOOKUP($A37,GateTab,9,FALSE())="","Incomplete",VLOOKUP($A37,GateTab,9,FALSE())),"Incomplete"))) | N37: =IF($A37="","",SUMPRODUCT((Register!$A$6:$A$185=$A37)*(Register!$T$6:$T$185<>"")*(Register!$O$6:$O$185<>"")*(Register!$T$6:$T$185<Register!$O$6:$O$185)))
B39: Legend | E39: =Scales!$B$6 -> L0 Manual | F39: =Scales!$B$7 -> L1 Assisted | G39: =Scales!$B$8 -> L2 AI-recommended | H39: =Scales!$B$9 -> L3 Human-approved | I39: =Scales!$B$10 -> L4 Autonomous | K39: First step that needs a human in this view
A41: Level distribution by process step (this view)
A42: Level | E42: =Scales!$B$15 -> Enrich | F42: =Scales!$B$16 -> Triage | G42: =Scales!$B$17 -> Contain | H42: =Scales!$B$18 -> Eradicate | I42: =Scales!$B$19 -> Recover | J42: =Scales!$B$20 -> Notify | K42: All steps
A43: 0 | B43: =Scales!$B$6 -> L0 Manual | E43: =COUNTIF(E$8:E$37,$A43) -> 0 | F43: =COUNTIF(F$8:F$37,$A43) -> 0 | G43: =COUNTIF(G$8:G$37,$A43) -> 1 | H43: =COUNTIF(H$8:H$37,$A43) -> 1 | I43: =COUNTIF(I$8:I$37,$A43) -> 1 | J43: =COUNTIF(J$8:J$37,$A43) -> 0 | K43: =SUM(E43:J43) -> 3
A44: 1 | B44: =Scales!$B$7 -> L1 Assisted | E44: =COUNTIF(E$8:E$37,$A44) -> 9 | F44: =COUNTIF(F$8:F$37,$A44) -> 8 | G44: =COUNTIF(G$8:G$37,$A44) -> 0 | H44: =COUNTIF(H$8:H$37,$A44) -> 8 | I44: =COUNTIF(I$8:I$37,$A44) -> 8 | J44: =COUNTIF(J$8:J$37,$A44) -> 10 | K44: =SUM(E44:J44) -> 43
A45: 2 | B45: =Scales!$B$8 -> L2 AI-recommended | E45: =COUNTIF(E$8:E$37,$A45) -> 0 | F45: =COUNTIF(F$8:F$37,$A45) -> 11 | G45: =COUNTIF(G$8:G$37,$A45) -> 8 | H45: =COUNTIF(H$8:H$37,$A45) -> 10 | I45: =COUNTIF(I$8:I$37,$A45) -> 11 | J45: =COUNTIF(J$8:J$37,$A45) -> 9 | K45: =SUM(E45:J45) -> 49
A46: 3 | B46: =Scales!$B$9 -> L3 Human-approved | E46: =COUNTIF(E$8:E$37,$A46) -> 0 | F46: =COUNTIF(F$8:F$37,$A46) -> 1 | G46: =COUNTIF(G$8:G$37,$A46) -> 8 | H46: =COUNTIF(H$8:H$37,$A46) -> 1 | I46: =COUNTIF(I$8:I$37,$A46) -> 0 | J46: =COUNTIF(J$8:J$37,$A46) -> 1 | K46: =SUM(E46:J46) -> 11
A47: 4 | B47: =Scales!$B$10 -> L4 Autonomous | E47: =COUNTIF(E$8:E$37,$A47) -> 11 | F47: =COUNTIF(F$8:F$37,$A47) -> 0 | G47: =COUNTIF(G$8:G$37,$A47) -> 3 | H47: =COUNTIF(H$8:H$37,$A47) -> 0 | I47: =COUNTIF(I$8:I$37,$A47) -> 0 | J47: =COUNTIF(J$8:J$37,$A47) -> 0 | K47: =SUM(E47:J47) -> 14
B48: Share running autonomously (L4) - distribution of assessed step rows, not of incidents | E48: =IF(SUM(E43:E47)=0,0,E47/SUM(E43:E47)) -> 0.55 | F48: =IF(SUM(F43:F47)=0,0,F47/SUM(F43:F47)) -> 0 | G48: =IF(SUM(G43:G47)=0,0,G47/SUM(G43:G47)) -> 0.15 | H48: =IF(SUM(H43:H47)=0,0,H47/SUM(H43:H47)) -> 0 | I48: =IF(SUM(I43:I47)=0,0,I47/SUM(I43:I47)) -> 0 | J48: =IF(SUM(J43:J47)=0,0,J47/SUM(J43:J47)) -> 0 | K48: =IF(SUM(K43:K47)=0,0,K47/SUM(K43:K47)) -> 0.11666667

Sheet Register
A1: Register
A2: One row per use case and process step. The recommended level is pure policy: risk appetite, reversibility, blast radius. Model confidence, the readiness gate and a non-waivable human-signature guardrail decide the release candidate.
A3: A row is rated by its least reversible element. An above-policy choice stays visible as a target and releases with a recorded approval (Exception approved = Yes). Formal authorization itself stays with the Control Tower (briefing, slide 17).
A5: ID | B5: Use case | C5: Domain | D5: Step | E5: Typical action | F5: Reversibility | G5: Blast radius | H5: Model confidence | I5: Appetite | J5: Recommended level (policy) | K5: Confidence adjustment | L5: Confidence ceiling | M5: Your choice | N5: Exception approved | O5: Level applied (target) | P5: Check | Q5: Level on critical assets | R5: Current level today | S5: Readiness gate | T5: Release candidate | U5: Limited by | V5: Notes
A6: UC01 | B6: =IF($A6="","",IF(COUNTIF('Use cases'!$A$5:$A$34,$A6)>1,"Duplicate ID",IFERROR(IF(VLOOKUP($A6,'Use cases'!$A$5:$B$34,2,FALSE())=0,"",VLOOKUP($A6,'Use cases'!$A$5:$B$34,2,FALSE())),""))) -> Phishing campaign containment | C6: =IF(OR($B6="",$B6="Duplicate ID"),"",IFERROR(VLOOKUP($A6,'Use cases'!$A$5:$C$34,3,FALSE()),"")) -> Email and collaboration | D6: Enrich | E6: Analyse headers, URLs and sender reputation; identify all recipients and who clicked. | F6: No state change | G6: Low | H6: High | I6: =IF(OR($B6="",$B6="Duplicate ID"),"",IFERROR(VLOOKUP($A6,'Use cases'!$A$5:$E$34,5,FALSE()),"")) -> Progressive | J6: =IF(OR($B6="",$B6="Duplicate ID"),"",IF(OR($F6="",$G6=""),"",IF(Policy!$B$24<>"OK","Config error",IFERROR(INDEX(Scales!$B$6:$B$10,1+INDEX(Policy!$C$5:$E$16,MATCH($F6&"|"&$G6,Policy!$G$5:$G$16,0),MATCH($I6,Policy!$C$4:$E$4,0))),"Config error")))) -> L4 Autonomous | K6: =IF($H6="","",IF($F6=Scales!$B$24,"exempt",IFERROR(IF(VLOOKUP($H6,Conf_Check,3,FALSE())="valid",VLOOKUP($H6,Conf_Adjust,2,FALSE()),"n/a"),"n/a"))) -> exempt | L6: =IF(OR($J6="",$J6="Config error"),"",IF(OR($F6=Scales!$B$24,AND(ISNUMBER($K6),$K6=0)),4,IF(ISNUMBER($K6),MAX(1,MATCH($J6,Scales!$B$6:$B$10,0)-1+$K6),1))) -> 4 | O6: =IF(OR($J6="",$J6="Config error",$E6="",$F6="",$G6="",$H6="",$R6=""),"",IF($M6="",MATCH($J6,Scales!$B$6:$B$10,0),IFERROR(MATCH($M6,Scales!$B$6:$B$10,0),MATCH($J6,Scales!$B$6:$B$10,0)))-1) -> 4 | P6: =IF($J6="",IF(AND($B6<>"",$B6<>"Duplicate ID"),"Incomplete assessment",""),IF($J6="Config error","Config error",IF($O6="","Incomplete assessment",IF($M6="","As recommended",IF(ISERROR(MATCH($M6,Scales!$B$6:$B$10,0)),"Invalid choice",IF(MATCH($M6,Scales!$B$6:$B$10,0)>MATCH($J6,Scales!$B$6:$B$10,0),"Above policy: needs sign-off",IF(MATCH($M6,Scales!$B$6:$B$10,0)<MATCH($J6,Scales!$B$6:$B$10,0),"More cautious than policy","As recommended"))))))) -> As recommended | Q6: =IF(OR($O6="",Policy!$B$24<>"OK"),"",IFERROR(MIN($O6,INDEX(Policy!$C$5:$E$16,MATCH($F6&"|"&Scales!$B$33,Policy!$G$5:$G$16,0),MATCH($I6,Policy!$C$4:$E$4,0))),"")) -> 4 | R6: 2 | S6: =IF($B6="","",IF(COUNTIF('Readiness gate'!$A$7:$A$36,$A6)<>1,"Incomplete",IFERROR(IF(VLOOKUP($A6,GateTab,IF($F6=Scales!$B$24,11,9),FALSE())="","Incomplete",VLOOKUP($A6,GateTab,IF($F6=Scales!$B$24,11,9),FALSE())),"Incomplete"))) -> Passed | T6: =IF($O6="","",MIN(IF(AND($O6>MATCH($J6,Scales!$B$6:$B$10,0)-1,$N6<>"Yes"),MATCH($J6,Scales!$B$6:$B$10,0)-1,$O6),$L6,IF($F6=Scales!$B$24,IF($S6="Passed",4,IF(NOT(ISNUMBER($R6)),0,IF(OR($R6<0,$R6>4,$R6<>INT($R6)),0,$R6))),IF(NOT(ISNUMBER($R6)),0,IF(OR($R6<0,$R6>4,$R6<>INT($R6)),0,$R6))+IF($S6="Passed",1,0)),IF(AND($F6<>Scales!$B$24,OR($F6=Scales!$B$27,$G6=Scales!$B$33)),3,4))) -> 4 | U6: =IF($O6="",IF(AND($B6<>"",$B6<>"Duplicate ID"),IF($J6="Config error","Config error","Incomplete assessment"),""),IF($T6>=$O6,IF(LEFT($P6,4)="More","Own choice","None"),MID(IF(AND($O6>MATCH($J6,Scales!$B$6:$B$10,0)-1,$N6<>"Yes",$T6=MATCH($J6,Scales!$B$6:$B$10,0)-1)," + Exception not approved","")&IF(AND($F6<>Scales!$B$24,OR($F6=Scales!$B$27,$G6=Scales!$B$33),$T6=3)," + Human-signature guardrail","")&IF($T6=$L6," + Model confidence","")&IF($T6=IF($F6=Scales!$B$24,IF($S6="Passed",4,IF(NOT(ISNUMBER($R6)),0,IF(OR($R6<0,$R6>4,$R6<>INT($R6)),0,$R6))),IF(NOT(ISNUMBER($R6)),0,IF(OR($R6<0,$R6>4,$R6<>INT($R6)),0,$R6))+IF($S6="Passed",1,0))," + "&IF($S6<>"Passed","Readiness gate","Readiness gate (one level per gate)"),""),4,200))) -> None
A7: UC01 | B7: =IF($A7="","",IF(COUNTIF('Use cases'!$A$5:$A$34,$A7)>1,"Duplicate ID",IFERROR(IF(VLOOKUP($A7,'Use cases'!$A$5:$B$34,2,FALSE())=0,"",VLOOKUP($A7,'Use cases'!$A$5:$B$34,2,FALSE())),""))) -> Phishing campaign containment | C7: =IF(OR($B7="",$B7="Duplicate ID"),"",IFERROR(VLOOKUP($A7,'Use cases'!$A$5:$C$34,3,FALSE()),"")) -> Email and collaboration | D7: Triage | E7: Classify the reported mail and decide whether it is part of a campaign. | F7: Fully reversible | G7: Low | H7: High | I7: =IF(OR($B7="",$B7="Duplicate ID"),"",IFERROR(VLOOKUP($A7,'Use cases'!$A$5:$E$34,5,FALSE()),"")) -> Progressive | J7: =IF(OR($B7="",$B7="Duplicate ID"),"",IF(OR($F7="",$G7=""),"",IF(Policy!$B$24<>"OK","Config error",IFERROR(INDEX(Scales!$B$6:$B$10,1+INDEX(Policy!$C$5:$E$16,MATCH($F7&"|"&$G7,Policy!$G$5:$G$16,0),MATCH($I7,Policy!$C$4:$E$4,0))),"Config error")))) -> L4 Autonomous | K7: =IF($H7="","",IF($F7=Scales!$B$24,"exempt",IFERROR(IF(VLOOKUP($H7,Conf_Check,3,FALSE())="valid",VLOOKUP($H7,Conf_Adjust,2,FALSE()),"n/a"),"n/a"))) -> 0 | L7: =IF(OR($J7="",$J7="Config error"),"",IF(OR($F7=Scales!$B$24,AND(ISNUMBER($K7),$K7=0)),4,IF(ISNUMBER($K7),MAX(1,MATCH($J7,Scales!$B$6:$B$10,0)-1+$K7),1))) -> 4 | O7: =IF(OR($J7="",$J7="Config error",$E7="",$F7="",$G7="",$H7="",$R7=""),"",IF($M7="",MATCH($J7,Scales!$B$6:$B$10,0),IFERROR(MATCH($M7,Scales!$B$6:$B$10,0),MATCH($J7,Scales!$B$6:$B$10,0)))-1) -> 4 | P7: =IF($J7="",IF(AND($B7<>"",$B7<>"Duplicate ID"),"Incomplete assessment",""),IF($J7="Config error","Config error",IF($O7="","Incomplete assessment",IF($M7="","As recommended",IF(ISERROR(MATCH($M7,Scales!$B$6:$B$10,0)),"Invalid choice",IF(MATCH($M7,Scales!$B$6:$B$10,0)>MATCH($J7,Scales!$B$6:$B$10,0),"Above policy: needs sign-off",IF(MATCH($M7,Scales!$B$6:$B$10,0)<MATCH($J7,Scales!$B$6:$B$10,0),"More cautious than policy","As recommended"))))))) -> As recommended | Q7: =IF(OR($O7="",Policy!$B$24<>"OK"),"",IFERROR(MIN($O7,INDEX(Policy!$C$5:$E$16,MATCH($F7&"|"&Scales!$B$33,Policy!$G$5:$G$16,0),MATCH($I7,Policy!$C$4:$E$4,0))),"")) -> 3 | R7: 2 | S7: =IF($B7="","",IF(COUNTIF('Readiness gate'!$A$7:$A$36,$A7)<>1,"Incomplete",IFERROR(IF(VLOOKUP($A7,GateTab,IF($F7=Scales!$B$24,11,9),FALSE())="","Incomplete",VLOOKUP($A7,GateTab,IF($F7=Scales!$B$24,11,9),FALSE())),"Incomplete"))) -> Passed | T7: =IF($O7="","",MIN(IF(AND($O7>MATCH($J7,Scales!$B$6:$B$10,0)-1,$N7<>"Yes"),MATCH($J7,Scales!$B$6:$B$10,0)-1,$O7),$L7,IF($F7=Scales!$B$24,IF($S7="Passed",4,IF(NOT(ISNUMBER($R7)),0,IF(OR($R7<0,$R7>4,$R7<>INT($R7)),0,$R7))),IF(NOT(ISNUMBER($R7)),0,IF(OR($R7<0,$R7>4,$R7<>INT($R7)),0,$R7))+IF($S7="Passed",1,0)),IF(AND($F7<>Scales!$B$24,OR($F7=Scales!$B$27,$G7=Scales!$B$33)),3,4))) -> 3 | U7: =IF($O7="",IF(AND($B7<>"",$B7<>"Duplicate ID"),IF($J7="Config error","Config error","Incomplete assessment"),""),IF($T7>=$O7,IF(LEFT($P7,4)="More","Own choice","None"),MID(IF(AND($O7>MATCH($J7,Scales!$B$6:$B$10,0)-1,$N7<>"Yes",$T7=MATCH($J7,Scales!$B$6:$B$10,0)-1)," + Exception not approved","")&IF(AND($F7<>Scales!$B$24,OR($F7=Scales!$B$27,$G7=Scales!$B$33),$T7=3)," + Human-signature guardrail","")&IF($T7=$L7," + Model confidence","")&IF($T7=IF($F7=Scales!$B$24,IF($S7="Passed",4,IF(NOT(ISNUMBER($R7)),0,IF(OR($R7<0,$R7>4,$R7<>INT($R7)),0,$R7))),IF(NOT(ISNUMBER($R7)),0,IF(OR($R7<0,$R7>4,$R7<>INT($R7)),0,$R7))+IF($S7="Passed",1,0))," + "&IF($S7<>"Passed","Readiness gate","Readiness gate (one level per gate)"),""),4,200))) -> Readiness gate (one level per gate)
A8: UC01 | B8: =IF($A8="","",IF(COUNTIF('Use cases'!$A$5:$A$34,$A8)>1,"Duplicate ID",IFERROR(IF(VLOOKUP($A8,'Use cases'!$A$5:$B$34,2,FALSE())=0,"",VLOOKUP($A8,'Use cases'!$A$5:$B$34,2,FALSE())),""))) -> Phishing campaign containment | C8: =IF(OR($B8="",$B8="Duplicate ID"),"",IFERROR(VLOOKUP($A8,'Use cases'!$A$5:$C$34,3,FALSE()),"")) -> Email and collaboration | D8: Contain | E8: Quarantine the mail across all mailboxes; block sender, domain and URL. | F8: Fully reversible | G8: Medium | H8: High | I8: =IF(OR($B8="",$B8="Duplicate ID"),"",IFERROR(VLOOKUP($A8,'Use cases'!$A$5:$E$34,5,FALSE()),"")) -> Progressive | J8: =IF(OR($B8="",$B8="Duplicate ID"),"",IF(OR($F8="",$G8=""),"",IF(Policy!$B$24<>"OK","Config error",IFERROR(INDEX(Scales!$B$6:$B$10,1+INDEX(Policy!$C$5:$E$16,MATCH($F8&"|"&$G8,Policy!$G$5:$G$16,0),MATCH($I8,Policy!$C$4:$E$4,0))),"Config error")))) -> L4 Autonomous | K8: =IF($H8="","",IF($F8=Scales!$B$24,"exempt",IFERROR(IF(VLOOKUP($H8,Conf_Check,3,FALSE())="valid",VLOOKUP($H8,Conf_Adjust,2,FALSE()),"n/a"),"n/a"))) -> 0 | L8: =IF(OR($J8="",$J8="Config error"),"",IF(OR($F8=Scales!$B$24,AND(ISNUMBER($K8),$K8=0)),4,IF(ISNUMBER($K8),MAX(1,MATCH($J8,Scales!$B$6:$B$10,0)-1+$K8),1))) -> 4 | O8: =IF(OR($J8="",$J8="Config error",$E8="",$F8="",$G8="",$H8="",$R8=""),"",IF($M8="",MATCH($J8,Scales!$B$6:$B$10,0),IFERROR(MATCH($M8,Scales!$B$6:$B$10,0),MATCH($J8,Scales!$B$6:$B$10,0)))-1) -> 4 | P8: =IF($J8="",IF(AND($B8<>"",$B8<>"Duplicate ID"),"Incomplete assessment",""),IF($J8="Config error","Config error",IF($O8="","Incomplete assessment",IF($M8="","As recommended",IF(ISERROR(MATCH($M8,Scales!$B$6:$B$10,0)),"Invalid choice",IF(MATCH($M8,Scales!$B$6:$B$10,0)>MATCH($J8,Scales!$B$6:$B$10,0),"Above policy: needs sign-off",IF(MATCH($M8,Scales!$B$6:$B$10,0)<MATCH($J8,Scales!$B$6:$B$10,0),"More cautious than policy","As recommended"))))))) -> As recommended | Q8: =IF(OR($O8="",Policy!$B$24<>"OK"),"",IFERROR(MIN($O8,INDEX(Policy!$C$5:$E$16,MATCH($F8&"|"&Scales!$B$33,Policy!$G$5:$G$16,0),MATCH($I8,Policy!$C$4:$E$4,0))),"")) -> 3 | R8: 3 | S8: =IF($B8="","",IF(COUNTIF('Readiness gate'!$A$7:$A$36,$A8)<>1,"Incomplete",IFERROR(IF(VLOOKUP($A8,GateTab,IF($F8=Scales!$B$24,11,9),FALSE())="","Incomplete",VLOOKUP($A8,GateTab,IF($F8=Scales!$B$24,11,9),FALSE())),"Incomplete"))) -> Passed | T8: =IF($O8="","",MIN(IF(AND($O8>MATCH($J8,Scales!$B$6:$B$10,0)-1,$N8<>"Yes"),MATCH($J8,Scales!$B$6:$B$10,0)-1,$O8),$L8,IF($F8=Scales!$B$24,IF($S8="Passed",4,IF(NOT(ISNUMBER($R8)),0,IF(OR($R8<0,$R8>4,$R8<>INT($R8)),0,$R8))),IF(NOT(ISNUMBER($R8)),0,IF(OR($R8<0,$R8>4,$R8<>INT($R8)),0,$R8))+IF($S8="Passed",1,0)),IF(AND($F8<>Scales!$B$24,OR($F8=Scales!$B$27,$G8=Scales!$B$33)),3,4))) -> 4 | U8: =IF($O8="",IF(AND($B8<>"",$B8<>"Duplicate ID"),IF($J8="Config error","Config error","Incomplete assessment"),""),IF($T8>=$O8,IF(LEFT($P8,4)="More","Own choice","None"),MID(IF(AND($O8>MATCH($J8,Scales!$B$6:$B$10,0)-1,$N8<>"Yes",$T8=MATCH($J8,Scales!$B$6:$B$10,0)-1)," + Exception not approved","")&IF(AND($F8<>Scales!$B$24,OR($F8=Scales!$B$27,$G8=Scales!$B$33),$T8=3)," + Human-signature guardrail","")&IF($T8=$L8," + Model confidence","")&IF($T8=IF($F8=Scales!$B$24,IF($S8="Passed",4,IF(NOT(ISNUMBER($R8)),0,IF(OR($R8<0,$R8>4,$R8<>INT($R8)),0,$R8))),IF(NOT(ISNUMBER($R8)),0,IF(OR($R8<0,$R8>4,$R8<>INT($R8)),0,$R8))+IF($S8="Passed",1,0))," + "&IF($S8<>"Passed","Readiness gate","Readiness gate (one level per gate)"),""),4,200))) -> None
A9: UC01 | B9: =IF($A9="","",IF(COUNTIF('Use cases'!$A$5:$A$34,$A9)>1,"Duplicate ID",IFERROR(IF(VLOOKUP($A9,'Use cases'!$A$5:$B$34,2,FALSE())=0,"",VLOOKUP($A9,'Use cases'!$A$5:$B$34,2,FALSE())),""))) -> Phishing campaign containment | C9: =IF(OR($B9="",$B9="Duplicate ID"),"",IFERROR(VLOOKUP($A9,'Use cases'!$A$5:$C$34,3,FALSE()),"")) -> Email and collaboration | D9: Eradicate | E9: Remove the campaign from all mailboxes (soft delete); block look-alike domains. | F9: Fully reversible | G9: Medium | H9: High | I9: =IF(OR($B9="",$B9="Duplicate ID"),"",IFERROR(VLOOKUP($A9,'Use cases'!$A$5:$E$34,5,FALSE()),"")) -> Progressive | J9: =IF(OR($B9="",$B9="Duplicate ID"),"",IF(OR($F9="",$G9=""),"",IF(Policy!$B$24<>"OK","Config error",IFERROR(INDEX(Scales!$B$6:$B$10,1+INDEX(Policy!$C$5:$E$16,MATCH($F9&"|"&$G9,Policy!$G$5:$G$16,0),MATCH($I9,Policy!$C$4:$E$4,0))),"Config error")))) -> L4 Autonomous | K9: =IF($H9="","",IF($F9=Scales!$B$24,"exempt",IFERROR(IF(VLOOKUP($H9,Conf_Check,3,FALSE())="valid",VLOOKUP($H9,Conf_Adjust,2,FALSE()),"n/a"),"n/a"))) -> 0 | L9: =IF(OR($J9="",$J9="Config error"),"",IF(OR($F9=Scales!$B$24,AND(ISNUMBER($K9),$K9=0)),4,IF(ISNUMBER($K9),MAX(1,MATCH($J9,Scales!$B$6:$B$10,0)-1+$K9),1))) -> 4 | O9: =IF(OR($J9="",$J9="Config error",$E9="",$F9="",$G9="",$H9="",$R9=""),"",IF($M9="",MATCH($J9,Scales!$B$6:$B$10,0),IFERROR(MATCH($M9,Scales!$B$6:$B$10,0),MATCH($J9,Scales!$B$6:$B$10,0)))-1) -> 4 | P9: =IF($J9="",IF(AND($B9<>"",$B9<>"Duplicate ID"),"Incomplete assessment",""),IF($J9="Config error","Config error",IF($O9="","Incomplete assessment",IF($M9="","As recommended",IF(ISERROR(MATCH($M9,Scales!$B$6:$B$10,0)),"Invalid choice",IF(MATCH($M9,Scales!$B$6:$B$10,0)>MATCH($J9,Scales!$B$6:$B$10,0),"Above policy: needs sign-off",IF(MATCH($M9,Scales!$B$6:$B$10,0)<MATCH($J9,Scales!$B$6:$B$10,0),"More cautious than policy","As recommended"))))))) -> As recommended | Q9: =IF(OR($O9="",Policy!$B$24<>"OK"),"",IFERROR(MIN($O9,INDEX(Policy!$C$5:$E$16,MATCH($F9&"|"&Scales!$B$33,Policy!$G$5:$G$16,0),MATCH($I9,Policy!$C$4:$E$4,0))),"")) -> 3 | R9: 2 | S9: =IF($B9="","",IF(COUNTIF('Readiness gate'!$A$7:$A$36,$A9)<>1,"Incomplete",IFERROR(IF(VLOOKUP($A9,GateTab,IF($F9=Scales!$B$24,11,9),FALSE())="","Incomplete",VLOOKUP($A9,GateTab,IF($F9=Scales!$B$24,11,9),FALSE())),"Incomplete"))) -> Passed | T9: =IF($O9="","",MIN(IF(AND($O9>MATCH($J9,Scales!$B$6:$B$10,0)-1,$N9<>"Yes"),MATCH($J9,Scales!$B$6:$B$10,0)-1,$O9),$L9,IF($F9=Scales!$B$24,IF($S9="Passed",4,IF(NOT(ISNUMBER($R9)),0,IF(OR($R9<0,$R9>4,$R9<>INT($R9)),0,$R9))),IF(NOT(ISNUMBER($R9)),0,IF(OR($R9<0,$R9>4,$R9<>INT($R9)),0,$R9))+IF($S9="Passed",1,0)),IF(AND($F9<>Scales!$B$24,OR($F9=Scales!$B$27,$G9=Scales!$B$33)),3,4))) -> 3 | U9: =IF($O9="",IF(AND($B9<>"",$B9<>"Duplicate ID"),IF($J9="Config error","Config error","Incomplete assessment"),""),IF($T9>=$O9,IF(LEFT($P9,4)="More","Own choice","None"),MID(IF(AND($O9>MATCH($J9,Scales!$B$6:$B$10,0)-1,$N9<>"Yes",$T9=MATCH($J9,Scales!$B$6:$B$10,0)-1)," + Exception not approved","")&IF(AND($F9<>Scales!$B$24,OR($F9=Scales!$B$27,$G9=Scales!$B$33),$T9=3)," + Human-signature guardrail","")&IF($T9=$L9," + Model confidence","")&IF($T9=IF($F9=Scales!$B$24,IF($S9="Passed",4,IF(NOT(ISNUMBER($R9)),0,IF(OR($R9<0,$R9>4,$R9<>INT($R9)),0,$R9))),IF(NOT(ISNUMBER($R9)),0,IF(OR($R9<0,$R9>4,$R9<>INT($R9)),0,$R9))+IF($S9="Passed",1,0))," + "&IF($S9<>"Passed","Readiness gate","Readiness gate (one level per gate)"),""),4,200))) -> Readiness gate (one level per gate)
A10: UC01 | B10: =IF($A10="","",IF(COUNTIF('Use cases'!$A$5:$A$34,$A10)>1,"Duplicate ID",IFERROR(IF(VLOOKUP($A10,'Use cases'!$A$5:$B$34,2,FALSE())=0,"",VLOOKUP($A10,'Use cases'!$A$5:$B$34,2,FALSE())),""))) -> Phishing campaign containment | C10: =IF(OR($B10="",$B10="Duplicate ID"),"",IFERROR(VLOOKUP($A10,'Use cases'!$A$5:$C$34,3,FALSE()),"")) -> Email and collaboration | D10: Recover | E10: Release wrongly quarantined mails; remove blocks once the campaign has ended. | F10: Fully reversible | G10: Low | H10: Medium | I10: =IF(OR($B10="",$B10="Duplicate ID"),"",IFERROR(VLOOKUP($A10,'Use cases'!$A$5:$E$34,5,FALSE()),"")) -> Progressive | J10: =IF(OR($B10="",$B10="Duplicate ID"),"",IF(OR($F10="",$G10=""),"",IF(Policy!$B$24<>"OK","Config error",IFERROR(INDEX(Scales!$B$6:$B$10,1+INDEX(Policy!$C$5:$E$16,MATCH($F10&"|"&$G10,Policy!$G$5:$G$16,0),MATCH($I10,Policy!$C$4:$E$4,0))),"Config error")))) -> L4 Autonomous | K10: =IF($H10="","",IF($F10=Scales!$B$24,"exempt",IFERROR(IF(VLOOKUP($H10,Conf_Check,3,FALSE())="valid",VLOOKUP($H10,Conf_Adjust,2,FALSE()),"n/a"),"n/a"))) -> -1 | L10: =IF(OR($J10="",$J10="Config error"),"",IF(OR($F10=Scales!$B$24,AND(ISNUMBER($K10),$K10=0)),4,IF(ISNUMBER($K10),MAX(1,MATCH($J10,Scales!$B$6:$B$10,0)-1+$K10),1))) -> 3 | O10: =IF(OR($J10="",$J10="Config error",$E10="",$F10="",$G10="",$H10="",$R10=""),"",IF($M10="",MATCH($J10,Scales!$B$6:$B$10,0),IFERROR(MATCH($M10,Scales!$B$6:$B$10,0),MATCH($J10,Scales!$B$6:$B$10,0)))-1) -> 4 | P10: =IF($J10="",IF(AND($B10<>"",$B10<>"Duplicate ID"),"Incomplete assessment",""),IF($J10="Config error","Config error",IF($O10="","Incomplete assessment",IF($M10="","As recommended",IF(ISERROR(MATCH($M10,Scales!$B$6:$B$10,0)),"Invalid choice",IF(MATCH($M10,Scales!$B$6:$B$10,0)>MATCH($J10,Scales!$B$6:$B$10,0),"Above policy: needs sign-off",IF(MATCH($M10,Scales!$B$6:$B$10,0)<MATCH($J10,Scales!$B$6:$B$10,0),"More cautious than policy","As recommended"))))))) -> As recommended | Q10: =IF(OR($O10="",Policy!$B$24<>"OK"),"",IFERROR(MIN($O10,INDEX(Policy!$C$5:$E$16,MATCH($F10&"|"&Scales!$B$33,Policy!$G$5:$G$16,0),MATCH($I10,Policy!$C$4:$E$4,0))),"")) -> 3 | R10: 1 | S10: =IF($B10="","",IF(COUNTIF('Readiness gate'!$A$7:$A$36,$A10)<>1,"Incomplete",IFERROR(IF(VLOOKUP($A10,GateTab,IF($F10=Scales!$B$24,11,9),FALSE())="","Incomplete",VLOOKUP($A10,GateTab,IF($F10=Scales!$B$24,11,9),FALSE())),"Incomplete"))) -> Passed | T10: =IF($O10="","",MIN(IF(AND($O10>MATCH($J10,Scales!$B$6:$B$10,0)-1,$N10<>"Yes"),MATCH($J10,Scales!$B$6:$B$10,0)-1,$O10),$L10,IF($F10=Scales!$B$24,IF($S10="Passed",4,IF(NOT(ISNUMBER($R10)),0,IF(OR($R10<0,$R10>4,$R10<>INT($R10)),0,$R10))),IF(NOT(ISNUMBER($R10)),0,IF(OR($R10<0,$R10>4,$R10<>INT($R10)),0,$R10))+IF($S10="Passed",1,0)),IF(AND($F10<>Scales!$B$24,OR($F10=Scales!$B$27,$G10=Scales!$B$33)),3,4))) -> 2 | U10: =IF($O10="",IF(AND($B10<>"",$B10<>"Duplicate ID"),IF($J10="Config error","Config error","Incomplete assessment"),""),IF($T10>=$O10,IF(LEFT($P10,4)="More","Own choice","None"),MID(IF(AND($O10>MATCH($J10,Scales!$B$6:$B$10,0)-1,$N10<>"Yes",$T10=MATCH($J10,Scales!$B$6:$B$10,0)-1)," + Exception not approved","")&IF(AND($F10<>Scales!$B$24,OR($F10=Scales!$B$27,$G10=Scales!$B$33),$T10=3)," + Human-signature guardrail","")&IF($T10=$L10," + Model confidence","")&IF($T10=IF($F10=Scales!$B$24,IF($S10="Passed",4,IF(NOT(ISNUMBER($R10)),0,IF(OR($R10<0,$R10>4,$R10<>INT($R10)),0,$R10))),IF(NOT(ISNUMBER($R10)),0,IF(OR($R10<0,$R10>4,$R10<>INT($R10)),0,$R10))+IF($S10="Passed",1,0))," + "&IF($S10<>"Passed","Readiness gate","Readiness gate (one level per gate)"),""),4,200))) -> Readiness gate (one level per gate)
A11: UC01 | B11: =IF($A11="","",IF(COUNTIF('Use cases'!$A$5:$A$34,$A11)>1,"Duplicate ID",IFERROR(IF(VLOOKUP($A11,'Use cases'!$A$5:$B$34,2,FALSE())=0,"",VLOOKUP($A11,'Use cases'!$A$5:$B$34,2,FALSE())),""))) -> Phishing campaign containment | C11: =IF(OR($B11="",$B11="Duplicate ID"),"",IFERROR(VLOOKUP($A11,'Use cases'!$A$5:$C$34,3,FALSE()),"")) -> Email and collaboration | D11: Notify | E11: Inform reporters and affected users; issue a campaign warning. | F11: Fully reversible | G11: Low | H11: High | I11: =IF(OR($B11="",$B11="Duplicate ID"),"",IFERROR(VLOOKUP($A11,'Use cases'!$A$5:$E$34,5,FALSE()),"")) -> Progressive | J11: =IF(OR($B11="",$B11="Duplicate ID"),"",IF(OR($F11="",$G11=""),"",IF(Policy!$B$24<>"OK","Config error",IFERROR(INDEX(Scales!$B$6:$B$10,1+INDEX(Policy!$C$5:$E$16,MATCH($F11&"|"&$G11,Policy!$G$5:$G$16,0),MATCH($I11,Policy!$C$4:$E$4,0))),"Config error")))) -> L4 Autonomous | K11: =IF($H11="","",IF($F11=Scales!$B$24,"exempt",IFERROR(IF(VLOOKUP($H11,Conf_Check,3,FALSE())="valid",VLOOKUP($H11,Conf_Adjust,2,FALSE()),"n/a"),"n/a"))) -> 0 | L11: =IF(OR($J11="",$J11="Config error"),"",IF(OR($F11=Scales!$B$24,AND(ISNUMBER($K11),$K11=0)),4,IF(ISNUMBER($K11),MAX(1,MATCH($J11,Scales!$B$6:$B$10,0)-1+$K11),1))) -> 4 | O11: =IF(OR($J11="",$J11="Config error",$E11="",$F11="",$G11="",$H11="",$R11=""),"",IF($M11="",MATCH($J11,Scales!$B$6:$B$10,0),IFERROR(MATCH($M11,Scales!$B$6:$B$10,0),MATCH($J11,Scales!$B$6:$B$10,0)))-1) -> 4 | P11: =IF($J11="",IF(AND($B11<>"",$B11<>"Duplicate ID"),"Incomplete assessment",""),IF($J11="Config error","Config error",IF($O11="","Incomplete assessment",IF($M11="","As recommended",IF(ISERROR(MATCH($M11,Scales!$B$6:$B$10,0)),"Invalid choice",IF(MATCH($M11,Scales!$B$6:$B$10,0)>MATCH($J11,Scales!$B$6:$B$10,0),"Above policy: needs sign-off",IF(MATCH($M11,Scales!$B$6:$B$10,0)<MATCH($J11,Scales!$B$6:$B$10,0),"More cautious than policy","As recommended"))))))) -> As recommended | Q11: =IF(OR($O11="",Policy!$B$24<>"OK"),"",IFERROR(MIN($O11,INDEX(Policy!$C$5:$E$16,MATCH($F11&"|"&Scales!$B$33,Policy!$G$5:$G$16,0),MATCH($I11,Policy!$C$4:$E$4,0))),"")) -> 3 | R11: 2 | S11: =IF($B11="","",IF(COUNTIF('Readiness gate'!$A$7:$A$36,$A11)<>1,"Incomplete",IFERROR(IF(VLOOKUP($A11,GateTab,IF($F11=Scales!$B$24,11,9),FALSE())="","Incomplete",VLOOKUP($A11,GateTab,IF($F11=Scales!$B$24,11,9),FALSE())),"Incomplete"))) -> Passed | T11: =IF($O11="","",MIN(IF(AND($O11>MATCH($J11,Scales!$B$6:$B$10,0)-1,$N11<>"Yes"),MATCH($J11,Scales!$B$6:$B$10,0)-1,$O11),$L11,IF($F11=Scales!$B$24,IF($S11="Passed",4,IF(NOT(ISNUMBER($R11)),0,IF(OR($R11<0,$R11>4,$R11<>INT($R11)),0,$R11))),IF(NOT(ISNUMBER($R11)),0,IF(OR($R11<0,$R11>4,$R11<>INT($R11)),0,$R11))+IF($S11="Passed",1,0)),IF(AND($F11<>Scales!$B$24,OR($F11=Scales!$B$27,$G11=Scales!$B$33)),3,4))) -> 3 | U11: =IF($O11="",IF(AND($B11<>"",$B11<>"Duplicate ID"),IF($J11="Config error","Config error","Incomplete assessment"),""),IF($T11>=$O11,IF(LEFT($P11,4)="More","Own choice","None"),MID(IF(AND($O11>MATCH($J11,Scales!$B$6:$B$10,0)-1,$N11<>"Yes",$T11=MATCH($J11,Scales!$B$6:$B$10,0)-1)," + Exception not approved","")&IF(AND($F11<>Scales!$B$24,OR($F11=Scales!$B$27,$G11=Scales!$B$33),$T11=3)," + Human-signature guardrail","")&IF($T11=$L11," + Model confidence","")&IF($T11=IF($F11=Scales!$B$24,IF($S11="Passed",4,IF(NOT(ISNUMBER($R11)),0,IF(OR($R11<0,$R11>4,$R11<>INT($R11)),0,$R11))),IF(NOT(ISNUMBER($R11)),0,IF(OR($R11<0,$R11>4,$R11<>INT($R11)),0,$R11))+IF($S11="Passed",1,0))," + "&IF($S11<>"Passed","Readiness gate","Readiness gate (one level per gate)"),""),4,200))) -> Readiness gate (one level per gate)
A12: UC02 | B12: =IF($A12="","",IF(COUNTIF('Use cases'!$A$5:$A$34,$A12)>1,"Duplicate ID",IFERROR(IF(VLOOKUP($A12,'Use cases'!$A$5:$B$34,2,FALSE())=0,"",VLOOKUP($A12,'Use cases'!$A$5:$B$34,2,FALSE())),""))) -> Malicious attachment detonation and mailbox clean-up | C12: =IF(OR($B12="",$B12="Duplicate ID"),"",IFERROR(VLOOKUP($A12,'Use cases'!$A$5:$C$34,3,FALSE()),"")) -> Email and collaboration | D12: Enrich | E12: Detonate the attachment in a sandbox; extract indicators; find recipients and executions. | F12: No state change | G12: Low | H12: High | I12: =IF(OR($B12="",$B12="Duplicate ID"),"",IFERROR(VLOOKUP($A12,'Use cases'!$A$5:$E$34,5,FALSE()),"")) -> Progressive | J12: =IF(OR($B12="",$B12="Duplicate ID"),"",IF(OR($F12="",$G12=""),"",IF(Policy!$B$24<>"OK","Config error",IFERROR(INDEX(Scales!$B$6:$B$10,1+INDEX(Policy!$C$5:$E$16,MATCH($F12&"|"&$G12,Policy!$G$5:$G$16,0),MATCH($I12,Policy!$C$4:$E$4,0))),"Config error")))) -> L4 Autonomous | K12: =IF($H12="","",IF($F12=Scales!$B$24,"exempt",IFERROR(IF(VLOOKUP($H12,Conf_Check,3,FALSE())="valid",VLOOKUP($H12,Conf_Adjust,2,FALSE()),"n/a"),"n/a"))) -> exempt | L12: =IF(OR($J12="",$J12="Config error"),"",IF(OR($F12=Scales!$B$24,AND(ISNUMBER($K12),$K12=0)),4,IF(ISNUMBER($K12),MAX(1,MATCH($J12,Scales!$B$6:$B$10,0)-1+$K12),1))) -> 4 | O12: =IF(OR($J12="",$J12="Config error",$E12="",$F12="",$G12="",$H12="",$R12=""),"",IF($M12="",MATCH($J12,Scales!$B$6:$B$10,0),IFERROR(MATCH($M12,Scales!$B$6:$B$10,0),MATCH($J12,Scales!$B$6:$B$10,0)))-1) -> 4 | P12: =IF($J12="",IF(AND($B12<>"",$B12<>"Duplicate ID"),"Incomplete assessment",""),IF($J12="Config error","Config error",IF($O12="","Incomplete assessment",IF($M12="","As recommended",IF(ISERROR(MATCH($M12,Scales!$B$6:$B$10,0)),"Invalid choice",IF(MATCH($M12,Scales!$B$6:$B$10,0)>MATCH($J12,Scales!$B$6:$B$10,0),"Above policy: needs sign-off",IF(MATCH($M12,Scales!$B$6:$B$10,0)<MATCH($J12,Scales!$B$6:$B$10,0),"More cautious than policy","As recommended"))))))) -> As recommended | Q12: =IF(OR($O12="",Policy!$B$24<>"OK"),"",IFERROR(MIN($O12,INDEX(Policy!$C$5:$E$16,MATCH($F12&"|"&Scales!$B$33,Policy!$G$5:$G$16,0),MATCH($I12,Policy!$C$4:$E$4,0))),"")) -> 4 | R12: 2 | S12: =IF($B12="","",IF(COUNTIF('Readiness gate'!$A$7:$A$36,$A12)<>1,"Incomplete",IFERROR(IF(VLOOKUP($A12,GateTab,IF($F12=Scales!$B$24,11,9),FALSE())="","Incomplete",VLOOKUP($A12,GateTab,IF($F12=Scales!$B$24,11,9),FALSE())),"Incomplete"))) -> Passed | T12: =IF($O12="","",MIN(IF(AND($O12>MATCH($J12,Scales!$B$6:$B$10,0)-1,$N12<>"Yes"),MATCH($J12,Scales!$B$6:$B$10,0)-1,$O12),$L12,IF($F12=Scales!$B$24,IF($S12="Passed",4,IF(NOT(ISNUMBER($R12)),0,IF(OR($R12<0,$R12>4,$R12<>INT($R12)),0,$R12))),IF(NOT(ISNUMBER($R12)),0,IF(OR($R12<0,$R12>4,$R12<>INT($R12)),0,$R12))+IF($S12="Passed",1,0)),IF(AND($F12<>Scales!$B$24,OR($F12=Scales!$B$27,$G12=Scales!$B$33)),3,4))) -> 4 | U12: =IF($O12="",IF(AND($B12<>"",$B12<>"Duplicate ID"),IF($J12="Config error","Config error","Incomplete assessment"),""),IF($T12>=$O12,IF(LEFT($P12,4)="More","Own choice","None"),MID(IF(AND($O12>MATCH($J12,Scales!$B$6:$B$10,0)-1,$N12<>"Yes",$T12=MATCH($J12,Scales!$B$6:$B$10,0)-1)," + Exception not approved","")&IF(AND($F12<>Scales!$B$24,OR($F12=Scales!$B$27,$G12=Scales!$B$33),$T12=3)," + Human-signature guardrail","")&IF($T12=$L12," + Model confidence","")&IF($T12=IF($F12=Scales!$B$24,IF($S12="Passed",4,IF(NOT(ISNUMBER($R12)),0,IF(OR($R12<0,$R12>4,$R12<>INT($R12)),0,$R12))),IF(NOT(ISNUMBER($R12)),0,IF(OR($R12<0,$R12>4,$R12<>INT($R12)),0,$R12))+IF($S12="Passed",1,0))," + "&IF($S12<>"Passed","Readiness gate","Readiness gate (one level per gate)"),""),4,200))) -> None
